Workbook

Sheet Decision
B2: ABNB | guidance-led event model
B3: GBV conversion track only. Q3 2026 through Q2 2027. Prepared 15 Sep 2026.
B5: =IF(ISNUMBER(F19),IF(F19>0,"Working Q4 guide is above the assumed Street guide proxy. ",IF(F19<0,"Working Q4 guide is below the assumed Street guide proxy. ","Working Q4 guide equals the assumed Street guide proxy. ")),"Working Q4 comparison is unavailable. ")&"Forecast and reaction tests have not established an investable edge. The proxy is conditional, not observed guide expectations." -> Working Q4 guide is above the assumed Street guide proxy. Forecast and reaction tests have not established an investable edge. The proxy is conditional, not observed guide expectations.
B9: Quarter | C9: Revenue $m | D9: Guide $m | E9: Street revenue $m | F9: Guide treatment
B10: 2026Q3 | C10: =Conversion!C11 -> 4808.3629 | D10: =Inputs!C35 -> 4730 | E10: =Conversion!C16 -> 4744.8819 | F10: Observed midpoint
B11: 2026Q4 | C11: =Conversion!D11 -> 3179.3437 | D11: =Conversion!D13 -> 3123.4191 | E11: =Conversion!D16 -> 3161.0215 | F11: Conditional estimate
B12: 2027Q1 | C12: =Conversion!E11 -> 3055.6806 | D12: =Conversion!E13 -> 3001.9313 | E12: =Conversion!E16 -> n.a. | F12: Conditional estimate
B13: 2027Q2 | C13: =Conversion!F11 -> 4048.3953 | D13: =Conversion!F13 -> 3977.1842 | E13: =Conversion!F16 -> n.a. | F13: Conditional estimate
B16: Next key guide: Q4 2026
B17: Our implied guide ($m) | F17: =Conversion!D13 -> 3123.4191
B18: Street guide proxy ($m) | F18: =Conversion!D18 -> 3105.4192
B19: Conditional gap ($m) | F19: =Conversion!D19 -> 17.999878
B20: Conditional gap (%) | F20: =Conversion!D20 -> 0.0057962796
B21: Q3 GBV break-even ($m) | F21: =Conversion!D26 -> 25780.297
B22: Q3 GBV change to break-even | F22: =Conversion!D27 -> -0.0087763123
B23: Q4 lambda change to break-even (bp) | F23: =Conversion!D25 -> -6.9387146
B25: A lower conditional guide requires weaker lagged GBV, lower conversion, or a larger management cushion. RNPL risk belongs in a measurable change to those inputs. A guide below revenue consensus alone is not evidence of a bearish surprise. Break-even thresholds are conditions, not probabilities or calibrated short triggers.
B31: Decision gates and next steps
B33: Gate | C33: Evidence in hand | D33: Missing evidence | E33: Next action
B34: Forecast quality | C34: Reproduced fixed replay; 12 / 10 matched observations | D34: Outperformance in both windows and stable deletions | E34: Keep conditional status; prospectively track input revisions
B35: Variant view | C35: Dated Q3 / Q4 revenue expectations; explicit Q4 threshold | D35: Observed guide expectations and Q1/Q2 Street quarters | E35: Refresh vendor-dated expectations before the event
B36: Price response | C36: 23-event daily gap and next-session panel | D36: Stable coefficient; release/call attribution | E36: Obtain entitled ABNB + QQQ timestamped event bars
B37: Trade execution | C37: Entry windows and information timing separated | D37: Net costs, borrow/option pricing, robust ex-ante rule | E37: Pre-register a rule before testing; do not infer a trade from this correlation
B40: Read order: Decision → Conversion → Forecast audit → Event study. Inputs holds the editable working assumptions; Event data keeps the full universe; Sources records evidence and limitations. The two-page memo is a static dated companion. Changing workbook inputs does not rewrite the historical audit or memo.

Sheet Conversion
B2: GBV conversion | four-quarter build
B3: Prepared 15 Sep 2026; inherited parameters through 13 Sep. No 2028 extension.
B5: USDm, except ratios | C5: 2026Q3 | D5: 2026Q4 | E5: 2027Q1 | F5: 2027Q2 | H5: Quarter | I5: Revenue | J5: Implied guide
B6: GBV: previous quarter | C6: =IF(ISNUMBER(Inputs!C7),Inputs!C7,"n.a.") -> 27200 | D6: =IF(ISNUMBER(Inputs!C8),Inputs!C8,"n.a.") -> 26008.556 | E6: =IF(ISNUMBER(Inputs!C9),Inputs!C9,"n.a.") -> 23008.326 | F6: =IF(ISNUMBER(Inputs!C10),Inputs!C10,"n.a.") -> 32424.358 | H6: 2026Q3 | I6: =C11 -> 4808.3629 | J6: =C13 -> 4723.784
B7: GBV: two quarters prior | C7: =IF(ISNUMBER(Inputs!C6),Inputs!C6,"n.a.") -> 29200 | D7: =IF(ISNUMBER(Inputs!C7),Inputs!C7,"n.a.") -> 27200 | E7: =IF(ISNUMBER(Inputs!C8),Inputs!C8,"n.a.") -> 26008.556 | F7: =IF(ISNUMBER(Inputs!C9),Inputs!C9,"n.a.") -> 23008.326 | H7: 2026Q4 | I7: =D11 -> 3179.3437 | J7: =D13 -> 3123.4191
B8: Weight: previous quarter | C8: =2/3 -> 0.66666667 | D8: =2/3 -> 0.66666667 | E8: =2/3 -> 0.66666667 | F8: =2/3 -> 0.66666667 | H8: 2027Q1 | I8: =E11 -> 3055.6806 | J8: =E13 -> 3001.9313
B9: Weighted lagged GBV | C9: =IF(AND(ISNUMBER(C6),ISNUMBER(C7)),IF(AND(C6>0,C7>0),C8*C6+(1-C8)*C7,"n.a."),"n.a.") -> 27866.667 | D9: =IF(AND(ISNUMBER(D6),ISNUMBER(D7)),IF(AND(D6>0,D7>0),D8*D6+(1-D8)*D7,"n.a."),"n.a.") -> 26405.704 | E9: =IF(AND(ISNUMBER(E6),ISNUMBER(E7)),IF(AND(E6>0,E7>0),E8*E6+(1-E8)*E7,"n.a."),"n.a.") -> 24008.403 | F9: =IF(AND(ISNUMBER(F6),ISNUMBER(F7)),IF(AND(F6>0,F7>0),F8*F6+(1-F8)*F7,"n.a."),"n.a.") -> 29285.681 | H9: 2027Q2 | I9: =F11 -> 4048.3953 | J9: =F13 -> 3977.1842
B10: Conversion lambda | C10: =IF(ISNUMBER(Inputs!C14),Inputs!C14,"n.a.") -> 0.17254891 | D10: =IF(ISNUMBER(Inputs!C15),Inputs!C15,"n.a.") -> 0.12040367 | E10: =IF(ISNUMBER(Inputs!C16),Inputs!C16,"n.a.") -> 0.12727546 | F10: =IF(ISNUMBER(Inputs!C17),Inputs!C17,"n.a.") -> 0.13823805
B11: Revenue forecast | C11: =IF(AND(ISNUMBER(C9),ISNUMBER(C10)),IF(C10>0,C9*C10,"n.a."),"n.a.") -> 4808.3629 | D11: =IF(AND(ISNUMBER(D9),ISNUMBER(D10)),IF(D10>0,D9*D10,"n.a."),"n.a.") -> 3179.3437 | E11: =IF(AND(ISNUMBER(E9),ISNUMBER(E10)),IF(E10>0,E9*E10,"n.a."),"n.a.") -> 3055.6806 | F11: =IF(AND(ISNUMBER(F9),ISNUMBER(F10)),IF(F10>0,F9*F10,"n.a."),"n.a.") -> 4048.3953
B12: Guidance cushion | C12: =IF(ISNUMBER(Inputs!D14),Inputs!D14,"n.a.") -> 0.01790491 | D12: =IF(ISNUMBER(Inputs!D15),Inputs!D15,"n.a.") -> 0.01790491 | E12: =IF(ISNUMBER(Inputs!D16),Inputs!D16,"n.a.") -> 0.01790491 | F12: =IF(ISNUMBER(Inputs!D17),Inputs!D17,"n.a.") -> 0.01790491
B13: Implied guide midpoint | C13: =IF(AND(ISNUMBER(C11),ISNUMBER(C12)),IF(C12>-1,C11/(1+C12),"n.a."),"n.a.") -> 4723.784 | D13: =IF(AND(ISNUMBER(D11),ISNUMBER(D12)),IF(D12>-1,D11/(1+D12),"n.a."),"n.a.") -> 3123.4191 | E13: =IF(AND(ISNUMBER(E11),ISNUMBER(E12)),IF(E12>-1,E11/(1+E12),"n.a."),"n.a.") -> 3001.9313 | F13: =IF(AND(ISNUMBER(F11),ISNUMBER(F12)),IF(F12>-1,F11/(1+F12),"n.a."),"n.a.") -> 3977.1842
B14: Guide status | C14: Already issued | D14: Conditional | E14: Conditional | F14: Conditional
B16: Street revenue | C16: =IF(ISNUMBER(Inputs!C24),Inputs!C24,"n.a.") -> 4744.8819 | D16: =IF(ISNUMBER(Inputs!C25),Inputs!C25,"n.a.") -> 3161.0215 | E16: =IF(ISNUMBER(Inputs!C26),Inputs!C26,"n.a.") -> n.a. | F16: =IF(ISNUMBER(Inputs!C27),Inputs!C27,"n.a.") -> n.a.
B17: Assumed Street cushion | C17: =IF(ISNUMBER(Inputs!C53),Inputs!C53,"n.a.") -> 0.01790491 | D17: =IF(ISNUMBER(Inputs!C54),Inputs!C54,"n.a.") -> 0.01790491 | E17: =IF(ISNUMBER(Inputs!C55),Inputs!C55,"n.a.") -> 0.01790491 | F17: =IF(ISNUMBER(Inputs!C56),Inputs!C56,"n.a.") -> 0.01790491
B18: Implied Street guide proxy | C18: ="Already issued" -> Already issued | D18: =IF(AND(ISNUMBER(D16),ISNUMBER(D17)),IF(D17>-1,D16/(1+D17),"n.a."),"n.a.") -> 3105.4192 | E18: =IF(AND(ISNUMBER(E16),ISNUMBER(E17)),IF(E17>-1,E16/(1+E17),"n.a."),"n.a.") -> n.a. | F18: =IF(AND(ISNUMBER(F16),ISNUMBER(F17)),IF(F17>-1,F16/(1+F17),"n.a."),"n.a.") -> n.a.
B19: Guide gap to proxy ($m) | C19: =IF(AND(ISNUMBER(C13),ISNUMBER(C18)),C13-C18,"n.a.") -> n.a. | D19: =IF(AND(ISNUMBER(D13),ISNUMBER(D18)),D13-D18,"n.a.") -> 17.999878 | E19: =IF(AND(ISNUMBER(E13),ISNUMBER(E18)),E13-E18,"n.a.") -> n.a. | F19: =IF(AND(ISNUMBER(F13),ISNUMBER(F18)),F13-F18,"n.a.") -> n.a.
B20: Guide gap to proxy (%) | C20: =IF(AND(ISNUMBER(C13),ISNUMBER(C18)),IF(C18>0,C13/C18-1,"n.a."),"n.a.") -> n.a. | D20: =IF(AND(ISNUMBER(D13),ISNUMBER(D18)),IF(D18>0,D13/D18-1,"n.a."),"n.a.") -> 0.0057962796 | E20: =IF(AND(ISNUMBER(E13),ISNUMBER(E18)),IF(E18>0,E13/E18-1,"n.a."),"n.a.") -> n.a. | F20: =IF(AND(ISNUMBER(F13),ISNUMBER(F18)),IF(F18>0,F13/F18-1,"n.a."),"n.a.") -> n.a.
B21: Direct guide expectation | C21: ="Already issued" -> Already issued | D21: =IF(ISNUMBER(Inputs!D25),Inputs!D25,"n.a.") -> n.a. | E21: =IF(ISNUMBER(Inputs!D26),Inputs!D26,"n.a.") -> n.a. | F21: =IF(ISNUMBER(Inputs!D27),Inputs!D27,"n.a.") -> n.a.
B22: Gap to direct guide ($m) | C22: =IF(AND(ISNUMBER(C13),ISNUMBER(C21)),C13-C21,"n.a.") -> n.a. | D22: =IF(AND(ISNUMBER(D13),ISNUMBER(D21)),D13-D21,"n.a.") -> n.a. | E22: =IF(AND(ISNUMBER(E13),ISNUMBER(E21)),E13-E21,"n.a.") -> n.a. | F22: =IF(AND(ISNUMBER(F13),ISNUMBER(F21)),F13-F21,"n.a.") -> n.a.
B24: Break-even lambda* | C24: =IF(AND(ISNUMBER(C16),ISNUMBER(C9)),C16/C9,"n.a.") -> 0.17027088 | D24: =IF(AND(ISNUMBER(D16),ISNUMBER(D9)),D16/D9,"n.a.") -> 0.1197098 | E24: =IF(AND(ISNUMBER(E16),ISNUMBER(E9)),E16/E9,"n.a.") -> n.a. | F24: =IF(AND(ISNUMBER(F16),ISNUMBER(F9)),F16/F9,"n.a.") -> n.a.
B25: Lambda change (bp)* | C25: =IF(AND(ISNUMBER(C24),ISNUMBER(C10)),(C24-C10)*10000,"n.a.") -> -22.780285 | D25: =IF(AND(ISNUMBER(D24),ISNUMBER(D10)),(D24-D10)*10000,"n.a.") -> -6.9387146 | E25: =IF(AND(ISNUMBER(E24),ISNUMBER(E10)),(E24-E10)*10000,"n.a.") -> n.a. | F25: =IF(AND(ISNUMBER(F24),ISNUMBER(F10)),(F24-F10)*10000,"n.a.") -> n.a.
B26: Break-even recent GBV* | C26: =IF(AND(ISNUMBER(C16),ISNUMBER(C10),ISNUMBER(C7)),IF(AND(C10>0,C7>0),(C16/C10-(1-C8)*C7)/C8,"n.a."),"n.a.") -> 26648.147 | D26: =IF(AND(ISNUMBER(D16),ISNUMBER(D10),ISNUMBER(D7)),IF(AND(D10>0,D7>0),(D16/D10-(1-D8)*D7)/D8,"n.a."),"n.a.") -> 25780.297 | E26: =IF(AND(ISNUMBER(E16),ISNUMBER(E10),ISNUMBER(E7)),IF(AND(E10>0,E7>0),(E16/E10-(1-E8)*E7)/E8,"n.a."),"n.a.") -> n.a. | F26: =IF(AND(ISNUMBER(F16),ISNUMBER(F10),ISNUMBER(F7)),IF(AND(F10>0,F7>0),(F16/F10-(1-F8)*F7)/F8,"n.a."),"n.a.") -> n.a.
B27: Recent GBV change (%)* | C27: =IF(AND(ISNUMBER(C26),ISNUMBER(C6)),IF(C6>0,C26/C6-1,"n.a."),"n.a.") -> -0.020288704 | D27: =IF(AND(ISNUMBER(D26),ISNUMBER(D6)),IF(D6>0,D26/D6-1,"n.a."),"n.a.") -> -0.0087763123 | E27: =IF(AND(ISNUMBER(E26),ISNUMBER(E6)),IF(E6>0,E26/E6-1,"n.a."),"n.a.") -> n.a. | F27: =IF(AND(ISNUMBER(F26),ISNUMBER(F6)),IF(F6>0,F26/F6-1,"n.a."),"n.a.") -> n.a.
B29: *Break-even ratios hold our other inputs fixed and equate model revenue with Street revenue. They are not observed Street GBV/conversion forecasts. A common cushion cancels from the relative guide gap. Q3 guide output is a diagnostic, never a future surprise.
B34: Q4 guide sensitivity | lambda change (basis points) across columns
B35: Q3 GBV change | C35: -20 | D35: -10 | E35: 0 | F35: 10 | G35: 20
B36: -0.04 | C36: =IF(AND(ISNUMBER($D$6),ISNUMBER($D$7),ISNUMBER($D$10),ISNUMBER($D$12)),IF(AND($D$6>0,$D$7>0,$D$10+C$35/10000>0,$D$12>-1),(($D$6*(1+$B36)*$D$8+$D$7*(1-$D$8))*($D$10+C$35/10000))/(1+$D$12),"n.a."),"n.a.") -> 2990.8609 | D36: =IF(AND(ISNUMBER($D$6),ISNUMBER($D$7),ISNUMBER($D$10),ISNUMBER($D$12)),IF(AND($D$6>0,$D$7>0,$D$10+D$35/10000>0,$D$12>-1),(($D$6*(1+$B36)*$D$8+$D$7*(1-$D$8))*($D$10+D$35/10000))/(1+$D$12),"n.a."),"n.a.") -> 3016.1208 | E36: =IF(AND(ISNUMBER($D$6),ISNUMBER($D$7),ISNUMBER($D$10),ISNUMBER($D$12)),IF(AND($D$6>0,$D$7>0,$D$10+E$35/10000>0,$D$12>-1),(($D$6*(1+$B36)*$D$8+$D$7*(1-$D$8))*($D$10+E$35/10000))/(1+$D$12),"n.a."),"n.a.") -> 3041.3807 | F36: =IF(AND(ISNUMBER($D$6),ISNUMBER($D$7),ISNUMBER($D$10),ISNUMBER($D$12)),IF(AND($D$6>0,$D$7>0,$D$10+F$35/10000>0,$D$12>-1),(($D$6*(1+$B36)*$D$8+$D$7*(1-$D$8))*($D$10+F$35/10000))/(1+$D$12),"n.a."),"n.a.") -> 3066.6405 | G36: =IF(AND(ISNUMBER($D$6),ISNUMBER($D$7),ISNUMBER($D$10),ISNUMBER($D$12)),IF(AND($D$6>0,$D$7>0,$D$10+G$35/10000>0,$D$12>-1),(($D$6*(1+$B36)*$D$8+$D$7*(1-$D$8))*($D$10+G$35/10000))/(1+$D$12),"n.a."),"n.a.") -> 3091.9004
B37: -0.02 | C37: =IF(AND(ISNUMBER($D$6),ISNUMBER($D$7),ISNUMBER($D$10),ISNUMBER($D$12)),IF(AND($D$6>0,$D$7>0,$D$10+C$35/10000>0,$D$12>-1),(($D$6*(1+$B37)*$D$8+$D$7*(1-$D$8))*($D$10+C$35/10000))/(1+$D$12),"n.a."),"n.a.") -> 3031.1988 | D37: =IF(AND(ISNUMBER($D$6),ISNUMBER($D$7),ISNUMBER($D$10),ISNUMBER($D$12)),IF(AND($D$6>0,$D$7>0,$D$10+D$35/10000>0,$D$12>-1),(($D$6*(1+$B37)*$D$8+$D$7*(1-$D$8))*($D$10+D$35/10000))/(1+$D$12),"n.a."),"n.a.") -> 3056.7993 | E37: =IF(AND(ISNUMBER($D$6),ISNUMBER($D$7),ISNUMBER($D$10),ISNUMBER($D$12)),IF(AND($D$6>0,$D$7>0,$D$10+E$35/10000>0,$D$12>-1),(($D$6*(1+$B37)*$D$8+$D$7*(1-$D$8))*($D$10+E$35/10000))/(1+$D$12),"n.a."),"n.a.") -> 3082.3999 | F37: =IF(AND(ISNUMBER($D$6),ISNUMBER($D$7),ISNUMBER($D$10),ISNUMBER($D$12)),IF(AND($D$6>0,$D$7>0,$D$10+F$35/10000>0,$D$12>-1),(($D$6*(1+$B37)*$D$8+$D$7*(1-$D$8))*($D$10+F$35/10000))/(1+$D$12),"n.a."),"n.a.") -> 3108.0004 | G37: =IF(AND(ISNUMBER($D$6),ISNUMBER($D$7),ISNUMBER($D$10),ISNUMBER($D$12)),IF(AND($D$6>0,$D$7>0,$D$10+G$35/10000>0,$D$12>-1),(($D$6*(1+$B37)*$D$8+$D$7*(1-$D$8))*($D$10+G$35/10000))/(1+$D$12),"n.a."),"n.a.") -> 3133.601
B38: 0 | C38: =IF(AND(ISNUMBER($D$6),ISNUMBER($D$7),ISNUMBER($D$10),ISNUMBER($D$12)),IF(AND($D$6>0,$D$7>0,$D$10+C$35/10000>0,$D$12>-1),(($D$6*(1+$B38)*$D$8+$D$7*(1-$D$8))*($D$10+C$35/10000))/(1+$D$12),"n.a."),"n.a.") -> 3071.5367 | D38: =IF(AND(ISNUMBER($D$6),ISNUMBER($D$7),ISNUMBER($D$10),ISNUMBER($D$12)),IF(AND($D$6>0,$D$7>0,$D$10+D$35/10000>0,$D$12>-1),(($D$6*(1+$B38)*$D$8+$D$7*(1-$D$8))*($D$10+D$35/10000))/(1+$D$12),"n.a."),"n.a.") -> 3097.4779 | E38: =IF(AND(ISNUMBER($D$6),ISNUMBER($D$7),ISNUMBER($D$10),ISNUMBER($D$12)),IF(AND($D$6>0,$D$7>0,$D$10+E$35/10000>0,$D$12>-1),(($D$6*(1+$B38)*$D$8+$D$7*(1-$D$8))*($D$10+E$35/10000))/(1+$D$12),"n.a."),"n.a.") -> 3123.4191 | F38: =IF(AND(ISNUMBER($D$6),ISNUMBER($D$7),ISNUMBER($D$10),ISNUMBER($D$12)),IF(AND($D$6>0,$D$7>0,$D$10+F$35/10000>0,$D$12>-1),(($D$6*(1+$B38)*$D$8+$D$7*(1-$D$8))*($D$10+F$35/10000))/(1+$D$12),"n.a."),"n.a.") -> 3149.3603 | G38: =IF(AND(ISNUMBER($D$6),ISNUMBER($D$7),ISNUMBER($D$10),ISNUMBER($D$12)),IF(AND($D$6>0,$D$7>0,$D$10+G$35/10000>0,$D$12>-1),(($D$6*(1+$B38)*$D$8+$D$7*(1-$D$8))*($D$10+G$35/10000))/(1+$D$12),"n.a."),"n.a.") -> 3175.3016
B39: 0.02 | C39: =IF(AND(ISNUMBER($D$6),ISNUMBER($D$7),ISNUMBER($D$10),ISNUMBER($D$12)),IF(AND($D$6>0,$D$7>0,$D$10+C$35/10000>0,$D$12>-1),(($D$6*(1+$B39)*$D$8+$D$7*(1-$D$8))*($D$10+C$35/10000))/(1+$D$12),"n.a."),"n.a.") -> 3111.8745 | D39: =IF(AND(ISNUMBER($D$6),ISNUMBER($D$7),ISNUMBER($D$10),ISNUMBER($D$12)),IF(AND($D$6>0,$D$7>0,$D$10+D$35/10000>0,$D$12>-1),(($D$6*(1+$B39)*$D$8+$D$7*(1-$D$8))*($D$10+D$35/10000))/(1+$D$12),"n.a."),"n.a.") -> 3138.1564 | E39: =IF(AND(ISNUMBER($D$6),ISNUMBER($D$7),ISNUMBER($D$10),ISNUMBER($D$12)),IF(AND($D$6>0,$D$7>0,$D$10+E$35/10000>0,$D$12>-1),(($D$6*(1+$B39)*$D$8+$D$7*(1-$D$8))*($D$10+E$35/10000))/(1+$D$12),"n.a."),"n.a.") -> 3164.4383 | F39: =IF(AND(ISNUMBER($D$6),ISNUMBER($D$7),ISNUMBER($D$10),ISNUMBER($D$12)),IF(AND($D$6>0,$D$7>0,$D$10+F$35/10000>0,$D$12>-1),(($D$6*(1+$B39)*$D$8+$D$7*(1-$D$8))*($D$10+F$35/10000))/(1+$D$12),"n.a."),"n.a.") -> 3190.7203 | G39: =IF(AND(ISNUMBER($D$6),ISNUMBER($D$7),ISNUMBER($D$10),ISNUMBER($D$12)),IF(AND($D$6>0,$D$7>0,$D$10+G$35/10000>0,$D$12>-1),(($D$6*(1+$B39)*$D$8+$D$7*(1-$D$8))*($D$10+G$35/10000))/(1+$D$12),"n.a."),"n.a.") -> 3217.0022
B40: 0.04 | C40: =IF(AND(ISNUMBER($D$6),ISNUMBER($D$7),ISNUMBER($D$10),ISNUMBER($D$12)),IF(AND($D$6>0,$D$7>0,$D$10+C$35/10000>0,$D$12>-1),(($D$6*(1+$B40)*$D$8+$D$7*(1-$D$8))*($D$10+C$35/10000))/(1+$D$12),"n.a."),"n.a.") -> 3152.2124 | D40: =IF(AND(ISNUMBER($D$6),ISNUMBER($D$7),ISNUMBER($D$10),ISNUMBER($D$12)),IF(AND($D$6>0,$D$7>0,$D$10+D$35/10000>0,$D$12>-1),(($D$6*(1+$B40)*$D$8+$D$7*(1-$D$8))*($D$10+D$35/10000))/(1+$D$12),"n.a."),"n.a.") -> 3178.835 | E40: =IF(AND(ISNUMBER($D$6),ISNUMBER($D$7),ISNUMBER($D$10),ISNUMBER($D$12)),IF(AND($D$6>0,$D$7>0,$D$10+E$35/10000>0,$D$12>-1),(($D$6*(1+$B40)*$D$8+$D$7*(1-$D$8))*($D$10+E$35/10000))/(1+$D$12),"n.a."),"n.a.") -> 3205.4576 | F40: =IF(AND(ISNUMBER($D$6),ISNUMBER($D$7),ISNUMBER($D$10),ISNUMBER($D$12)),IF(AND($D$6>0,$D$7>0,$D$10+F$35/10000>0,$D$12>-1),(($D$6*(1+$B40)*$D$8+$D$7*(1-$D$8))*($D$10+F$35/10000))/(1+$D$12),"n.a."),"n.a.") -> 3232.0802 | G40: =IF(AND(ISNUMBER($D$6),ISNUMBER($D$7),ISNUMBER($D$10),ISNUMBER($D$12)),IF(AND($D$6>0,$D$7>0,$D$10+G$35/10000>0,$D$12>-1),(($D$6*(1+$B40)*$D$8+$D$7*(1-$D$8))*($D$10+G$35/10000))/(1+$D$12),"n.a."),"n.a.") -> 3258.7028
B42: Sensitivity values are conditional guide levels, not forecasts with assigned probabilities. GBV and conversion can move together. RNPL could affect booking timing, cancellations or conversion; without identified incremental data, adding another haircut would double-count an assumption.

Sheet Inputs
B2: Model inputs | one conditional working path
B3: Blue values are editable. Green cells link to another sheet. USD millions unless stated.
B5: GBV quarter | C5: GBV $m | D5: Input status | E5: Available by | F5: Lineage / limitation
B6: 2026Q1 | C6: 29200 | D6: Reported, original rounded convention | E6: 2026-05-07 | F6: Exact filing comparison shown separately
B7: 2026Q2 | C7: 27200 | D7: Reported, original rounded convention | E7: 2026-08-06 | F7: Exact filing comparison shown separately
B8: 2026Q3 | C8: 26008.556 | D8: Conditional GBV assumption | E8: 2026-09-13 | F8: Originally component-derived; shared-input uncertainty
B9: 2026Q4 | C9: 23008.326 | D9: Conditional GBV assumption | E9: 2026-09-13 | F9: Originally component-derived; shared-input uncertainty
B10: 2027Q1 | C10: 32424.358 | D10: Conditional GBV assumption | E10: 2026-09-13 | F10: Not a validated Q1 GBV forecast
B13: Target | C13: Conversion lambda | D13: Cushion | E13: Lambda n | F13: Last lambda observation
B14: 2026Q3 | C14: 0.17254891 | D14: 0.01790491 | E14: 5 | F14: 2025-11-06
B15: 2026Q4 | C15: 0.12040367 | D15: 0.01790491 | E15: 5 | F15: 2026-02-12
B16: 2027Q1 | C16: 0.12727546 | D16: 0.01790491 | E16: 6 | F16: 2026-05-07
B17: 2027Q2 | C17: 0.13823805 | D17: 0.01790491 | E17: 6 | F17: 2026-08-06
B19: Lambda is a revenue / weighted-lag-GBV ratio, not a commission take rate. Weights are a fixed empirical mapping, not literal booking-cohort shares. Cushion = revenue / issued guide - 1. Eight realized quarters supply the inherited median.
B23: Quarter | C23: Street revenue | D23: Direct guide expectation | E23: Observed at (UTC) | F23: Named source
B24: 2026Q3 | C24: 4744.8819 | E24: 2026-09-13T15:20Z | F24: Yahoo Finance (LSEG family)
B25: 2026Q4 | C25: 3161.0215 | E25: 2026-09-13T15:20Z | F25: Yahoo Finance (LSEG family)
B26: 2027Q1 | F26: Unavailable; no vendor substitution
B27: 2027Q2 | F27: Unavailable; no vendor substitution
B29: Direct guide expectations are unobserved. If an admissible direct estimate is entered, add its vendor and timestamp here before using it. Q1/Q2 2027 Street revenue remains unavailable; do not split annual estimates.
B33: Observed Q3 guide | C33: USDm | D33: Disclosure date
B34: Low | C34: 4690 | D34: 2026-08-06
B35: Midpoint | C35: 4730 | D35: 2026-08-06
B36: High | C36: 4770 | D36: 2026-08-06
B39: Precision check: change the GBV inputs only, not lambda
B40: Quarter | C40: Exact-input revenue | D40: Delta from rounded | E40: Scope
B41: 2026Q3 | C41: 4813.0218 | D41: 4.6588205 | E41: Frozen lambda; SEC GBV 29,187 / 27,247
B42: 2026Q4 | C42: 3181.23 | D42: 1.8863242 | E42: Frozen lambda; SEC GBV 29,187 / 27,247
B43: 2027Q1 | C43: 3055.6806 | D43: 0 | E43: Frozen lambda; SEC GBV 29,187 / 27,247
B44: 2027Q2 | C44: 4048.3953 | D44: 0 | E44: Frozen lambda; SEC GBV 29,187 / 27,247
B47: The current GBV assumptions inherit the prior L4 working case, including inputs originally derived from the component track. This is a shared input dependency, not independent confirmation. Q1 2027 GBV is an assumption needed for the explicit Q2 conversion. No second RNPL, fee or FX haircut is added.
B52: Target | C52: Street cushion assumption | D52: Convention
B53: 2026Q3 | C53: 0.01790491 | D53: Common at default; independently editable
B54: 2026Q4 | C54: 0.01790491 | D54: Common at default; independently editable
B55: 2027Q1 | C55: 0.01790491 | D55: Common at default; independently editable
B56: 2027Q2 | C56: 0.01790491 | D56: Common at default; independently editable
B58: The Street cushion is an assumption, not observed guide expectations. It starts equal to our cushion. Editing our cushion alone holds this benchmark fixed; shared-cushion cancellation applies only when both use the same value. Historical audit figures remain frozen.

Sheet Forecast audit
B2: Forecast risk | fixed earlier-origin replay
B3: W1 and W2 are nested. Historical analysis is already explored; these results are not a new holdout.
B5: Guide RMSE, $m | C5: W1 (n=12) | D5: W2 (n=10) | E5: Interpretation
B6: GBV conversion candidate | C6: 63.444678 | D6: 63.696189 | E6: Promotion hurdle failed
B7: Guide-growth baseline | C7: 74.330786 | D7: 60.834441 | E7: Same target rows
B8: Revenue-naive + cushion | C8: 117.30903 | D8: 121.92589 | E8: Same target rows
B10: Scores use the project midpoint +/- $0.5m convention. Raw candidate RMSE is $63.9m / $64.1m. Candidate does not beat the guide-growth baseline in W2 and fails deletion robustness. Historical origins were roughly 48-62 days before the guide; this is not a calibrated Q1/Q2 2027 risk band.
B15: Variance, USDm squared | C15: W1 | D15: W2
B16: GBV input | C16: 3714.1363 | D16: 4130.9404
B17: Conversion | C17: 2202.1253 | D17: 2556.5336
B18: Cushion | C18: 909.26377 | D18: 1072.2191
B19: Covariance contribution | C19: -2798.2733 | D19: -3662.6743
B20: Reconciled total | C20: =SUM(C16:C19) -> 4027.2521 | D20: =SUM(D16:D19) -> 4097.0188
B22: Exact symmetric (Shapley) attribution sums to raw guide error. Standalone factor variance cannot be added without covariance. The exact cells reconcile the W1 diagonal and covariance terms to 4,027.3 USDm squared. Observed population SD is $63.5m; independence would imply $82.6m. This ex-post decomposition explains historical error, not available trading features.
B27: Replacing only unknown GBV with realized GBV lowers raw guide RMSE to $36.4m / $38.7m. That is an oracle diagnostic, not a tradable strategy. Two events account for 51% / 61% of squared error; small samples and influential events prevent stable promotion. No new optimized predictor was fitted.
B34: Target quarter | C34: GBV effect | D34: Conversion effect | E34: Cushion effect | F34: Raw guide error
B35: 2023Q2 | C35: 13.192818 | D35: 15.451656 | E35: 3.0464342 | F35: 31.690908
B36: 2023Q4 | C36: -59.34154 | D36: -19.142362 | E36: -4.2219805 | F36: -82.705882
B37: 2024Q1 | C37: 27.98837 | D37: -37.015161 | E37: 36.850076 | F37: 27.823285
B38: 2024Q2 | C38: 46.462362 | D38: 64.504333 | E38: -30.566144 | F38: 80.400552
B39: 2024Q3 | C39: 27.246121 | D39: 52.698124 | E39: -60.939075 | F39: 19.00517
B40: 2024Q4 | C40: 16.537767 | D40: -45.053542 | E40: 3.6538717 | F40: -24.861903
B41: 2025Q1 | C41: -47.590074 | D41: 106.35656 | E41: -33.986141 | F41: 24.780346
B42: 2025Q2 | C42: 135.04181 | D42: -63.086198 | E42: 7.3647203 | F42: 79.32033
B43: 2025Q3 | C43: -92.677404 | D43: 20.045839 | E43: -46.729603 | F43: -119.36117
B44: 2025Q4 | C44: -48.272232 | D44: -13.114405 | E44: 34.211189 | F44: -27.175448
B45: 2026Q1 | C45: -28.752518 | D45: 22.439728 | E45: 16.516368 | F45: 10.203579
B46: 2026Q2 | C46: -72.364976 | D46: -0.89837336 | E46: -31.013073 | F46: -104.27642
B49: Historical outputs stay frozen when working inputs change.
B51: Validation boundary: this earlier-origin replay used the frozen ex-COVID conversion variant. The current working four-quarter case inherits seasonal EWM conversion. The replay identifies method risks and failed promotion; its error statistics are not a direct backtest or calibrated interval for the current EWM case.

Sheet Event study
B2: Earnings reactions | association, not a price law
B3: 23 events / 20 numeric forward guides / 16 raw comparison proxies / 15 implied-guide proxies.
B5: All-event association | C5: n | D5: Pearson r | E5: Slope | F5: 95% low | G5: 95% high | I5: Raw proxy % | J5: Excess gap % | K5: Excess session %
B6: Raw proxy: gap | C6: 16 | D6: 0.3244505 | E6: 1.1166659 | F6: -0.96626333 | G6: 3.1995951 | I6: 2.166065 | J6: -7.5224394 | K6: 4.1143616
B7: Raw proxy: session | C7: 16 | D7: 0.30990864 | E7: 0.51377374 | F7: -0.29367767 | G7: 1.3212252 | I7: -0.54054054 | J7: -5.862554 | K7: -4.6056048
B8: Implied proxy: gap | C8: 15 | D8: 0.28675596 | E8: 0.97369998 | F8: -1.0428821 | G8: 2.990282 | I8: 5.6213018 | J8: 8.1566665 | K8: 4.0147986
B9: Implied proxy: session | C9: 15 | D9: 0.20801373 | E9: 0.33613938 | F9: -0.35910628 | G9: 1.031385 | I9: -0.82644628 | J9: -14.322629 | K9: 2.7258091
I10: 4.0372671 | J10: -0.81538671 | K10: 0.77378544
B11: Slope units: percentage points of excess stock return per 1 percentage point of comparison proxy. All 12 primary Holm-adjusted p-values are 1.0. Intervals include zero; leave-event/year results are unstable. This does not prove no relationship; it means this panel has not established a reliable trading response. | I11: -1.3761468 | J11: 1.2615109 | K11: -6.2475115
I12: 0.98522167 | J12: -3.7221483 | K12: 0.94124585
I13: -1.0948905 | J13: -7.2177734 | K13: 0.1502544
I14: -0.20661157 | J14: -8.5203996 | K14: -0.25896692
I15: -2.173913 | J15: 12.135606 | K15: 1.6458252
I16: -0.65789474 | J16: -3.3555598 | K16: 2.9645147
I17: 0.24691358 | J17: -8.5215501 | K17: 0.13432443
I18: 0.74906367 | J18: 4.6686232 | K18: -3.912518
I19: 3.1620553 | J19: 9.0941224 | K19: -4.2927496
I20: 3.1791908 | J20: -2.3790055 | K20: 0.82030442
I21: 2.6030369 | J21: 7.8428942 | K21: 7.717879
B36: Entry method | C36: Signal available | D36: What can be measured | E36: Current verdict
B37: Before release | C37: Earlier GBV/conversion forecast + contemporaneous expectations | D37: Origin-to-exit return, including intervening exposure | E37: No promoted edge; sparse matched history
B38: Next regular open | C38: Published guide comparison; other release news already known | D38: Next open-to-close or explicitly chosen later exit | E38: Gap is already completed; association is insufficient
B39: During release / call | C39: Timestamped guide/news and executable quote | D39: Release-to-call and call legs with costs | E39: Unavailable: no verified intraday panel
B42: The original proxy compares an issued guide with expected realized revenue. The adjusted proxy assumes a historical common cushion; it is not observed guide expectations. In the earlier-origin model comparison, the shared cushion cancels exactly, so the relative signal is the same as candidate revenue / origin Street revenue - 1. No causal call attribution or calibrated stock-price target is assigned.
B48: Reported quarter | C48: Excess gap % | D48: Excess session %
B49: ='Event data'!B6 -> 2020Q4 | C49: ='Event data'!M6 -> 5.6917566 | D49: ='Event data'!N6 -> 6.8087814
B50: ='Event data'!B7 -> 2021Q1 | C50: ='Event data'!M7 -> 0.40086714 | D50: ='Event data'!N7 -> 1.3818242
B51: ='Event data'!B8 -> 2021Q2 | C51: ='Event data'!M8 -> -3.0685082 | D51: ='Event data'!N8 -> 3.9064827
B52: ='Event data'!B9 -> 2021Q3 | C52: ='Event data'!M9 -> 3.8578969 | D52: ='Event data'!N9 -> 8.6704678
B53: ='Event data'!B10 -> 2021Q4 | C53: ='Event data'!M10 -> -0.33709397 | D53: ='Event data'!N10 -> 4.053008
B54: ='Event data'!B11 -> 2022Q1 | C54: ='Event data'!M11 -> 5.05321 | D54: ='Event data'!N11 -> -0.84303554
B55: ='Event data'!B12 -> 2022Q2 | C55: ='Event data'!M12 -> -7.5224394 | D55: ='Event data'!N12 -> 4.1143616
B56: ='Event data'!B13 -> 2022Q3 | C56: ='Event data'!M13 -> -5.862554 | D56: ='Event data'!N13 -> -4.6056048
B57: ='Event data'!B14 -> 2022Q4 | C57: ='Event data'!M14 -> 8.1566665 | D57: ='Event data'!N14 -> 4.0147986
B58: ='Event data'!B15 -> 2023Q1 | C58: ='Event data'!M15 -> -14.322629 | D58: ='Event data'!N15 -> 2.7258091
B59: ='Event data'!B16 -> 2023Q2 | C59: ='Event data'!M16 -> -0.81538671 | D59: ='Event data'!N16 -> 0.77378544
B60: ='Event data'!B17 -> 2023Q3 | C60: ='Event data'!M17 -> 1.2615109 | D60: ='Event data'!N17 -> -6.2475115
... B71: ='Event data'!B28 -> 2026Q2 | C71: ='Event data'!M28 -> 7.8428942 | D71: ='Event data'!N28 -> 7.717879

Sheet Event data
B2: Earnings data | all 23 events
B3: Daily raw ABNB and QQQ OHLC; gap = pre-release close to next open; session = next open to close.
B5: Reported quarter | C5: Release date | D5: Guided quarter | E5: Issued guide $m | F5: Revenue Street $m | G5: Guide / revenue proxy % | H5: Guide / implied proxy % | I5: ABNB gap % | J5: ABNB session % | K5: QQQ gap % | L5: QQQ session % | M5: Excess gap % | N5: Excess session % | O5: Excess close-close % | P5: Vendor | Q5: Consensus timestamp | R5: Eligibility
B6: 2020Q4 | C6: 2021-02-25 | I6: 6.6571434 | J6: 6.2673879 | K6: 0.96538684 | L6: -0.54139352 | M6: 5.6917566 | N6: 6.8087814 | O6: 12.922994 | R6: no_numeric_forward_guide
B7: 2021Q1 | C7: 2021-05-13 | I7: 1.4217257 | J7: 2.5566563 | K7: 1.0208586 | L7: 1.1748321 | M7: 0.40086714 | N7: 1.3818242 | O7: 1.8070466 | R7: no_numeric_forward_guide
B8: 2021Q2 | C8: 2021-08-12 | I8: -2.9705527 | J8: 4.1592736 | K8: 0.097955506 | L8: 0.25279095 | M8: -3.0685082 | N8: 3.9064827 | O8: 0.71417342 | R8: no_numeric_forward_guide
B9: 2021Q3 | C9: 2021-11-04 | D9: 2021Q4 | E9: 1435 | I9: 4.3149325 | J9: 8.3105032 | K9: 0.45703564 | L9: -0.35996461 | M9: 3.8578969 | N9: 8.6704678 | O9: 12.888602 | R9: quarantined_or_unattributed
B10: 2021Q4 | C10: 2022-02-15 | D10: 2022Q1 | E10: 1445 | I10: -0.98573282 | J10: 4.6804461 | K10: -0.64863885 | L10: 0.62743801 | M10: -0.33709397 | N10: 4.053008 | O10: 3.6738472 | R10: quarantined_or_unattributed
B11: 2022Q1 | C11: 2022-05-03 | D11: 2022Q2 | E11: 2080 | I11: 5.2068987 | J11: 2.3795408 | K11: 0.15368867 | L11: 3.2225764 | M11: 5.05321 | N11: -0.84303554 | O11: 4.329122 | R11: quarantined_or_unattributed
B12: 2022Q2 | C12: 2022-08-02 | D12: 2022Q3 | E12: 2830 | F12: 2770 | G12: 2.166065 | I12: -6.9752434 | J12: 6.2785847 | K12: 0.54719603 | L12: 2.1642231 | M12: -7.5224394 | N12: 4.1143616 | O12: -3.8578669 | P12: StreetAccount | Q12: 2022-08-02 | R12: eligible_original:date_only_morning_convention
B13: 2022Q3 | C13: 2022-11-01 | D13: 2022Q4 | E13: 1840 | F13: 1850 | G13: -0.54054054 | H13: 3.8645843 | I13: -5.8734583 | J13: -8.0227904 | K13: -0.010904286 | L13: -3.4171857 | M13: -5.862554 | N13: -4.6056048 | O13: -9.9973161 | P13: Refinitiv | Q13: 2022-11-01 | R13: eligible_original:date_only_morning_convention
B14: 2022Q4 | C14: 2023-02-14 | D14: 2023Q1 | E14: 1785 | F14: 1690 | G14: 5.6213018 | H14: 8.9680146 | I14: 7.5535675 | J14: 5.3923035 | K14: -0.60309897 | L14: 1.3775049 | M14: 8.1566665 | N14: 4.0147986 | O14: 12.587084 | P14: Refinitiv | Q14: 2023-02-14 | R14: eligible_original:date_only_morning_convention
B15: 2023Q1 | C15: 2023-05-09 | D15: 2023Q2 | E15: 2400 | F15: 2420 | G15: -0.82644628 | H15: 2.5152713 | I15: -13.551587 | J15: 3.0405134 | K15: 0.77104227 | L15: 0.31470429 | M15: -14.322629 | N15: 2.7258091 | O15: -12.011284 | P15: Refinitiv | Q15: 2023-05-09 | R15: eligible_original:date_only_morning_convention
B16: 2023Q2 | C16: 2023-08-03 | D16: 2023Q3 | E16: 3350 | F16: 3220 | G16: 4.0372671 | H16: 6.7826506 | I16: -0.29103041 | J16: -0.2135709 | K16: 0.5243563 | L16: -0.98735634 | M16: -0.81538671 | N16: 0.77378544 | O16: -0.035802454 | P16: Refinitiv | Q16: 2023-08-03 | R16: eligible_original:date_only_morning_convention
B17: 2023Q3 | C17: 2023-11-01 | D17: 2023Q4 | E17: 2150 | F17: 2180 | G17: -1.3761468 | H17: 1.9470483 | I17: 2.5445726 | J17: -5.7219835 | K17: 1.2830617 | L17: 0.52552798 | M17: 1.2615109 | N17: -6.2475115 | O17: -5.1383435 | P17: LSEG | Q17: 2023-11-01 | R17: eligible_original:date_only_morning_convention
B18: 2023Q4 | C18: 2024-02-13 | D18: 2024Q1 | E18: 2050 | F18: 2030 | G18: 0.98522167 | H18: 3.6500664 | I18: -3.0897782 | J18: 1.3957261 | K18: 0.6323701 | L18: 0.45448022 | M18: -3.7221483 | N18: 0.94124585 | O18: -2.8269012 | P18: LSEG | Q18: 2024-02-13 | R18: eligible_original:date_only_morning_convention
B19: 2024Q1 | C19: 2024-05-08 | D19: 2024Q2 | E19: 2710 | F19: 2740 | G19: -1.0948905 | H19: 1.4128079 | I19: -7.1564207 | J19: 0.30695561 | K19: 0.061352773 | L19: 0.15670122 | M19: -7.2177734 | N19: 0.1502544 | O19: -7.0895822 | P19: LSEG | Q19: 2024-05-08 | R19: eligible_original:date_only_morning_convention
B20: 2024Q2 | C20: 2024-08-06 | D20: 2024Q3 | E20: 3700 | I20: -13.819268 | J20: 0.50693675 | K20: 1.5835077 | L20: -2.6249191 | M20: -15.402775 | N20: 3.1318559 | O20: -12.299409 | R20: quarantined_or_unattributed
B21: 2024Q3 | C21: 2024-11-07 | D21: 2024Q4 | E21: 2415 | F21: 2420 | G21: -0.20661157 | H21: 2.3236088 | I21: -8.617763 | J21: -0.04455154 | K21: -0.097363403 | L21: 0.21441538 | M21: -8.5203996 | N21: -0.25896692 | O21: -8.7753184 | P21: LSEG | Q21: 2024-11-07 | R21: eligible_original:date_only_morning_convention
B22: 2024Q4 | C22: 2025-02-13 | D22: 2025Q1 | E22: 2250 | F22: 2300 | G22: -2.173913 | H22: 0.2773789 | I22: 12.15613 | J22: 2.0450742 | K22: 0.020523483 | L22: 0.39924901 | M22: 12.135606 | N22: 1.6458252 | O22: 14.029951 | P22: LSEG | Q22: 2025-02-13 | R22: eligible_original:date_only_morning_convention
B23: 2025Q1 | C23: 2025-05-01 | D23: 2025Q2 | E23: 3020 | F23: 3040 | G23: -0.65789474 | H23: 1.5972957 | I23: -2.3465879 | J23: 3.4351806 | K23: 1.0089719 | L23: 0.47066592 | M23: -3.3555598 | N23: 2.9645147 | O23: -0.47640352 | P23: LSEG | Q23: 2025-05-01 | R23: eligible_original:date_only_morning_convention
B24: 2025Q2 | C24: 2025-08-06 | D24: 2025Q3 | E24: 4060 | F24: 4050 | G24: 0.24691358 | H24: 2.2992167 | I24: -7.7547914 | J24: -0.29074471 | K24: 0.76675871 | L24: -0.42506914 | M24: -8.5215501 | N24: 0.13432443 | O24: -8.3614198 | P24: LSEG | Q24: 2025-08-06 | R24: eligible_original:date_only_morning_convention
B25: 2025Q3 | C25: 2025-11-06 | D25: 2025Q4 | E25: 2690 | F25: 2670 | G25: 0.74906367 | H25: 2.7235143 | I25: 4.1193097 | J25: -3.6774416 | K25: -0.54931343 | L25: 0.23507631 | M25: 4.6686232 | N25: -3.912518 | O25: 0.6059113 | P25: LSEG | Q25: 2025-11-06 | R25: eligible_original:date_only_morning_convention
B26: 2025Q4 | C26: 2026-02-12 | D26: 2026Q1 | E26: 2610 | F26: 2530 | G26: 3.1620553 | H26: 5.1833973 | I26: 9.059156 | J26: -4.0445957 | K26: -0.034966364 | L26: 0.24815387 | M26: 9.0941224 | N26: -4.2927496 | O26: 4.4350533 | P26: LSEG | Q26: 2026-02-12 | R26: eligible_original:date_only_morning_convention
B27: 2026Q1 | C27: 2026-05-07 | D27: 2026Q2 | E27: 3570 | F27: 3460 | G27: 3.1791908 | H27: 5.2008685 | I27: -1.6623997 | J27: 2.4362031 | K27: 0.71660582 | L27: 1.6158987 | M27: -2.3790055 | N27: 0.82030442 | O27: -1.6107801 | P27: LSEG | Q27: 2026-05-07 | R27: eligible_original:date_only_morning_convention
B28: 2026Q2 | C28: 2026-08-06 | D28: 2026Q3 | E28: 4730 | F28: 4610 | G28: 2.6030369 | H28: 4.6134256 | I28: 8.6125017 | J28: 8.1177964 | K28: 0.76960747 | L28: 0.39991735 | M28: 7.8428942 | N28: 7.717879 | O28: 16.256841 | P28: LSEG | Q28: 2026-08-06 | R28: eligible_original:date_only_morning_convention
B31: Returns in this sheet are percentage points, not decimal fractions. Excess = ABNB leg minus QQQ leg. Close-close is calculated from each ticker's compounded legs, not the sum of excess gap and excess session. A guide comparison is known only after the release; it cannot be used to earn the completed gap.

Sheet Sources
B2: Sources and audit trail
B3: Source precision is not forecast accuracy. Vendor families are not independent replications.
B5: Item | C5: Coverage / date | D5: Source or path | E5: Interpretation | F5: Status
B6: Q3 issued guide | C6: 6 Aug 2026 | D6: https://www.sec.gov/Archives/edgar/data/1559720/000119312526337928/d70413dex991.htm | E6: $4,690–4,770m; midpoint $4,730m | F6: Observed
B7: Current expectations | C7: 13 Sep 2026 15:20:58 UTC | D7: L0_vintage_register.csv; Yahoo / LSEG-family API | E7: Q3 $4,744.88187m; Q4 $3,161.02149m; n=36 | F7: Revenue estimates
B8: Other vendor panels | C8: 10–13 Sep 2026 | D8: L0 current/pit_history rows, separate vendor families | E8: Zacks/DoltHub one family; S&P separately attributed | F8: No silent mixing
B9: Parameters | C9: Frozen through 13 Sep 2026 | D9: kernel_engine_v2/engine.py; KPI panel; calendar; cushion series | E9: 4 seasonal EWM ratios + 1 cushion; zero new optimized parameters | F9: Inherited estimates
B10: GBV scenario | C10: L4 working case | D10: lane4_revenue_v2/snapshot_v1 + lane4_model_v2/snapshot_v2 | E10: Shared component-derived input ancestry; Q1 GBV assumption | F10: Conditional
B11: Forecast replay | C11: Fixed earlier origins | D11: gbv_event_v1/forecast_v1/results_v1 | E11: 20 frozen CSVs reproduced; 617 strict date checks; leakage poisoning | F11: Promotion failed
B12: Reaction study | C12: run_v3 | D12: gbv_event_v1/events_v1/run_v3 | E12: 23 full events; 16 raw / 15 adjusted proxies; 12 primary tests | F12: Descriptive
B13: Daily price provenance | C13: Retrieved 13 Sep; through 11 Sep | D13: returns_v1/ohlc_daily.csv; Yahoo/yfinance raw bars | E13: CRLF and LF byte hashes differ; normalized content agrees | F13: Daily only
B14: Intraday coverage | C14: 0 verified event panels | D14: GE_SOURCE_RESULTS_v2.md | E14: Daily gap combines release, call and overnight information | F14: Unavailable
B15: Forward call date | C15: Project planning estimate | D15: GE_SOURCE_RESULTS_v2.md | E15: 5 Nov 2026 not confirmed by issuer in bounded source check | F15: Planning only
B16: Validation scope | C16: Historical audit | D16: GE_PREREG_v1.md | E16: Previously examined data; nested W1/W2; small samples | F16: No new holdout
B20: Input file | C20: SHA256 | D20: Local relative path
B21: model.json | C21: 91f8eb92d4a94ba52750e5aefb8a74f6a03fa50f5b548cbd1101c22f46b1e349 | D21: data\processed\forecast_methods\gbv_event_v1\integration_v2\model.json
B22: frozen_scores.csv | C22: 942a3a46e653a66cb36a1e2a2e9613f66b653fb57302d154c490189583517341 | D22: data\processed\forecast_methods\gbv_event_v1\forecast_v1\results_v1\frozen_scores.csv
B23: per_event_decomposition.csv | C23: 3c30a923837781e8cae4217e641e7cad9687c11dcb946ce262a9822f2c5d8565 | D23: data\processed\forecast_methods\gbv_event_v1\forecast_v1\results_v1\per_event_decomposition.csv
B24: variance_reconciliation.csv | C24: d8b91a1af15cae7cf0ad9879fd702acc69b9534cb5682db2faabf8c08690d48e | D24: data\processed\forecast_methods\gbv_event_v1\forecast_v1\results_v1\variance_reconciliation.csv
B25: shapley_cross_moments.csv | C25: 3915a753d56a06e9e6dad9f1dabf7baad74eb202a6517f8aa606977bc8533d8f | D25: data\processed\forecast_methods\gbv_event_v1\forecast_v1\results_v1\shapley_cross_moments.csv
B26: event_panel.csv | C26: 6327bc888826bf2d9cbef8bb0207c9a4a3cd350afbb6cf7aaa81da3ae13aae0b | D26: data\processed\forecast_methods\gbv_event_v1\events_v1\run_v3\event_panel.csv
B27: associations.csv | C27: 11af6979ecc86c89d59a48e96a1f2e25cd4b4ff35f57fe45bd41f102f5ce0f0f | D27: data\processed\forecast_methods\gbv_event_v1\events_v1\run_v3\associations.csv
B28: pre_event_forecast_join.csv | C28: d9163addfdd10240894ef4bc7532d75ba09bd9001cc28dcd4f8bb302d3d9cf4e | D28: data\processed\forecast_methods\gbv_event_v1\events_v1\run_v3\pre_event_forecast_join.csv
