Workbook
Name Scenario: Inputs!$B$4
Name SharePrice: Inputs!$F$8
Name CostOfEquity: Inputs!$F$11
Name ExitMultiple: Inputs!$F$14

Sheet Inputs
A1: ABNB driver model - Inputs
A2: Overnight run 6-7 Sep 2026 (workstream 13). Yellow cells are inputs; everything downstream is a live formula. The other hard numbers in the file are the History actuals table, the external Street / Card bars (each with its vendor and date) and the Recon sheet's Python-mirror column. Sources name the workstream that supplied the value.
A4: SCENARIO SELECTOR (1 = Bear, 2 = Base, 3 = Bull) | B4: 2 | G4: Drives the Active column here and the Active column on Valuation (sections 1-4) and Card_5Nov. All three scenarios are computed in full on Revenue / Costs / Cash, so the Bear / Base / Bull columns never move when this cell changes.
A6: A. VALUATION AND CONTROL INPUTS
A7: Parameter | B7: Unit | C7: Bear | D7: Base | E7: Bull | F7: Active | G7: Source
A8: Share price (4 Sep 2026 close) | B8: $ | C8: 181.94 | D8: 181.94 | E8: 181.94 | F8: =CHOOSE(Inputs!$B$4,C8,D8,E8) | G8: Close 4 Sep 2026
A9: Net cash ex float, 30 Jun 2026 ($M) | B9: $M | C9: 9593 | D9: 9593 | E9: 9593 | F9: =CHOOSE(Inputs!$B$4,C9,D9,E9) | G9: WS12; 2Q26 XBRL. Funds held for clients ($12,224M) excluded
A10: Diluted shares, 2Q26 (M) | B10: M | C10: 597 | D10: 597 | E10: 597 | F10: =CHOOSE(Inputs!$B$4,C10,D10,E10) | G10: 2Q26 diluted weighted-average (XBRL)
A11: Cost of equity | C11: 0.115 | D11: 0.105 | E11: 0.103 | F11: =CHOOSE(Inputs!$B$4,C11,D11,E11) | G11: WS09 10.5-11.5% (Rf 4.78% + beta 1.2-1.3 x ERP 4.5-5.5%); WS12 CAPM 10.3%
A12: Terminal growth | C12: 0.025 | D12: 0.03 | E12: 0.03 | F12: =CHOOSE(Inputs!$B$4,C12,D12,E12) | G12: WS12 2.5-3.0%
A13: DCF start growth (year-1 FCF growth, fades to terminal) | C13: 0 | D13: 0.09 | E13: 0.15 | F13: =CHOOSE(Inputs!$B$4,C13,D13,E13) | G13: a round number just under the model's own FY2026E-FY2028E FCF CAGR of 9.9%, clipped to 0-15%. A ten-year fade started from a single scenario year's FCF growth (-21% bear, +26% bull) is an extrapolation artefact, not a valuation
A14: Exit EV / FY27E adj. EBITDA (x) | B14: x | C14: 13.5 | D14: 16.5 | E14: 18.5 | F14: =CHOOSE(Inputs!$B$4,C14,D14,E14) | G14: WS12 12_exit_multiple_recommendation.csv (time-series / cross-section / intrinsic blend)
A15: Exit EV / FY27E FCF (x) | B15: x | C15: 11.3 | D15: 14.3 | E15: 17.3 | F15: =CHOOSE(Inputs!$B$4,C15,D15,E15) | G15: 5 Sep set (15/19/23x) rescaled by WS12's 0.75x haircut to the EBITDA multiple
A16: Exit P / FY27E SBC-adj. FCF (x) | B16: x | C16: 15 | D16: 19.5 | E16: 24 | F16: =CHOOSE(Inputs!$B$4,C16,D16,E16) | G16: same 0.75x haircut on the 5 Sep 20/26/32x
A17: Exit P / FY27E earnings proxy (x) | B17: x | C17: 15 | D17: 19.5 | E17: 24 | F17: =CHOOSE(Inputs!$B$4,C17,D17,E17) | G17: same 0.75x haircut on the 5 Sep 20/26/32x
A18: RSU tax withholding, % of SBC | C18: 0.35 | D18: 0.35 | E18: 0.35 | F18: =CHOOSE(Inputs!$B$4,C18,D18,E18) | G18: FY2025 withholding $561M on SBC $1,581M = 35.5%
A19: Share price growth used for buyback/issuance math | C19: 0.05 | D19: 0.05 | E19: 0.05 | F19: =CHOOSE(Inputs!$B$4,C19,D19,E19) | G19: 5 Sep convention: buybacks and RSU issuance at a price rising 5% a year
A20: Incremental EBITDA margin on new-business revenue | C20: 0.7 | D20: 0.7 | E20: 0.7 | F20: =CHOOSE(Inputs!$B$4,C20,D20,E20) | G20: incremental margin on sponsored listings and Services; ads near 100%, Services lower
A21: Adj. EBITDA margin cap | C21: 0.38 | D21: 0.38 | E21: 0.38 | F21: =CHOOSE(Inputs!$B$4,C21,D21,E21) | G21: WS07: the realistic adj. EBITDA ceiling is 38%, against BKNG's five-year EBITDA-proxy range of 30.0-37.4%. Binds only in the bull case
A22: DCF fade period (years) | B22: yrs | C22: 10 | D22: 10 | E22: 10 | F22: =CHOOSE(Inputs!$B$4,C22,D22,E22) | G22: 5 Sep reverse-DCF convention: 10-year fade to terminal. LAYOUT-FIXED: the DCF grid on Valuation section 3 is ten written-out rows, so changing this cell does not resize the grid and has no effect on any output
A24: B. ANNUAL DRIVERS BY FISCAL YEAR
A25: FY2026E driver | B25: Unit | C25: Bear | D25: Base | E25: Bull | F25: Active | G25: Source
A26: Take rate change vs prior year (bps) | B26: bps | C26: -5 | D26: 0 | E26: 5 | F26: =CHOOSE(Inputs!$B$4,C26,D26,E26) | G26: WS07 lever; management guided FY26 take rate flat (2Q26 call)
A27: Cost of revenue per $ GBV, y/y change | B27: y/y | C27: 0.005 | D27: 0 | E27: -0.005 | F27: =CHOOSE(Inputs!$B$4,C27,D27,E27) | G27: WS07 lever; 2Q26 10-Q merchant fees and chargebacks
A28: Operations & support cash per night, y/y change | B28: y/y | C28: -0.04 | D28: -0.05 | E28: -0.06 | F28: =CHOOSE(Inputs!$B$4,C28,D28,E28) | G28: WS07 lever; 1H26 -3.8%, support cost per booking -16%
A29: Product development cash (ex-SBC), y/y growth | B29: y/y | C29: 0.115 | D29: 0.11 | E29: 0.105 | F29: =CHOOSE(Inputs!$B$4,C29,D29,E29) | G29: WS07 lever; 1H26 +11%
A30: Brand & performance marketing, y/y growth | B30: y/y | C30: 0.28 | D30: 0.25 | E30: 0.23 | F30: =CHOOSE(Inputs!$B$4,C30,D30,E30) | G30: WS07 lever; 1H26 brand+performance +32%
A31: Field operations & policy cash (new-business investment), y/y growth | B31: y/y | C31: 0.2 | D31: 0.18 | E31: 0.16 | F31: =CHOOSE(Inputs!$B$4,C31,D31,E31) | G31: WS07 lever; field ops +24% in 1H26
A32: G&A cash, y/y growth | B32: y/y | C32: 0.03 | D32: 0.02 | E32: 0 | F32: =CHOOSE(Inputs!$B$4,C32,D32,E32) | G32: WS07 lever; 1H26 +1%
A33: D&A + other add-backs, % of revenue | B33: % rev | C33: 0.009 | D33: 0.009 | E33: 0.009 | F33: =CHOOSE(Inputs!$B$4,C33,D33,E33) | G33: WS07 lever
A34: SBC, y/y growth | B34: y/y | C34: 0.16 | D34: 0.13 | E34: 0.1 | F34: =CHOOSE(Inputs!$B$4,C34,D34,E34) | G34: WS07 lever; 1H26 +14.7%, guided below FY25
A35: Interest income ($M) | B35: $M | C35: 620 | D35: 660 | E35: 700 | F35: =CHOOSE(Inputs!$B$4,C35,D35,E35) | G35: WS07 lever; $12.1bn cash + ST investments
A36: Interest expense ($M) | B36: $M | C36: 125 | D36: 120 | E36: 115 | F36: =CHOOSE(Inputs!$B$4,C36,D36,E36) | G36: WS07 lever; $2.5bn notes at 4.40-5.25%
A37: Cash taxes, % of revenue | B37: % rev | C37: 0.035 | D37: 0.026 | E37: 0.02 | F37: =CHOOSE(Inputs!$B$4,C37,D37,E37) | G37: WS07 lever; FY25 cash taxes 1.9% of revenue
... A46: D&A, % of revenue | B46: % rev | C46: 0.007 | D46: 0.007 | E46: 0.007 | F46: =CHOOSE(Inputs!$B$4,C46,D46,E46) | G46: WS07; D&A 0.6-0.8% of revenue since 2023
A48: FY2027E driver | B48: Unit | C48: Bear | D48: Base | E48: Bull | F48: Active | G48: Source
A49: Take rate change vs prior year (bps) | B49: bps | C49: -15 | D49: 0 | E49: 15 | F49: =CHOOSE(Inputs!$B$4,C49,D49,E49) | G49: WS07 lever; single fee vs the 6-10% direct-link pilot (WS11)
A50: Cost of revenue per $ GBV, y/y change | B50: y/y | C50: 0.015 | D50: 0 | E50: -0.01 | F50: =CHOOSE(Inputs!$B$4,C50,D50,E50) | G50: WS07 lever
A51: Operations & support cash per night, y/y change | B51: y/y | C51: -0.02 | D51: -0.05 | E51: -0.07 | F51: =CHOOSE(Inputs!$B$4,C51,D51,E51) | G51: WS07 lever
A52: Product development cash (ex-SBC), y/y growth | B52: y/y | C52: 0.09 | D52: 0.1 | E52: 0.1 | F52: =CHOOSE(Inputs!$B$4,C52,D52,E52) | G52: WS07 lever
A53: Brand & performance marketing, y/y growth | B53: y/y | C53: 0.12 | D53: 0.16 | E53: 0.145 | F53: =CHOOSE(Inputs!$B$4,C53,D53,E53) | G53: WS07 lever
A54: Field operations & policy cash (new-business investment), y/y growth | B54: y/y | C54: 0.1 | D54: 0.14 | E54: 0.12 | F54: =CHOOSE(Inputs!$B$4,C54,D54,E54) | G54: WS07 lever
A55: G&A cash, y/y growth | B55: y/y | C55: 0.05 | D55: 0.055 | E55: 0.045 | F55: =CHOOSE(Inputs!$B$4,C55,D55,E55) | G55: WS07 lever
A56: D&A + other add-backs, % of revenue | B56: % rev | C56: 0.009 | D56: 0.009 | E56: 0.009 | F56: =CHOOSE(Inputs!$B$4,C56,D56,E56) | G56: WS07 lever
A57: SBC, y/y growth | B57: y/y | C57: 0.14 | D57: 0.1 | E57: 0.06 | F57: =CHOOSE(Inputs!$B$4,C57,D57,E57) | G57: WS07 lever
A58: Interest income ($M) | B58: $M | C58: 540 | D58: 620 | E58: 690 | F58: =CHOOSE(Inputs!$B$4,C58,D58,E58) | G58: WS07 lever
A59: Interest expense ($M) | B59: $M | C59: 128 | D59: 125 | E59: 122 | F59: =CHOOSE(Inputs!$B$4,C59,D59,E59) | G59: WS07 lever
A60: Cash taxes, % of revenue | B60: % rev | C60: 0.045 | D60: 0.034 | E60: 0.026 | F60: =CHOOSE(Inputs!$B$4,C60,D60,E60) | G60: WS07 lever
... A69: D&A, % of revenue | B69: % rev | C69: 0.007 | D69: 0.007 | E69: 0.007 | F69: =CHOOSE(Inputs!$B$4,C69,D69,E69) | G69: WS07
A71: FY2028E driver | B71: Unit | C71: Bear | D71: Base | E71: Bull | F71: Active | G71: Source
A72: Take rate change vs prior year (bps) | B72: bps | C72: -10 | D72: 5 | E72: 20 | F72: =CHOOSE(Inputs!$B$4,C72,D72,E72) | G72: WS07 lever; bull is the sponsored-listings case
A73: Cost of revenue per $ GBV, y/y change | B73: y/y | C73: 0.01 | D73: -0.005 | E73: -0.015 | F73: =CHOOSE(Inputs!$B$4,C73,D73,E73) | G73: WS07 lever
A74: Operations & support cash per night, y/y change | B74: y/y | C74: -0.02 | D74: -0.05 | E74: -0.07 | F74: =CHOOSE(Inputs!$B$4,C74,D74,E74) | G74: WS07 lever
A75: Product development cash (ex-SBC), y/y growth | B75: y/y | C75: 0.085 | D75: 0.095 | E75: 0.095 | F75: =CHOOSE(Inputs!$B$4,C75,D75,E75) | G75: WS07 lever
A76: Brand & performance marketing, y/y growth | B76: y/y | C76: 0.11 | D76: 0.135 | E76: 0.125 | F76: =CHOOSE(Inputs!$B$4,C76,D76,E76) | G76: WS07 lever
A77: Field operations & policy cash (new-business investment), y/y growth | B77: y/y | C77: 0.09 | D77: 0.12 | E77: 0.105 | F77: =CHOOSE(Inputs!$B$4,C77,D77,E77) | G77: WS07 lever
A78: G&A cash, y/y growth | B78: y/y | C78: 0.05 | D78: 0.05 | E78: 0.04 | F78: =CHOOSE(Inputs!$B$4,C78,D78,E78) | G78: WS07 lever
A79: D&A + other add-backs, % of revenue | B79: % rev | C79: 0.009 | D79: 0.009 | E79: 0.009 | F79: =CHOOSE(Inputs!$B$4,C79,D79,E79) | G79: WS07 lever
A80: SBC, y/y growth | B80: y/y | C80: 0.12 | D80: 0.08 | E80: 0.04 | F80: =CHOOSE(Inputs!$B$4,C80,D80,E80) | G80: WS07 lever
A81: Interest income ($M) | B81: $M | C81: 500 | D81: 590 | E81: 680 | F81: =CHOOSE(Inputs!$B$4,C81,D81,E81) | G81: WS07 lever
A82: Interest expense ($M) | B82: $M | C82: 128 | D82: 125 | E82: 122 | F82: =CHOOSE(Inputs!$B$4,C82,D82,E82) | G82: WS07 lever
A83: Cash taxes, % of revenue | B83: % rev | C83: 0.052 | D83: 0.04 | E83: 0.032 | F83: =CHOOSE(Inputs!$B$4,C83,D83,E83) | G83: WS07 lever
... A96: FX effect on ADR, FY2028E | B96: y/y | C96: 0 | D96: 0 | E96: 0 | F96: =CHOOSE(Inputs!$B$4,C96,D96,E96) | G96: same; a fraction, percent-formatted, not a percentage-point number
A98: C. QUARTERLY DRIVERS 3Q26 - 4Q27
A99: Quarter / driver | B99: Unit | C99: Bear | D99: Base | E99: Bull | F99: Active | G99: Source
A100: 3Q26 North America nights growth | B100: y/y % | C100: 5 | D100: 7 | E100: 9 | F100: =CHOOSE(Inputs!$B$4,C100,D100,E100) | G100: WS10 10_regional_forecast.csv
A101: 3Q26 EMEA nights growth | B101: y/y % | C101: 6 | D101: 8 | E101: 10 | F101: =CHOOSE(Inputs!$B$4,C101,D101,E101) | G101: WS10 10_regional_forecast.csv
A102: 3Q26 Latin America nights growth | B102: y/y % | C102: 15 | D102: 18 | E102: 21 | F102: =CHOOSE(Inputs!$B$4,C102,D102,E102) | G102: WS10 10_regional_forecast.csv
A103: 3Q26 Asia Pacific nights growth | B103: y/y % | C103: 14 | D103: 17 | E103: 19 | F103: =CHOOSE(Inputs!$B$4,C103,D103,E103) | G103: WS10 10_regional_forecast.csv
A104: 3Q26 ADR ex-FX growth | B104: y/y % | C104: 2 | D104: 3 | E104: 4 | F104: =CHOOSE(Inputs!$B$4,C104,D104,E104) | G104: WS10 (2026 quarters); WS06 and WS07 both +2.5% base for FY27
A105: 3Q26 FX effect on revenue | B105: pp | C105: 3 | D105: 3 | E105: 3 | F105: =CHOOSE(Inputs!$B$4,C105,D105,E105) | G105: 2Q26 letter guide (+3.0pp); WS05 lagged fit says +2.19pp
A106: 3Q26 FX effect on ADR | B106: pp | C106: 0.8 | D106: 0.8 | E106: 0.8 | F106: =CHOOSE(Inputs!$B$4,C106,D106,E106) | G106: WS05 05_fx_schedule.csv broad-USD ADR fit, re-estimated by WS08 (r 0.96)
A107: 3Q26 Adj. EBITDA margin (2026 quarters only) | B107: % | C107: 48.3 | D107: 49 | E107: 50.2 | F107: =CHOOSE(Inputs!$B$4,C107,D107,E107) | G107: WS07 5 Nov card: guide is 'down slightly' from 3Q25's 50.1%
A108: 4Q26 North America nights growth | B108: y/y % | C108: 4 | D108: 7 | E108: 9 | F108: =CHOOSE(Inputs!$B$4,C108,D108,E108) | G108: WS10 10_regional_forecast.csv
A109: 4Q26 EMEA nights growth | B109: y/y % | C109: 5 | D109: 7 | E109: 9 | F109: =CHOOSE(Inputs!$B$4,C109,D109,E109) | G109: WS10 10_regional_forecast.csv
A110: 4Q26 Latin America nights growth | B110: y/y % | C110: 14 | D110: 18 | E110: 21 | F110: =CHOOSE(Inputs!$B$4,C110,D110,E110) | G110: WS10 10_regional_forecast.csv
A111: 4Q26 Asia Pacific nights growth | B111: y/y % | C111: 13 | D111: 17 | E111: 19 | F111: =CHOOSE(Inputs!$B$4,C111,D111,E111) | G111: WS10 10_regional_forecast.csv
... A146: 4Q27 FX effect on ADR | B146: pp | C146: -1.31 | D146: 0.49 | E146: 1.86 | F146: =CHOOSE(Inputs!$B$4,C146,D146,E146) | G146: WS05 05_fx_schedule.csv broad-USD ADR fit, re-estimated by WS08 (r 0.96)
A149: D. REGULATORY NIGHTS DRAG (WS11 median, incremental pp of y/y growth)
A150: Year / region | B150: Unit | C150: Value | G150: Source
A151: FY2026 North America | B151: pp | C151: 0.03 | G151: WS11 11_regulatory_overlay.csv, regenerated after the WS22 (audit A06) conditional-dependency repair; cumulative run-rate loss vs the 2Q26 baseline (EMEA 0.36 / 1.07 / 2.03%, NA 0.03 / 0.08 / 0.15%), differenced into a y/y growth drag. Scaled by the 'Regulatory drag multiplier' above.
A152: FY2026 EMEA | B152: pp | C152: 0.36 | G152: WS11 11_regulatory_overlay.csv, regenerated after the WS22 (audit A06) conditional-dependency repair; cumulative run-rate loss vs the 2Q26 baseline (EMEA 0.36 / 1.07 / 2.03%, NA 0.03 / 0.08 / 0.15%), differenced into a y/y growth drag. Scaled by the 'Regulatory drag multiplier' above.
A153: FY2026 Latin America | B153: pp | C153: 0 | G153: WS11 11_regulatory_overlay.csv, regenerated after the WS22 (audit A06) conditional-dependency repair; cumulative run-rate loss vs the 2Q26 baseline (EMEA 0.36 / 1.07 / 2.03%, NA 0.03 / 0.08 / 0.15%), differenced into a y/y growth drag. Scaled by the 'Regulatory drag multiplier' above.
A154: FY2026 Asia Pacific | B154: pp | C154: 0 | G154: WS11 11_regulatory_overlay.csv, regenerated after the WS22 (audit A06) conditional-dependency repair; cumulative run-rate loss vs the 2Q26 baseline (EMEA 0.36 / 1.07 / 2.03%, NA 0.03 / 0.08 / 0.15%), differenced into a y/y growth drag. Scaled by the 'Regulatory drag multiplier' above.
A155: FY2027 North America | B155: pp | C155: 0.05 | G155: WS11 11_regulatory_overlay.csv, regenerated after the WS22 (audit A06) conditional-dependency repair; cumulative run-rate loss vs the 2Q26 baseline (EMEA 0.36 / 1.07 / 2.03%, NA 0.03 / 0.08 / 0.15%), differenced into a y/y growth drag. Scaled by the 'Regulatory drag multiplier' above.
A156: FY2027 EMEA | B156: pp | C156: 0.71 | G156: WS11 11_regulatory_overlay.csv, regenerated after the WS22 (audit A06) conditional-dependency repair; cumulative run-rate loss vs the 2Q26 baseline (EMEA 0.36 / 1.07 / 2.03%, NA 0.03 / 0.08 / 0.15%), differenced into a y/y growth drag. Scaled by the 'Regulatory drag multiplier' above.
A157: FY2027 Latin America | B157: pp | C157: 0 | G157: WS11 11_regulatory_overlay.csv, regenerated after the WS22 (audit A06) conditional-dependency repair; cumulative run-rate loss vs the 2Q26 baseline (EMEA 0.36 / 1.07 / 2.03%, NA 0.03 / 0.08 / 0.15%), differenced into a y/y growth drag. Scaled by the 'Regulatory drag multiplier' above.
A158: FY2027 Asia Pacific | B158: pp | C158: 0 | G158: WS11 11_regulatory_overlay.csv, regenerated after the WS22 (audit A06) conditional-dependency repair; cumulative run-rate loss vs the 2Q26 baseline (EMEA 0.36 / 1.07 / 2.03%, NA 0.03 / 0.08 / 0.15%), differenced into a y/y growth drag. Scaled by the 'Regulatory drag multiplier' above.
A159: FY2028 North America | B159: pp | C159: 0.07 | G159: WS11 11_regulatory_overlay.csv, regenerated after the WS22 (audit A06) conditional-dependency repair; cumulative run-rate loss vs the 2Q26 baseline (EMEA 0.36 / 1.07 / 2.03%, NA 0.03 / 0.08 / 0.15%), differenced into a y/y growth drag. Scaled by the 'Regulatory drag multiplier' above.
A160: FY2028 EMEA | B160: pp | C160: 0.96 | G160: WS11 11_regulatory_overlay.csv, regenerated after the WS22 (audit A06) conditional-dependency repair; cumulative run-rate loss vs the 2Q26 baseline (EMEA 0.36 / 1.07 / 2.03%, NA 0.03 / 0.08 / 0.15%), differenced into a y/y growth drag. Scaled by the 'Regulatory drag multiplier' above.
A161: FY2028 Latin America | B161: pp | C161: 0 | G161: WS11 11_regulatory_overlay.csv, regenerated after the WS22 (audit A06) conditional-dependency repair; cumulative run-rate loss vs the 2Q26 baseline (EMEA 0.36 / 1.07 / 2.03%, NA 0.03 / 0.08 / 0.15%), differenced into a y/y growth drag. Scaled by the 'Regulatory drag multiplier' above.
A162: FY2028 Asia Pacific | B162: pp | C162: 0 | G162: WS11 11_regulatory_overlay.csv, regenerated after the WS22 (audit A06) conditional-dependency repair; cumulative run-rate loss vs the 2Q26 baseline (EMEA 0.36 / 1.07 / 2.03%, NA 0.03 / 0.08 / 0.15%), differenced into a y/y growth drag. Scaled by the 'Regulatory drag multiplier' above.
A164: E. DOCUMENTED ALTERNATIVES - values a workstream supplied that lost the base-case argument. Not referenced by any formula; swap them in deliberately.
A165: Item | B165: Alternative (not used) | C165: In the base case | G165: Why the base wins
A166: FY27 revenue FX | B166: 0.0 pp -- contemporaneous FX (WS10, and the 5 Sep driver model) | C166: -0.63 pp -- WS05 lagged fit (in the base) | G166: WS05 fits revenue FX on the mean EUR/USD y/y at t-1 and t-2 (n 17, r 0.80) and validates it against the guided +3.0pp for 3Q26. The contemporaneous version has no such validation and 84% of the 4Q26 driver is already realised.
A167: 3Q26 revenue FX | B167: +2.19 pp -- WS05 lagged fit | C167: +3.00 pp -- 2Q26 letter guide (in the base) | G167: The company quantified it; the fit's +/-0.8pp error band covers the guide.
A168: FY27 ADR FX | B168: -0.11 pp -- WS05 EUR/USD-basis ADR fit | C168: +0.19 pp -- broad-USD-basis fit (in the base) | G168: WS08 re-estimated the broad-USD version on 2022Q2-2026Q2 (r 0.96) and walk-forward tested it at 0.44x the naive error. The choice moves the ADR/GBV display only; revenue runs off the revenue-FX line.
A169: FY27 revenue growth | B169: +12.4% (WS10 regional build, gross of regulation, FX 0); +10.3% (WS05 probability-weighted); +11.2% (WS07 levers) | C169: model output (WS10 nights net of WS11 regulation, WS06/WS07 ADR ex-FX, WS05 FX) | G169: The base takes the only bottom-up nights build (WS10), the ADR ex-FX that two workstreams agree on (WS06 and WS07 both +2.5% against WS10's +3.0%), WS05's FX schedule and WS11's regulatory drag.
A170: FY27 adj. EBITDA margin | B170: 36.4% -- WS05 probability-weighted macro scenarios | C170: model output -- WS07 lever build (36.6% on WS07's own revenue) | G170: WS05's figure is a sensitivity-weighted overlay on WS07's base; WS07's is bottom-up by cost line. The gap is 0.2pp.
A171: Exit multiple, FY27E EV / adj. EBITDA | B171: 18 / 22 / 25.5x -- model/assumptions.md, 5 Sep | C171: 13.5 / 16.5 / 18.5x -- WS12 (in the base) | G171: The 5 Sep set held today's LTM multiple flat. WS12 blends a time-series regression (+0.48 turns per point of NTM growth), a peer cross-section and an intrinsic fade DCF; all three land below 22x.
...

Sheet History
A1: History - quarterly KPIs and cost lines, 1Q21 to 2Q26
A2: Source: data/processed/overnight/02_kpi_panel_quarterly.csv (WS02), data/processed/abnb_capital_return_quarterly.csv. Actuals, not formulas.
A4: Quarter | B4: Nights & experiences booked (M) | C4: GBV ($M) | D4: ADR ($) | E4: Revenue ($M) | F4: Take rate (%) | G4: Adj. EBITDA ($M) | H4: Adj. EBITDA margin (%) | I4: SBC ($M) | J4: FCF ($M) | K4: Buybacks ($M) | L4: RSU tax withholding ($M) | M4: Diluted WA shares (M) | N4: Net income ($M) | O4: Cost of revenue, GAAP ($M) | P4: Ops & support, GAAP ($M) | Q4: Product development, GAAP ($M) | R4: Sales & marketing, GAAP ($M) | S4: G&A, GAAP ($M) | T4: Cost of revenue, cash ($M) | U4: Ops & support, cash ($M) | V4: Product development, cash ($M) | W4: Sales & marketing, cash ($M) | X4: G&A, cash ($M)
A5: 1Q21 | B5: 64.4 | C5: 10300 | D5: 159.82 | E5: 887 | F5: 8.61 | G5: -59 | H5: -6.7 | I5: 229.5 | J5: 598.7 | L5: 130.4 | M5: 601 | N5: -1172.2 | O5: 254.5 | P5: 185.4 | Q5: 363.1 | R5: 229.1 | S5: 189.8 | T5: 254.5 | U5: 174 | V5: 219.4 | W5: 203.2 | X5: 141.3
A6: 2Q21 | B6: 83.1 | C6: 13400 | D6: 161.45 | E6: 1335 | F6: 9.96 | G6: 217 | H6: 16.3 | I6: 232.9 | J6: 782 | L6: 8.5 | M6: 611.7 | N6: -68.2 | O6: 294.4 | P6: 208.1 | Q6: 349.7 | R6: 315.3 | S6: 218.3 | T6: 294.4 | U6: 193.9 | V6: 205.9 | W6: 291.2 | X6: 167.6
A7: 3Q21 | B7: 79.7 | C7: 11900 | D7: 149.15 | E7: 2237 | F7: 18.8 | G7: 1101 | H7: 49.2 | I7: 210.8 | J7: 529.2 | L7: 15.7 | M7: 681.9 | N7: 833.9 | O7: 311.6 | P7: 228.3 | Q7: 344.4 | R7: 290.9 | S7: 210.7 | T7: 311.6 | U7: 217.1 | V7: 213.1 | W7: 267.2 | X7: 166
A8: 4Q21 | B8: 73.4 | C8: 11300 | D8: 153.61 | E8: 1532 | F8: 13.56 | G8: 333 | H8: 21.7 | I8: 225.9 | J8: 378.1 | K8: 0 | L8: 22.4 | M8: 569.4 | N8: 54.5 | O8: 295.5 | P8: 225.1 | Q8: 367.8 | R8: 350.7 | S8: 217.2 | T8: 295.5 | U8: 213.4 | V8: 241.5 | W8: 324.4 | X8: 155.8
A9: 1Q22 | B9: 102.1 | C9: 17200 | D9: 168.07 | E9: 1509 | F9: 8.77 | G9: 229 | H9: 15.2 | I9: 195 | J9: 1196 | K9: 0 | L9: 205 | M9: 635 | N9: -19 | O9: 363 | P9: 232.7 | Q9: 363 | R9: 345 | S9: 210 | T9: 363 | U9: 221 | V9: 245.1 | W9: 323.8 | X9: 165.9
A10: 2Q22 | B10: 103.7 | C10: 17000 | D10: 163.74 | E10: 2104 | F10: 12.38 | G10: 711 | H10: 33.8 | I10: 247 | J10: 796 | K10: 0 | L10: 140 | M10: 684 | N10: 379 | O10: 390 | P10: 258 | Q10: 375 | R10: 379 | S10: 244 | T10: 390 | U10: 241.1 | V10: 230.1 | W10: 349.9 | X10: 187.8
A11: 3Q22 | B11: 99.7 | C11: 15600 | D11: 156.44 | E11: 2884 | F11: 18.49 | G11: 1457 | H11: 50.5 | I11: 234 | J11: 958 | K11: 1000 | L11: 146 | M11: 680 | N11: 1214 | O11: 401 | P11: 290 | Q11: 366 | R11: 384 | S11: 240 | T11: 401 | U11: 272.1 | V11: 230.1 | W11: 356.6 | X11: 186.9
A12: 4Q22 | B12: 88.2 | C12: 13500 | D12: 152.81 | E12: 1902 | F12: 14.09 | G12: 506 | H12: 26.6 | I12: 254 | J12: 455 | K12: 500 | L12: 116 | M12: 721 | N12: 319.1 | O12: 345 | P12: 260 | Q12: 398 | R12: 408 | S12: 256 | T12: 345 | U12: 243 | V12: 249 | W12: 372 | X12: 204
A13: 1Q23 | B13: 121.1 | C13: 20400 | D13: 168.43 | E13: 1818 | F13: 8.91 | G13: 262 | H13: 14.4 | I13: 240 | J13: 1581 | K13: 493 | L13: 151 | M13: 670 | N13: 117 | O13: 428 | P13: 282 | Q13: 420 | R13: 450 | S13: 243 | T13: 428 | U13: 267 | V13: 271 | W13: 422 | X13: 195
A14: 2Q23 | B14: 115.1 | C14: 19100 | D14: 166.01 | E14: 2484 | F14: 13.01 | G14: 819 | H14: 33 | I14: 304 | J14: 900 | K14: 507 | L14: 721 | M14: 665 | N14: 650 | O14: 432 | P14: 317 | Q14: 451 | R14: 486 | S14: 275 | T14: 432 | U14: 298 | V14: 260 | W14: 450 | X14: 217
A15: 3Q23 | B15: 113.2 | C15: 18300 | D15: 161.38 | E15: 3397 | F15: 18.56 | G15: 1834 | H15: 54 | I15: 286 | J15: 1310 | K15: 500 | L15: 151 | M15: 660 | N15: 4374 | O15: 459 | P15: 316 | Q15: 419 | R15: 403 | S15: 304 | T15: 459 | U15: 299 | V15: 244 | W15: 370 | X15: 243
A16: 4Q23 | B16: 98.8 | C16: 15500 | D16: 156.73 | E16: 2218 | F16: 14.31 | G16: 738 | H16: 33.3 | I16: 270 | J16: 46 | K16: 752 | L16: 201 | M16: 653 | N16: -349.2 | O16: 384 | P16: 271 | Q16: 432 | R16: 424 | S16: 1203 | T16: 384 | U16: 254 | V16: 253 | W16: 391 | X16: 1142
A17: 1Q24 | B17: 132.6 | C17: 22900 | D17: 172.88 | E17: 2142 | F17: 9.35 | G17: 424 | H17: 19.8 | I17: 295 | J17: 1909 | K17: 750 | L17: 155 | M17: 654 | N17: 264 | O17: 480 | P17: 285 | Q17: 475 | R17: 514 | S17: 287 | T17: 480 | U17: 266 | V17: 290 | W17: 479 | X17: 231
A18: 2Q24 | B18: 125.1 | C18: 21200 | D18: 169.53 | E18: 2748 | F18: 12.96 | G18: 894 | H18: 32.5 | I18: 382 | J18: 1043 | K18: 749 | L18: 154 | M18: 649 | N18: 555 | O18: 506 | P18: 338 | Q18: 519 | R18: 573 | S18: 315 | T18: 506 | U18: 314 | V18: 280 | W18: 527 | X18: 242
A19: 3Q24 | B19: 122.8 | C19: 20100 | D19: 163.64 | E19: 3732 | F19: 18.57 | G19: 1958 | H19: 52.5 | I19: 362 | J19: 1074 | K19: 1093 | L19: 113 | M19: 642 | N19: 1368 | O19: 465 | P19: 369 | Q19: 524 | R19: 514 | S19: 335 | T19: 465 | U19: 347 | V19: 294 | W19: 471 | X19: 268
... A26: 2Q26 | B26: 148.3 | C26: 27200 | D26: 183.73 | E26: 3608 | F26: 13.26 | G26: 1261 | H26: 35 | I26: 487 | J26: 1253 | K26: 1051 | L26: 165 | M26: 597 | N26: 816 | O26: 633 | P26: 361 | Q26: 672 | R26: 875 | S26: 309 | T26: 633 | U26: 323 | V26: 374 | W26: 808 | X26: 225
A28: MODEL ANCHORS - the actuals the forecast grows off (formulas over the table above)
A29: Item | B29: Value | C29: Source / formula
A30: FY2025 nights (M) | B30: =B21+B22+B23+B24
A31: FY2025 GBV ($M) | B31: =C21+C22+C23+C24
A32: FY2025 revenue ($M) | B32: =E21+E22+E23+E24
A33: FY2025 ADR ($) | B33: =History!$B$31/History!$B$30
A34: FY2025 take rate | B34: =History!$B$32/History!$B$31
A35: FY2025 adj. EBITDA ($M) | B35: =G21+G22+G23+G24
A36: FY2025 SBC ($M) | B36: =I21+I22+I23+I24
A37: FY2025 cost of revenue, cash ($M) | B37: 2086 | C37: WS07 actuals()
A38: FY2025 ops & support, cash ($M) | B38: 1237 | C38: WS07 actuals()
A39: FY2025 product development, cash ($M) | B39: 1337 | C39: WS07 actuals()
A40: FY2025 brand & performance marketing ($M) | B40: 1595 | C40: WS07 07_cost_lines_per_night.csv
A41: FY2025 field operations & policy, cash ($M) | B41: 781 | C41: S&M cash less brand & performance
A42: FY2025 G&A, cash ($M) | B42: 1069 | C42: WS07 actuals()
A43: FY2025 new-business revenue outside GBV x take ($M) | B43: 12 | C43: WS11: Services $12M; sponsored listings did not exist
A44: 1H2026 nights (M) | B44: =B25+B26 | C44: actual
A45: 1H2026 GBV ($M) | B45: =C25+C26 | C45: actual
A46: 1H2026 revenue ($M) | B46: =E25+E26 | C46: actual
A47: 1H2026 FCF ($M) | B47: =J25+J26 | C47: actual
A48: 1H2026 buybacks ($M) | B48: =K25+K26 | C48: actual
A49: 1H2026 RSU withholding ($M) | B49: =L25+L26 | C49: actual
A50: 1H2026 SBC ($M) | B50: =I25+I26 | C50: actual; used by the 2H26 share roll
A51: 3Q25 nights (M) | B51: =B23
A52: 3Q25 GBV ($M) | B52: =C23
A53: 3Q25 ADR ($) | B53: =D23
A54: 3Q25 revenue ($M) | B54: =E23
A55: 3Q25 take rate | B55: =F23/100
A56: 3Q25 North America share of nights | B56: 0.307 | C56: WS10 10_regional_panel_quarterly.csv, normalised to 100%
A57: 3Q25 EMEA share of nights | B57: 0.4 | C57: WS10 10_regional_panel_quarterly.csv, normalised to 100%
A58: 3Q25 Latin America share of nights | B58: 0.135 | C58: WS10 10_regional_panel_quarterly.csv, normalised to 100%
A59: 3Q25 Asia Pacific share of nights | B59: 0.158 | C59: WS10 10_regional_panel_quarterly.csv, normalised to 100%
A60: 4Q25 nights (M) | B60: =B24
A61: 4Q25 GBV ($M) | B61: =C24
A62: 4Q25 ADR ($) | B62: =D24
A63: 4Q25 revenue ($M) | B63: =E24
A64: 4Q25 take rate | B64: =F24/100
A65: 4Q25 North America share of nights | B65: 0.2997003 | C65: WS10 10_regional_panel_quarterly.csv, normalised to 100%
A66: 4Q25 EMEA share of nights | B66: 0.3996004 | C66: WS10 10_regional_panel_quarterly.csv, normalised to 100%
A67: 4Q25 Latin America share of nights | B67: 0.13986014 | C67: WS10 10_regional_panel_quarterly.csv, normalised to 100%
A68: 4Q25 Asia Pacific share of nights | B68: 0.16083916 | C68: WS10 10_regional_panel_quarterly.csv, normalised to 100%
A69: 1Q26 nights (M) | B69: =B25
A70: 1Q26 GBV ($M) | B70: =C25
A71: 1Q26 ADR ($) | B71: =D25
A72: 1Q26 revenue ($M) | B72: =E25
A73: 1Q26 take rate | B73: =F25/100
A74: 1Q26 North America share of nights | B74: 0.293 | C74: WS10 10_regional_panel_quarterly.csv, normalised to 100%
A75: 1Q26 EMEA share of nights | B75: 0.397 | C75: WS10 10_regional_panel_quarterly.csv, normalised to 100%
A76: 1Q26 Latin America share of nights | B76: 0.147 | C76: WS10 10_regional_panel_quarterly.csv, normalised to 100%
A77: 1Q26 Asia Pacific share of nights | B77: 0.163 | C77: WS10 10_regional_panel_quarterly.csv, normalised to 100%
A78: 2Q26 nights (M) | B78: =B26
A79: 2Q26 GBV ($M) | B79: =C26
A80: 2Q26 ADR ($) | B80: =D26
A81: 2Q26 revenue ($M) | B81: =E26
A82: 2Q26 take rate | B82: =F26/100
A83: 2Q26 North America share of nights | B83: 0.29329329 | C83: WS10 10_regional_panel_quarterly.csv, normalised to 100%
A84: 2Q26 EMEA share of nights | B84: 0.3963964 | C84: WS10 10_regional_panel_quarterly.csv, normalised to 100%
A85: 2Q26 Latin America share of nights | B85: 0.14814815 | C85: WS10 10_regional_panel_quarterly.csv, normalised to 100%
A86: 2Q26 Asia Pacific share of nights | B86: 0.16216216 | C86: WS10 10_regional_panel_quarterly.csv, normalised to 100%
A87: FY2025 North America share of nights | B87: 0.31128862 | C87: nights-weighted mean of the four 2025 quarters (WS10)
A88: FY2025 EMEA share of nights | B88: 0.39483373 | C88: nights-weighted mean of the four 2025 quarters (WS10)
A89: FY2025 Latin America share of nights | B89: 0.13580712 | C89: nights-weighted mean of the four 2025 quarters (WS10)
A90: FY2025 Asia Pacific share of nights | B90: 0.15807053 | C90: nights-weighted mean of the four 2025 quarters (WS10)
A91: Memo: seasonal adj. EBITDA margin spread, 1Q, 2023-2025 mean (pts vs the full year) | B91: -0.18579308 | C91: not used by any formula: the 2027 quarterly margins run off the 2026 spread instead, so 3Q27 stays continuous with the 3Q26 card margin
A92: Memo: seasonal adj. EBITDA margin spread, 2Q, 2023-2025 mean (pts vs the full year) | B92: -0.03045975 | C92: not used by any formula: the 2027 quarterly margins run off the 2026 spread instead, so 3Q27 stays continuous with the 3Q26 card margin
A93: Memo: seasonal adj. EBITDA margin spread, 3Q, 2023-2025 mean (pts vs the full year) | B93: 0.16087358 | C93: not used by any formula: the 2027 quarterly margins run off the 2026 spread instead, so 3Q27 stays continuous with the 3Q26 card margin
A94: Memo: seasonal adj. EBITDA margin spread, 4Q, 2023-2025 mean (pts vs the full year) | B94: -0.053126416 | C94: not used by any formula: the 2027 quarterly margins run off the 2026 spread instead, so 3Q27 stays continuous with the 3Q26 card margin
... A98: Seasonal share of full-year nights / revenue, 4Q | B98: 0.224994 | C98: 2023-2025 mean; revenue share 22.5%
A99: 1Q26 adj. EBITDA margin (actual) | B99: =H25/100 | C99: actual; used as the 2027 seasonal template
A100: 2Q26 adj. EBITDA margin (actual) | B100: =H26/100 | C100: actual; used as the 2027 seasonal template
A101: LTM revenue ($M) | B101: 13159 | C101: 3Q25-2Q26
A102: LTM adj. EBITDA ($M) | B102: 4617 | C102: 3Q25-2Q26
A103: LTM FCF ($M) | B103: 4827 | C103: 3Q25-2Q26
A104: LTM SBC ($M) | B104: 1696 | C104: 3Q25-2Q26
A106: FY2025 CASH-BRIDGE ANCHORS - the FY2025A memo column on Costs and Cash. No forecast year depends on these.
A107: Item | B107: Value | C107: Source / formula
A108: FY2025 D&A ($M) | B108: 91 | C108: data/processed/abnb_fcf_bridge.csv, sum of 1Q25-4Q25 (da)
A109: FY2025 D&A and other add-backs ($M) | B109: 161 | C109: data/processed/abnb_fcf_bridge.csv, sum of 1Q25-4Q25 (da 91 + other_addbacks 70)
A110: FY2025 interest income ($M) | B110: 705 | C110: data/processed/abnb_fcf_bridge.csv, sum of 1Q25-4Q25 (interest_income)
A111: FY2025 interest expense ($M) | B111: 0 | C111: data/processed/abnb_fcf_bridge.csv, sum of 1Q25-4Q25 reports zero in every quarter of 2025; the note coupon sits inside other income/(expense) in that bridge. Memo only - the forecast years take interest expense from Inputs
A112: FY2025 other income / (expense) ($M) | B112: -112 | C112: data/processed/abnb_fcf_bridge.csv, sum of 1Q25-4Q25 (other_income_expense)
...

Sheet Revenue
A1: Revenue build - quarterly 3Q26 to 4Q27 and annual FY2026E to FY2028E
A2: nights by region x ADR (ex-FX x FX) = GBV; revenue = GBV x take rate x the FX timing wedge, plus new business outside GBV. FY2026 = 1H26 actual + 3Q26 + 4Q26.
A4: BEAR CASE
A5: Line | B5: Unit | C5: 3Q26 | D5: 4Q26 | E5: 1Q27 | F5: 2Q27 | G5: 3Q27 | H5: 4Q27 | I5: FY2026E | J5: FY2027E | K5: FY2028E
A6: Prior-year nights, North America | B6: M | C6: =History!$B$51*History!$B$56 | D6: =History!$B$60*History!$B$65 | E6: =History!$B$69*History!$B$74 | F6: =History!$B$78*History!$B$83 | G6: =C18 | H6: =D18
A7: Prior-year nights, EMEA | B7: M | C7: =History!$B$51*History!$B$57 | D7: =History!$B$60*History!$B$66 | E7: =History!$B$69*History!$B$75 | F7: =History!$B$78*History!$B$84 | G7: =C19 | H7: =D19
A8: Prior-year nights, Latin America | B8: M | C8: =History!$B$51*History!$B$58 | D8: =History!$B$60*History!$B$67 | E8: =History!$B$69*History!$B$76 | F8: =History!$B$78*History!$B$85 | G8: =C20 | H8: =D20
A9: Prior-year nights, Asia Pacific | B9: M | C9: =History!$B$51*History!$B$59 | D9: =History!$B$60*History!$B$68 | E9: =History!$B$69*History!$B$77 | F9: =History!$B$78*History!$B$86 | G9: =C21 | H9: =D21
A10: Nights growth, North America | B10: y/y | C10: =Inputs!$C$100/100 | D10: =Inputs!$C$108/100 | E10: =Inputs!$C$116/100 | F10: =Inputs!$C$124/100 | G10: =Inputs!$C$132/100 | H10: =Inputs!$C$140/100
A11: Nights growth, EMEA | B11: y/y | C11: =Inputs!$C$101/100 | D11: =Inputs!$C$109/100 | E11: =Inputs!$C$117/100 | F11: =Inputs!$C$125/100 | G11: =Inputs!$C$133/100 | H11: =Inputs!$C$141/100
A12: Nights growth, Latin America | B12: y/y | C12: =Inputs!$C$102/100 | D12: =Inputs!$C$110/100 | E12: =Inputs!$C$118/100 | F12: =Inputs!$C$126/100 | G12: =Inputs!$C$134/100 | H12: =Inputs!$C$142/100
A13: Nights growth, Asia Pacific | B13: y/y | C13: =Inputs!$C$103/100 | D13: =Inputs!$C$111/100 | E13: =Inputs!$C$119/100 | F13: =Inputs!$C$127/100 | G13: =Inputs!$C$135/100 | H13: =Inputs!$C$143/100
A14: Regulatory drag, North America | B14: pp | C14: =Inputs!$C$43*Inputs!$C$151/100 | D14: =Inputs!$C$43*Inputs!$C$151/100 | E14: =Inputs!$C$66*Inputs!$C$155/100 | F14: =Inputs!$C$66*Inputs!$C$155/100 | G14: =Inputs!$C$66*Inputs!$C$155/100 | H14: =Inputs!$C$66*Inputs!$C$155/100 | K14: =Inputs!$C$89*Inputs!$C$159/100
A15: Regulatory drag, EMEA | B15: pp | C15: =Inputs!$C$43*Inputs!$C$152/100 | D15: =Inputs!$C$43*Inputs!$C$152/100 | E15: =Inputs!$C$66*Inputs!$C$156/100 | F15: =Inputs!$C$66*Inputs!$C$156/100 | G15: =Inputs!$C$66*Inputs!$C$156/100 | H15: =Inputs!$C$66*Inputs!$C$156/100 | K15: =Inputs!$C$89*Inputs!$C$160/100
A16: Regulatory drag, Latin America | B16: pp | C16: =Inputs!$C$43*Inputs!$C$153/100 | D16: =Inputs!$C$43*Inputs!$C$153/100 | E16: =Inputs!$C$66*Inputs!$C$157/100 | F16: =Inputs!$C$66*Inputs!$C$157/100 | G16: =Inputs!$C$66*Inputs!$C$157/100 | H16: =Inputs!$C$66*Inputs!$C$157/100 | K16: =Inputs!$C$89*Inputs!$C$161/100
A17: Regulatory drag, Asia Pacific | B17: pp | C17: =Inputs!$C$43*Inputs!$C$154/100 | D17: =Inputs!$C$43*Inputs!$C$154/100 | E17: =Inputs!$C$66*Inputs!$C$158/100 | F17: =Inputs!$C$66*Inputs!$C$158/100 | G17: =Inputs!$C$66*Inputs!$C$158/100 | H17: =Inputs!$C$66*Inputs!$C$158/100 | K17: =Inputs!$C$89*Inputs!$C$162/100
A18: Nights, North America | B18: M | C18: =C6*(1+C10-C14) | D18: =D6*(1+D10-D14) | E18: =E6*(1+E10-E14) | F18: =F6*(1+F10-F14) | G18: =G6*(1+G10-G14) | H18: =H6*(1+H10-H14) | I18: =D18/D22*I22 | J18: =SUM(E18:H18) | K18: =J18/J22*K22
A19: Nights, EMEA | B19: M | C19: =C7*(1+C11-C15) | D19: =D7*(1+D11-D15) | E19: =E7*(1+E11-E15) | F19: =F7*(1+F11-F15) | G19: =G7*(1+G11-G15) | H19: =H7*(1+H11-H15) | I19: =D19/D22*I22 | J19: =SUM(E19:H19) | K19: =J19/J22*K22
A20: Nights, Latin America | B20: M | C20: =C8*(1+C12-C16) | D20: =D8*(1+D12-D16) | E20: =E8*(1+E12-E16) | F20: =F8*(1+F12-F16) | G20: =G8*(1+G12-G16) | H20: =H8*(1+H12-H16) | I20: =D20/D22*I22 | J20: =SUM(E20:H20) | K20: =J20/J22*K22
A21: Nights, Asia Pacific | B21: M | C21: =C9*(1+C13-C17) | D21: =D9*(1+D13-D17) | E21: =E9*(1+E13-E17) | F21: =F9*(1+F13-F17) | G21: =G9*(1+G13-G17) | H21: =H9*(1+H13-H17) | I21: =D21/D22*I22 | J21: =SUM(E21:H21) | K21: =J21/J22*K22
A22: Nights & experiences booked | B22: M | C22: =C18+C19+C20+C21 | D22: =D18+D19+D20+D21 | E22: =E18+E19+E20+E21 | F22: =F18+F19+F20+F21 | G22: =G18+G19+G20+G21 | H22: =H18+H19+H20+H21 | I22: =History!$B$44+C22+D22 | J22: =SUM(E22:H22) | K22: =J22*(1+Inputs!$C$93-J18/J22*K14-J19/J22*K15-J20/J22*K16-J21/J22*K17)
A23: Nights growth | B23: y/y | C23: =C22/History!$B$51-1 | D23: =D22/History!$B$60-1 | E23: =E22/History!$B$69-1 | F23: =F22/History!$B$78-1 | G23: =G22/C22-1 | H23: =H22/D22-1 | I23: =I22/History!$B$30-1 | J23: =J22/I22-1 | K23: =K22/J22-1
A24: ADR ex-FX growth | B24: y/y | C24: =Inputs!$C$104/100 | D24: =Inputs!$C$112/100 | E24: =Inputs!$C$120/100 | F24: =Inputs!$C$128/100 | G24: =Inputs!$C$136/100 | H24: =Inputs!$C$144/100 | K24: =Inputs!$C$94
A25: FX effect on ADR | B25: pp | C25: =Inputs!$C$106/100 | D25: =Inputs!$C$114/100 | E25: =Inputs!$C$122/100 | F25: =Inputs!$C$130/100 | G25: =Inputs!$C$138/100 | H25: =Inputs!$C$146/100 | K25: =Inputs!$C$96
A26: ADR | B26: $ | C26: =History!$B$53*(1+C24)*(1+C25) | D26: =History!$B$62*(1+D24)*(1+D25) | E26: =History!$B$71*(1+E24)*(1+E25) | F26: =History!$B$80*(1+F24)*(1+F25) | G26: =C26*(1+G24)*(1+G25) | H26: =D26*(1+H24)*(1+H25) | I26: =I28/I22 | J26: =J28/J22 | K26: =K28/K22
A27: ADR growth (reported) | B27: y/y | C27: =C26/History!$B$53-1 | D27: =D26/History!$B$62-1 | E27: =E26/History!$B$71-1 | F27: =F26/History!$B$80-1 | G27: =G26/C26-1 | H27: =H26/D26-1 | I27: =I26/History!$B$33-1 | J27: =J26/I26-1 | K27: =K26/J26-1
A28: Gross booking value | B28: $M | C28: =C22*C26 | D28: =D22*D26 | E28: =E22*E26 | F28: =F22*F26 | G28: =G22*G26 | H28: =H22*H26 | I28: =History!$B$45+C28+D28 | J28: =SUM(E28:H28) | K28: =K22*J26*(1+K24)*(1+K25)
A29: GBV growth | B29: y/y | C29: =C28/History!$B$52-1 | D29: =D28/History!$B$61-1 | E29: =E28/History!$B$70-1 | F29: =F28/History!$B$79-1 | G29: =G28/C28-1 | H29: =H28/D28-1 | I29: =I28/History!$B$31-1 | J29: =J28/I28-1 | K29: =K28/J28-1
A30: Take rate, assumed (prior-year quarter + bps) | B30: % | C30: =History!$B$55+Inputs!$C$26/10000 | D30: =History!$B$64+Inputs!$C$26/10000 | E30: =History!$B$73+Inputs!$C$49/10000 | F30: =History!$B$82+Inputs!$C$49/10000 | G30: =C30+Inputs!$C$49/10000 | H30: =D30+Inputs!$C$49/10000 | I30: =(History!$B$46+C28*C30+D28*D30)/I28 | J30: =(E28*E30+F28*F30+G28*G30+H28*H30)/J28 | K30: =J30+Inputs!$C$72/10000
A31: FX effect on revenue (lagged) | B31: pp | C31: =Inputs!$C$105/100 | D31: =Inputs!$C$113/100 | E31: =Inputs!$C$121/100 | F31: =Inputs!$C$129/100 | G31: =Inputs!$C$137/100 | H31: =Inputs!$C$145/100 | K31: =Inputs!$C$95
A32: FX timing wedge (revenue FX less ADR FX) | B32: pp | C32: =(1+C31)/(1+C25)-1 | D32: =(1+D31)/(1+D25)-1 | E32: =(1+E31)/(1+E25)-1 | F32: =(1+F31)/(1+F25)-1 | G32: =(1+G31)/(1+G25)-1 | H32: =(1+H31)/(1+H25)-1 | K32: =(1+K31)/(1+K25)-1
A33: Core revenue (GBV x take x wedge) | B33: $M | C33: =C28*C30*(1+C32) | D33: =D28*D30*(1+D32) | E33: =E28*E30*(1+E32) | F33: =F28*F30*(1+F32) | G33: =G28*G30*(1+G32) | H33: =H28*H30*(1+H32) | I33: =History!$B$46+C33+D33 | J33: =SUM(E33:H33) | K33: =K28*K30*(1+K32)
A34: Implied reported take rate (core revenue / GBV) | B34: % | C34: =C33/C28 | D34: =D33/D28 | E34: =E33/E28 | F34: =F33/F28 | G34: =G33/G28 | H34: =H33/H28 | I34: =I33/I28 | J34: =J33/J28 | K34: =K33/K28
A35: New business outside GBV x take, incremental | B35: $M | C35: =I35*C33/(C33+D33) | D35: =I35*D33/(C33+D33) | E35: =J35*E33/SUM(E33:H33) | F35: =J35*F33/SUM(E33:H33) | G35: =J35*G33/SUM(E33:H33) | H35: =J35*H33/SUM(E33:H33) | I35: =Inputs!$C$41-History!$B$43*I33/History!$B$32 | J35: =Inputs!$C$64-History!$B$43*J33/History!$B$32 | K35: =Inputs!$C$87-History!$B$43*K33/History!$B$32
A36: REVENUE | B36: $M | C36: =C33+C35 | D36: =D33+D35 | E36: =E33+E35 | F36: =F33+F35 | G36: =G33+G35 | H36: =H33+H35 | I36: =I33+I35 | J36: =J33+J35 | K36: =K33+K35
A37: Revenue growth | B37: y/y | C37: =C36/History!$B$54-1 | D37: =D36/History!$B$63-1 | E37: =E36/History!$B$72-1 | F37: =F36/History!$B$81-1 | G37: =G36/C36-1 | H37: =H36/D36-1 | I37: =I36/History!$B$32-1 | J37: =J36/I36-1 | K37: =K36/J36-1
A38: Seasonal margin spread vs FY2026 (2027 quarters) | B38: pts | E38: =History!$B$99-Costs!$D$22 | F38: =History!$B$100-Costs!$D$22 | G38: =Inputs!$C$107/100-Costs!$D$22 | H38: =Inputs!$C$115/100-Costs!$D$22
A39: Correction so the 2027 quarters reproduce the FY2027 margin | B39: pts | E39: =-(E38*E36+F38*F36+G38*G36+H38*H36)/SUM(E36:H36) | F39: =-(E38*E36+F38*F36+G38*G36+H38*H36)/SUM(E36:H36) | G39: =-(E38*E36+F38*F36+G38*G36+H38*H36)/SUM(E36:H36) | H39: =-(E38*E36+F38*F36+G38*G36+H38*H36)/SUM(E36:H36)
A40: Adj. EBITDA margin | B40: % | C40: =Inputs!$C$107/100 | D40: =Inputs!$C$115/100 | E40: =Costs!$E$22+E38+E39 | F40: =Costs!$E$22+F38+F39 | G40: =Costs!$E$22+G38+G39 | H40: =Costs!$E$22+H38+H39 | I40: =Costs!$D$22 | J40: =Costs!$E$22 | K40: =Costs!$F$22
A41: Adj. EBITDA | B41: $M | C41: =C36*C40 | D41: =D36*D40 | E41: =E36*E40 | F41: =F36*F40 | G41: =G36*G40 | H41: =H36*H40 | I41: =Costs!$D$21 | J41: =Costs!$E$21 | K41: =Costs!$F$21
A42: Memo: seasonal share of full-year nights | B42: % | C42: =C22/I22 | D42: =D22/I22 | E42: =E22/J22 | F42: =F22/J22 | G42: =G22/J22 | H42: =H22/J22
A43: Memo: 2023-2025 mean seasonal share | B43: % | C43: =History!$B$97 | D43: =History!$B$98 | E43: =History!$B$95 | F43: =History!$B$96 | G43: =History!$B$97 | H43: =History!$B$98
A45: BASE CASE
A46: Line | B46: Unit | C46: 3Q26 | D46: 4Q26 | E46: 1Q27 | F46: 2Q27 | G46: 3Q27 | H46: 4Q27 | I46: FY2026E | J46: FY2027E | K46: FY2028E
A47: Prior-year nights, North America | B47: M | C47: =History!$B$51*History!$B$56 | D47: =History!$B$60*History!$B$65 | E47: =History!$B$69*History!$B$74 | F47: =History!$B$78*History!$B$83 | G47: =C59 | H47: =D59
A48: Prior-year nights, EMEA | B48: M | C48: =History!$B$51*History!$B$57 | D48: =History!$B$60*History!$B$66 | E48: =History!$B$69*History!$B$75 | F48: =History!$B$78*History!$B$84 | G48: =C60 | H48: =D60
A49: Prior-year nights, Latin America | B49: M | C49: =History!$B$51*History!$B$58 | D49: =History!$B$60*History!$B$67 | E49: =History!$B$69*History!$B$76 | F49: =History!$B$78*History!$B$85 | G49: =C61 | H49: =D61
A50: Prior-year nights, Asia Pacific | B50: M | C50: =History!$B$51*History!$B$59 | D50: =History!$B$60*History!$B$68 | E50: =History!$B$69*History!$B$77 | F50: =History!$B$78*History!$B$86 | G50: =C62 | H50: =D62
A51: Nights growth, North America | B51: y/y | C51: =Inputs!$D$100/100 | D51: =Inputs!$D$108/100 | E51: =Inputs!$D$116/100 | F51: =Inputs!$D$124/100 | G51: =Inputs!$D$132/100 | H51: =Inputs!$D$140/100
A52: Nights growth, EMEA | B52: y/y | C52: =Inputs!$D$101/100 | D52: =Inputs!$D$109/100 | E52: =Inputs!$D$117/100 | F52: =Inputs!$D$125/100 | G52: =Inputs!$D$133/100 | H52: =Inputs!$D$141/100
A53: Nights growth, Latin America | B53: y/y | C53: =Inputs!$D$102/100 | D53: =Inputs!$D$110/100 | E53: =Inputs!$D$118/100 | F53: =Inputs!$D$126/100 | G53: =Inputs!$D$134/100 | H53: =Inputs!$D$142/100
A54: Nights growth, Asia Pacific | B54: y/y | C54: =Inputs!$D$103/100 | D54: =Inputs!$D$111/100 | E54: =Inputs!$D$119/100 | F54: =Inputs!$D$127/100 | G54: =Inputs!$D$135/100 | H54: =Inputs!$D$143/100
A55: Regulatory drag, North America | B55: pp | C55: =Inputs!$D$43*Inputs!$C$151/100 | D55: =Inputs!$D$43*Inputs!$C$151/100 | E55: =Inputs!$D$66*Inputs!$C$155/100 | F55: =Inputs!$D$66*Inputs!$C$155/100 | G55: =Inputs!$D$66*Inputs!$C$155/100 | H55: =Inputs!$D$66*Inputs!$C$155/100 | K55: =Inputs!$D$89*Inputs!$C$159/100
A56: Regulatory drag, EMEA | B56: pp | C56: =Inputs!$D$43*Inputs!$C$152/100 | D56: =Inputs!$D$43*Inputs!$C$152/100 | E56: =Inputs!$D$66*Inputs!$C$156/100 | F56: =Inputs!$D$66*Inputs!$C$156/100 | G56: =Inputs!$D$66*Inputs!$C$156/100 | H56: =Inputs!$D$66*Inputs!$C$156/100 | K56: =Inputs!$D$89*Inputs!$C$160/100
A57: Regulatory drag, Latin America | B57: pp | C57: =Inputs!$D$43*Inputs!$C$153/100 | D57: =Inputs!$D$43*Inputs!$C$153/100 | E57: =Inputs!$D$66*Inputs!$C$157/100 | F57: =Inputs!$D$66*Inputs!$C$157/100 | G57: =Inputs!$D$66*Inputs!$C$157/100 | H57: =Inputs!$D$66*Inputs!$C$157/100 | K57: =Inputs!$D$89*Inputs!$C$161/100
A58: Regulatory drag, Asia Pacific | B58: pp | C58: =Inputs!$D$43*Inputs!$C$154/100 | D58: =Inputs!$D$43*Inputs!$C$154/100 | E58: =Inputs!$D$66*Inputs!$C$158/100 | F58: =Inputs!$D$66*Inputs!$C$158/100 | G58: =Inputs!$D$66*Inputs!$C$158/100 | H58: =Inputs!$D$66*Inputs!$C$158/100 | K58: =Inputs!$D$89*Inputs!$C$162/100
A59: Nights, North America | B59: M | C59: =C47*(1+C51-C55) | D59: =D47*(1+D51-D55) | E59: =E47*(1+E51-E55) | F59: =F47*(1+F51-F55) | G59: =G47*(1+G51-G55) | H59: =H47*(1+H51-H55) | I59: =D59/D63*I63 | J59: =SUM(E59:H59) | K59: =J59/J63*K63
A60: Nights, EMEA | B60: M | C60: =C48*(1+C52-C56) | D60: =D48*(1+D52-D56) | E60: =E48*(1+E52-E56) | F60: =F48*(1+F52-F56) | G60: =G48*(1+G52-G56) | H60: =H48*(1+H52-H56) | I60: =D60/D63*I63 | J60: =SUM(E60:H60) | K60: =J60/J63*K63
A61: Nights, Latin America | B61: M | C61: =C49*(1+C53-C57) | D61: =D49*(1+D53-D57) | E61: =E49*(1+E53-E57) | F61: =F49*(1+F53-F57) | G61: =G49*(1+G53-G57) | H61: =H49*(1+H53-H57) | I61: =D61/D63*I63 | J61: =SUM(E61:H61) | K61: =J61/J63*K63
A62: Nights, Asia Pacific | B62: M | C62: =C50*(1+C54-C58) | D62: =D50*(1+D54-D58) | E62: =E50*(1+E54-E58) | F62: =F50*(1+F54-F58) | G62: =G50*(1+G54-G58) | H62: =H50*(1+H54-H58) | I62: =D62/D63*I63 | J62: =SUM(E62:H62) | K62: =J62/J63*K63
A63: Nights & experiences booked | B63: M | C63: =C59+C60+C61+C62 | D63: =D59+D60+D61+D62 | E63: =E59+E60+E61+E62 | F63: =F59+F60+F61+F62 | G63: =G59+G60+G61+G62 | H63: =H59+H60+H61+H62 | I63: =History!$B$44+C63+D63 | J63: =SUM(E63:H63) | K63: =J63*(1+Inputs!$D$93-J59/J63*K55-J60/J63*K56-J61/J63*K57-J62/J63*K58)
A64: Nights growth | B64: y/y | C64: =C63/History!$B$51-1 | D64: =D63/History!$B$60-1 | E64: =E63/History!$B$69-1 | F64: =F63/History!$B$78-1 | G64: =G63/C63-1 | H64: =H63/D63-1 | I64: =I63/History!$B$30-1 | J64: =J63/I63-1 | K64: =K63/J63-1
A65: ADR ex-FX growth | B65: y/y | C65: =Inputs!$D$104/100 | D65: =Inputs!$D$112/100 | E65: =Inputs!$D$120/100 | F65: =Inputs!$D$128/100 | G65: =Inputs!$D$136/100 | H65: =Inputs!$D$144/100 | K65: =Inputs!$D$94
A66: FX effect on ADR | B66: pp | C66: =Inputs!$D$106/100 | D66: =Inputs!$D$114/100 | E66: =Inputs!$D$122/100 | F66: =Inputs!$D$130/100 | G66: =Inputs!$D$138/100 | H66: =Inputs!$D$146/100 | K66: =Inputs!$D$96
A67: ADR | B67: $ | C67: =History!$B$53*(1+C65)*(1+C66) | D67: =History!$B$62*(1+D65)*(1+D66) | E67: =History!$B$71*(1+E65)*(1+E66) | F67: =History!$B$80*(1+F65)*(1+F66) | G67: =C67*(1+G65)*(1+G66) | H67: =D67*(1+H65)*(1+H66) | I67: =I69/I63 | J67: =J69/J63 | K67: =K69/K63
A68: ADR growth (reported) | B68: y/y | C68: =C67/History!$B$53-1 | D68: =D67/History!$B$62-1 | E68: =E67/History!$B$71-1 | F68: =F67/History!$B$80-1 | G68: =G67/C67-1 | H68: =H67/D67-1 | I68: =I67/History!$B$33-1 | J68: =J67/I67-1 | K68: =K67/J67-1
A69: Gross booking value | B69: $M | C69: =C63*C67 | D69: =D63*D67 | E69: =E63*E67 | F69: =F63*F67 | G69: =G63*G67 | H69: =H63*H67 | I69: =History!$B$45+C69+D69 | J69: =SUM(E69:H69) | K69: =K63*J67*(1+K65)*(1+K66)
A70: GBV growth | B70: y/y | C70: =C69/History!$B$52-1 | D70: =D69/History!$B$61-1 | E70: =E69/History!$B$70-1 | F70: =F69/History!$B$79-1 | G70: =G69/C69-1 | H70: =H69/D69-1 | I70: =I69/History!$B$31-1 | J70: =J69/I69-1 | K70: =K69/J69-1
A71: Take rate, assumed (prior-year quarter + bps) | B71: % | C71: =History!$B$55+Inputs!$D$26/10000 | D71: =History!$B$64+Inputs!$D$26/10000 | E71: =History!$B$73+Inputs!$D$49/10000 | F71: =History!$B$82+Inputs!$D$49/10000 | G71: =C71+Inputs!$D$49/10000 | H71: =D71+Inputs!$D$49/10000 | I71: =(History!$B$46+C69*C71+D69*D71)/I69 | J71: =(E69*E71+F69*F71+G69*G71+H69*H71)/J69 | K71: =J71+Inputs!$D$72/10000
A72: FX effect on revenue (lagged) | B72: pp | C72: =Inputs!$D$105/100 | D72: =Inputs!$D$113/100 | E72: =Inputs!$D$121/100 | F72: =Inputs!$D$129/100 | G72: =Inputs!$D$137/100 | H72: =Inputs!$D$145/100 | K72: =Inputs!$D$95
A73: FX timing wedge (revenue FX less ADR FX) | B73: pp | C73: =(1+C72)/(1+C66)-1 | D73: =(1+D72)/(1+D66)-1 | E73: =(1+E72)/(1+E66)-1 | F73: =(1+F72)/(1+F66)-1 | G73: =(1+G72)/(1+G66)-1 | H73: =(1+H72)/(1+H66)-1 | K73: =(1+K72)/(1+K66)-1
A74: Core revenue (GBV x take x wedge) | B74: $M | C74: =C69*C71*(1+C73) | D74: =D69*D71*(1+D73) | E74: =E69*E71*(1+E73) | F74: =F69*F71*(1+F73) | G74: =G69*G71*(1+G73) | H74: =H69*H71*(1+H73) | I74: =History!$B$46+C74+D74 | J74: =SUM(E74:H74) | K74: =K69*K71*(1+K73)
A75: Implied reported take rate (core revenue / GBV) | B75: % | C75: =C74/C69 | D75: =D74/D69 | E75: =E74/E69 | F75: =F74/F69 | G75: =G74/G69 | H75: =H74/H69 | I75: =I74/I69 | J75: =J74/J69 | K75: =K74/K69
A76: New business outside GBV x take, incremental | B76: $M | C76: =I76*C74/(C74+D74) | D76: =I76*D74/(C74+D74) | E76: =J76*E74/SUM(E74:H74) | F76: =J76*F74/SUM(E74:H74) | G76: =J76*G74/SUM(E74:H74) | H76: =J76*H74/SUM(E74:H74) | I76: =Inputs!$D$41-History!$B$43*I74/History!$B$32 | J76: =Inputs!$D$64-History!$B$43*J74/History!$B$32 | K76: =Inputs!$D$87-History!$B$43*K74/History!$B$32
A77: REVENUE | B77: $M | C77: =C74+C76 | D77: =D74+D76 | E77: =E74+E76 | F77: =F74+F76 | G77: =G74+G76 | H77: =H74+H76 | I77: =I74+I76 | J77: =J74+J76 | K77: =K74+K76
A78: Revenue growth | B78: y/y | C78: =C77/History!$B$54-1 | D78: =D77/History!$B$63-1 | E78: =E77/History!$B$72-1 | F78: =F77/History!$B$81-1 | G78: =G77/C77-1 | H78: =H77/D77-1 | I78: =I77/History!$B$32-1 | J78: =J77/I77-1 | K78: =K77/J77-1
A79: Seasonal margin spread vs FY2026 (2027 quarters) | B79: pts | E79: =History!$B$99-Costs!$D$52 | F79: =History!$B$100-Costs!$D$52 | G79: =Inputs!$D$107/100-Costs!$D$52 | H79: =Inputs!$D$115/100-Costs!$D$52
A80: Correction so the 2027 quarters reproduce the FY2027 margin | B80: pts | E80: =-(E79*E77+F79*F77+G79*G77+H79*H77)/SUM(E77:H77) | F80: =-(E79*E77+F79*F77+G79*G77+H79*H77)/SUM(E77:H77) | G80: =-(E79*E77+F79*F77+G79*G77+H79*H77)/SUM(E77:H77) | H80: =-(E79*E77+F79*F77+G79*G77+H79*H77)/SUM(E77:H77)
A81: Adj. EBITDA margin | B81: % | C81: =Inputs!$D$107/100 | D81: =Inputs!$D$115/100 | E81: =Costs!$E$52+E79+E80 | F81: =Costs!$E$52+F79+F80 | G81: =Costs!$E$52+G79+G80 | H81: =Costs!$E$52+H79+H80 | I81: =Costs!$D$52 | J81: =Costs!$E$52 | K81: =Costs!$F$52
A82: Adj. EBITDA | B82: $M | C82: =C77*C81 | D82: =D77*D81 | E82: =E77*E81 | F82: =F77*F81 | G82: =G77*G81 | H82: =H77*H81 | I82: =Costs!$D$51 | J82: =Costs!$E$51 | K82: =Costs!$F$51
A83: Memo: seasonal share of full-year nights | B83: % | C83: =C63/I63 | D83: =D63/I63 | E83: =E63/J63 | F83: =F63/J63 | G83: =G63/J63 | H83: =H63/J63
A84: Memo: 2023-2025 mean seasonal share | B84: % | C84: =History!$B$97 | D84: =History!$B$98 | E84: =History!$B$95 | F84: =History!$B$96 | G84: =History!$B$97 | H84: =History!$B$98
A86: BULL CASE
A87: Line | B87: Unit | C87: 3Q26 | D87: 4Q26 | E87: 1Q27 | F87: 2Q27 | G87: 3Q27 | H87: 4Q27 | I87: FY2026E | J87: FY2027E | K87: FY2028E
A88: Prior-year nights, North America | B88: M | C88: =History!$B$51*History!$B$56 | D88: =History!$B$60*History!$B$65 | E88: =History!$B$69*History!$B$74 | F88: =History!$B$78*History!$B$83 | G88: =C100 | H88: =D100
A89: Prior-year nights, EMEA | B89: M | C89: =History!$B$51*History!$B$57 | D89: =History!$B$60*History!$B$66 | E89: =History!$B$69*History!$B$75 | F89: =History!$B$78*History!$B$84 | G89: =C101 | H89: =D101
A90: Prior-year nights, Latin America | B90: M | C90: =History!$B$51*History!$B$58 | D90: =History!$B$60*History!$B$67 | E90: =History!$B$69*History!$B$76 | F90: =History!$B$78*History!$B$85 | G90: =C102 | H90: =D102
A91: Prior-year nights, Asia Pacific | B91: M | C91: =History!$B$51*History!$B$59 | D91: =History!$B$60*History!$B$68 | E91: =History!$B$69*History!$B$77 | F91: =History!$B$78*History!$B$86 | G91: =C103 | H91: =D103
A92: Nights growth, North America | B92: y/y | C92: =Inputs!$E$100/100 | D92: =Inputs!$E$108/100 | E92: =Inputs!$E$116/100 | F92: =Inputs!$E$124/100 | G92: =Inputs!$E$132/100 | H92: =Inputs!$E$140/100
A93: Nights growth, EMEA | B93: y/y | C93: =Inputs!$E$101/100 | D93: =Inputs!$E$109/100 | E93: =Inputs!$E$117/100 | F93: =Inputs!$E$125/100 | G93: =Inputs!$E$133/100 | H93: =Inputs!$E$141/100
A94: Nights growth, Latin America | B94: y/y | C94: =Inputs!$E$102/100 | D94: =Inputs!$E$110/100 | E94: =Inputs!$E$118/100 | F94: =Inputs!$E$126/100 | G94: =Inputs!$E$134/100 | H94: =Inputs!$E$142/100
A95: Nights growth, Asia Pacific | B95: y/y | C95: =Inputs!$E$103/100 | D95: =Inputs!$E$111/100 | E95: =Inputs!$E$119/100 | F95: =Inputs!$E$127/100 | G95: =Inputs!$E$135/100 | H95: =Inputs!$E$143/100
A96: Regulatory drag, North America | B96: pp | C96: =Inputs!$E$43*Inputs!$C$151/100 | D96: =Inputs!$E$43*Inputs!$C$151/100 | E96: =Inputs!$E$66*Inputs!$C$155/100 | F96: =Inputs!$E$66*Inputs!$C$155/100 | G96: =Inputs!$E$66*Inputs!$C$155/100 | H96: =Inputs!$E$66*Inputs!$C$155/100 | K96: =Inputs!$E$89*Inputs!$C$159/100
A97: Regulatory drag, EMEA | B97: pp | C97: =Inputs!$E$43*Inputs!$C$152/100 | D97: =Inputs!$E$43*Inputs!$C$152/100 | E97: =Inputs!$E$66*Inputs!$C$156/100 | F97: =Inputs!$E$66*Inputs!$C$156/100 | G97: =Inputs!$E$66*Inputs!$C$156/100 | H97: =Inputs!$E$66*Inputs!$C$156/100 | K97: =Inputs!$E$89*Inputs!$C$160/100
A98: Regulatory drag, Latin America | B98: pp | C98: =Inputs!$E$43*Inputs!$C$153/100 | D98: =Inputs!$E$43*Inputs!$C$153/100 | E98: =Inputs!$E$66*Inputs!$C$157/100 | F98: =Inputs!$E$66*Inputs!$C$157/100 | G98: =Inputs!$E$66*Inputs!$C$157/100 | H98: =Inputs!$E$66*Inputs!$C$157/100 | K98: =Inputs!$E$89*Inputs!$C$161/100
A99: Regulatory drag, Asia Pacific | B99: pp | C99: =Inputs!$E$43*Inputs!$C$154/100 | D99: =Inputs!$E$43*Inputs!$C$154/100 | E99: =Inputs!$E$66*Inputs!$C$158/100 | F99: =Inputs!$E$66*Inputs!$C$158/100 | G99: =Inputs!$E$66*Inputs!$C$158/100 | H99: =Inputs!$E$66*Inputs!$C$158/100 | K99: =Inputs!$E$89*Inputs!$C$162/100
A100: Nights, North America | B100: M | C100: =C88*(1+C92-C96) | D100: =D88*(1+D92-D96) | E100: =E88*(1+E92-E96) | F100: =F88*(1+F92-F96) | G100: =G88*(1+G92-G96) | H100: =H88*(1+H92-H96) | I100: =D100/D104*I104 | J100: =SUM(E100:H100) | K100: =J100/J104*K104
A101: Nights, EMEA | B101: M | C101: =C89*(1+C93-C97) | D101: =D89*(1+D93-D97) | E101: =E89*(1+E93-E97) | F101: =F89*(1+F93-F97) | G101: =G89*(1+G93-G97) | H101: =H89*(1+H93-H97) | I101: =D101/D104*I104 | J101: =SUM(E101:H101) | K101: =J101/J104*K104
A102: Nights, Latin America | B102: M | C102: =C90*(1+C94-C98) | D102: =D90*(1+D94-D98) | E102: =E90*(1+E94-E98) | F102: =F90*(1+F94-F98) | G102: =G90*(1+G94-G98) | H102: =H90*(1+H94-H98) | I102: =D102/D104*I104 | J102: =SUM(E102:H102) | K102: =J102/J104*K104
A103: Nights, Asia Pacific | B103: M | C103: =C91*(1+C95-C99) | D103: =D91*(1+D95-D99) | E103: =E91*(1+E95-E99) | F103: =F91*(1+F95-F99) | G103: =G91*(1+G95-G99) | H103: =H91*(1+H95-H99) | I103: =D103/D104*I104 | J103: =SUM(E103:H103) | K103: =J103/J104*K104
...

Sheet Costs
A1: Cost stack, adj. EBITDA and net income - lever by lever
A2: Mechanics from WS07 07_margin_lever_model.py: cost of revenue on GBV dollars, operations & support on nights, the rest on cash growth rates.
A4: BEAR CASE
A5: Line | B5: Unit | C5: FY2025A | D5: FY2026E | E5: FY2027E | F5: FY2028E
A6: Revenue | B6: $M | C6: =History!$B$32 | D6: =Revenue!$I$36 | E6: =Revenue!$J$36 | F6: =Revenue!$K$36
A7: GBV | B7: $M | C7: =History!$B$31 | D7: =Revenue!$I$28 | E7: =Revenue!$J$28 | F7: =Revenue!$K$28
A8: Nights | B8: M | C8: =History!$B$30 | D8: =Revenue!$I$22 | E8: =Revenue!$J$22 | F8: =Revenue!$K$22
A9: Cost of revenue, cash | B9: $M | C9: =History!$B$37 | D9: =C9/C7*(1+Inputs!$C$27)*D7 | E9: =D9/D7*(1+Inputs!$C$50)*E7 | F9: =E9/E7*(1+Inputs!$C$73)*F7
A10: Operations & support, cash | B10: $M | C10: =History!$B$38 | D10: =C10/C8*(1+Inputs!$C$28)*D8 | E10: =D10/D8*(1+Inputs!$C$51)*E8 | F10: =E10/E8*(1+Inputs!$C$74)*F8
A11: Product development, cash (ex-SBC) | B11: $M | C11: =History!$B$39 | D11: =C11*(1+Inputs!$C$29) | E11: =D11*(1+Inputs!$C$52) | F11: =E11*(1+Inputs!$C$75)
A12: Brand & performance marketing | B12: $M | C12: =History!$B$40 | D12: =C12*(1+Inputs!$C$30) | E12: =D12*(1+Inputs!$C$53) | F12: =E12*(1+Inputs!$C$76)
A13: Field operations & policy, cash | B13: $M | C13: =History!$B$41 | D13: =C13*(1+Inputs!$C$31) | E13: =D13*(1+Inputs!$C$54) | F13: =E13*(1+Inputs!$C$77)
A14: G&A, cash | B14: $M | C14: =History!$B$42 | D14: =C14*(1+Inputs!$C$32) | E14: =D14*(1+Inputs!$C$55) | F14: =E14*(1+Inputs!$C$78)
A15: New-business cost of the incremental revenue | B15: $M | C15: =0 | D15: =Revenue!$I$35*(1-Inputs!$C$20) | E15: =Revenue!$J$35*(1-Inputs!$C$20) | F15: =Revenue!$K$35*(1-Inputs!$C$20)
A16: AI referral cost | B16: $M | C16: =0 | D16: =D6*Inputs!$C$40 | E16: =E6*Inputs!$C$63 | F16: =F6*Inputs!$C$86
A17: Total cash costs | B17: $M | C17: =C9+C10+C11+C12+C13+C14+C15+C16 | D17: =D9+D10+D11+D12+D13+D14+D15+D16 | E17: =E9+E10+E11+E12+E13+E14+E15+E16 | F17: =F9+F10+F11+F12+F13+F14+F15+F16
A18: D&A and other add-backs | B18: $M | C18: =History!$B$109 | D18: =D6*Inputs!$C$33 | E18: =E6*Inputs!$C$56 | F18: =F6*Inputs!$C$79
A19: Adj. EBITDA before the WS07 38% ceiling | B19: $M | C19: =History!$B$35 | D19: =D6-D17+D18 | E19: =E6-E17+E18 | F19: =F6-F17+F18
A20: Margin before the ceiling | B20: % | C20: =C19/C6 | D20: =D19/D6 | E20: =E19/E6 | F20: =F19/F6
A21: ADJUSTED EBITDA (capped at the WS07 ceiling) | B21: $M | C21: =History!$B$35 | D21: =MIN(D19,D6*Inputs!$C$21) | E21: =MIN(E19,E6*Inputs!$C$21) | F21: =MIN(F19,F6*Inputs!$C$21)
A22: Adj. EBITDA margin | B22: % | C22: =C21/C6 | D22: =D21/D6 | E22: =E21/E6 | F22: =F21/F6
A23: Stock-based compensation | B23: $M | C23: =History!$B$36 | D23: =C23*(1+Inputs!$C$34) | E23: =D23*(1+Inputs!$C$57) | F23: =E23*(1+Inputs!$C$80)
A24: SBC, % of revenue | B24: % | C24: =C23/C6 | D24: =D23/D6 | E24: =E23/E6 | F24: =F23/F6
A25: D&A | B25: $M | C25: =History!$B$108 | D25: =D6*Inputs!$C$46 | E25: =E6*Inputs!$C$69 | F25: =F6*Inputs!$C$92
A26: GAAP operating income | B26: $M | D26: =D21-D23-D18 | E26: =E21-E23-E18 | F26: =F21-F23-F18
A27: GAAP operating margin | B27: % | D27: =D26/D6 | E27: =E26/E6 | F27: =F26/F6
A28: Interest income | B28: $M | C28: =History!$B$110 | D28: =Inputs!$C$35 | E28: =Inputs!$C$58 | F28: =Inputs!$C$81
A29: Interest expense | B29: $M | C29: =History!$B$111 | D29: =Inputs!$C$36 | E29: =Inputs!$C$59 | F29: =Inputs!$C$82
A30: Pre-tax income | B30: $M | D30: =D26+D28-D29 | E30: =E26+E28-E29 | F30: =F26+F28-F29
A31: Effective tax rate | B31: % | D31: =Inputs!$C$39 | E31: =Inputs!$C$62 | F31: =Inputs!$C$85
A32: Net income | B32: $M | D32: =D30*(1-D31) | E32: =E30*(1-E31) | F32: =F30*(1-F31)
A34: BASE CASE
A35: Line | B35: Unit | C35: FY2025A | D35: FY2026E | E35: FY2027E | F35: FY2028E
A36: Revenue | B36: $M | C36: =History!$B$32 | D36: =Revenue!$I$77 | E36: =Revenue!$J$77 | F36: =Revenue!$K$77
A37: GBV | B37: $M | C37: =History!$B$31 | D37: =Revenue!$I$69 | E37: =Revenue!$J$69 | F37: =Revenue!$K$69
A38: Nights | B38: M | C38: =History!$B$30 | D38: =Revenue!$I$63 | E38: =Revenue!$J$63 | F38: =Revenue!$K$63
A39: Cost of revenue, cash | B39: $M | C39: =History!$B$37 | D39: =C39/C37*(1+Inputs!$D$27)*D37 | E39: =D39/D37*(1+Inputs!$D$50)*E37 | F39: =E39/E37*(1+Inputs!$D$73)*F37
A40: Operations & support, cash | B40: $M | C40: =History!$B$38 | D40: =C40/C38*(1+Inputs!$D$28)*D38 | E40: =D40/D38*(1+Inputs!$D$51)*E38 | F40: =E40/E38*(1+Inputs!$D$74)*F38
A41: Product development, cash (ex-SBC) | B41: $M | C41: =History!$B$39 | D41: =C41*(1+Inputs!$D$29) | E41: =D41*(1+Inputs!$D$52) | F41: =E41*(1+Inputs!$D$75)
A42: Brand & performance marketing | B42: $M | C42: =History!$B$40 | D42: =C42*(1+Inputs!$D$30) | E42: =D42*(1+Inputs!$D$53) | F42: =E42*(1+Inputs!$D$76)
A43: Field operations & policy, cash | B43: $M | C43: =History!$B$41 | D43: =C43*(1+Inputs!$D$31) | E43: =D43*(1+Inputs!$D$54) | F43: =E43*(1+Inputs!$D$77)
A44: G&A, cash | B44: $M | C44: =History!$B$42 | D44: =C44*(1+Inputs!$D$32) | E44: =D44*(1+Inputs!$D$55) | F44: =E44*(1+Inputs!$D$78)
A45: New-business cost of the incremental revenue | B45: $M | C45: =0 | D45: =Revenue!$I$76*(1-Inputs!$D$20) | E45: =Revenue!$J$76*(1-Inputs!$D$20) | F45: =Revenue!$K$76*(1-Inputs!$D$20)
A46: AI referral cost | B46: $M | C46: =0 | D46: =D36*Inputs!$D$40 | E46: =E36*Inputs!$D$63 | F46: =F36*Inputs!$D$86
A47: Total cash costs | B47: $M | C47: =C39+C40+C41+C42+C43+C44+C45+C46 | D47: =D39+D40+D41+D42+D43+D44+D45+D46 | E47: =E39+E40+E41+E42+E43+E44+E45+E46 | F47: =F39+F40+F41+F42+F43+F44+F45+F46
A48: D&A and other add-backs | B48: $M | C48: =History!$B$109 | D48: =D36*Inputs!$D$33 | E48: =E36*Inputs!$D$56 | F48: =F36*Inputs!$D$79
A49: Adj. EBITDA before the WS07 38% ceiling | B49: $M | C49: =History!$B$35 | D49: =D36-D47+D48 | E49: =E36-E47+E48 | F49: =F36-F47+F48
A50: Margin before the ceiling | B50: % | C50: =C49/C36 | D50: =D49/D36 | E50: =E49/E36 | F50: =F49/F36
A51: ADJUSTED EBITDA (capped at the WS07 ceiling) | B51: $M | C51: =History!$B$35 | D51: =MIN(D49,D36*Inputs!$D$21) | E51: =MIN(E49,E36*Inputs!$D$21) | F51: =MIN(F49,F36*Inputs!$D$21)
A52: Adj. EBITDA margin | B52: % | C52: =C51/C36 | D52: =D51/D36 | E52: =E51/E36 | F52: =F51/F36
A53: Stock-based compensation | B53: $M | C53: =History!$B$36 | D53: =C53*(1+Inputs!$D$34) | E53: =D53*(1+Inputs!$D$57) | F53: =E53*(1+Inputs!$D$80)
A54: SBC, % of revenue | B54: % | C54: =C53/C36 | D54: =D53/D36 | E54: =E53/E36 | F54: =F53/F36
A55: D&A | B55: $M | C55: =History!$B$108 | D55: =D36*Inputs!$D$46 | E55: =E36*Inputs!$D$69 | F55: =F36*Inputs!$D$92
A56: GAAP operating income | B56: $M | D56: =D51-D53-D48 | E56: =E51-E53-E48 | F56: =F51-F53-F48
A57: GAAP operating margin | B57: % | D57: =D56/D36 | E57: =E56/E36 | F57: =F56/F36
A58: Interest income | B58: $M | C58: =History!$B$110 | D58: =Inputs!$D$35 | E58: =Inputs!$D$58 | F58: =Inputs!$D$81
A59: Interest expense | B59: $M | C59: =History!$B$111 | D59: =Inputs!$D$36 | E59: =Inputs!$D$59 | F59: =Inputs!$D$82
A60: Pre-tax income | B60: $M | D60: =D56+D58-D59 | E60: =E56+E58-E59 | F60: =F56+F58-F59
A61: Effective tax rate | B61: % | D61: =Inputs!$D$39 | E61: =Inputs!$D$62 | F61: =Inputs!$D$85
A62: Net income | B62: $M | D62: =D60*(1-D61) | E62: =E60*(1-E61) | F62: =F60*(1-F61)
A64: BULL CASE
A65: Line | B65: Unit | C65: FY2025A | D65: FY2026E | E65: FY2027E | F65: FY2028E
A66: Revenue | B66: $M | C66: =History!$B$32 | D66: =Revenue!$I$118 | E66: =Revenue!$J$118 | F66: =Revenue!$K$118
A67: GBV | B67: $M | C67: =History!$B$31 | D67: =Revenue!$I$110 | E67: =Revenue!$J$110 | F67: =Revenue!$K$110
A68: Nights | B68: M | C68: =History!$B$30 | D68: =Revenue!$I$104 | E68: =Revenue!$J$104 | F68: =Revenue!$K$104
A69: Cost of revenue, cash | B69: $M | C69: =History!$B$37 | D69: =C69/C67*(1+Inputs!$E$27)*D67 | E69: =D69/D67*(1+Inputs!$E$50)*E67 | F69: =E69/E67*(1+Inputs!$E$73)*F67
A70: Operations & support, cash | B70: $M | C70: =History!$B$38 | D70: =C70/C68*(1+Inputs!$E$28)*D68 | E70: =D70/D68*(1+Inputs!$E$51)*E68 | F70: =E70/E68*(1+Inputs!$E$74)*F68
A71: Product development, cash (ex-SBC) | B71: $M | C71: =History!$B$39 | D71: =C71*(1+Inputs!$E$29) | E71: =D71*(1+Inputs!$E$52) | F71: =E71*(1+Inputs!$E$75)
A72: Brand & performance marketing | B72: $M | C72: =History!$B$40 | D72: =C72*(1+Inputs!$E$30) | E72: =D72*(1+Inputs!$E$53) | F72: =E72*(1+Inputs!$E$76)
A73: Field operations & policy, cash | B73: $M | C73: =History!$B$41 | D73: =C73*(1+Inputs!$E$31) | E73: =D73*(1+Inputs!$E$54) | F73: =E73*(1+Inputs!$E$77)
A74: G&A, cash | B74: $M | C74: =History!$B$42 | D74: =C74*(1+Inputs!$E$32) | E74: =D74*(1+Inputs!$E$55) | F74: =E74*(1+Inputs!$E$78)
A75: New-business cost of the incremental revenue | B75: $M | C75: =0 | D75: =Revenue!$I$117*(1-Inputs!$E$20) | E75: =Revenue!$J$117*(1-Inputs!$E$20) | F75: =Revenue!$K$117*(1-Inputs!$E$20)
A76: AI referral cost | B76: $M | C76: =0 | D76: =D66*Inputs!$E$40 | E76: =E66*Inputs!$E$63 | F76: =F66*Inputs!$E$86
A77: Total cash costs | B77: $M | C77: =C69+C70+C71+C72+C73+C74+C75+C76 | D77: =D69+D70+D71+D72+D73+D74+D75+D76 | E77: =E69+E70+E71+E72+E73+E74+E75+E76 | F77: =F69+F70+F71+F72+F73+F74+F75+F76
A78: D&A and other add-backs | B78: $M | C78: =History!$B$109 | D78: =D66*Inputs!$E$33 | E78: =E66*Inputs!$E$56 | F78: =F66*Inputs!$E$79
A79: Adj. EBITDA before the WS07 38% ceiling | B79: $M | C79: =History!$B$35 | D79: =D66-D77+D78 | E79: =E66-E77+E78 | F79: =F66-F77+F78
A80: Margin before the ceiling | B80: % | C80: =C79/C66 | D80: =D79/D66 | E80: =E79/E66 | F80: =F79/F66
A81: ADJUSTED EBITDA (capped at the WS07 ceiling) | B81: $M | C81: =History!$B$35 | D81: =MIN(D79,D66*Inputs!$E$21) | E81: =MIN(E79,E66*Inputs!$E$21) | F81: =MIN(F79,F66*Inputs!$E$21)
A82: Adj. EBITDA margin | B82: % | C82: =C81/C66 | D82: =D81/D66 | E82: =E81/E66 | F82: =F81/F66
A83: Stock-based compensation | B83: $M | C83: =History!$B$36 | D83: =C83*(1+Inputs!$E$34) | E83: =D83*(1+Inputs!$E$57) | F83: =E83*(1+Inputs!$E$80)
A84: SBC, % of revenue | B84: % | C84: =C83/C66 | D84: =D83/D66 | E84: =E83/E66 | F84: =F83/F66
A85: D&A | B85: $M | C85: =History!$B$108 | D85: =D66*Inputs!$E$46 | E85: =E66*Inputs!$E$69 | F85: =F66*Inputs!$E$92
A86: GAAP operating income | B86: $M | D86: =D81-D83-D78 | E86: =E81-E83-E78 | F86: =F81-F83-F78
A87: GAAP operating margin | B87: % | D87: =D86/D66 | E87: =E86/E66 | F87: =F86/F66
A88: Interest income | B88: $M | C88: =History!$B$110 | D88: =Inputs!$E$35 | E88: =Inputs!$E$58 | F88: =Inputs!$E$81
A89: Interest expense | B89: $M | C89: =History!$B$111 | D89: =Inputs!$E$36 | E89: =Inputs!$E$59 | F89: =Inputs!$E$82
A90: Pre-tax income | B90: $M | D90: =D86+D88-D89 | E90: =E86+E88-E89 | F90: =F86+F88-F89
A91: Effective tax rate | B91: % | D91: =Inputs!$E$39 | E91: =Inputs!$E$62 | F91: =Inputs!$E$85
A92: Net income | B92: $M | D92: =D90*(1-D91) | E92: =E90*(1-E91) | F92: =F90*(1-F91)

Sheet Cash
A1: Free cash flow, buybacks and the share-count path
A2: FCF bridge from WS07. Share count: buybacks and RSU issuance at a price growing 5% a year, 35% of SBC withheld for tax. Both roll-forwards start from the same 2Q26 actual (net cash $9,593M, 597M diluted shares) and both consume the SAME flows: for FY2026 only the 2H26 buyback (FY26 less the 1H26 actual $2,139M) and only 2H26 SBC (FY26 less the 1H26 actual $897M); FY2027 and FY2028 take the full year. WS17 finding 3 (the FY2026 share roll applied the FULL-YEAR buyback and SBC to a 30 Jun 2026 count, double-counting the 1H26 repurchase and understating FY2026E shares by 8.55M) was fixed by WS18 here and in 13_driver_model.py. See research/notes/overnight/18_corrections-applied.md.
A4: BEAR CASE
A5: Line | B5: Unit | C5: FY2025A | D5: FY2026E | E5: FY2027E | F5: FY2028E
A6: Adjusted EBITDA | B6: $M | C6: =Costs!$C$21 | D6: =Costs!$D$21 | E6: =Costs!$E$21 | F6: =Costs!$F$21
A7: + Interest income | B7: $M | C7: =History!$B$110 | D7: =Costs!$D$28 | E7: =Costs!$E$28 | F7: =Costs!$F$28
A8: - Interest expense | B8: $M | C8: =-History!$B$111 | D8: =-Costs!$D$29 | E8: =-Costs!$E$29 | F8: =-Costs!$F$29
A9: + Other income / (expense) | B9: $M | C9: =History!$B$112 | D9: =0 | E9: =0 | F9: =0
A10: - Cash taxes | B10: $M | C10: =History!$B$113 | D10: =-Costs!$D$6*Inputs!$C$37 | E10: =-Costs!$E$6*Inputs!$C$60 | F10: =-Costs!$F$6*Inputs!$C$83
A11: + Change in unearned fees | B11: $M | C11: =History!$B$114 | D11: =Costs!$D$6*Inputs!$C$38 | E11: =Costs!$E$6*Inputs!$C$61 | F11: =Costs!$F$6*Inputs!$C$84
A12: + Working-capital residual | B12: $M | C12: =History!$B$115 | D12: =Costs!$D$6*Inputs!$C$45 | E12: =Costs!$E$6*Inputs!$C$68 | F12: =Costs!$F$6*Inputs!$C$91
A13: - Capex | B13: $M | C13: =History!$B$116 | D13: =-Costs!$D$6*Inputs!$C$44 | E13: =-Costs!$E$6*Inputs!$C$67 | F13: =-Costs!$F$6*Inputs!$C$90
A14: FREE CASH FLOW | B14: $M | C14: =C6+C7+C8+C9+C10+C11+C12+C13 | D14: =D6+D7+D8+D9+D10+D11+D12+D13 | E14: =E6+E7+E8+E9+E10+E11+E12+E13 | F14: =F6+F7+F8+F9+F10+F11+F12+F13
A15: FCF margin | B15: % | C15: =C14/History!$B$32 | D15: =D14/Costs!$D$6 | E15: =E14/Costs!$E$6 | F15: =F14/Costs!$F$6
A16: FCF / adj. EBITDA | B16: % | C16: =C14/C6 | D16: =D14/D6 | E16: =E14/E6 | F16: =F14/F6
A17: SBC | B17: $M | C17: =History!$B$36 | D17: =Costs!$D$23 | E17: =Costs!$E$23 | F17: =Costs!$F$23
A18: SBC-ADJUSTED FCF | B18: $M | C18: =C14-C17 | D18: =D14-D17 | E18: =E14-E17 | F18: =F14-F17
A19: SBC-adjusted FCF margin | B19: % | D19: =D18/Costs!$D$6 | E19: =E18/Costs!$E$6 | F19: =F18/Costs!$F$6
A20: Share price used for buybacks and issuance | B20: $ | C20: =Inputs!$C$8 | D20: =Inputs!$C$8*(1+Inputs!$C$19)^0 | E20: =Inputs!$C$8*(1+Inputs!$C$19)^1 | F20: =Inputs!$C$8*(1+Inputs!$C$19)^2
A21: Buybacks | B21: $M | C21: =History!$B$117 | D21: =Inputs!$C$42 | E21: =Inputs!$C$65 | F21: =Inputs!$C$88
A22: RSU tax withholding | B22: $M | C22: =History!$B$118 | D22: =D17*Inputs!$C$18 | E22: =E17*Inputs!$C$18 | F22: =F17*Inputs!$C$18
A23: Diluted shares, period end (FY2025A col = the 2Q26 actual) | B23: M | C23: =Inputs!$C$10 | D23: =C23-(D21-History!$B$48)/D20+(D17-History!$B$50)/D20*(1-Inputs!$C$18) | E23: =D23-E21/E20+E17/E20*(1-Inputs!$C$18) | F23: =E23-F21/F20+F17/F20*(1-Inputs!$C$18)
A24: FCF per share | B24: $ | D24: =D14/D23 | E24: =E14/E23 | F24: =F14/F23
A25: SBC-adjusted FCF per share | B25: $ | D25: =D18/D23 | E25: =E18/E23 | F25: =F18/F23
A26: Earnings proxy per share (net income / shares) | B26: $ | D26: =Costs!$D$32/D23 | E26: =Costs!$E$32/E23 | F26: =Costs!$F$32/F23
A27: Net cash ex float, period end (FY2025A col = the 30 Jun 2026 actual) | B27: $M | C27: =Inputs!$C$9 | D27: =C27+(D14-History!$B$47)-(D21-History!$B$48)-(D22-History!$B$49) | E27: =D27+E14-E21-E22 | F27: =E27+F14-F21-F22
A29: BASE CASE
A30: Line | B30: Unit | C30: FY2025A | D30: FY2026E | E30: FY2027E | F30: FY2028E
A31: Adjusted EBITDA | B31: $M | C31: =Costs!$C$51 | D31: =Costs!$D$51 | E31: =Costs!$E$51 | F31: =Costs!$F$51
A32: + Interest income | B32: $M | C32: =History!$B$110 | D32: =Costs!$D$58 | E32: =Costs!$E$58 | F32: =Costs!$F$58
A33: - Interest expense | B33: $M | C33: =-History!$B$111 | D33: =-Costs!$D$59 | E33: =-Costs!$E$59 | F33: =-Costs!$F$59
A34: + Other income / (expense) | B34: $M | C34: =History!$B$112 | D34: =0 | E34: =0 | F34: =0
A35: - Cash taxes | B35: $M | C35: =History!$B$113 | D35: =-Costs!$D$36*Inputs!$D$37 | E35: =-Costs!$E$36*Inputs!$D$60 | F35: =-Costs!$F$36*Inputs!$D$83
A36: + Change in unearned fees | B36: $M | C36: =History!$B$114 | D36: =Costs!$D$36*Inputs!$D$38 | E36: =Costs!$E$36*Inputs!$D$61 | F36: =Costs!$F$36*Inputs!$D$84
A37: + Working-capital residual | B37: $M | C37: =History!$B$115 | D37: =Costs!$D$36*Inputs!$D$45 | E37: =Costs!$E$36*Inputs!$D$68 | F37: =Costs!$F$36*Inputs!$D$91
A38: - Capex | B38: $M | C38: =History!$B$116 | D38: =-Costs!$D$36*Inputs!$D$44 | E38: =-Costs!$E$36*Inputs!$D$67 | F38: =-Costs!$F$36*Inputs!$D$90
A39: FREE CASH FLOW | B39: $M | C39: =C31+C32+C33+C34+C35+C36+C37+C38 | D39: =D31+D32+D33+D34+D35+D36+D37+D38 | E39: =E31+E32+E33+E34+E35+E36+E37+E38 | F39: =F31+F32+F33+F34+F35+F36+F37+F38
A40: FCF margin | B40: % | C40: =C39/History!$B$32 | D40: =D39/Costs!$D$36 | E40: =E39/Costs!$E$36 | F40: =F39/Costs!$F$36
A41: FCF / adj. EBITDA | B41: % | C41: =C39/C31 | D41: =D39/D31 | E41: =E39/E31 | F41: =F39/F31
A42: SBC | B42: $M | C42: =History!$B$36 | D42: =Costs!$D$53 | E42: =Costs!$E$53 | F42: =Costs!$F$53
A43: SBC-ADJUSTED FCF | B43: $M | C43: =C39-C42 | D43: =D39-D42 | E43: =E39-E42 | F43: =F39-F42
A44: SBC-adjusted FCF margin | B44: % | D44: =D43/Costs!$D$36 | E44: =E43/Costs!$E$36 | F44: =F43/Costs!$F$36
A45: Share price used for buybacks and issuance | B45: $ | C45: =Inputs!$D$8 | D45: =Inputs!$D$8*(1+Inputs!$D$19)^0 | E45: =Inputs!$D$8*(1+Inputs!$D$19)^1 | F45: =Inputs!$D$8*(1+Inputs!$D$19)^2
A46: Buybacks | B46: $M | C46: =History!$B$117 | D46: =Inputs!$D$42 | E46: =Inputs!$D$65 | F46: =Inputs!$D$88
A47: RSU tax withholding | B47: $M | C47: =History!$B$118 | D47: =D42*Inputs!$D$18 | E47: =E42*Inputs!$D$18 | F47: =F42*Inputs!$D$18
A48: Diluted shares, period end (FY2025A col = the 2Q26 actual) | B48: M | C48: =Inputs!$D$10 | D48: =C48-(D46-History!$B$48)/D45+(D42-History!$B$50)/D45*(1-Inputs!$D$18) | E48: =D48-E46/E45+E42/E45*(1-Inputs!$D$18) | F48: =E48-F46/F45+F42/F45*(1-Inputs!$D$18)
A49: FCF per share | B49: $ | D49: =D39/D48 | E49: =E39/E48 | F49: =F39/F48
A50: SBC-adjusted FCF per share | B50: $ | D50: =D43/D48 | E50: =E43/E48 | F50: =F43/F48
A51: Earnings proxy per share (net income / shares) | B51: $ | D51: =Costs!$D$62/D48 | E51: =Costs!$E$62/E48 | F51: =Costs!$F$62/F48
A52: Net cash ex float, period end (FY2025A col = the 30 Jun 2026 actual) | B52: $M | C52: =Inputs!$D$9 | D52: =C52+(D39-History!$B$47)-(D46-History!$B$48)-(D47-History!$B$49) | E52: =D52+E39-E46-E47 | F52: =E52+F39-F46-F47
A54: BULL CASE
A55: Line | B55: Unit | C55: FY2025A | D55: FY2026E | E55: FY2027E | F55: FY2028E
A56: Adjusted EBITDA | B56: $M | C56: =Costs!$C$81 | D56: =Costs!$D$81 | E56: =Costs!$E$81 | F56: =Costs!$F$81
A57: + Interest income | B57: $M | C57: =History!$B$110 | D57: =Costs!$D$88 | E57: =Costs!$E$88 | F57: =Costs!$F$88
A58: - Interest expense | B58: $M | C58: =-History!$B$111 | D58: =-Costs!$D$89 | E58: =-Costs!$E$89 | F58: =-Costs!$F$89
A59: + Other income / (expense) | B59: $M | C59: =History!$B$112 | D59: =0 | E59: =0 | F59: =0
A60: - Cash taxes | B60: $M | C60: =History!$B$113 | D60: =-Costs!$D$66*Inputs!$E$37 | E60: =-Costs!$E$66*Inputs!$E$60 | F60: =-Costs!$F$66*Inputs!$E$83
A61: + Change in unearned fees | B61: $M | C61: =History!$B$114 | D61: =Costs!$D$66*Inputs!$E$38 | E61: =Costs!$E$66*Inputs!$E$61 | F61: =Costs!$F$66*Inputs!$E$84
A62: + Working-capital residual | B62: $M | C62: =History!$B$115 | D62: =Costs!$D$66*Inputs!$E$45 | E62: =Costs!$E$66*Inputs!$E$68 | F62: =Costs!$F$66*Inputs!$E$91
A63: - Capex | B63: $M | C63: =History!$B$116 | D63: =-Costs!$D$66*Inputs!$E$44 | E63: =-Costs!$E$66*Inputs!$E$67 | F63: =-Costs!$F$66*Inputs!$E$90
A64: FREE CASH FLOW | B64: $M | C64: =C56+C57+C58+C59+C60+C61+C62+C63 | D64: =D56+D57+D58+D59+D60+D61+D62+D63 | E64: =E56+E57+E58+E59+E60+E61+E62+E63 | F64: =F56+F57+F58+F59+F60+F61+F62+F63
A65: FCF margin | B65: % | C65: =C64/History!$B$32 | D65: =D64/Costs!$D$66 | E65: =E64/Costs!$E$66 | F65: =F64/Costs!$F$66
A66: FCF / adj. EBITDA | B66: % | C66: =C64/C56 | D66: =D64/D56 | E66: =E64/E56 | F66: =F64/F56
A67: SBC | B67: $M | C67: =History!$B$36 | D67: =Costs!$D$83 | E67: =Costs!$E$83 | F67: =Costs!$F$83
A68: SBC-ADJUSTED FCF | B68: $M | C68: =C64-C67 | D68: =D64-D67 | E68: =E64-E67 | F68: =F64-F67
A69: SBC-adjusted FCF margin | B69: % | D69: =D68/Costs!$D$66 | E69: =E68/Costs!$E$66 | F69: =F68/Costs!$F$66
A70: Share price used for buybacks and issuance | B70: $ | C70: =Inputs!$E$8 | D70: =Inputs!$E$8*(1+Inputs!$E$19)^0 | E70: =Inputs!$E$8*(1+Inputs!$E$19)^1 | F70: =Inputs!$E$8*(1+Inputs!$E$19)^2
A71: Buybacks | B71: $M | C71: =History!$B$117 | D71: =Inputs!$E$42 | E71: =Inputs!$E$65 | F71: =Inputs!$E$88
A72: RSU tax withholding | B72: $M | C72: =History!$B$118 | D72: =D67*Inputs!$E$18 | E72: =E67*Inputs!$E$18 | F72: =F67*Inputs!$E$18
A73: Diluted shares, period end (FY2025A col = the 2Q26 actual) | B73: M | C73: =Inputs!$E$10 | D73: =C73-(D71-History!$B$48)/D70+(D67-History!$B$50)/D70*(1-Inputs!$E$18) | E73: =D73-E71/E70+E67/E70*(1-Inputs!$E$18) | F73: =E73-F71/F70+F67/F70*(1-Inputs!$E$18)
A74: FCF per share | B74: $ | D74: =D64/D73 | E74: =E64/E73 | F74: =F64/F73
A75: SBC-adjusted FCF per share | B75: $ | D75: =D68/D73 | E75: =E68/E73 | F75: =F68/F73
A76: Earnings proxy per share (net income / shares) | B76: $ | D76: =Costs!$D$92/D73 | E76: =Costs!$E$92/E73 | F76: =Costs!$F$92/F73
A77: Net cash ex float, period end (FY2025A col = the 30 Jun 2026 actual) | B77: $M | C77: =Inputs!$E$9 | D77: =C77+(D64-History!$B$47)-(D71-History!$B$48)-(D72-History!$B$49) | E77: =D77+E64-E71-E72 | F77: =E77+F64-F71-F72

Sheet Valuation
A1: Valuation - exit multiples, DCF, football field, reverse DCF
A2: Exit multiples from WS12; cost of equity from WS09/WS12. Every price is a live formula off Costs and Cash.
A4: 1. FY2027E BASIS
A5: Item | B5: Bear | C5: Base | D5: Bull | E5: Active (Inputs!B4)
A6: Adj. EBITDA, FY2027E ($M) | B6: =Costs!$E$21 | C6: =Costs!$E$51 | D6: =Costs!$E$81 | E6: =CHOOSE(Inputs!$B$4,B6,C6,D6)
A7: FCF, FY2027E ($M) | B7: =Cash!$E$14 | C7: =Cash!$E$39 | D7: =Cash!$E$64 | E7: =CHOOSE(Inputs!$B$4,B7,C7,D7)
A8: SBC-adjusted FCF, FY2027E ($M) | B8: =Cash!$E$18 | C8: =Cash!$E$43 | D8: =Cash!$E$68 | E8: =CHOOSE(Inputs!$B$4,B8,C8,D8)
A9: Earnings proxy per share, FY2027E ($) | B9: =Cash!$E$26 | C9: =Cash!$E$51 | D9: =Cash!$E$76 | E9: =CHOOSE(Inputs!$B$4,B9,C9,D9)
A10: Net cash ex float, FY2027E ($M) | B10: =Cash!$E$27 | C10: =Cash!$E$52 | D10: =Cash!$E$77 | E10: =CHOOSE(Inputs!$B$4,B10,C10,D10)
A11: Diluted shares, FY2027E (M) | B11: =Cash!$E$23 | C11: =Cash!$E$48 | D11: =Cash!$E$73 | E11: =CHOOSE(Inputs!$B$4,B11,C11,D11)
A12: Adj. EBITDA, FY2028E ($M) | B12: =Costs!$F$21 | C12: =Costs!$F$51 | D12: =Costs!$F$81 | E12: =CHOOSE(Inputs!$B$4,B12,C12,D12)
A13: Net cash ex float, FY2028E ($M) | B13: =Cash!$F$27 | C13: =Cash!$F$52 | D13: =Cash!$F$77 | E13: =CHOOSE(Inputs!$B$4,B13,C13,D13)
A14: Diluted shares, FY2028E (M) | B14: =Cash!$F$23 | C14: =Cash!$F$48 | D14: =Cash!$F$73 | E14: =CHOOSE(Inputs!$B$4,B14,C14,D14)
A15: FCF, FY2028E ($M) | B15: =Cash!$F$14 | C15: =Cash!$F$39 | D15: =Cash!$F$64 | E15: =CHOOSE(Inputs!$B$4,B15,C15,D15)
A17: 2. PRICE PER LENS
A18: Lens | B18: Bear | C18: Base | D18: Bull | E18: Active (Inputs!B4) | F18: Multiple source
A19: EV / adj. EBITDA, FY2027E | B19: =(Inputs!$C$14*B6+B10)/B11 | C19: =(Inputs!$D$14*C6+C10)/C11 | D19: =(Inputs!$E$14*D6+D10)/D11 | E19: =CHOOSE(Inputs!$B$4,B19,C19,D19) | F19: WS12 13.5 / 16.5 / 18.5x
A20: EV / FCF, FY2027E | B20: =(Inputs!$C$15*B7+B10)/B11 | C20: =(Inputs!$D$15*C7+C10)/C11 | D20: =(Inputs!$E$15*D7+D10)/D11 | E20: =CHOOSE(Inputs!$B$4,B20,C20,D20) | F20: 5 Sep 15/19/23x rescaled by WS12's 0.75x haircut
A21: P / SBC-adjusted FCF, FY2027E | B21: =Inputs!$C$16*B8/B11 | C21: =Inputs!$D$16*C8/C11 | D21: =Inputs!$E$16*D8/D11 | E21: =CHOOSE(Inputs!$B$4,B21,C21,D21) | F21: same 0.75x haircut on 20/26/32x
A22: P / earnings proxy, FY2027E | B22: =Inputs!$C$17*B9 | C22: =Inputs!$D$17*C9 | D22: =Inputs!$E$17*D9 | E22: =CHOOSE(Inputs!$B$4,B22,C22,D22) | F22: same
A23: EV / adj. EBITDA, FY2028E (discounted 1 yr at the cost of equity) | B23: =(Inputs!$C$14*B12+B13)/B14/(1+Inputs!$C$11) | C23: =(Inputs!$D$14*C12+C13)/C14/(1+Inputs!$D$11) | D23: =(Inputs!$E$14*D12+D13)/D14/(1+Inputs!$E$11) | E23: =CHOOSE(Inputs!$B$4,B23,C23,D23) | F23: WS12 multiples on the FY28 basis, discounted to the ~Sep-2027 target date
A24: Sensitivity (not in the football field): EV / adj. EBITDA, FY2028E, UNDISCOUNTED (value as of end-FY2028) | B24: =(Inputs!$C$14*B12+B13)/B14 | C24: =(Inputs!$D$14*C12+C13)/C14 | D24: =(Inputs!$E$14*D12+D13)/D14 | E24: =CHOOSE(Inputs!$B$4,B24,C24,D24) | F24: date-mixing sensitivity; see model/assumptions.md
A26: 3. DCF ON FY2027E FCF - 10-year fade to terminal growth, discounted at the cost of equity | H26: start growth = the 'DCF start growth' input, fading linearly to terminal growth
A27: Year | B27: Bear: FCF ($M) | C27: Base: FCF ($M) | D27: Bull: FCF ($M) | E27: Bear: PV ($M) | F27: Base: PV ($M) | G27: Bull: PV ($M)
A28: 1 | B28: =B7*(1+(Inputs!$C$13+(Inputs!$C$12-Inputs!$C$13)*($A28-1)/9)) | C28: =C7*(1+(Inputs!$D$13+(Inputs!$D$12-Inputs!$D$13)*($A28-1)/9)) | D28: =D7*(1+(Inputs!$E$13+(Inputs!$E$12-Inputs!$E$13)*($A28-1)/9)) | E28: =B28/(1+Inputs!$C$11)^$A28 | F28: =C28/(1+Inputs!$D$11)^$A28 | G28: =D28/(1+Inputs!$E$11)^$A28
A29: 2 | B29: =B28*(1+(Inputs!$C$13+(Inputs!$C$12-Inputs!$C$13)*($A29-1)/9)) | C29: =C28*(1+(Inputs!$D$13+(Inputs!$D$12-Inputs!$D$13)*($A29-1)/9)) | D29: =D28*(1+(Inputs!$E$13+(Inputs!$E$12-Inputs!$E$13)*($A29-1)/9)) | E29: =B29/(1+Inputs!$C$11)^$A29 | F29: =C29/(1+Inputs!$D$11)^$A29 | G29: =D29/(1+Inputs!$E$11)^$A29
A30: 3 | B30: =B29*(1+(Inputs!$C$13+(Inputs!$C$12-Inputs!$C$13)*($A30-1)/9)) | C30: =C29*(1+(Inputs!$D$13+(Inputs!$D$12-Inputs!$D$13)*($A30-1)/9)) | D30: =D29*(1+(Inputs!$E$13+(Inputs!$E$12-Inputs!$E$13)*($A30-1)/9)) | E30: =B30/(1+Inputs!$C$11)^$A30 | F30: =C30/(1+Inputs!$D$11)^$A30 | G30: =D30/(1+Inputs!$E$11)^$A30
A31: 4 | B31: =B30*(1+(Inputs!$C$13+(Inputs!$C$12-Inputs!$C$13)*($A31-1)/9)) | C31: =C30*(1+(Inputs!$D$13+(Inputs!$D$12-Inputs!$D$13)*($A31-1)/9)) | D31: =D30*(1+(Inputs!$E$13+(Inputs!$E$12-Inputs!$E$13)*($A31-1)/9)) | E31: =B31/(1+Inputs!$C$11)^$A31 | F31: =C31/(1+Inputs!$D$11)^$A31 | G31: =D31/(1+Inputs!$E$11)^$A31
A32: 5 | B32: =B31*(1+(Inputs!$C$13+(Inputs!$C$12-Inputs!$C$13)*($A32-1)/9)) | C32: =C31*(1+(Inputs!$D$13+(Inputs!$D$12-Inputs!$D$13)*($A32-1)/9)) | D32: =D31*(1+(Inputs!$E$13+(Inputs!$E$12-Inputs!$E$13)*($A32-1)/9)) | E32: =B32/(1+Inputs!$C$11)^$A32 | F32: =C32/(1+Inputs!$D$11)^$A32 | G32: =D32/(1+Inputs!$E$11)^$A32
A33: 6 | B33: =B32*(1+(Inputs!$C$13+(Inputs!$C$12-Inputs!$C$13)*($A33-1)/9)) | C33: =C32*(1+(Inputs!$D$13+(Inputs!$D$12-Inputs!$D$13)*($A33-1)/9)) | D33: =D32*(1+(Inputs!$E$13+(Inputs!$E$12-Inputs!$E$13)*($A33-1)/9)) | E33: =B33/(1+Inputs!$C$11)^$A33 | F33: =C33/(1+Inputs!$D$11)^$A33 | G33: =D33/(1+Inputs!$E$11)^$A33
A34: 7 | B34: =B33*(1+(Inputs!$C$13+(Inputs!$C$12-Inputs!$C$13)*($A34-1)/9)) | C34: =C33*(1+(Inputs!$D$13+(Inputs!$D$12-Inputs!$D$13)*($A34-1)/9)) | D34: =D33*(1+(Inputs!$E$13+(Inputs!$E$12-Inputs!$E$13)*($A34-1)/9)) | E34: =B34/(1+Inputs!$C$11)^$A34 | F34: =C34/(1+Inputs!$D$11)^$A34 | G34: =D34/(1+Inputs!$E$11)^$A34
A35: 8 | B35: =B34*(1+(Inputs!$C$13+(Inputs!$C$12-Inputs!$C$13)*($A35-1)/9)) | C35: =C34*(1+(Inputs!$D$13+(Inputs!$D$12-Inputs!$D$13)*($A35-1)/9)) | D35: =D34*(1+(Inputs!$E$13+(Inputs!$E$12-Inputs!$E$13)*($A35-1)/9)) | E35: =B35/(1+Inputs!$C$11)^$A35 | F35: =C35/(1+Inputs!$D$11)^$A35 | G35: =D35/(1+Inputs!$E$11)^$A35
A36: 9 | B36: =B35*(1+(Inputs!$C$13+(Inputs!$C$12-Inputs!$C$13)*($A36-1)/9)) | C36: =C35*(1+(Inputs!$D$13+(Inputs!$D$12-Inputs!$D$13)*($A36-1)/9)) | D36: =D35*(1+(Inputs!$E$13+(Inputs!$E$12-Inputs!$E$13)*($A36-1)/9)) | E36: =B36/(1+Inputs!$C$11)^$A36 | F36: =C36/(1+Inputs!$D$11)^$A36 | G36: =D36/(1+Inputs!$E$11)^$A36
A37: 10 | B37: =B36*(1+(Inputs!$C$13+(Inputs!$C$12-Inputs!$C$13)*($A37-1)/9)) | C37: =C36*(1+(Inputs!$D$13+(Inputs!$D$12-Inputs!$D$13)*($A37-1)/9)) | D37: =D36*(1+(Inputs!$E$13+(Inputs!$E$12-Inputs!$E$13)*($A37-1)/9)) | E37: =B37/(1+Inputs!$C$11)^$A37 | F37: =C37/(1+Inputs!$D$11)^$A37 | G37: =D37/(1+Inputs!$E$11)^$A37
A38: Terminal value (Gordon), discounted | E38: =B37*(1+Inputs!$C$12)/(Inputs!$C$11-Inputs!$C$12)/(1+Inputs!$C$11)^$A37 | F38: =C37*(1+Inputs!$D$12)/(Inputs!$D$11-Inputs!$D$12)/(1+Inputs!$D$11)^$A37 | G38: =D37*(1+Inputs!$E$12)/(Inputs!$E$11-Inputs!$E$12)/(1+Inputs!$E$11)^$A37
A39: Enterprise value ($M) | E39: =SUM(E28:E37)+E38 | F39: =SUM(F28:F37)+F38 | G39: =SUM(G28:G37)+G38
A40: DCF value per share ($) | B40: =(E39+B10)/B11 | C40: =(F39+C10)/C11 | D40: =(G39+D10)/D11 | E40: =CHOOSE(Inputs!$B$4,B40,C40,D40) | H40: column E on this row is the Active (Inputs!B4) selection, not a PV
A42: 4. FOOTBALL FIELD AND IMPLIED UPSIDE
A43: Measure | B43: Bear | C43: Base | D43: Bull | E43: Active (Inputs!B4)
A44: Football field: Low | B44: =MIN(B19,B20,B21,B22,B23,B40) | C44: =MIN(C19,C20,C21,C22,C23,C40) | D44: =MIN(D19,D20,D21,D22,D23,D40) | E44: =CHOOSE(Inputs!$B$4,B44,C44,D44)
A45: Football field: High | B45: =MAX(B19,B20,B21,B22,B23,B40) | C45: =MAX(C19,C20,C21,C22,C23,C40) | D45: =MAX(D19,D20,D21,D22,D23,D40) | E45: =CHOOSE(Inputs!$B$4,B45,C45,D45)
A46: Football field: Mean of lenses | B46: =AVERAGE(B19,B20,B21,B22,B23,B40) | C46: =AVERAGE(C19,C20,C21,C22,C23,C40) | D46: =AVERAGE(D19,D20,D21,D22,D23,D40) | E46: =CHOOSE(Inputs!$B$4,B46,C46,D46)
A47: Spot price ($) | B47: =Inputs!$C$8 | C47: =Inputs!$D$8 | D47: =Inputs!$E$8 | E47: =CHOOSE(Inputs!$B$4,B47,C47,D47)
A48: Implied upside vs spot: Low | B48: =B44/B47-1 | C48: =C44/C47-1 | D48: =D44/D47-1 | E48: =E44/E47-1
A49: Implied upside vs spot: High | B49: =B45/B47-1 | C49: =C45/C47-1 | D49: =D45/D47-1 | E49: =E45/E47-1
A50: Implied upside vs spot: Mean of lenses | B50: =B46/B47-1 | C50: =C46/C47-1 | D50: =D46/D47-1 | E50: =E46/E47-1
A51: Memo: price on the 5 Sep exit multiples (18 / 22 / 25.5x) | B51: =(18.0*B6+B10)/B11 | C51: =(22.0*C6+C10)/C11 | D51: =(25.5*D6+D10)/D11
A53: 5. REVERSE DCF - what growth the spot price discounts
A54: Assumed 10-year FCF growth | B54: Value per share, reported FCF | C54: Value per share, SBC-adjusted FCF | E54: Constant growth for ten years then a Gordon terminal - the 5 Sep note's convention, so the two are comparable. Reads off the base-case cost of equity and terminal growth; the implied growth is where the value column crosses spot ($181.94).
A55: 0.03 | B55: =(History!$B$103*(((1+A55)/(1+Inputs!$D$11))^1+((1+A55)/(1+Inputs!$D$11))^2+((1+A55)/(1+Inputs!$D$11))^3+((1+A55)/(1+Inputs!$D$11))^4+((1+A55)/(1+Inputs!$D$11))^5+((1+A55)/(1+Inputs!$D$11))^6+((1+A55)/(1+Inputs!$D$11))^7+((1+A55)/(1+Inputs!$D$11))^8+((1+A55)/(1+Inputs!$D$11))^9+((1+A55)/(1+Inputs!$D$11))^10)+History!$B$103*(1+A55)^10*(1+Inputs!$D$12)/(Inputs!$D$11-Inputs!$D$12)/(1+Inputs!$D$11)^10+Inputs!$D$9)/Inputs!$D$10 | C55: =((History!$B$103-History!$B$104)*(((1+A55)/(1+Inputs!$D$11))^1+((1+A55)/(1+Inputs!$D$11))^2+((1+A55)/(1+Inputs!$D$11))^3+((1+A55)/(1+Inputs!$D$11))^4+((1+A55)/(1+Inputs!$D$11))^5+((1+A55)/(1+Inputs!$D$11))^6+((1+A55)/(1+Inputs!$D$11))^7+((1+A55)/(1+Inputs!$D$11))^8+((1+A55)/(1+Inputs!$D$11))^9+((1+A55)/(1+Inputs!$D$11))^10)+(History!$B$103-History!$B$104)*(1+A55)^10*(1+Inputs!$D$12)/(Inputs!$D$11-Inputs!$D$12)/(1+Inputs!$D$11)^10+Inputs!$D$9)/Inputs!$D$10
A56: 0.05 | B56: =(History!$B$103*(((1+A56)/(1+Inputs!$D$11))^1+((1+A56)/(1+Inputs!$D$11))^2+((1+A56)/(1+Inputs!$D$11))^3+((1+A56)/(1+Inputs!$D$11))^4+((1+A56)/(1+Inputs!$D$11))^5+((1+A56)/(1+Inputs!$D$11))^6+((1+A56)/(1+Inputs!$D$11))^7+((1+A56)/(1+Inputs!$D$11))^8+((1+A56)/(1+Inputs!$D$11))^9+((1+A56)/(1+Inputs!$D$11))^10)+History!$B$103*(1+A56)^10*(1+Inputs!$D$12)/(Inputs!$D$11-Inputs!$D$12)/(1+Inputs!$D$11)^10+Inputs!$D$9)/Inputs!$D$10 | C56: =((History!$B$103-History!$B$104)*(((1+A56)/(1+Inputs!$D$11))^1+((1+A56)/(1+Inputs!$D$11))^2+((1+A56)/(1+Inputs!$D$11))^3+((1+A56)/(1+Inputs!$D$11))^4+((1+A56)/(1+Inputs!$D$11))^5+((1+A56)/(1+Inputs!$D$11))^6+((1+A56)/(1+Inputs!$D$11))^7+((1+A56)/(1+Inputs!$D$11))^8+((1+A56)/(1+Inputs!$D$11))^9+((1+A56)/(1+Inputs!$D$11))^10)+(History!$B$103-History!$B$104)*(1+A56)^10*(1+Inputs!$D$12)/(Inputs!$D$11-Inputs!$D$12)/(1+Inputs!$D$11)^10+Inputs!$D$9)/Inputs!$D$10
A57: 0.07 | B57: =(History!$B$103*(((1+A57)/(1+Inputs!$D$11))^1+((1+A57)/(1+Inputs!$D$11))^2+((1+A57)/(1+Inputs!$D$11))^3+((1+A57)/(1+Inputs!$D$11))^4+((1+A57)/(1+Inputs!$D$11))^5+((1+A57)/(1+Inputs!$D$11))^6+((1+A57)/(1+Inputs!$D$11))^7+((1+A57)/(1+Inputs!$D$11))^8+((1+A57)/(1+Inputs!$D$11))^9+((1+A57)/(1+Inputs!$D$11))^10)+History!$B$103*(1+A57)^10*(1+Inputs!$D$12)/(Inputs!$D$11-Inputs!$D$12)/(1+Inputs!$D$11)^10+Inputs!$D$9)/Inputs!$D$10 | C57: =((History!$B$103-History!$B$104)*(((1+A57)/(1+Inputs!$D$11))^1+((1+A57)/(1+Inputs!$D$11))^2+((1+A57)/(1+Inputs!$D$11))^3+((1+A57)/(1+Inputs!$D$11))^4+((1+A57)/(1+Inputs!$D$11))^5+((1+A57)/(1+Inputs!$D$11))^6+((1+A57)/(1+Inputs!$D$11))^7+((1+A57)/(1+Inputs!$D$11))^8+((1+A57)/(1+Inputs!$D$11))^9+((1+A57)/(1+Inputs!$D$11))^10)+(History!$B$103-History!$B$104)*(1+A57)^10*(1+Inputs!$D$12)/(Inputs!$D$11-Inputs!$D$12)/(1+Inputs!$D$11)^10+Inputs!$D$9)/Inputs!$D$10
A58: 0.075 | B58: =(History!$B$103*(((1+A58)/(1+Inputs!$D$11))^1+((1+A58)/(1+Inputs!$D$11))^2+((1+A58)/(1+Inputs!$D$11))^3+((1+A58)/(1+Inputs!$D$11))^4+((1+A58)/(1+Inputs!$D$11))^5+((1+A58)/(1+Inputs!$D$11))^6+((1+A58)/(1+Inputs!$D$11))^7+((1+A58)/(1+Inputs!$D$11))^8+((1+A58)/(1+Inputs!$D$11))^9+((1+A58)/(1+Inputs!$D$11))^10)+History!$B$103*(1+A58)^10*(1+Inputs!$D$12)/(Inputs!$D$11-Inputs!$D$12)/(1+Inputs!$D$11)^10+Inputs!$D$9)/Inputs!$D$10 | C58: =((History!$B$103-History!$B$104)*(((1+A58)/(1+Inputs!$D$11))^1+((1+A58)/(1+Inputs!$D$11))^2+((1+A58)/(1+Inputs!$D$11))^3+((1+A58)/(1+Inputs!$D$11))^4+((1+A58)/(1+Inputs!$D$11))^5+((1+A58)/(1+Inputs!$D$11))^6+((1+A58)/(1+Inputs!$D$11))^7+((1+A58)/(1+Inputs!$D$11))^8+((1+A58)/(1+Inputs!$D$11))^9+((1+A58)/(1+Inputs!$D$11))^10)+(History!$B$103-History!$B$104)*(1+A58)^10*(1+Inputs!$D$12)/(Inputs!$D$11-Inputs!$D$12)/(1+Inputs!$D$11)^10+Inputs!$D$9)/Inputs!$D$10
A59: 0.09 | B59: =(History!$B$103*(((1+A59)/(1+Inputs!$D$11))^1+((1+A59)/(1+Inputs!$D$11))^2+((1+A59)/(1+Inputs!$D$11))^3+((1+A59)/(1+Inputs!$D$11))^4+((1+A59)/(1+Inputs!$D$11))^5+((1+A59)/(1+Inputs!$D$11))^6+((1+A59)/(1+Inputs!$D$11))^7+((1+A59)/(1+Inputs!$D$11))^8+((1+A59)/(1+Inputs!$D$11))^9+((1+A59)/(1+Inputs!$D$11))^10)+History!$B$103*(1+A59)^10*(1+Inputs!$D$12)/(Inputs!$D$11-Inputs!$D$12)/(1+Inputs!$D$11)^10+Inputs!$D$9)/Inputs!$D$10 | C59: =((History!$B$103-History!$B$104)*(((1+A59)/(1+Inputs!$D$11))^1+((1+A59)/(1+Inputs!$D$11))^2+((1+A59)/(1+Inputs!$D$11))^3+((1+A59)/(1+Inputs!$D$11))^4+((1+A59)/(1+Inputs!$D$11))^5+((1+A59)/(1+Inputs!$D$11))^6+((1+A59)/(1+Inputs!$D$11))^7+((1+A59)/(1+Inputs!$D$11))^8+((1+A59)/(1+Inputs!$D$11))^9+((1+A59)/(1+Inputs!$D$11))^10)+(History!$B$103-History!$B$104)*(1+A59)^10*(1+Inputs!$D$12)/(Inputs!$D$11-Inputs!$D$12)/(1+Inputs!$D$11)^10+Inputs!$D$9)/Inputs!$D$10
A60: 0.11 | B60: =(History!$B$103*(((1+A60)/(1+Inputs!$D$11))^1+((1+A60)/(1+Inputs!$D$11))^2+((1+A60)/(1+Inputs!$D$11))^3+((1+A60)/(1+Inputs!$D$11))^4+((1+A60)/(1+Inputs!$D$11))^5+((1+A60)/(1+Inputs!$D$11))^6+((1+A60)/(1+Inputs!$D$11))^7+((1+A60)/(1+Inputs!$D$11))^8+((1+A60)/(1+Inputs!$D$11))^9+((1+A60)/(1+Inputs!$D$11))^10)+History!$B$103*(1+A60)^10*(1+Inputs!$D$12)/(Inputs!$D$11-Inputs!$D$12)/(1+Inputs!$D$11)^10+Inputs!$D$9)/Inputs!$D$10 | C60: =((History!$B$103-History!$B$104)*(((1+A60)/(1+Inputs!$D$11))^1+((1+A60)/(1+Inputs!$D$11))^2+((1+A60)/(1+Inputs!$D$11))^3+((1+A60)/(1+Inputs!$D$11))^4+((1+A60)/(1+Inputs!$D$11))^5+((1+A60)/(1+Inputs!$D$11))^6+((1+A60)/(1+Inputs!$D$11))^7+((1+A60)/(1+Inputs!$D$11))^8+((1+A60)/(1+Inputs!$D$11))^9+((1+A60)/(1+Inputs!$D$11))^10)+(History!$B$103-History!$B$104)*(1+A60)^10*(1+Inputs!$D$12)/(Inputs!$D$11-Inputs!$D$12)/(1+Inputs!$D$11)^10+Inputs!$D$9)/Inputs!$D$10
A61: 0.13 | B61: =(History!$B$103*(((1+A61)/(1+Inputs!$D$11))^1+((1+A61)/(1+Inputs!$D$11))^2+((1+A61)/(1+Inputs!$D$11))^3+((1+A61)/(1+Inputs!$D$11))^4+((1+A61)/(1+Inputs!$D$11))^5+((1+A61)/(1+Inputs!$D$11))^6+((1+A61)/(1+Inputs!$D$11))^7+((1+A61)/(1+Inputs!$D$11))^8+((1+A61)/(1+Inputs!$D$11))^9+((1+A61)/(1+Inputs!$D$11))^10)+History!$B$103*(1+A61)^10*(1+Inputs!$D$12)/(Inputs!$D$11-Inputs!$D$12)/(1+Inputs!$D$11)^10+Inputs!$D$9)/Inputs!$D$10 | C61: =((History!$B$103-History!$B$104)*(((1+A61)/(1+Inputs!$D$11))^1+((1+A61)/(1+Inputs!$D$11))^2+((1+A61)/(1+Inputs!$D$11))^3+((1+A61)/(1+Inputs!$D$11))^4+((1+A61)/(1+Inputs!$D$11))^5+((1+A61)/(1+Inputs!$D$11))^6+((1+A61)/(1+Inputs!$D$11))^7+((1+A61)/(1+Inputs!$D$11))^8+((1+A61)/(1+Inputs!$D$11))^9+((1+A61)/(1+Inputs!$D$11))^10)+(History!$B$103-History!$B$104)*(1+A61)^10*(1+Inputs!$D$12)/(Inputs!$D$11-Inputs!$D$12)/(1+Inputs!$D$11)^10+Inputs!$D$9)/Inputs!$D$10
A62: 0.135 | B62: =(History!$B$103*(((1+A62)/(1+Inputs!$D$11))^1+((1+A62)/(1+Inputs!$D$11))^2+((1+A62)/(1+Inputs!$D$11))^3+((1+A62)/(1+Inputs!$D$11))^4+((1+A62)/(1+Inputs!$D$11))^5+((1+A62)/(1+Inputs!$D$11))^6+((1+A62)/(1+Inputs!$D$11))^7+((1+A62)/(1+Inputs!$D$11))^8+((1+A62)/(1+Inputs!$D$11))^9+((1+A62)/(1+Inputs!$D$11))^10)+History!$B$103*(1+A62)^10*(1+Inputs!$D$12)/(Inputs!$D$11-Inputs!$D$12)/(1+Inputs!$D$11)^10+Inputs!$D$9)/Inputs!$D$10 | C62: =((History!$B$103-History!$B$104)*(((1+A62)/(1+Inputs!$D$11))^1+((1+A62)/(1+Inputs!$D$11))^2+((1+A62)/(1+Inputs!$D$11))^3+((1+A62)/(1+Inputs!$D$11))^4+((1+A62)/(1+Inputs!$D$11))^5+((1+A62)/(1+Inputs!$D$11))^6+((1+A62)/(1+Inputs!$D$11))^7+((1+A62)/(1+Inputs!$D$11))^8+((1+A62)/(1+Inputs!$D$11))^9+((1+A62)/(1+Inputs!$D$11))^10)+(History!$B$103-History!$B$104)*(1+A62)^10*(1+Inputs!$D$12)/(Inputs!$D$11-Inputs!$D$12)/(1+Inputs!$D$11)^10+Inputs!$D$9)/Inputs!$D$10
A63: 0.15 | B63: =(History!$B$103*(((1+A63)/(1+Inputs!$D$11))^1+((1+A63)/(1+Inputs!$D$11))^2+((1+A63)/(1+Inputs!$D$11))^3+((1+A63)/(1+Inputs!$D$11))^4+((1+A63)/(1+Inputs!$D$11))^5+((1+A63)/(1+Inputs!$D$11))^6+((1+A63)/(1+Inputs!$D$11))^7+((1+A63)/(1+Inputs!$D$11))^8+((1+A63)/(1+Inputs!$D$11))^9+((1+A63)/(1+Inputs!$D$11))^10)+History!$B$103*(1+A63)^10*(1+Inputs!$D$12)/(Inputs!$D$11-Inputs!$D$12)/(1+Inputs!$D$11)^10+Inputs!$D$9)/Inputs!$D$10 | C63: =((History!$B$103-History!$B$104)*(((1+A63)/(1+Inputs!$D$11))^1+((1+A63)/(1+Inputs!$D$11))^2+((1+A63)/(1+Inputs!$D$11))^3+((1+A63)/(1+Inputs!$D$11))^4+((1+A63)/(1+Inputs!$D$11))^5+((1+A63)/(1+Inputs!$D$11))^6+((1+A63)/(1+Inputs!$D$11))^7+((1+A63)/(1+Inputs!$D$11))^8+((1+A63)/(1+Inputs!$D$11))^9+((1+A63)/(1+Inputs!$D$11))^10)+(History!$B$103-History!$B$104)*(1+A63)^10*(1+Inputs!$D$12)/(Inputs!$D$11-Inputs!$D$12)/(1+Inputs!$D$11)^10+Inputs!$D$9)/Inputs!$D$10
A64: 0.17 | B64: =(History!$B$103*(((1+A64)/(1+Inputs!$D$11))^1+((1+A64)/(1+Inputs!$D$11))^2+((1+A64)/(1+Inputs!$D$11))^3+((1+A64)/(1+Inputs!$D$11))^4+((1+A64)/(1+Inputs!$D$11))^5+((1+A64)/(1+Inputs!$D$11))^6+((1+A64)/(1+Inputs!$D$11))^7+((1+A64)/(1+Inputs!$D$11))^8+((1+A64)/(1+Inputs!$D$11))^9+((1+A64)/(1+Inputs!$D$11))^10)+History!$B$103*(1+A64)^10*(1+Inputs!$D$12)/(Inputs!$D$11-Inputs!$D$12)/(1+Inputs!$D$11)^10+Inputs!$D$9)/Inputs!$D$10 | C64: =((History!$B$103-History!$B$104)*(((1+A64)/(1+Inputs!$D$11))^1+((1+A64)/(1+Inputs!$D$11))^2+((1+A64)/(1+Inputs!$D$11))^3+((1+A64)/(1+Inputs!$D$11))^4+((1+A64)/(1+Inputs!$D$11))^5+((1+A64)/(1+Inputs!$D$11))^6+((1+A64)/(1+Inputs!$D$11))^7+((1+A64)/(1+Inputs!$D$11))^8+((1+A64)/(1+Inputs!$D$11))^9+((1+A64)/(1+Inputs!$D$11))^10)+(History!$B$103-History!$B$104)*(1+A64)^10*(1+Inputs!$D$12)/(Inputs!$D$11-Inputs!$D$12)/(1+Inputs!$D$11)^10+Inputs!$D$9)/Inputs!$D$10
A65: Solved implied 10-year growth at spot (constant growth, then terminal): | B65: 0.085116765 | C65: 0.14416428 | E65: Reported FCF (LTM $4827M) | F65: SBC-adjusted FCF (LTM $3131M)
A66: Check: value per share at the solved growth, less spot (0.00 = still current) | B66: =(History!$B$103*(((1+B65)/(1+Inputs!$D$11))^1+((1+B65)/(1+Inputs!$D$11))^2+((1+B65)/(1+Inputs!$D$11))^3+((1+B65)/(1+Inputs!$D$11))^4+((1+B65)/(1+Inputs!$D$11))^5+((1+B65)/(1+Inputs!$D$11))^6+((1+B65)/(1+Inputs!$D$11))^7+((1+B65)/(1+Inputs!$D$11))^8+((1+B65)/(1+Inputs!$D$11))^9+((1+B65)/(1+Inputs!$D$11))^10)+History!$B$103*(1+B65)^10*(1+Inputs!$D$12)/(Inputs!$D$11-Inputs!$D$12)/(1+Inputs!$D$11)^10+Inputs!$D$9)/Inputs!$D$10-Inputs!$D$8 | C66: =((History!$B$103-History!$B$104)*(((1+C65)/(1+Inputs!$D$11))^1+((1+C65)/(1+Inputs!$D$11))^2+((1+C65)/(1+Inputs!$D$11))^3+((1+C65)/(1+Inputs!$D$11))^4+((1+C65)/(1+Inputs!$D$11))^5+((1+C65)/(1+Inputs!$D$11))^6+((1+C65)/(1+Inputs!$D$11))^7+((1+C65)/(1+Inputs!$D$11))^8+((1+C65)/(1+Inputs!$D$11))^9+((1+C65)/(1+Inputs!$D$11))^10)+(History!$B$103-History!$B$104)*(1+C65)^10*(1+Inputs!$D$12)/(Inputs!$D$11-Inputs!$D$12)/(1+Inputs!$D$11)^10+Inputs!$D$9)/Inputs!$D$10-Inputs!$D$8 | E66: The solved cells above are yellow because they are an input, not a formula: a bisection run in analysis/src/overnight/13_driver_model.py. If this row stops reading 0.00, re-run that script - the cost of equity or the terminal growth moved.
A68: 6. SCENARIO GRID - FY2027E revenue growth x adj. EBITDA margin x exit multiple
A69: Price at the base exit multiple; rows = FY27 revenue growth, columns = FY27 margin
A70: Revenue growth \ margin | B70: 0.32 | C70: 0.34 | D70: 0.355 | E70: 0.365 | F70: 0.375 | G70: 0.39 | H70: 0.41
A71: 0.04 | B71: =(Inputs!$D$14*Revenue!$I$77*(1+$A71)*B$70+Cash!$E$52)/Cash!$E$48 | C71: =(Inputs!$D$14*Revenue!$I$77*(1+$A71)*C$70+Cash!$E$52)/Cash!$E$48 | D71: =(Inputs!$D$14*Revenue!$I$77*(1+$A71)*D$70+Cash!$E$52)/Cash!$E$48 | E71: =(Inputs!$D$14*Revenue!$I$77*(1+$A71)*E$70+Cash!$E$52)/Cash!$E$48 | F71: =(Inputs!$D$14*Revenue!$I$77*(1+$A71)*F$70+Cash!$E$52)/Cash!$E$48 | G71: =(Inputs!$D$14*Revenue!$I$77*(1+$A71)*G$70+Cash!$E$52)/Cash!$E$48 | H71: =(Inputs!$D$14*Revenue!$I$77*(1+$A71)*H$70+Cash!$E$52)/Cash!$E$48
A72: 0.06 | B72: =(Inputs!$D$14*Revenue!$I$77*(1+$A72)*B$70+Cash!$E$52)/Cash!$E$48 | C72: =(Inputs!$D$14*Revenue!$I$77*(1+$A72)*C$70+Cash!$E$52)/Cash!$E$48 | D72: =(Inputs!$D$14*Revenue!$I$77*(1+$A72)*D$70+Cash!$E$52)/Cash!$E$48 | E72: =(Inputs!$D$14*Revenue!$I$77*(1+$A72)*E$70+Cash!$E$52)/Cash!$E$48 | F72: =(Inputs!$D$14*Revenue!$I$77*(1+$A72)*F$70+Cash!$E$52)/Cash!$E$48 | G72: =(Inputs!$D$14*Revenue!$I$77*(1+$A72)*G$70+Cash!$E$52)/Cash!$E$48 | H72: =(Inputs!$D$14*Revenue!$I$77*(1+$A72)*H$70+Cash!$E$52)/Cash!$E$48
A73: 0.08 | B73: =(Inputs!$D$14*Revenue!$I$77*(1+$A73)*B$70+Cash!$E$52)/Cash!$E$48 | C73: =(Inputs!$D$14*Revenue!$I$77*(1+$A73)*C$70+Cash!$E$52)/Cash!$E$48 | D73: =(Inputs!$D$14*Revenue!$I$77*(1+$A73)*D$70+Cash!$E$52)/Cash!$E$48 | E73: =(Inputs!$D$14*Revenue!$I$77*(1+$A73)*E$70+Cash!$E$52)/Cash!$E$48 | F73: =(Inputs!$D$14*Revenue!$I$77*(1+$A73)*F$70+Cash!$E$52)/Cash!$E$48 | G73: =(Inputs!$D$14*Revenue!$I$77*(1+$A73)*G$70+Cash!$E$52)/Cash!$E$48 | H73: =(Inputs!$D$14*Revenue!$I$77*(1+$A73)*H$70+Cash!$E$52)/Cash!$E$48
A74: 0.1 | B74: =(Inputs!$D$14*Revenue!$I$77*(1+$A74)*B$70+Cash!$E$52)/Cash!$E$48 | C74: =(Inputs!$D$14*Revenue!$I$77*(1+$A74)*C$70+Cash!$E$52)/Cash!$E$48 | D74: =(Inputs!$D$14*Revenue!$I$77*(1+$A74)*D$70+Cash!$E$52)/Cash!$E$48 | E74: =(Inputs!$D$14*Revenue!$I$77*(1+$A74)*E$70+Cash!$E$52)/Cash!$E$48 | F74: =(Inputs!$D$14*Revenue!$I$77*(1+$A74)*F$70+Cash!$E$52)/Cash!$E$48 | G74: =(Inputs!$D$14*Revenue!$I$77*(1+$A74)*G$70+Cash!$E$52)/Cash!$E$48 | H74: =(Inputs!$D$14*Revenue!$I$77*(1+$A74)*H$70+Cash!$E$52)/Cash!$E$48
A75: 0.12 | B75: =(Inputs!$D$14*Revenue!$I$77*(1+$A75)*B$70+Cash!$E$52)/Cash!$E$48 | C75: =(Inputs!$D$14*Revenue!$I$77*(1+$A75)*C$70+Cash!$E$52)/Cash!$E$48 | D75: =(Inputs!$D$14*Revenue!$I$77*(1+$A75)*D$70+Cash!$E$52)/Cash!$E$48 | E75: =(Inputs!$D$14*Revenue!$I$77*(1+$A75)*E$70+Cash!$E$52)/Cash!$E$48 | F75: =(Inputs!$D$14*Revenue!$I$77*(1+$A75)*F$70+Cash!$E$52)/Cash!$E$48 | G75: =(Inputs!$D$14*Revenue!$I$77*(1+$A75)*G$70+Cash!$E$52)/Cash!$E$48 | H75: =(Inputs!$D$14*Revenue!$I$77*(1+$A75)*H$70+Cash!$E$52)/Cash!$E$48
A76: 0.14 | B76: =(Inputs!$D$14*Revenue!$I$77*(1+$A76)*B$70+Cash!$E$52)/Cash!$E$48 | C76: =(Inputs!$D$14*Revenue!$I$77*(1+$A76)*C$70+Cash!$E$52)/Cash!$E$48 | D76: =(Inputs!$D$14*Revenue!$I$77*(1+$A76)*D$70+Cash!$E$52)/Cash!$E$48 | E76: =(Inputs!$D$14*Revenue!$I$77*(1+$A76)*E$70+Cash!$E$52)/Cash!$E$48 | F76: =(Inputs!$D$14*Revenue!$I$77*(1+$A76)*F$70+Cash!$E$52)/Cash!$E$48 | G76: =(Inputs!$D$14*Revenue!$I$77*(1+$A76)*G$70+Cash!$E$52)/Cash!$E$48 | H76: =(Inputs!$D$14*Revenue!$I$77*(1+$A76)*H$70+Cash!$E$52)/Cash!$E$48
A77: 0.16 | B77: =(Inputs!$D$14*Revenue!$I$77*(1+$A77)*B$70+Cash!$E$52)/Cash!$E$48 | C77: =(Inputs!$D$14*Revenue!$I$77*(1+$A77)*C$70+Cash!$E$52)/Cash!$E$48 | D77: =(Inputs!$D$14*Revenue!$I$77*(1+$A77)*D$70+Cash!$E$52)/Cash!$E$48 | E77: =(Inputs!$D$14*Revenue!$I$77*(1+$A77)*E$70+Cash!$E$52)/Cash!$E$48 | F77: =(Inputs!$D$14*Revenue!$I$77*(1+$A77)*F$70+Cash!$E$52)/Cash!$E$48 | G77: =(Inputs!$D$14*Revenue!$I$77*(1+$A77)*G$70+Cash!$E$52)/Cash!$E$48 | H77: =(Inputs!$D$14*Revenue!$I$77*(1+$A77)*H$70+Cash!$E$52)/Cash!$E$48

Sheet Street
A1: Street consensus versus our base case
A2: Consensus from WS04 04_current_consensus.csv (Zacks and S&P Global Market Intelligence, 3-4 Sep 2026). The bull case has to differ from these, not from LTM actuals.
A4: Line | B4: Street | C4: n / range | D4: Our base | E4: Delta ($ or x) | F4: Delta (%) | G4: Vendor
A5: FY2026 revenue ($M) | B5: 14100 | C5: 8 est, 13,960-14,210 | D5: =Revenue!$I$77 | E5: =D5-B5 | F5: =D5/B5-1 | G5: Zacks 4 Sep 26
A6: FY2026 revenue ($M), second source | B6: 14160 | C6: 43 est, 13,800-14,300 | D6: =Revenue!$I$77 | E6: =D6-B6 | F6: =D6/B6-1 | G6: S&P Global 3 Sep 26
A7: FY2026 adj. EPS ($) | B7: 5.23 | C7: 13 est, 4.85-5.74 | D7: =Cash!$D$51 | E7: =D7-B7 | F7: =D7/B7-1 | G7: Zacks 4 Sep 26
A8: FY2026 FCF ($M) | B8: 5350 | C8: - | D8: =Cash!$D$39 | E8: =D8-B8 | F8: =D8/B8-1 | G8: S&P Global 3 Sep 26
A9: FY2027 revenue ($M) | B9: 15730 | C9: 13 est, 14,990-16,290 | D9: =Revenue!$J$77 | E9: =D9-B9 | F9: =D9/B9-1 | G9: Zacks 4 Sep 26
A10: FY2027 revenue ($M), second source | B10: 15760 | C10: 43 est | D10: =Revenue!$J$77 | E10: =D10-B10 | F10: =D10/B10-1 | G10: S&P Global 3 Sep 26
A11: FY2027 adj. EPS ($) | B11: 6.02 | C11: 13 est, 5.35-6.80 | D11: =Cash!$E$51 | E11: =D11-B11 | F11: =D11/B11-1 | G11: Zacks 4 Sep 26
A12: 3Q2026 revenue ($M) | B12: 4740 | C12: 7 est, 4,720-4,770 | D12: =Revenue!$C$77 | E12: =D12-B12 | F12: =D12/B12-1 | G12: Zacks 4 Sep 26
A13: 3Q2026 adj. EPS ($) | B13: 2.87 | C13: 11 est, 2.52-3.28 | G13: Zacks 4 Sep 26
A14: 4Q2026 revenue ($M) | B14: 3200 | C14: 10 est, 3,050-3,700 | D14: =Revenue!$D$77 | E14: =D14-B14 | F14: =D14/B14-1 | G14: Zacks 4 Sep 26
A15: Mean price target ($) | B15: 178.96 | C15: 46 analysts, 125-220 | D15: =Valuation!$C$46 | E15: =D15-B15 | F15: =D15/B15-1 | G15: S&P Global / TipRanks 3 Sep 26
A17: Historical beat behaviour (WS02, WS04) - how to read our base against the guide
A18: Median revenue beat vs guide midpoint, all 19 guided prints | B18: 0.0252 | G18: WS02 02_guidance_cushion_series.csv
A19: Median revenue beat vs guide midpoint, last 8 prints | B19: 0.0179 | G19: WS02; the cushion has halved
A20: Median revenue beat vs Street, post-2022 (n 14) | B20: 0.017 | G20: WS04 04_consensus_at_print.csv
A21: Probability the print lands above the top of the guide range | B21: 0.78947368 | G21: WS02: 15 of 19
A22: Day-1 excess return explained by the beat | B22: 0.04 | G22: WS04 / the 5 Sep note: R-squared 0.04, LOO negative
A23: 20-day drift zero-crossing, nights surprise vs Street | B23: 0.0183 | G23: WS04 post-2022 fit: excess_20d = -5.19 + 2.834 x nights surprise

Sheet Card_5Nov
A1: 5 November 2026 card - the Q3 2026 print
A2: Model columns are live formulas off the Revenue and Costs sheets; the Active column follows the scenario selector on Inputs!B4. External bars are constants with their source. Q3 2026 reports 5 Nov 2026 (Zacks expected date).
A4: Line | B4: Bear | C4: Base | D4: Bull | E4: Active (Inputs!B4) | F4: Company guide | G4: Street / cushion bar | H4: Source of the bar
A5: 3Q26 revenue ($M) | B5: =Revenue!$C$36 | C5: =Revenue!$C$77 | D5: =Revenue!$C$118 | E5: =CHOOSE(Inputs!$B$4,B5,C5,D5) | F5: $4,690-4,770m (+15-17%) | G5: Street $4,740m; cushion-adj $4,815m | H5: 2Q26 letter; WS04 Zacks 7 est; WS02 02_q3_2026_guide_card.csv (last-8 median cushion +1.79%)
A6: revenue growth y/y | B6: =Revenue!$C$37 | C6: =Revenue!$C$78 | D6: =Revenue!$C$119 | E6: =CHOOSE(Inputs!$B$4,B6,C6,D6) | F6: +15% to +17% | G6: +15.79% (Street) | H6: WS02, WS04
A7: 3Q26 nights (M) | B7: =Revenue!$C$22 | C7: =Revenue!$C$63 | D7: =Revenue!$C$104 | E7: =CHOOSE(Inputs!$B$4,B7,C7,D7) | F7: low double-digit growth | G7: 144-146m (derived) | H7: WS04 04_q3_2026_breakeven.csv; WS02 puts the cushion-adjusted range at 150-154m
A8: nights growth y/y | B8: =Revenue!$C$23 | C8: =Revenue!$C$64 | D8: =Revenue!$C$105 | E8: =CHOOSE(Inputs!$B$4,B8,C8,D8) | F8: 'low double digit' (10-12%) | G8: WS08 nowcast +12.1% (9.3-14.9) | H8: WS08 08_q3_2026_nowcast.csv demand_eq; naive baseline +10.3%
A9: 3Q26 ADR ($) | B9: =Revenue!$C$26 | C9: =Revenue!$C$67 | D9: =Revenue!$C$108 | E9: =CHOOSE(Inputs!$B$4,B9,C9,D9) | F9: 'up moderately' | G9: - | H9: 2Q26 letter
A10: ADR growth y/y | B10: =Revenue!$C$27 | C10: =Revenue!$C$68 | D10: =Revenue!$C$109 | E10: =CHOOSE(Inputs!$B$4,B10,C10,D10) | F10: - | G10: +4.05% (WS08) | H10: WS08: ex-FX run-rate +3.25% plus FX +0.80pp; r 0.96, walk-forward 0.44x naive
A11: of which FX | B11: =Revenue!$C$25 | C11: =Revenue!$C$66 | D11: =Revenue!$C$107 | E11: =CHOOSE(Inputs!$B$4,B11,C11,D11) | F11: - | G11: +0.80pp | H11: WS05 05_fx_schedule.csv broad-USD fit; WS08 refit
A12: 3Q26 GBV ($M) | B12: =Revenue!$C$28 | C12: =Revenue!$C$69 | D12: =Revenue!$C$110 | E12: =CHOOSE(Inputs!$B$4,B12,C12,D12) | F12: mid-teens growth | G12: $26.6-27.2bn (WS02 cushion) | H12: 2Q26 letter; WS02
A13: GBV growth y/y | B13: =Revenue!$C$29 | C13: =Revenue!$C$70 | D13: =Revenue!$C$111 | E13: =CHOOSE(Inputs!$B$4,B13,C13,D13) | F13: mid teens (14-16%) | G13: 16-19% | H13: WS02
A14: 3Q26 take rate | B14: =Revenue!$C$30 | C14: =Revenue!$C$71 | D14: =Revenue!$C$112 | E14: =CHOOSE(Inputs!$B$4,B14,C14,D14) | F14: 'relatively in line y/y' | G14: 17.9% +/- 0.2pt | H14: 2Q26 call; WS02. 3Q25 actual 17.88%
A15: 3Q26 adj. EBITDA margin | B15: =Revenue!$C$40 | C15: =Revenue!$C$81 | D15: =Revenue!$C$122 | E15: =CHOOSE(Inputs!$B$4,B15,C15,D15) | F15: 'down slightly' vs 50.1% | G15: 48.7-50.0% | H15: WS07 5 Nov card (bear 48.3 / base 49.0 / bull 50.2); WS02 says 9 of 10 such ceilings were met
A16: 3Q26 adj. EBITDA ($M) | B16: =Revenue!$C$41 | C16: =Revenue!$C$82 | D16: =Revenue!$C$123 | E16: =CHOOSE(Inputs!$B$4,B16,C16,D16) | F16: up y/y | G16: $2,300-2,400m (derived) | H16: WS04 04_q3_2026_breakeven.csv
A18: THE Q4 GUIDE - what the print's reaction actually runs on
A19: 4Q26 revenue ($M), our forecast | B19: =Revenue!$D$36 | C19: =Revenue!$D$77 | D19: =Revenue!$D$118 | E19: =CHOOSE(Inputs!$B$4,B19,C19,D19) | F19: no guide yet | G19: Street $3,200m (3,050-3,700) | H19: WS04 Zacks 10 est - the widest spread in the table (21% high-low)
A20: 4Q26 revenue growth | B20: =Revenue!$D$37 | C20: =Revenue!$D$78 | D20: =Revenue!$D$119 | E20: =CHOOSE(Inputs!$B$4,B20,C20,D20) | F20: - | G20: +11-13% expected | H20: WS05: FX goes from about +3pp in Q3 to -0.4pp in Q4 and 84% of it is already realised
A21: 4Q26 nights growth | B21: =Revenue!$D$23 | C21: =Revenue!$D$64 | D21: =Revenue!$D$105 | E21: =CHOOSE(Inputs!$B$4,B21,C21,D21) | F21: - | G21: accelerating vs Q3 is the bull tell | H21: WS05: post-2022 an accelerating nights guide averaged +6.7% day-1 (n 5), a decelerating one -5.4% (n 9)
A22: FY26 revenue ($M) | B22: =Revenue!$I$36 | C22: =Revenue!$I$77 | D22: =Revenue!$I$118 | E22: =CHOOSE(Inputs!$B$4,B22,C22,D22) | F22: 'at least mid teens' growth | G22: Street $14,100-14,160m | H22: 2Q26 letter; WS04
A23: FY26 revenue growth | B23: =Revenue!$I$37 | C23: =Revenue!$I$78 | D23: =Revenue!$I$119 | E23: =CHOOSE(Inputs!$B$4,B23,C23,D23) | F23: at least +14-16% | G23: +15.2% to +15.6% | H23: WS04
A24: FY26 adj. EBITDA margin | B24: =Costs!$D$22 | C24: =Costs!$D$52 | D24: =Costs!$D$82 | E24: =CHOOSE(Inputs!$B$4,B24,C24,D24) | F24: 'at least 35.5%' | G24: 36.1-36.9% on the FY24/FY25 cushion | H24: WS02: FY24 beat the floor by 140bp, FY25 by 60bp
A26: CONTEXT AND BASE RATES
A27: Alt-data demand index, 3Q26 to date (z) | C27: -0.325 | H27: WS08 08_demand_index_quarterly.csv, demand_eq; 2Q26 was -0.509, so the index improved. Only 4 of 7 components are populated for 3Q26 and no composite beat a naive baseline walk-forward.
A28: Funds-held backlog nowcast, 3Q26 revenue growth | C28: 0.12 | H28: WS08 08_backlog_tests.csv: funds held +10.46% y/y at 2Q26 x slope 0.60. Under-shot 1Q26 by 3.4pp and 2Q26 by 2.8pp because RNPL defers guest cash to check-in; add ~3pp.
A29: Mean absolute day-1 move on a print | C29: 0.0707 | H29: WS09, n 23; median 6.87%
A30: Mean 20-session post-print excess drift | C30: -0.037 | H30: WS09, n 23, t -2.16
A31: Nights-acceleration sign rule hit rate | C31: 0.80952381 | H31: WS01/predictive study: the sign of the nights-growth acceleration has set the day-1 direction in 17 of 21 prints
A32: Share of day-1 move that is re-rating, not estimates | C32: 0.97 | H32: WS12: day-1 move correlates +0.97 with the change in the EV/NTM-revenue multiple, +0.09 with the estimate change
A33: One turn of EV / NTM EBITDA | C33: 9.11 | H33: WS12: $9.11 per share = 5.0% at $181.94
A34: November excess return vs QQQ, 2021-2025 | C34: -0.051 | H34: WS09: ABNB has underperformed in every November since 2021

Sheet Recon
A1: Reconciliation: the Python mirror against this workbook
A2: Column B is the Python mirror (13_driver_model.py), column C is this workbook and column D is a live Excel formula, so Excel re-checks the difference every time the file is opened. Every |delta| should be 0.00. The same 216 outputs are also checked outside Excel by analysis/src/overnight/13_xlsx_eval.py. Workstream 17 then rebuilt the file in Excel 16.0 itself (Application.CalculateFullRebuild via COM): 0 error cells in 5,544, no circular reference, all 216 outputs and all 2,348 formula cells agreeing with the mirror to better than 1e-6 relative (worst 4.2e-15). Full results: data/processed/overnight/13_reconciliation.csv and 17_excel_vs_python.csv; the audit is research/notes/overnight/17_excel-audit.md.
A4: Item | B4: Python mirror | C4: Workbook cell | D4: Delta | E4: Cell reference
A5: Bear FY2026 revenue ($M) | B5: 13933.349 | C5: =Revenue!$I$36 | D5: =C5-B5 | E5: Revenue!$I$36
A6: Bear FY2026 nights (M) | B6: 579.09738 | C6: =Revenue!$I$22 | D6: =C6-B6 | E6: Revenue!$I$22
A7: Bear FY2026 GBV ($M) | B7: 103758.74 | C7: =Revenue!$I$28 | D7: =C7-B7 | E7: Revenue!$I$28
A8: Bear FY2026 adj. EBITDA ($M) | B8: 4812.2867 | C8: =Costs!$D$21 | D8: =C8-B8 | E8: Costs!$D$21
A9: Bear FY2026 adj. EBITDA margin | B9: 0.34537904 | C9: =Costs!$D$22 | D9: =C9-B9 | E9: Costs!$D$22
A10: Bear FY2026 net income ($M) | B10: 2644.862 | C10: =Costs!$D$32 | D10: =C10-B10 | E10: Costs!$D$32
A11: Bear FY2026 FCF ($M) | B11: 4554.8859 | C11: =Cash!$D$14 | D11: =C11-B11 | E11: Cash!$D$14
A12: Bear FY2026 SBC-adj FCF ($M) | B12: 2720.9259 | C12: =Cash!$D$18 | D12: =C12-B12 | E12: Cash!$D$18
A13: Bear FY2026 diluted shares (M) | B13: 589.01948 | C13: =Cash!$D$23 | D13: =C13-B13 | E13: Cash!$D$23
A14: Bear FY2026 FCF per share ($) | B14: 7.732997 | C14: =Cash!$D$24 | D14: =C14-B14 | E14: Cash!$D$24
A15: Bear FY2026 net cash ($M) | B15: 8792.9999 | C15: =Cash!$D$27 | D15: =C15-B15 | E15: Cash!$D$27
A16: Bear FY2027 revenue ($M) | B16: 14180.974 | C16: =Revenue!$J$36 | D16: =C16-B16 | E16: Revenue!$J$36
A17: Bear FY2027 nights (M) | B17: 611.22284 | C17: =Revenue!$J$22 | D17: =C17-B17 | E17: Revenue!$J$22
A18: Bear FY2027 GBV ($M) | B18: 108038.48 | C18: =Revenue!$J$28 | D18: =C18-B18 | E18: Revenue!$J$28
A19: Bear FY2027 adj. EBITDA ($M) | B19: 4026.9273 | C19: =Costs!$E$21 | D19: =C19-B19 | E19: Costs!$E$21
A20: Bear FY2027 adj. EBITDA margin | B20: 0.2839669 | C20: =Costs!$E$22 | D20: =C20-B20 | E20: Costs!$E$22
A21: Bear FY2027 net income ($M) | B21: 1754.2614 | C21: =Costs!$E$32 | D21: =C21-B21 | E21: Costs!$E$32
A22: Bear FY2027 FCF ($M) | B22: 3531.3449 | C22: =Cash!$E$14 | D22: =C22-B22 | E22: Cash!$E$14
A23: Bear FY2027 SBC-adj FCF ($M) | B23: 1440.6305 | C23: =Cash!$E$18 | D23: =C23-B23 | E23: Cash!$E$18
A24: Bear FY2027 diluted shares (M) | B24: 580.42933 | C24: =Cash!$E$23 | D24: =C24-B24 | E24: Cash!$E$23
A25: Bear FY2027 FCF per share ($) | B25: 6.0840222 | C25: =Cash!$E$24 | D25: =C25-B25 | E25: Cash!$E$24
A26: Bear FY2027 net cash ($M) | B26: 8592.5948 | C26: =Cash!$E$27 | D26: =C26-B26 | E26: Cash!$E$27
A27: Bear FY2028 revenue ($M) | B27: 14970.671 | C27: =Revenue!$K$36 | D27: =C27-B27 | E27: Revenue!$K$36
A28: Bear FY2028 nights (M) | B28: 638.41455 | C28: =Revenue!$K$22 | D28: =C28-B28 | E28: Revenue!$K$22
A29: Bear FY2028 GBV ($M) | B29: 113973.28 | C29: =Revenue!$K$28 | D29: =C29-B29 | E29: Revenue!$K$28
A30: Bear FY2028 adj. EBITDA ($M) | B30: 3814.4838 | C30: =Costs!$F$21 | D30: =C30-B30 | E30: Costs!$F$21
A31: Bear FY2028 adj. EBITDA margin | B31: 0.25479712 | C31: =Costs!$F$22 | D31: =C31-B31 | E31: Costs!$F$22
A32: Bear FY2028 net income ($M) | B32: 1351.0166 | C32: =Costs!$F$32 | D32: =C32-B32 | E32: Costs!$F$32
A33: Bear FY2028 FCF ($M) | B33: 3123.5661 | C33: =Cash!$F$14 | D33: =C33-B33 | E33: Cash!$F$14
A34: Bear FY2028 SBC-adj FCF ($M) | B34: 781.96602 | C34: =Cash!$F$18 | D34: =C34-B34 | E34: Cash!$F$18
A35: Bear FY2028 diluted shares (M) | B35: 573.06123 | C35: =Cash!$F$23 | D35: =C35-B35 | E35: Cash!$F$23
A36: Bear FY2028 FCF per share ($) | B36: 5.4506674 | C36: =Cash!$F$24 | D36: =C36-B36 | E36: Cash!$F$24
A37: Bear FY2028 net cash ($M) | B37: 7896.6009 | C37: =Cash!$F$27 | D37: =C37-B37 | E37: Cash!$F$27
A38: Bear 3Q26 revenue ($M) | B38: 4632.3551 | C38: =Revenue!$C$36 | D38: =C38-B38 | E38: Revenue!$C$36
A39: Bear 3Q26 nights (M) | B39: 144.17596 | C39: =Revenue!$C$22 | D39: =C39-B39 | E39: Revenue!$C$22
A40: Bear 3Q26 ADR ($) | B40: 176.11353 | C40: =Revenue!$C$26 | D40: =C40-B40 | E40: Revenue!$C$26
A41: Bear 3Q26 adj. EBITDA ($M) | B41: 2237.4275 | C41: =Revenue!$C$41 | D41: =C41-B41 | E41: Revenue!$C$41
A42: Bear 3Q26 adj. EBITDA margin | B42: 0.483 | C42: =Revenue!$C$40 | D42: =C42-B42 | E42: Revenue!$C$40
A43: Bear 4Q26 revenue ($M) | B43: 3014.9938 | C43: =Revenue!$D$36 | D43: =C43-B43 | E43: Revenue!$D$36
A44: Bear 4Q26 nights (M) | B44: 130.42142 | C44: =Revenue!$D$22 | D44: =C44-B44 | E44: Revenue!$D$22
A45: Bear 4Q26 ADR ($) | B45: 168.43399 | C45: =Revenue!$D$26 | D45: =C45-B45 | E45: Revenue!$D$26
A46: Bear 4Q26 adj. EBITDA ($M) | B46: 798.97336 | C46: =Revenue!$D$41 | D46: =C46-B46 | E46: Revenue!$D$41
A47: Bear 4Q26 adj. EBITDA margin | B47: 0.265 | C47: =Revenue!$D$40 | D47: =C47-B47 | E47: Revenue!$D$40
A48: Bear 1Q27 revenue ($M) | B48: 2766.3959 | C48: =Revenue!$E$36 | D48: =C48-B48 | E48: Revenue!$E$36
A49: Bear 1Q27 nights (M) | B49: 164.836 | C49: =Revenue!$E$22 | D49: =C49-B49 | E49: Revenue!$E$22
A50: Bear 1Q27 ADR ($) | B50: 183.63136 | C50: =Revenue!$E$26 | D50: =C50-B50 | E50: Revenue!$E$26
A51: Bear 1Q27 adj. EBITDA ($M) | B51: 368.4408 | C51: =Revenue!$E$41 | D51: =C51-B51 | E51: Revenue!$E$41
A52: Bear 1Q27 adj. EBITDA margin | B52: 0.13318441 | C52: =Revenue!$E$40 | D52: =C52-B52 | E52: Revenue!$E$40
A53: Bear 2Q27 revenue ($M) | B53: 3719.3299 | C53: =Revenue!$F$36 | D53: =C53-B53 | E53: Revenue!$F$36
A54: Bear 2Q27 nights (M) | B54: 156.50474 | C54: =Revenue!$F$22 | D54: =C54-B54 | E54: Revenue!$F$22
A55: Bear 2Q27 ADR ($) | B55: 180.35286 | C55: =Revenue!$F$26 | D55: =C55-B55 | E55: Revenue!$F$26
A56: Bear 2Q27 adj. EBITDA ($M) | B56: 1075.5722 | C56: =Revenue!$F$41 | D56: =C56-B56 | E56: Revenue!$F$41
A57: Bear 2Q27 adj. EBITDA margin | B57: 0.28918441 | C57: =Revenue!$F$40 | D57: =C57-B57 | E57: Revenue!$F$40
A58: Bear 3Q27 revenue ($M) | B58: 4640.663 | C58: =Revenue!$G$36 | D58: =C58-B58 | E58: Revenue!$G$36
A59: Bear 3Q27 nights (M) | B59: 152.15255 | C59: =Revenue!$G$22 | D59: =C59-B59 | E59: Revenue!$G$22
A60: Bear 3Q27 ADR ($) | B60: 173.64124 | C60: =Revenue!$G$26 | D60: =C60-B60 | E60: Revenue!$G$26
A61: Bear 3Q27 adj. EBITDA ($M) | B61: 1959.2156 | C61: =Revenue!$G$41 | D61: =C61-B61 | E61: Revenue!$G$41
A62: Bear 3Q27 adj. EBITDA margin | B62: 0.42218441 | C62: =Revenue!$G$40 | D62: =C62-B62 | E62: Revenue!$G$40
A63: Bear 4Q27 revenue ($M) | B63: 3054.5854 | C63: =Revenue!$H$36 | D63: =C63-B63 | E63: Revenue!$H$36
A64: Bear 4Q27 nights (M) | B64: 137.72955 | C64: =Revenue!$H$22 | D64: =C64-B64 | E64: Revenue!$H$22
A65: Bear 4Q27 ADR ($) | B65: 167.88977 | C65: =Revenue!$H$26 | D65: =C65-B65 | E65: Revenue!$H$26
A66: Bear 4Q27 adj. EBITDA ($M) | B66: 623.69872 | C66: =Revenue!$H$41 | D66: =C66-B66 | E66: Revenue!$H$41
A67: Bear 4Q27 adj. EBITDA margin | B67: 0.20418441 | C67: =Revenue!$H$40 | D67: =C67-B67 | E67: Revenue!$H$40
A68: Bear Football field low | B68: 37.230127 | C68: =Valuation!$B$44 | D68: =C68-B68 | E68: Valuation!$B$44
A69: Bear Football field high | B69: 108.46473 | C69: =Valuation!$B$45 | D69: =C69-B69 | E69: Valuation!$B$45
A70: Bear Football field mean | B70: 74.178216 | C70: =Valuation!$B$46 | D70: =C70-B70 | E70: Valuation!$B$46
A71: Bear price: EV / adj. EBITDA, FY27E | B71: 108.46473 | C71: =Valuation!$B$19 | D71: =C71-B71 | E71: Valuation!$B$19
A72: Bear price: EV / FCF, FY27E | B72: 83.553311 | C72: =Valuation!$B$20 | D72: =C72-B72 | E72: Valuation!$B$20
A73: Bear price: P / SBC-adjusted FCF, FY27E | B73: 37.230127 | C73: =Valuation!$B$21 | D73: =C73-B73 | E73: Valuation!$B$21
A74: Bear price: P / earnings proxy, FY27E | B74: 45.335272 | C74: =Valuation!$B$22 | D74: =C74-B74 | E74: Valuation!$B$22
A75: Bear price: EV / adj. EBITDA, FY28E | B75: 92.950776 | C75: =Valuation!$B$23 | D75: =C75-B75 | E75: Valuation!$B$23
A76: Bear price: DCF on FCF | B76: 77.535075 | C76: =Valuation!$B$40 | D76: =C76-B76 | E76: Valuation!$B$40
A77: Base FY2026 revenue ($M) | B77: 14232.532 | C77: =Revenue!$I$77 | D77: =C77-B77 | E77: Revenue!$I$77
A78: Base FY2026 nights (M) | B78: 585.69727 | C78: =Revenue!$I$63 | D78: =C78-B78 | E78: Revenue!$I$63
A79: Base FY2026 GBV ($M) | B79: 105614.33 | C79: =Revenue!$I$69 | D79: =C79-B79 | E79: Revenue!$I$69
A80: Base FY2026 adj. EBITDA ($M) | B80: 5158.0356 | C80: =Costs!$D$51 | D80: =C80-B80 | E80: Costs!$D$51
A81: Base FY2026 adj. EBITDA margin | B81: 0.36241167 | C81: =Costs!$D$52 | D81: =C81-B81 | E81: Costs!$D$52
A82: Base FY2026 net income ($M) | B82: 3064.5644 | C82: =Costs!$D$62 | D82: =C82-B82 | E82: Costs!$D$62
A83: Base FY2026 FCF ($M) | B83: 5128.7343 | C83: =Cash!$D$39 | D83: =C83-B83 | E83: Cash!$D$39
A84: Base FY2026 SBC-adj FCF ($M) | B84: 3342.2043 | C84: =Cash!$D$43 | D84: =C84-B84 | E84: Cash!$D$43
A85: Base FY2026 diluted shares (M) | B85: 588.85003 | C85: =Cash!$D$48 | D85: =C85-B85 | E85: Cash!$D$48
A86: Base FY2026 FCF per share ($) | B86: 8.7097463 | C86: =Cash!$D$49 | D86: =C86-B86 | E86: Cash!$D$49
A87: Base FY2026 net cash ($M) | B87: 9383.4488 | C87: =Cash!$D$52 | D87: =C87-B87 | E87: Cash!$D$52
A88: Base FY2027 revenue ($M) | B88: 15842.036 | C88: =Revenue!$J$77 | D88: =C88-B88 | E88: Revenue!$J$77
A89: Base FY2027 nights (M) | B89: 637.6445 | C89: =Revenue!$J$63 | D89: =C89-B89 | E89: Revenue!$J$63
A90: Base FY2027 GBV ($M) | B90: 118081.26 | C90: =Revenue!$J$69 | D90: =C90-B90 | E90: Revenue!$J$69
A91: Base FY2027 adj. EBITDA ($M) | B91: 5685.7698 | C91: =Costs!$E$51 | D91: =C91-B91 | E91: Costs!$E$51
A92: Base FY2027 adj. EBITDA margin | B92: 0.35890398 | C92: =Costs!$E$52 | D92: =C92-B92 | E92: Costs!$E$52
A93: Base FY2027 net income ($M) | B93: 3258.4068 | C93: =Costs!$E$62 | D93: =C93-B93 | E93: Costs!$E$62
A94: Base FY2027 FCF ($M) | B94: 5420.3521 | C94: =Cash!$E$39 | D94: =C94-B94 | E94: Cash!$E$39
A95: Base FY2027 SBC-adj FCF ($M) | B95: 3455.1691 | C95: =Cash!$E$43 | D95: =C95-B95 | E95: Cash!$E$43
A96: Base FY2027 diluted shares (M) | B96: 574.59818 | C96: =Cash!$E$48 | D96: =C96-B96 | E96: Cash!$E$48
A97: Base FY2027 FCF per share ($) | B97: 9.4332914 | C97: =Cash!$E$49 | D97: =C97-B97 | E97: Cash!$E$49
A98: Base FY2027 net cash ($M) | B98: 10115.987 | C98: =Cash!$E$52 | D98: =C98-B98 | E98: Cash!$E$52
A99: Base FY2028 revenue ($M) | B99: 17947.136 | C99: =Revenue!$K$77 | D99: =C99-B99 | E99: Revenue!$K$77
A100: Base FY2028 nights (M) | B100: 685.15684 | C100: =Revenue!$K$63 | D100: =C100-B100 | E100: Revenue!$K$63
A101: Base FY2028 GBV ($M) | B101: 130051.76 | C101: =Revenue!$K$69 | D101: =C101-B101 | E101: Revenue!$K$69
...
