Workbook

Sheet Cover
B2: Airbnb (ABNB): the team's forecasting model in one workbook
B3: 2026 Citadel Intercollegiate Stock Pitch Competition. Built 16 Sep 2026 from the repo's processed outputs (main at PR #56). Prelim memo due 2 Oct 2026; next print 5 Nov 2026 (3Q26).
A5: What this is
B6: • One place to see everything the team has built for the upcoming quarters: the revenue model (nights x ADR x FX x take rate), the cost stack line by line, a full income statement to FY27, the operating schedules behind them, the annotated stock history, the two reverse-DCF studies, and the Street/guidance comparison with its price implications.
B7: • Nothing here is typed in by hand: every blue number is read from a CSV in data/processed (the path is beside it or in the Sources block at the foot of each tab); every black number is an Excel formula. Rebuild with: py -3.13 analysis/src/model_workbook/build.py (the script recalculates in Excel and saves the cached values).
B8: • Two cases run through the workbook. BASE = the team model (bridge v3 revenue path, 40_line_build costs). SHORT = the pitch case added 15 Sep (the 4Q25-1Q26 bundle and the World Cup flattered 1H26 nights; RNPL eligibility expanding into a cohort that cancels more; costs at management's budget). STREET = LSEG/Bloomberg consensus, 11-12 Sep 2026.
A10: How to read it
B11: Blue font | C11: hard-coded source value from a repo CSV
B12: Black font | C12: formula in this sheet
B13: Green font | C13: link to another tab
B14: Grey italic | C14: note, source, caveat
B15: Yellow fill | C15: forecast column (3Q26E onward)
B16: Green fill | C16: team base case
B17: Orange fill | C17: short (pitch) case
B18: Grey fill | C18: Street consensus
B19: Pink fill | C19: bear / warning
B20: • The Income Statement tab has a scenario dropdown in cell B3 (Base, the two Short cases, evidence-only costs, revenue/cost bear and bull). The forecast columns on the Income Statement, Margins and Operating Schedules tabs re-flow to the chosen scenario; the Revenue Model and 5 Nov & Street tabs always show Base, Short and Street side by side.
B21: • Units are USD millions unless a row says otherwise; nights in millions; GBV in $bn; percentages are y/y unless labelled '% of revenue'. Quarters are labelled 1Q23A ... 4Q27E.
B22: • Forecast vs scenario: 3Q26 is a tested forecast (the calibrated margin combination beat the Street 14/14 and 10/10 at h=0 in the two backtest windows; the revenue bridge and nights index were scored through the harness). 4Q26 margin is quoted from the Street (no h=1 edge). FY27 is a labelled spending scenario. FY28 is a roll-forward, not a forecast. The short case is a mechanism-plus-current-data view, not a backtest.
A24: Tab map
B25: Income Statement | C25: Quarterly 1Q23A-4Q27E and FY23-FY27: KPIs, cash cost lines, adjusted EBITDA, GAAP bridge to EPS. Scenario dropdown. Street and Short comparison rows underneath.
B26: Revenue Model | C26: Nights (with the regional and lap builds), ADR ex-FX and FX, GBV, take rate, the bridge conversion, revenue; bear/bull/short scenarios; Street on every KPI; the 3Q26 guide in force and the 4Q26 guide the model implies; guide history.
B27: Margins | C27: Each cost line with its drivers, the 3Q26 'down slightly' reconciliation, the 5 Nov margin card (calibrated run), the FY26 sentence expectation and budget identity, FY27 scenario grid, sensitivities, the short case quarter by quarter, seasonality.
B28: Operating Schedules | C28: Bookings and unit economics, revenue by region, the 2027 nights and ADR builds, FX paths, unit-cost drivers, below-EBITDA items, the full parameter sheet.
B29: 5 Nov & Street | C29: Key items side by side (Street / base / short / management delivered), the 5 Nov sequence the model expects, and what each path implies for the price (joint solve, fixed multiple, print reaction, repricing ladder).
B30: Stock Chart | C30: Annotated price history since the IPO: every earnings reaction, every 7%+ day and its driver, and the read-across to 5 Nov.
B31: Reverse DCF - Mgmt | C31: What management's words are worth: Literal / Delivered / Ambition cases, inputs, implied prices by lens, reverse-DCF growth.
B32: Reverse DCF - Market | C32: What the price, the options market and the sell-side tape are paying for; the reaction function; the positioning card.
B33: Scenario Data | C33: The data block behind the dropdown (every scenario x line x quarter). Reference only.
A35: The numbers in one table
B36: Item | C36: Street | D36: Team base | E36: Short (pitch) | F36: Base vs Street | G36: Short vs Street
B37: 3Q26 revenue ($m) | C37: 4744.3221 | D37: 4804.0355 | E37: 4680.9 | F37: =D37/C37-1 -> 0.012586283 | G37: =E37/C37-1 -> -0.013368005
B38: 3Q26 nights y/y | C38: 0.11527 | D38: 0.0989 | E38: 0.085 | F38: =D38-C38 -> -0.01637 | G38: =E38-C38 -> -0.03027
B39: 3Q26 adj. EBITDA ($m) | C39: 2361.5218 | D39: 2419.6425 | E39: 2289.8152 | F39: =D39/C39-1 -> 0.024611549 | G39: =E39/C39-1 -> -0.030364556
B40: 3Q26 adj. EBITDA margin | C40: 0.49775747 | D40: 0.50366874 | E40: 0.48918268 | F40: =D40-C40 -> 0.0059112654 | G40: =E40-C40 -> -0.0085747881
B41: 3Q26 EPS ($) | C41: 2.84539 | D41: 2.9071599 | E41: 2.7144969 | F41: =D41/C41-1 -> 0.021708758 | G41: =E41/C41-1 -> -0.046001803
B42: 4Q26 revenue ($m) | C42: 3161.8163 | D42: 3178.1078 | E42: 2965.8677 | F42: =D42/C42-1 -> 0.0051525859 | G42: =E42/C42-1 -> -0.061973428
B43: 4Q26 adj. EBITDA ($m) | C43: 913.68388 | D43: 898.87164 | E43: 699.60784 | F43: =D43/C43-1 -> -0.016211557 | G43: =E43/C43-1 -> -0.2342999
B44: FY26 revenue ($m) | C44: 14189.557 | D44: 14268.143 | E44: 13932.768 | F44: =D44/C44-1 -> 0.0055383159 | G44: =E44/C44-1 -> -0.018097068
B45: FY26 adj. EBITDA margin | C45: 0.35615785 | D45: 0.3573355 | E45: 0.34231699 | F45: =D45-C45 -> 0.0011776509 | G45: =E45-C45 -> -0.013840862
B46: FY26 EPS ($) | C46: 5.31259 | D46: 5.276011 | F46: =D46/C46-1 -> -0.0068853453
B47: FY27 revenue ($m) | C47: 15819.339 | D47: 15828.607 | E47: 14913.512 | F47: =D47/C47-1 -> 0.00058582472 | G47: =E47/C47-1 -> -0.057260781
B48: FY27 adj. EBITDA ($m) | C48: 5766.0992 | D48: 5644.2042 | E48: 4761.4354 | F48: =D48/C48-1 -> -0.02113993 | G48: =E48/C48-1 -> -0.1742363
B49: FY27 adj. EBITDA margin | C49: 0.36449684 | D49: 0.35658251 | E49: 0.3192699 | F49: =D49-C49 -> -0.0079143327 | G49: =E49-C49 -> -0.045226937
B50: FY27 EPS ($) | C50: 6.22753 | D50: 5.9331363 | E50: 4.5839264 | F50: =D50/C50-1 -> -0.04727295 | G50: =E50/C50-1 -> -0.26392544
A52: The pitch in six lines (short; see 5 Nov & Street for the arithmetic)
B53: • The market is positioned for an accelerating 3Q26 nights print (Street +11.5%, every estimate at or above 2Q26's +10.3%); the team's nowcast is a deceleration (+9.9% base, band 8.5-11.0; +8.5% short). On the only print reaction with statistical support (post-2022 sign rule, n 14) a decelerating print has averaged -5.6% day-1 excess against a 9.5% options-implied dispersion.
B54: • 1H26 nights were flattered by the 4Q25-1Q26 bundle and the June-July World Cup; the underlying rate is 6-7%, not 9-10%. RNPL eligibility is widening into a cohort that cancels more, with no volume offset in the alt data.
B55: • On the short path the 4Q26 revenue guide lands 6-10% below the Street and FY26 needs a $177M marketing cut to hold the 35.5% floor; FY27 EBITDA is $4.8bn / 31.9% against the Street's $5.8bn / 36.5%.
B56: • Even on the team's own base path, 5 Nov is 'a beat on dollars, not points' (3Q26 EBITDA $2,420m vs $2,362m) followed by a 4Q26 guide midpoint about 3% below the Street, because the Street prices the guide plus the cushion.
B57: • The Street's FY27 margin needs the marketing ramp to stop (43.7% incremental margin); the line build's S&M path (19.4% -> 21.3% -> 21.9% of revenue) gives 35.7%, the calibrated run 34.6%.
B58: • Price: $170 pays 16x for FY27 revenue of $15.7-15.9bn (the Street and the team base); the team bear is worth $121-137 and the short case about $140-148 on the same arithmetic (indicative).
A60: Provenance and what not to quote
B61: • Revenue: bridge v3 (PR #52, 12 Sep) on the quarterly nights path (PR #32), ADR card v3 (PR #46), the FX-lag kernel (WS05) and the WS06 v2b 2027 path. Margins: the 13-15 Sep margin build (PR #56): calibrated combination (23_final_model, Codex-audited, 18 findings closed) and the line build (40_line_build, Codex read-only check, 7 findings fixed). Reverse DCF: PR #49 and the 12-13 Sep market-implied run. Stock history: the predictive study.
B62: • Withdrawn numbers (do not quote): P(beat) 0.77 (now 0.779), the 3Q26 band $2,299-2,499m (now $2,337-2,462m), 'attained coverage 82-91%', 'Airbnb has no cost dial', S&M $790M/+35% (now $781M/+33.5%), FY27 S&M $3,740M/23.6% (run) or the WS31b 4Q26 margin profile of 24.7-25.9%. The full kill list is in docs/revenue-forecast-strategy/AGENT_BRIEF.md section 6 and docs/margin-build/SYNTHESIS.md section 9.
B63: • Consensus is a comparison column, never an input. Every consensus value in this workbook carries its vendor and pull date. The Bloomberg KPI distribution is a 5-12 Sep pull, the LSEG means are 11 Sep.
B64: • Open items for the team (from the margin build): the revenue_leg_live harness patch; reconcile or retire WS31b; a genuine h=1 object for 4Q26; the G&A residual allocation; the 5 Nov 10-Q S&M split will settle whether the ramp is a commitment or a dial.

Sheet Income Statement
A1: Airbnb income statement: actuals 1Q23-2Q26, forecast 3Q26-4Q27, FY23-FY27
A2: USD millions unless stated. Blue = source value (10-Q/10-K panel, 40_line_build), black = formula. Forecast columns (yellow) follow the scenario chosen in B3 and pull from the 'Scenario Data' tab. Adjusted EBITDA = revenue less cash costs plus D&A (cash cost lines are GAAP less SBC and other add-backs, as management defines them).
A3: Scenario shown in the forecast columns → | B3: Base (team model) | G3: =INDEX('Scenario Data'!$M$5:$M$14,MATCH($B$3,'Scenario Data'!$L$5:$L$14,0)) -> base | H3: ← scenario key (used by the lookups). Pick from the dropdown in B3: Base, the two Short (pitch) cases, evidence-only costs, or the bear/bull revenue and cost cases.
B4: 1Q23 | C4: 2Q23 | D4: 3Q23 | E4: 4Q23 | F4: 1Q24 | G4: 2Q24 | H4: 3Q24 | I4: 4Q24 | J4: 1Q25 | K4: 2Q25 | L4: 3Q25 | M4: 4Q25 | N4: 1Q26 | O4: 2Q26 | P4: 3Q26 | Q4: 4Q26 | R4: 1Q27 | S4: 2Q27 | T4: 3Q27 | U4: 4Q27 | W4: FY23 | X4: FY24 | Y4: FY25 | Z4: FY26 | AA4: FY27
A5: Quarter | B5: 1Q23A | C5: 2Q23A | D5: 3Q23A | E5: 4Q23A | F5: 1Q24A | G5: 2Q24A | H5: 3Q24A | I5: 4Q24A | J5: 1Q25A | K5: 2Q25A | L5: 3Q25A | M5: 4Q25A | N5: 1Q26A | O5: 2Q26A | P5: 3Q26E | Q5: 4Q26E | R5: 1Q27E | S5: 2Q27E | T5: 3Q27E | U5: 4Q27E | W5: FY23 | X5: FY24 | Y5: FY25 | Z5: FY26E | AA5: FY27E
A6: Operating KPIs
A7: Nights & seats booked (m) | B7: 121.1 | C7: 115.1 | D7: 113.2 | E7: 98.8 | F7: 132.6 | G7: 125.1 | H7: 122.8 | I7: 111 | J7: 143.1 | K7: 134.4 | L7: 133.6 | M7: 121.9 | N7: 156.2 | O7: 148.3 | P7: =INDEX('Scenario Data'!$D$5:$I$345,MATCH($G$3&"|nights_m",'Scenario Data'!$A$5:$A$345,0),MATCH(P$4,'Scenario Data'!$D$4:$I$4,0)) -> 146.813 | Q7: =INDEX('Scenario Data'!$D$5:$I$345,MATCH($G$3&"|nights_m",'Scenario Data'!$A$5:$A$345,0),MATCH(Q$4,'Scenario Data'!$D$4:$I$4,0)) -> 131.7983 | R7: =INDEX('Scenario Data'!$D$5:$I$345,MATCH($G$3&"|nights_m",'Scenario Data'!$A$5:$A$345,0),MATCH(R$4,'Scenario Data'!$D$4:$I$4,0)) -> 169.0178 | S7: =INDEX('Scenario Data'!$D$5:$I$345,MATCH($G$3&"|nights_m",'Scenario Data'!$A$5:$A$345,0),MATCH(S$4,'Scenario Data'!$D$4:$I$4,0)) -> 157.1001 | T7: =INDEX('Scenario Data'!$D$5:$I$345,MATCH($G$3&"|nights_m",'Scenario Data'!$A$5:$A$345,0),MATCH(T$4,'Scenario Data'!$D$4:$I$4,0)) -> 155.958 | U7: =INDEX('Scenario Data'!$D$5:$I$345,MATCH($G$3&"|nights_m",'Scenario Data'!$A$5:$A$345,0),MATCH(U$4,'Scenario Data'!$D$4:$I$4,0)) -> 139.7655 | W7: 448.2 | X7: 491.5 | Y7: 533 | Z7: =SUM(N7:O7,P7:Q7) -> 583.1113 | AA7: =SUM(R7:U7) -> 621.8414
A8: y/y | F8: =IFERROR(F7/B7-1,"") -> 0.094962841 | G8: =IFERROR(G7/C7-1,"") -> 0.086880973 | H8: =IFERROR(H7/D7-1,"") -> 0.084805654 | I8: =IFERROR(I7/E7-1,"") -> 0.12348178 | J8: =IFERROR(J7/F7-1,"") -> 0.07918552 | K8: =IFERROR(K7/G7-1,"") -> 0.074340528 | L8: =IFERROR(L7/H7-1,"") -> 0.087947883 | M8: =IFERROR(M7/I7-1,"") -> 0.098198198 | ... U8: =IFERROR(U7/Q7-1,"") -> 0.060449945 | X8: =IFERROR(X7/W7-1,"") -> 0.096608657 | Y8: =IFERROR(Y7/X7-1,"") -> 0.084435402 | Z8: =IFERROR(Z7/Y7-1,"") -> 0.094017448 | AA8: =IFERROR(AA7/Z7-1,"") -> 0.066419738
A9: Gross booking value ($bn) | B9: 20.4 | C9: 19.1 | D9: 18.3 | E9: 15.5 | F9: 22.9 | G9: 21.2 | H9: 20.1 | I9: 17.6 | J9: 24.5 | K9: 23.5 | L9: 22.9 | M9: 20.4 | N9: 29.2 | O9: 27.2 | P9: =INDEX('Scenario Data'!$D$5:$I$345,MATCH($G$3&"|gbv_busd",'Scenario Data'!$A$5:$A$345,0),MATCH(P$4,'Scenario Data'!$D$4:$I$4,0)) -> 26.028 | Q9: =INDEX('Scenario Data'!$D$5:$I$345,MATCH($G$3&"|gbv_busd",'Scenario Data'!$A$5:$A$345,0),MATCH(Q$4,'Scenario Data'!$D$4:$I$4,0)) -> 22.9873 | R9: =INDEX('Scenario Data'!$D$5:$I$345,MATCH($G$3&"|gbv_busd",'Scenario Data'!$A$5:$A$345,0),MATCH(R$4,'Scenario Data'!$D$4:$I$4,0)) -> 32.5996 | S9: =INDEX('Scenario Data'!$D$5:$I$345,MATCH($G$3&"|gbv_busd",'Scenario Data'!$A$5:$A$345,0),MATCH(S$4,'Scenario Data'!$D$4:$I$4,0)) -> 29.6479 | T9: =INDEX('Scenario Data'!$D$5:$I$345,MATCH($G$3&"|gbv_busd",'Scenario Data'!$A$5:$A$345,0),MATCH(T$4,'Scenario Data'!$D$4:$I$4,0)) -> 28.3908 | U9: =INDEX('Scenario Data'!$D$5:$I$345,MATCH($G$3&"|gbv_busd",'Scenario Data'!$A$5:$A$345,0),MATCH(U$4,'Scenario Data'!$D$4:$I$4,0)) -> 24.8342 | W9: 73.3 | X9: 81.8 | Y9: 91.3 | Z9: =SUM(N9:O9,P9:Q9) -> 105.4153 | AA9: =SUM(R9:U9) -> 115.4725
A10: y/y | F10: =IFERROR(F9/B9-1,"") -> 0.12254902 | G10: =IFERROR(G9/C9-1,"") -> 0.10994764 | H10: =IFERROR(H9/D9-1,"") -> 0.098360656 | I10: =IFERROR(I9/E9-1,"") -> 0.13548387 | J10: =IFERROR(J9/F9-1,"") -> 0.069868996 | K10: =IFERROR(K9/G9-1,"") -> 0.10849057 | L10: =IFERROR(L9/H9-1,"") -> 0.13930348 | M10: =IFERROR(M9/I9-1,"") -> 0.15909091 | ... U10: =IFERROR(U9/Q9-1,"") -> 0.080344364 | X10: =IFERROR(X9/W9-1,"") -> 0.1159618 | Y10: =IFERROR(Y9/X9-1,"") -> 0.11613692 | Z10: =IFERROR(Z9/Y9-1,"") -> 0.1546035 | AA10: =IFERROR(AA9/Z9-1,"") -> 0.095405506
A11: ADR ($, = GBV / nights) | B11: =IFERROR(B9/B7*1000,"") -> 168.45582 | C11: =IFERROR(C9/C7*1000,"") -> 165.94266 | D11: =IFERROR(D9/D7*1000,"") -> 161.66078 | E11: =IFERROR(E9/E7*1000,"") -> 156.88259 | F11: =IFERROR(F9/F7*1000,"") -> 172.69985 | G11: =IFERROR(G9/G7*1000,"") -> 169.46443 | H11: =IFERROR(H9/H7*1000,"") -> 163.68078 | I11: =IFERROR(I9/I7*1000,"") -> 158.55856 | ... U11: =IFERROR(U9/U7*1000,"") -> 177.68476 | W11: =IFERROR(W9/W7*1000,"") -> 163.54306 | X11: =IFERROR(X9/X7*1000,"") -> 166.4293 | Y11: =IFERROR(Y9/Y7*1000,"") -> 171.29456 | Z11: =IFERROR(Z9/Z7*1000,"") -> 180.78075 | AA11: =IFERROR(AA9/AA7*1000,"") -> 185.69446
A12: y/y | F12: =IFERROR(F11/B11-1,"") -> 0.025193712 | G12: =IFERROR(G11/C11-1,"") -> 0.021222812 | H12: =IFERROR(H11/D11-1,"") -> 0.012495328 | I12: =IFERROR(I11/E11-1,"") -> 0.010682941 | J12: =IFERROR(J11/F11-1,"") -> -0.0086329223 | K12: =IFERROR(K11/G11-1,"") -> 0.031786978 | L12: =IFERROR(L11/H11-1,"") -> 0.047204099 | M12: =IFERROR(M11/I11-1,"") -> 0.055447834 | ... U12: =IFERROR(U11/Q11-1,"") -> 0.018760356 | X12: =IFERROR(X11/W11-1,"") -> 0.017648177 | Y12: =IFERROR(Y11/X11-1,"") -> 0.0292332 | Z12: =IFERROR(Z11/Y11-1,"") -> 0.055379424 | AA12: =IFERROR(AA11/Z11-1,"") -> 0.027180449
A14: Income statement (adjusted EBITDA build, then GAAP bridge)
A15: Revenue | B15: 1818 | C15: 2484 | D15: 3397 | E15: 2218 | F15: 2142 | G15: 2748 | H15: 3732 | I15: 2480 | J15: 2272 | K15: 3096 | L15: 4095 | M15: 2778 | N15: 2678 | O15: 3608 | P15: =INDEX('Scenario Data'!$D$5:$I$345,MATCH($G$3&"|revenue",'Scenario Data'!$A$5:$A$345,0),MATCH(P$4,'Scenario Data'!$D$4:$I$4,0)) -> 4804.0355 | Q15: =INDEX('Scenario Data'!$D$5:$I$345,MATCH($G$3&"|revenue",'Scenario Data'!$A$5:$A$345,0),MATCH(Q$4,'Scenario Data'!$D$4:$I$4,0)) -> 3178.1078 | R15: =INDEX('Scenario Data'!$D$5:$I$345,MATCH($G$3&"|revenue",'Scenario Data'!$A$5:$A$345,0),MATCH(R$4,'Scenario Data'!$D$4:$I$4,0)) -> 3053.1293 | S15: =INDEX('Scenario Data'!$D$5:$I$345,MATCH($G$3&"|revenue",'Scenario Data'!$A$5:$A$345,0),MATCH(S$4,'Scenario Data'!$D$4:$I$4,0)) -> 4028.9807 | T15: =INDEX('Scenario Data'!$D$5:$I$345,MATCH($G$3&"|revenue",'Scenario Data'!$A$5:$A$345,0),MATCH(T$4,'Scenario Data'!$D$4:$I$4,0)) -> 5280.7325 | U15: =INDEX('Scenario Data'!$D$5:$I$345,MATCH($G$3&"|revenue",'Scenario Data'!$A$5:$A$345,0),MATCH(U$4,'Scenario Data'!$D$4:$I$4,0)) -> 3465.7641 | W15: 9917 | X15: 11102 | Y15: 12241 | Z15: =SUM(N15:O15,P15:Q15) -> 14268.143 | AA15: =SUM(R15:U15) -> 15828.607
A16: y/y | F16: =IFERROR(F15/B15-1,"") -> 0.17821782 | G16: =IFERROR(G15/C15-1,"") -> 0.10628019 | H16: =IFERROR(H15/D15-1,"") -> 0.098616426 | I16: =IFERROR(I15/E15-1,"") -> 0.11812444 | J16: =IFERROR(J15/F15-1,"") -> 0.060690943 | K16: =IFERROR(K15/G15-1,"") -> 0.12663755 | L16: =IFERROR(L15/H15-1,"") -> 0.097266881 | M16: =IFERROR(M15/I15-1,"") -> 0.12016129 | ... U16: =IFERROR(U15/Q15-1,"") -> 0.090511813 | X16: =IFERROR(X15/W15-1,"") -> 0.11949178 | Y16: =IFERROR(Y15/X15-1,"") -> 0.10259413 | Z16: =IFERROR(Z15/Y15-1,"") -> 0.16560275 | AA16: =IFERROR(AA15/Z15-1,"") -> 0.10936695
A17: Take rate (revenue / GBV) | B17: =IFERROR(B15/B9/1000,"") -> 0.089117647 | C17: =IFERROR(C15/C9/1000,"") -> 0.13005236 | D17: =IFERROR(D15/D9/1000,"") -> 0.18562842 | E17: =IFERROR(E15/E9/1000,"") -> 0.14309677 | F17: =IFERROR(F15/F9/1000,"") -> 0.093537118 | G17: =IFERROR(G15/G9/1000,"") -> 0.12962264 | H17: =IFERROR(H15/H9/1000,"") -> 0.18567164 | I17: =IFERROR(I15/I9/1000,"") -> 0.14090909 | ... U17: =IFERROR(U15/U9/1000,"") -> 0.1395561 | W17: =IFERROR(W15/W9/1000,"") -> 0.13529332 | X17: =IFERROR(X15/X9/1000,"") -> 0.13572127 | Y17: =IFERROR(Y15/Y9/1000,"") -> 0.13407448 | Z17: =IFERROR(Z15/Z9/1000,"") -> 0.13535173 | AA17: =IFERROR(AA15/AA9/1000,"") -> 0.13707685
A19: Cost of revenue (cash) | B19: 428 | C19: 432 | D19: 459 | E19: 384 | F19: 480 | G19: 506 | H19: 465 | I19: 427 | J19: 506 | K19: 544 | L19: 549 | M19: 487 | N19: 581 | O19: 633 | P19: =INDEX('Scenario Data'!$D$5:$I$345,MATCH($G$3&"|cor_cash",'Scenario Data'!$A$5:$A$345,0),MATCH(P$4,'Scenario Data'!$D$4:$I$4,0)) -> 640.78412 | Q19: =INDEX('Scenario Data'!$D$5:$I$345,MATCH($G$3&"|cor_cash",'Scenario Data'!$A$5:$A$345,0),MATCH(Q$4,'Scenario Data'!$D$4:$I$4,0)) -> 578.03946 | R19: =INDEX('Scenario Data'!$D$5:$I$345,MATCH($G$3&"|cor_cash",'Scenario Data'!$A$5:$A$345,0),MATCH(R$4,'Scenario Data'!$D$4:$I$4,0)) -> 706.00359 | S19: =INDEX('Scenario Data'!$D$5:$I$345,MATCH($G$3&"|cor_cash",'Scenario Data'!$A$5:$A$345,0),MATCH(S$4,'Scenario Data'!$D$4:$I$4,0)) -> 727.29954 | T19: =INDEX('Scenario Data'!$D$5:$I$345,MATCH($G$3&"|cor_cash",'Scenario Data'!$A$5:$A$345,0),MATCH(T$4,'Scenario Data'!$D$4:$I$4,0)) -> 699.45368 | U19: =INDEX('Scenario Data'!$D$5:$I$345,MATCH($G$3&"|cor_cash",'Scenario Data'!$A$5:$A$345,0),MATCH(U$4,'Scenario Data'!$D$4:$I$4,0)) -> 626.85228 | W19: 1703 | X19: 1878 | Y19: 2086 | Z19: =SUM(N19:O19,P19:Q19) -> 2432.8236 | AA19: =SUM(R19:U19) -> 2759.6091
A20: Operations & support (cash) | B20: 267 | C20: 298 | D20: 299 | E20: 254 | F20: 266 | G20: 314 | H20: 347 | I20: 265 | J20: 282 | K20: 309 | L20: 343 | M20: 303 | N20: 301 | O20: 323 | P20: =INDEX('Scenario Data'!$D$5:$I$345,MATCH($G$3&"|ops_cash",'Scenario Data'!$A$5:$A$345,0),MATCH(P$4,'Scenario Data'!$D$4:$I$4,0)) -> 361.44309 | Q20: =INDEX('Scenario Data'!$D$5:$I$345,MATCH($G$3&"|ops_cash",'Scenario Data'!$A$5:$A$345,0),MATCH(Q$4,'Scenario Data'!$D$4:$I$4,0)) -> 318.28709 | R20: =INDEX('Scenario Data'!$D$5:$I$345,MATCH($G$3&"|ops_cash",'Scenario Data'!$A$5:$A$345,0),MATCH(R$4,'Scenario Data'!$D$4:$I$4,0)) -> 319.08609 | S20: =INDEX('Scenario Data'!$D$5:$I$345,MATCH($G$3&"|ops_cash",'Scenario Data'!$A$5:$A$345,0),MATCH(S$4,'Scenario Data'!$D$4:$I$4,0)) -> 340.96824 | T20: =INDEX('Scenario Data'!$D$5:$I$345,MATCH($G$3&"|ops_cash",'Scenario Data'!$A$5:$A$345,0),MATCH(T$4,'Scenario Data'!$D$4:$I$4,0)) -> 381.7591 | U20: =INDEX('Scenario Data'!$D$5:$I$345,MATCH($G$3&"|ops_cash",'Scenario Data'!$A$5:$A$345,0),MATCH(U$4,'Scenario Data'!$D$4:$I$4,0)) -> 336.06248 | W20: 1118 | X20: 1192 | Y20: 1237 | Z20: =SUM(N20:O20,P20:Q20) -> 1303.7302 | AA20: =SUM(R20:U20) -> 1377.8759
A21: Product development (cash) | B21: 271 | C21: 260 | D21: 244 | E21: 253 | F21: 290 | G21: 280 | H21: 294 | I21: 306 | J21: 338 | K21: 331 | L21: 333 | M21: 335 | N21: 375 | O21: 374 | P21: =INDEX('Scenario Data'!$D$5:$I$345,MATCH($G$3&"|pd_cash",'Scenario Data'!$A$5:$A$345,0),MATCH(P$4,'Scenario Data'!$D$4:$I$4,0)) -> 359.09488 | Q21: =INDEX('Scenario Data'!$D$5:$I$345,MATCH($G$3&"|pd_cash",'Scenario Data'!$A$5:$A$345,0),MATCH(Q$4,'Scenario Data'!$D$4:$I$4,0)) -> 369.02512 | R21: =INDEX('Scenario Data'!$D$5:$I$345,MATCH($G$3&"|pd_cash",'Scenario Data'!$A$5:$A$345,0),MATCH(R$4,'Scenario Data'!$D$4:$I$4,0)) -> 414.12379 | S21: =INDEX('Scenario Data'!$D$5:$I$345,MATCH($G$3&"|pd_cash",'Scenario Data'!$A$5:$A$345,0),MATCH(S$4,'Scenario Data'!$D$4:$I$4,0)) -> 400.79642 | T21: =INDEX('Scenario Data'!$D$5:$I$345,MATCH($G$3&"|pd_cash",'Scenario Data'!$A$5:$A$345,0),MATCH(T$4,'Scenario Data'!$D$4:$I$4,0)) -> 399.65871 | U21: =INDEX('Scenario Data'!$D$5:$I$345,MATCH($G$3&"|pd_cash",'Scenario Data'!$A$5:$A$345,0),MATCH(U$4,'Scenario Data'!$D$4:$I$4,0)) -> 410.71068 | W21: 1028 | X21: 1170 | Y21: 1337 | Z21: =SUM(N21:O21,P21:Q21) -> 1477.12 | AA21: =SUM(R21:U21) -> 1625.2896
A22: Sales & marketing (cash) | B22: 422 | C22: 450 | D22: 370 | E22: 391 | F22: 479 | G22: 527 | H22: 471 | I22: 501 | J22: 519 | K22: 639 | L22: 585 | M22: 633 | N22: 696 | O22: 808 | P22: =INDEX('Scenario Data'!$D$5:$I$345,MATCH($G$3&"|sm_cash",'Scenario Data'!$A$5:$A$345,0),MATCH(P$4,'Scenario Data'!$D$4:$I$4,0)) -> 778.31581 | Q22: =INDEX('Scenario Data'!$D$5:$I$345,MATCH($G$3&"|sm_cash",'Scenario Data'!$A$5:$A$345,0),MATCH(Q$4,'Scenario Data'!$D$4:$I$4,0)) -> 758.10753 | R22: =INDEX('Scenario Data'!$D$5:$I$345,MATCH($G$3&"|sm_cash",'Scenario Data'!$A$5:$A$345,0),MATCH(R$4,'Scenario Data'!$D$4:$I$4,0)) -> 829.27179 | S22: =INDEX('Scenario Data'!$D$5:$I$345,MATCH($G$3&"|sm_cash",'Scenario Data'!$A$5:$A$345,0),MATCH(S$4,'Scenario Data'!$D$4:$I$4,0)) -> 935.13627 | T22: =INDEX('Scenario Data'!$D$5:$I$345,MATCH($G$3&"|sm_cash",'Scenario Data'!$A$5:$A$345,0),MATCH(T$4,'Scenario Data'!$D$4:$I$4,0)) -> 819.9308 | U22: =INDEX('Scenario Data'!$D$5:$I$345,MATCH($G$3&"|sm_cash",'Scenario Data'!$A$5:$A$345,0),MATCH(U$4,'Scenario Data'!$D$4:$I$4,0)) -> 875.28478 | W22: 1633 | X22: 1978 | Y22: 2376 | Z22: =SUM(N22:O22,P22:Q22) -> 3040.4233 | AA22: =SUM(R22:U22) -> 3459.6236
A23: General & administrative (cash, ex lodging-tax reserves) | B23: 191 | C23: 219 | D23: 202 | E23: 211 | F23: 223 | G23: 242 | H23: 210 | I23: 226 | J23: 235 | K23: 244 | L23: 257 | M23: 259 | N23: 226 | O23: 227 | P23: =INDEX('Scenario Data'!$D$5:$I$345,MATCH($G$3&"|ga_cash",'Scenario Data'!$A$5:$A$345,0),MATCH(P$4,'Scenario Data'!$D$4:$I$4,0)) -> 265.38907 | Q23: =INDEX('Scenario Data'!$D$5:$I$345,MATCH($G$3&"|ga_cash",'Scenario Data'!$A$5:$A$345,0),MATCH(Q$4,'Scenario Data'!$D$4:$I$4,0)) -> 276.41093 | R23: =INDEX('Scenario Data'!$D$5:$I$345,MATCH($G$3&"|ga_cash",'Scenario Data'!$A$5:$A$345,0),MATCH(R$4,'Scenario Data'!$D$4:$I$4,0)) -> 249.22724 | S23: =INDEX('Scenario Data'!$D$5:$I$345,MATCH($G$3&"|ga_cash",'Scenario Data'!$A$5:$A$345,0),MATCH(S$4,'Scenario Data'!$D$4:$I$4,0)) -> 271.5804 | T23: =INDEX('Scenario Data'!$D$5:$I$345,MATCH($G$3&"|ga_cash",'Scenario Data'!$A$5:$A$345,0),MATCH(T$4,'Scenario Data'!$D$4:$I$4,0)) -> 256.53902 | U23: =INDEX('Scenario Data'!$D$5:$I$345,MATCH($G$3&"|ga_cash",'Scenario Data'!$A$5:$A$345,0),MATCH(U$4,'Scenario Data'!$D$4:$I$4,0)) -> 267.19333 | W23: 823 | X23: 901 | Y23: 995 | Z23: =SUM(N23:O23,P23:Q23) -> 994.8 | AA23: =SUM(R23:U23) -> 1044.54
A24: Total cash costs | B24: =SUM(B19:B23) -> 1579 | C24: =SUM(C19:C23) -> 1659 | D24: =SUM(D19:D23) -> 1574 | E24: =SUM(E19:E23) -> 1493 | F24: =SUM(F19:F23) -> 1738 | G24: =SUM(G19:G23) -> 1869 | H24: =SUM(H19:H23) -> 1787 | I24: =SUM(I19:I23) -> 1725 | ... U24: =SUM(U19:U23) -> 2516.1036 | W24: =SUM(W19:W23) -> 6305 | X24: =SUM(X19:X23) -> 7119 | Y24: =SUM(Y19:Y23) -> 8031 | Z24: =SUM(Z19:Z23) -> 9248.8971 | AA24: =SUM(AA19:AA23) -> 10266.938
A25: % of revenue | B25: =IFERROR(B24/B15,"") -> 0.86853685 | C25: =IFERROR(C24/C15,"") -> 0.6678744 | D25: =IFERROR(D24/D15,"") -> 0.46335001 | E25: =IFERROR(E24/E15,"") -> 0.67312894 | F25: =IFERROR(F24/F15,"") -> 0.81139122 | G25: =IFERROR(G24/G15,"") -> 0.680131 | H25: =IFERROR(H24/H15,"") -> 0.47883173 | I25: =IFERROR(I24/I15,"") -> 0.69556452 | ... U25: =IFERROR(U24/U15,"") -> 0.72598812 | W25: =IFERROR(W24/W15,"") -> 0.63577695 | X25: =IFERROR(X24/X15,"") -> 0.64123581 | Y25: =IFERROR(Y24/Y15,"") -> 0.65607385 | Z25: =IFERROR(Z24/Z15,"") -> 0.64822009 | AA25: =IFERROR(AA24/AA15,"") -> 0.64863184
A26: Depreciation & amortisation (inside the cash lines) | B26: 11 | C26: 9 | D26: 8 | E26: 16 | F26: 14 | G26: 14 | H26: 15 | I26: 22 | J26: 25 | K26: 21 | L26: 22 | M26: 23 | N26: 22 | O26: 17 | P26: =INDEX('Scenario Data'!$D$5:$I$345,MATCH($G$3&"|da",'Scenario Data'!$A$5:$A$345,0),MATCH(P$4,'Scenario Data'!$D$4:$I$4,0)) -> 20.633971 | Q26: =INDEX('Scenario Data'!$D$5:$I$345,MATCH($G$3&"|da",'Scenario Data'!$A$5:$A$345,0),MATCH(Q$4,'Scenario Data'!$D$4:$I$4,0)) -> 20.633971 | R26: =INDEX('Scenario Data'!$D$5:$I$345,MATCH($G$3&"|da",'Scenario Data'!$A$5:$A$345,0),MATCH(R$4,'Scenario Data'!$D$4:$I$4,0)) -> 20.633971 | S26: =INDEX('Scenario Data'!$D$5:$I$345,MATCH($G$3&"|da",'Scenario Data'!$A$5:$A$345,0),MATCH(S$4,'Scenario Data'!$D$4:$I$4,0)) -> 20.633971 | T26: =INDEX('Scenario Data'!$D$5:$I$345,MATCH($G$3&"|da",'Scenario Data'!$A$5:$A$345,0),MATCH(T$4,'Scenario Data'!$D$4:$I$4,0)) -> 20.633971 | U26: =INDEX('Scenario Data'!$D$5:$I$345,MATCH($G$3&"|da",'Scenario Data'!$A$5:$A$345,0),MATCH(U$4,'Scenario Data'!$D$4:$I$4,0)) -> 20.633971 | W26: 44 | X26: 65 | Y26: 91 | Z26: =SUM(N26:O26,P26:Q26) -> 80.267941 | AA26: =SUM(R26:U26) -> 82.535882
A27: Other add-backs / reconciling items (history only) | B27: 12 | C27: -15 | D27: 3 | E27: -3 | F27: 6 | G27: 1 | H27: -2 | I27: -12 | J27: 0 | K27: -7 | L27: 1 | M27: 2 | N27: -2 | O27: 1 | W27: -3 | X27: -7 | Y27: -4 | Z27: =SUM(N27:O27,P27:Q27) -> -1 | AA27: =SUM(R27:U27) -> 0 | AC27: History: reported adjusted EBITDA less (revenue - cash costs + D&A); lodging-tax reserves, restructuring and rounding. Forecast: nil by construction.
A28: Adjusted EBITDA | B28: =B15-B24+B26+B27 -> 262 | C28: =C15-C24+C26+C27 -> 819 | D28: =D15-D24+D26+D27 -> 1834 | E28: =E15-E24+E26+E27 -> 738 | F28: =F15-F24+F26+F27 -> 424 | G28: =G15-G24+G26+G27 -> 894 | H28: =H15-H24+H26+H27 -> 1958 | I28: =I15-I24+I26+I27 -> 765 | ... O28: =O15-O24+O26+O27 -> 1261 | P28: =P15-P24+P26 -> 2419.6425 | Q28: =Q15-Q24+Q26 -> 898.87164 | R28: =R15-R24+R26 -> 556.05077 | S28: =S15-S24+S26 -> 1373.8338 | T28: =T15-T24+T26 -> 2744.0252 | U28: =U15-U24+U26 -> 970.29451 | W28: =W15-W24+W26+IF(ISNUMBER(W27),W27,0) -> 3653 | X28: =X15-X24+X26+IF(ISNUMBER(X27),X27,0) -> 4041 | Y28: =Y15-Y24+Y26+IF(ISNUMBER(Y27),Y27,0) -> 4297 | Z28: =Z15-Z24+Z26+IF(ISNUMBER(Z27),Z27,0) -> 5098.5141 | AA28: =AA15-AA24+AA26+IF(ISNUMBER(AA27),AA27,0) -> 5644.2042
A29: Adjusted EBITDA margin | B29: =IFERROR(B28/B15,"") -> 0.14411441 | C29: =IFERROR(C28/C15,"") -> 0.32971014 | D29: =IFERROR(D28/D15,"") -> 0.53988814 | E29: =IFERROR(E28/E15,"") -> 0.33273219 | F29: =IFERROR(F28/F15,"") -> 0.19794585 | G29: =IFERROR(G28/G15,"") -> 0.32532751 | H29: =IFERROR(H28/H15,"") -> 0.52465166 | I29: =IFERROR(I28/I15,"") -> 0.30846774 | ... U29: =IFERROR(U28/U15,"") -> 0.27996554 | W29: =IFERROR(W28/W15,"") -> 0.36835737 | X29: =IFERROR(X28/X15,"") -> 0.36398847 | Y29: =IFERROR(Y28/Y15,"") -> 0.35103341 | Z29: =IFERROR(Z28/Z15,"") -> 0.3573355 | AA29: =IFERROR(AA28/AA15,"") -> 0.35658251
A30: y/y | F30: =IFERROR(F28/B28-1,"") -> 0.61832061 | G30: =IFERROR(G28/C28-1,"") -> 0.091575092 | H30: =IFERROR(H28/D28-1,"") -> 0.067611778 | I30: =IFERROR(I28/E28-1,"") -> 0.036585366 | J30: =IFERROR(J28/F28-1,"") -> -0.016509434 | K30: =IFERROR(K28/G28-1,"") -> 0.16666667 | L30: =IFERROR(L28/H28-1,"") -> 0.047497446 | M30: =IFERROR(M28/I28-1,"") -> 0.02745098 | ... U30: =IFERROR(U28/Q28-1,"") -> 0.079458364 | X30: =IFERROR(X28/W28-1,"") -> 0.10621407 | Y30: =IFERROR(Y28/X28-1,"") -> 0.063350656 | Z30: =IFERROR(Z28/Y28-1,"") -> 0.18652877 | AA30: =IFERROR(AA28/Z28-1,"") -> 0.10702924
A32: Stock-based compensation | B32: 240 | C32: 304 | D32: 286 | E32: 290 | F32: 295 | G32: 382 | H32: 362 | I32: 368 | J32: 358 | K32: 424 | L32: 399 | M32: 411 | N32: 410 | O32: 487 | P32: =INDEX('Scenario Data'!$D$5:$I$345,MATCH($G$3&"|sbc",'Scenario Data'!$A$5:$A$345,0),MATCH(P$4,'Scenario Data'!$D$4:$I$4,0)) -> 451.57919 | Q32: =INDEX('Scenario Data'!$D$5:$I$345,MATCH($G$3&"|sbc",'Scenario Data'!$A$5:$A$345,0),MATCH(Q$4,'Scenario Data'!$D$4:$I$4,0)) -> 465.16051 | R32: =INDEX('Scenario Data'!$D$5:$I$345,MATCH($G$3&"|sbc",'Scenario Data'!$A$5:$A$345,0),MATCH(R$4,'Scenario Data'!$D$4:$I$4,0)) -> 464.02874 | S32: =INDEX('Scenario Data'!$D$5:$I$345,MATCH($G$3&"|sbc",'Scenario Data'!$A$5:$A$345,0),MATCH(S$4,'Scenario Data'!$D$4:$I$4,0)) -> 551.1756 | T32: =INDEX('Scenario Data'!$D$5:$I$345,MATCH($G$3&"|sbc",'Scenario Data'!$A$5:$A$345,0),MATCH(T$4,'Scenario Data'!$D$4:$I$4,0)) -> 511.08712 | U32: =INDEX('Scenario Data'!$D$5:$I$345,MATCH($G$3&"|sbc",'Scenario Data'!$A$5:$A$345,0),MATCH(U$4,'Scenario Data'!$D$4:$I$4,0)) -> 526.45816 | W32: 1120 | X32: 1407 | Y32: 1592 | Z32: =SUM(N32:O32,P32:Q32) -> 1813.7397 | AA32: =SUM(R32:U32) -> 2052.7496
A33: % of revenue | B33: =IFERROR(B32/B15,"") -> 0.1320132 | C33: =IFERROR(C32/C15,"") -> 0.12238325 | D33: =IFERROR(D32/D15,"") -> 0.084191934 | E33: =IFERROR(E32/E15,"") -> 0.13074842 | F33: =IFERROR(F32/F15,"") -> 0.13772176 | G33: =IFERROR(G32/G15,"") -> 0.13901019 | H33: =IFERROR(H32/H15,"") -> 0.096998928 | I33: =IFERROR(I32/I15,"") -> 0.1483871 | ... U33: =IFERROR(U32/U15,"") -> 0.15190248 | W33: =IFERROR(W32/W15,"") -> 0.11293738 | X33: =IFERROR(X32/X15,"") -> 0.12673392 | Y33: =IFERROR(Y32/Y15,"") -> 0.13005473 | Z33: =IFERROR(Z32/Z15,"") -> 0.12711813 | AA33: =IFERROR(AA32/AA15,"") -> 0.12968606
A34: Other GAAP items vs the adjusted stack (history only) | B34: -16 | C34: 17 | D34: -44 | E34: -928 | F34: -14 | G34: -1 | H34: -56 | I34: 55 | J34: 4 | K34: 14 | L34: -5 | M34: -83 | N34: -1 | O34: 1 | W34: -971 | X34: -16 | Y34: -70 | Z34: =SUM(N34:O34,P34:Q34) -> 0 | AA34: =SUM(R34:U34) -> 0 | AC34: History: reported operating income less (adjusted EBITDA - D&A - SBC): restructuring, lodging-tax reserves, acquisition items. Forecast: nil.
A35: Operating income (GAAP) | B35: =B28-B26-B32+B34 -> -5 | C35: =C28-C26-C32+C34 -> 523 | D35: =D28-D26-D32+D34 -> 1496 | E35: =E28-E26-E32+E34 -> -496 | F35: =F28-F26-F32+F34 -> 101 | G35: =G28-G26-G32+G34 -> 497 | H35: =H28-H26-H32+H34 -> 1525 | I35: =I28-I26-I32+I34 -> 430 | ... O35: =O28-O26-O32+O34 -> 758 | P35: =P28-P26-P32 -> 1947.4293 | Q35: =Q28-Q26-Q32 -> 413.07716 | R35: =R28-R26-R32 -> 71.388062 | S35: =S28-S26-S32 -> 802.02423 | T35: =T28-T26-T32 -> 2212.3041 | U35: =U28-U26-U32 -> 423.20238 | W35: =W28-W26-W32+IF(ISNUMBER(W34),W34,0) -> 1518 | X35: =X28-X26-X32+IF(ISNUMBER(X34),X34,0) -> 2553 | Y35: =Y28-Y26-Y32+IF(ISNUMBER(Y34),Y34,0) -> 2544 | Z35: =Z28-Z26-Z32+IF(ISNUMBER(Z34),Z34,0) -> 3204.5065 | AA35: =AA28-AA26-AA32+IF(ISNUMBER(AA34),AA34,0) -> 3508.9187
A36: Operating margin | B36: =IFERROR(B35/B15,"") -> -0.002750275 | C36: =IFERROR(C35/C15,"") -> 0.2105475 | D36: =IFERROR(D35/D15,"") -> 0.44038858 | E36: =IFERROR(E35/E15,"") -> -0.22362489 | F36: =IFERROR(F35/F15,"") -> 0.047152194 | G36: =IFERROR(G35/G15,"") -> 0.18085881 | H36: =IFERROR(H35/H15,"") -> 0.40862808 | I36: =IFERROR(I35/I15,"") -> 0.1733871 | ... U36: =IFERROR(U35/U15,"") -> 0.1221094 | W36: =IFERROR(W35/W15,"") -> 0.15307049 | X36: =IFERROR(X35/X15,"") -> 0.22995857 | Y36: =IFERROR(Y35/Y15,"") -> 0.20782616 | Z36: =IFERROR(Z35/Z15,"") -> 0.2245917 | AA36: =IFERROR(AA35/AA15,"") -> 0.2216821
A37: Interest income | B37: 146 | C37: 191 | D37: 192 | E37: 192 | F37: 202 | G37: 226 | H37: 207 | I37: 183 | J37: 173 | K37: 190 | L37: 180 | M37: 162 | N37: 155 | O37: 183 | P37: =INDEX('Scenario Data'!$D$5:$I$345,MATCH($G$3&"|interest_income",'Scenario Data'!$A$5:$A$345,0),MATCH(P$4,'Scenario Data'!$D$4:$I$4,0)) -> 183.54893 | Q37: =INDEX('Scenario Data'!$D$5:$I$345,MATCH($G$3&"|interest_income",'Scenario Data'!$A$5:$A$345,0),MATCH(Q$4,'Scenario Data'!$D$4:$I$4,0)) -> 165.49547 | R37: =INDEX('Scenario Data'!$D$5:$I$345,MATCH($G$3&"|interest_income",'Scenario Data'!$A$5:$A$345,0),MATCH(R$4,'Scenario Data'!$D$4:$I$4,0)) -> 180.26226 | S37: =INDEX('Scenario Data'!$D$5:$I$345,MATCH($G$3&"|interest_income",'Scenario Data'!$A$5:$A$345,0),MATCH(S$4,'Scenario Data'!$D$4:$I$4,0)) -> 202.84769 | T37: =INDEX('Scenario Data'!$D$5:$I$345,MATCH($G$3&"|interest_income",'Scenario Data'!$A$5:$A$345,0),MATCH(T$4,'Scenario Data'!$D$4:$I$4,0)) -> 191.14509 | U37: =INDEX('Scenario Data'!$D$5:$I$345,MATCH($G$3&"|interest_income",'Scenario Data'!$A$5:$A$345,0),MATCH(U$4,'Scenario Data'!$D$4:$I$4,0)) -> 171.15508 | W37: 721 | X37: 818 | Y37: 705 | Z37: =SUM(N37:O37,P37:Q37) -> 687.0444 | AA37: =SUM(R37:U37) -> 745.41011
A38: Interest expense | B38: 4 | C38: 2 | D38: 6 | E38: 71 | G38: 9 | H38: 2 | I38: 10 | J38: 5 | K38: 6 | L38: 6 | M38: 26 | N38: 21 | O38: 37 | P38: =INDEX('Scenario Data'!$D$5:$I$345,MATCH($G$3&"|interest_expense",'Scenario Data'!$A$5:$A$345,0),MATCH(P$4,'Scenario Data'!$D$4:$I$4,0)) -> 37 | Q38: =INDEX('Scenario Data'!$D$5:$I$345,MATCH($G$3&"|interest_expense",'Scenario Data'!$A$5:$A$345,0),MATCH(Q$4,'Scenario Data'!$D$4:$I$4,0)) -> 37 | R38: =INDEX('Scenario Data'!$D$5:$I$345,MATCH($G$3&"|interest_expense",'Scenario Data'!$A$5:$A$345,0),MATCH(R$4,'Scenario Data'!$D$4:$I$4,0)) -> 37 | S38: =INDEX('Scenario Data'!$D$5:$I$345,MATCH($G$3&"|interest_expense",'Scenario Data'!$A$5:$A$345,0),MATCH(S$4,'Scenario Data'!$D$4:$I$4,0)) -> 37 | T38: =INDEX('Scenario Data'!$D$5:$I$345,MATCH($G$3&"|interest_expense",'Scenario Data'!$A$5:$A$345,0),MATCH(T$4,'Scenario Data'!$D$4:$I$4,0)) -> 37 | U38: =INDEX('Scenario Data'!$D$5:$I$345,MATCH($G$3&"|interest_expense",'Scenario Data'!$A$5:$A$345,0),MATCH(U$4,'Scenario Data'!$D$4:$I$4,0)) -> 37 | W38: 83 | Y38: 43 | Z38: =SUM(N38:O38,P38:Q38) -> 132 | AA38: =SUM(R38:U38) -> 148
A39: Other income / (expense), net | B39: -7 | C39: -36 | D39: -3 | E39: -8 | F39: -10 | G39: -33 | H39: 5 | I39: 19 | J39: -33 | K39: -17 | L39: -7 | M39: -12 | N39: 61 | O39: -7 | P39: =INDEX('Scenario Data'!$D$5:$I$345,MATCH($G$3&"|other_income",'Scenario Data'!$A$5:$A$345,0),MATCH(P$4,'Scenario Data'!$D$4:$I$4,0)) -> 3.7 | Q39: =INDEX('Scenario Data'!$D$5:$I$345,MATCH($G$3&"|other_income",'Scenario Data'!$A$5:$A$345,0),MATCH(Q$4,'Scenario Data'!$D$4:$I$4,0)) -> 3.7 | R39: =INDEX('Scenario Data'!$D$5:$I$345,MATCH($G$3&"|other_income",'Scenario Data'!$A$5:$A$345,0),MATCH(R$4,'Scenario Data'!$D$4:$I$4,0)) -> 3.7 | S39: =INDEX('Scenario Data'!$D$5:$I$345,MATCH($G$3&"|other_income",'Scenario Data'!$A$5:$A$345,0),MATCH(S$4,'Scenario Data'!$D$4:$I$4,0)) -> 3.7 | T39: =INDEX('Scenario Data'!$D$5:$I$345,MATCH($G$3&"|other_income",'Scenario Data'!$A$5:$A$345,0),MATCH(T$4,'Scenario Data'!$D$4:$I$4,0)) -> 3.7 | U39: =INDEX('Scenario Data'!$D$5:$I$345,MATCH($G$3&"|other_income",'Scenario Data'!$A$5:$A$345,0),MATCH(U$4,'Scenario Data'!$D$4:$I$4,0)) -> 3.7 | W39: -54 | X39: -40 | Y39: -69 | Z39: =SUM(N39:O39,P39:Q39) -> 61.4 | AA39: =SUM(R39:U39) -> 14.8
A40: Pre-tax income | B40: =B35+B37-B38+B39 -> 130 | C40: =C35+C37-C38+C39 -> 676 | D40: =D35+D37-D38+D39 -> 1679 | E40: =E35+E37-E38+E39 -> -383 | F40: =F35+F37-F38+F39 -> 293 | G40: =G35+G37-G38+G39 -> 681 | H40: =H35+H37-H38+H39 -> 1735 | I40: =I35+I37-I38+I39 -> 622 | ... U40: =U35+U37-U38+U39 -> 561.05746 | W40: =W35+W37-W38+W39 -> 2102 | X40: =X35+X37-X38+X39 -> 3331 | Y40: =Y35+Y37-Y38+Y39 -> 3137 | Z40: =Z35+Z37-Z38+Z39 -> 3820.9509 | AA40: =AA35+AA37-AA38+AA39 -> 4121.1288
A41: Income tax provision / (benefit) | B41: 13.4 | C41: 26 | D41: -2695 | E41: -34 | F41: 29 | G41: 126 | H41: 367 | I41: 161 | J41: 19 | K41: 137 | L41: 418 | M41: 52 | N41: 121 | O41: 81 | P41: =INDEX('Scenario Data'!$D$5:$I$345,MATCH($G$3&"|tax",'Scenario Data'!$A$5:$A$345,0),MATCH(P$4,'Scenario Data'!$D$4:$I$4,0)) -> 377.58209 | Q41: =INDEX('Scenario Data'!$D$5:$I$345,MATCH($G$3&"|tax",'Scenario Data'!$A$5:$A$345,0),MATCH(Q$4,'Scenario Data'!$D$4:$I$4,0)) -> 98.149072 | R41: =INDEX('Scenario Data'!$D$5:$I$345,MATCH($G$3&"|tax",'Scenario Data'!$A$5:$A$345,0),MATCH(R$4,'Scenario Data'!$D$4:$I$4,0)) -> 38.211306 | S41: =INDEX('Scenario Data'!$D$5:$I$345,MATCH($G$3&"|tax",'Scenario Data'!$A$5:$A$345,0),MATCH(S$4,'Scenario Data'!$D$4:$I$4,0)) -> 170.02509 | T41: =INDEX('Scenario Data'!$D$5:$I$345,MATCH($G$3&"|tax",'Scenario Data'!$A$5:$A$345,0),MATCH(T$4,'Scenario Data'!$D$4:$I$4,0)) -> 414.7761 | U41: =INDEX('Scenario Data'!$D$5:$I$345,MATCH($G$3&"|tax",'Scenario Data'!$A$5:$A$345,0),MATCH(U$4,'Scenario Data'!$D$4:$I$4,0)) -> 98.185055 | W41: -2690 | X41: 683 | Y41: 626 | Z41: =SUM(N41:O41,P41:Q41) -> 677.73116 | AA41: =SUM(R41:U41) -> 721.19755 | AC41: 4Q23 carries the $2.7bn valuation-allowance release; FY23 GAAP net income is not comparable.
A42: Effective tax rate | B42: =IFERROR(B41/B40,"") -> 0.10307692 | C42: =IFERROR(C41/C40,"") -> 0.038461538 | D42: =IFERROR(D41/D40,"") -> -1.6051221 | E42: =IFERROR(E41/E40,"") -> 0.088772846 | F42: =IFERROR(F41/F40,"") -> 0.098976109 | G42: =IFERROR(G41/G40,"") -> 0.18502203 | H42: =IFERROR(H41/H40,"") -> 0.21152738 | I42: =IFERROR(I41/I40,"") -> 0.25884244 | ... U42: =IFERROR(U41/U40,"") -> 0.175 | W42: =IFERROR(W41/W40,"") -> -1.2797336 | X42: =IFERROR(X41/X40,"") -> 0.20504353 | Y42: =IFERROR(Y41/Y40,"") -> 0.19955371 | Z42: =IFERROR(Z41/Z40,"") -> 0.17737238 | AA42: =IFERROR(AA41/AA40,"") -> 0.175
A43: Net income | B43: =B40-B41 -> 116.6 | C43: =C40-C41 -> 650 | D43: =D40-D41 -> 4374 | E43: =E40-E41 -> -349 | F43: =F40-F41 -> 264 | G43: =G40-G41 -> 555 | H43: =H40-H41 -> 1368 | I43: =I40-I41 -> 461 | ... U43: =U40-U41 -> 462.8724 | W43: =W40-W41 -> 4792 | X43: =X40-X41 -> 2648 | Y43: =Y40-Y41 -> 2511 | Z43: =Z40-Z41 -> 3143.2197 | AA43: =AA40-AA41 -> 3399.9313
A44: Net margin | B44: =IFERROR(B43/B15,"") -> 0.064136414 | C44: =IFERROR(C43/C15,"") -> 0.26167472 | D44: =IFERROR(D43/D15,"") -> 1.2876067 | E44: =IFERROR(E43/E15,"") -> -0.15734896 | F44: =IFERROR(F43/F15,"") -> 0.1232493 | G44: =IFERROR(G43/G15,"") -> 0.20196507 | H44: =IFERROR(H43/H15,"") -> 0.36655949 | I44: =IFERROR(I43/I15,"") -> 0.1858871 | ... U44: =IFERROR(U43/U15,"") -> 0.13355566 | W44: =IFERROR(W43/W15,"") -> 0.48321065 | X44: =IFERROR(X43/X15,"") -> 0.23851558 | Y44: =IFERROR(Y43/Y15,"") -> 0.2051303 | Z44: =IFERROR(Z43/Z15,"") -> 0.22029634 | AA44: =IFERROR(AA43/AA15,"") -> 0.21479663
A45: Diluted weighted-average shares (m) | B45: 670 | C45: 665 | D45: 660 | E45: 640 | F45: 654 | G45: 649 | H45: 642 | I45: 636 | J45: 632 | K45: 626 | L45: 621 | M45: 614 | N45: 608 | O45: 597 | P45: =INDEX('Scenario Data'!$D$5:$I$345,MATCH($G$3&"|diluted_shares_m",'Scenario Data'!$A$5:$A$345,0),MATCH(P$4,'Scenario Data'!$D$4:$I$4,0)) -> 591.67581 | Q45: =INDEX('Scenario Data'!$D$5:$I$345,MATCH($G$3&"|diluted_shares_m",'Scenario Data'!$A$5:$A$345,0),MATCH(Q$4,'Scenario Data'!$D$4:$I$4,0)) -> 586.35163 | R45: =INDEX('Scenario Data'!$D$5:$I$345,MATCH($G$3&"|diluted_shares_m",'Scenario Data'!$A$5:$A$345,0),MATCH(R$4,'Scenario Data'!$D$4:$I$4,0)) -> 581.02744 | S45: =INDEX('Scenario Data'!$D$5:$I$345,MATCH($G$3&"|diluted_shares_m",'Scenario Data'!$A$5:$A$345,0),MATCH(S$4,'Scenario Data'!$D$4:$I$4,0)) -> 575.70325 | T45: =INDEX('Scenario Data'!$D$5:$I$345,MATCH($G$3&"|diluted_shares_m",'Scenario Data'!$A$5:$A$345,0),MATCH(T$4,'Scenario Data'!$D$4:$I$4,0)) -> 570.37907 | U45: =INDEX('Scenario Data'!$D$5:$I$345,MATCH($G$3&"|diluted_shares_m",'Scenario Data'!$A$5:$A$345,0),MATCH(U$4,'Scenario Data'!$D$4:$I$4,0)) -> 565.05488 | W45: =AVERAGE(B45:E45) -> 658.75 | X45: =AVERAGE(F45:I45) -> 645.25 | Y45: =AVERAGE(J45:M45) -> 623.25 | Z45: =AVERAGE(N45:O45,P45:Q45) -> 595.75686 | AA45: =AVERAGE(R45:U45) -> 573.04116
A46: Diluted EPS ($) | B46: =IFERROR(B43/B45,"") -> 0.17402985 | C46: =IFERROR(C43/C45,"") -> 0.97744361 | D46: =IFERROR(D43/D45,"") -> 6.6272727 | E46: =IFERROR(E43/E45,"") -> -0.5453125 | F46: =IFERROR(F43/F45,"") -> 0.40366972 | G46: =IFERROR(G43/G45,"") -> 0.85516179 | H46: =IFERROR(H43/H45,"") -> 2.1308411 | I46: =IFERROR(I43/I45,"") -> 0.72484277 | ... U46: =IFERROR(U43/U45,"") -> 0.81916362 | W46: =IFERROR(W43/W45,"") -> 7.2743833 | X46: =IFERROR(X43/X45,"") -> 4.1038357 | Y46: =IFERROR(Y43/Y45,"") -> 4.0288809 | Z46: =IFERROR(Z43/Z45,"") -> 5.276011 | AA46: =IFERROR(AA43/AA45,"") -> 5.9331363 | AC46: History EPS is net income / diluted shares from the panel; it can differ from the reported figure by a cent. Forecast: 40_line_build M7 bridge.
A47: Diluted EPS as reported ($) | B47: 0.18 | C47: 0.98 | D47: 6.63 | E47: -0.55 | F47: 0.41 | G47: 0.86 | H47: 2.13 | I47: 0.73 | J47: 0.24 | K47: 1.03 | L47: 2.21 | M47: 0.56 | N47: 0.26 | O47: 1.37
A49: Memo: cash and capital return (history)
A50: Free cash flow | B50: 1581 | C50: 900 | D50: 1310 | E50: 46 | F50: 1909 | G50: 1043 | H50: 1074 | I50: 458 | J50: 1781 | K50: 962 | L50: 1349 | M50: 521 | N50: 1704 | O50: 1253 | W50: 3837 | X50: 4484 | Y50: 4613 | Z50: =SUM(N50:O50,P50:Q50) -> 2957 | AA50: =SUM(R50:U50) -> 0
A51: FCF margin | B51: =IFERROR(B50/B15,"") -> 0.86963696 | C51: =IFERROR(C50/C15,"") -> 0.36231884 | D51: =IFERROR(D50/D15,"") -> 0.38563438 | E51: =IFERROR(E50/E15,"") -> 0.020739405 | F51: =IFERROR(F50/F15,"") -> 0.89122316 | G51: =IFERROR(G50/G15,"") -> 0.37954876 | H51: =IFERROR(H50/H15,"") -> 0.28778135 | I51: =IFERROR(I50/I15,"") -> 0.18467742 | ... U51: =IFERROR(U50/U15,"") -> 0 | W51: =IFERROR(W50/W15,"") -> 0.38691136 | X51: =IFERROR(X50/X15,"") -> 0.40389119 | Y51: =IFERROR(Y50/Y15,"") -> 0.3768483 | Z51: =IFERROR(Z50/Z15,"") -> 0.2072449 | AA51: =IFERROR(AA50/AA15,"") -> 0
A52: Share repurchases | B52: 493 | C52: 507 | D52: 500 | E52: 752 | F52: 750 | G52: 749 | H52: 1093 | I52: 838 | J52: 807 | K52: 1010 | L52: 877 | M52: 1095 | N52: 1088 | O52: 1051 | W52: 2252 | X52: 3430 | Y52: 3789 | Z52: =SUM(N52:O52,P52:Q52) -> 2139 | AA52: =SUM(R52:U52) -> 0
A54: Comparison rows (do not move with the dropdown) | B54: Street = LSEG mean 11 Sep 2026 (quarters 1Q27-4Q27 n 17-19); Short = pitch case with costs at budget
A55: Revenue: Street (LSEG) | P55: 4744.3221 | Q55: 3161.8163 | R55: 3010.3238 | S55: 4036.9356 | T55: 5269.9673 | U55: 3528.9194 | Z55: 14189.557 | AA55: 15819.339
A56: Revenue: Base (team) | P56: 4804.0355 | Q56: 3178.1078 | R56: 3053.1293 | S56: 4028.9807 | T56: 5280.7325 | U56: 3465.7641 | Z56: 14268.143 | AA56: 15828.607
A57: Revenue: Short case (pitch) | P57: 4680.9 | Q57: 2965.8677 | R57: 2835.5346 | S57: 3762.9716 | T57: 4988.1742 | U57: 3326.8311 | Z57: 13932.768 | AA57: 14913.512
A58: Adj. EBITDA: Street (LSEG) | P58: 2361.5218 | Q58: 913.68388 | R58: 610.73207 | S58: 1451.7143 | T58: 2695.5528 | U58: 1068.3961 | Z58: 5053.7221 | AA58: 5766.0992
A59: Adj. EBITDA: Base (team) | P59: 2419.6425 | Q59: 898.87164 | R59: 556.05077 | S59: 1373.8338 | T59: 2744.0252 | U59: 970.29451 | Z59: 5098.5141 | AA59: 5644.2042
A60: Adj. EBITDA: Short case (pitch) | P60: 2289.8152 | Q60: 699.60784 | R60: 360.79561 | S60: 1128.5782 | T60: 2449.0347 | U60: 823.02692 | Z60: 4769.4231 | AA60: 4761.4354
A61: Adj. EBITDA margin: Street (LSEG) | P61: 0.49775747 | Q61: 0.28897437 | R61: 0.2028792 | S61: 0.35960799 | T61: 0.51149326 | U61: 0.30275446 | Z61: 0.35615785 | AA61: 0.36449684
A62: Adj. EBITDA margin: Base (team) | P62: 0.50366874 | Q62: 0.28283233 | R62: 0.18212487 | S62: 0.34098793 | T62: 0.51962965 | U62: 0.27996554 | Z62: 0.3573355 | AA62: 0.35658251
A63: Adj. EBITDA margin: Short case (pitch) | P63: 0.48918268 | Q63: 0.2358864 | R63: 0.12724077 | S63: 0.29991674 | T63: 0.49096815 | U63: 0.24739066 | Z63: 0.34231699 | AA63: 0.3192699
A64: Diluted EPS: Street (LSEG) | P64: 2.84539 | Q64: 0.86154 | Z64: 5.31259 | AA64: 6.22753
A65: Diluted EPS: Base (team) | P65: 2.9071599 | Q65: 0.7625519 | R65: 0.3100353 | S65: 1.3922917 | T65: 3.4281992 | U65: 0.81916362 | Z65: 5.276011 | AA65: 5.9331363
A66: Diluted EPS: Short case (pitch) | P66: 2.7144969 | Q66: 0.47084354 | R66: 0.014140544 | S66: 1.0168801 | T66: 2.9808855 | U66: 0.58915804 | AA66: 4.5839264
A68: Sources (paths relative to the repo root)
A69: Quarterly and annual GAAP lines, cash cost lines, SBC, D&A, shares | B69: data/processed/margin_build/02_financial_panel/02_panel_quarterly.csv, 02_panel_annual.csv
A70: Nights, GBV, ADR, reported adjusted EBITDA, FCF, buybacks | B70: data/processed/abnb_driver_history_quarterly.csv
A71: Forecast lines by scenario (base, bear/bull, evidence-only) | B71: data/processed/margin_build/40_line_build/40_lines_quarterly.csv; note docs/margin-build/notes/40_line_build.md
A72: Short case (pitch) quarterly lines | B72: data/processed/margin_build/40_line_build/40_short_case_quarterly.csv, 40_short_case_summary.csv
A73: Street consensus | B73: data/processed/margin_build/03_consensus_pit/03_current_consensus.csv (LSEG 11 Sep 2026); 23_final_model/23_vs_consensus.csv

Sheet Revenue Model
A1: Revenue model: nights x ADR (ex-FX + FX) = GBV; GBV x take rate = revenue
A2: Base path = bridge v3 for 3Q26-4Q26 (team nights baseline PR #32, ADR card v3, FX kernel) and the WS06 v2b path for 2027. Blue = source value, black = formula. Percent changes are y/y. FX shown in percentage points of y/y growth.
A5: Quarter | B5: 1Q23A | C5: 2Q23A | D5: 3Q23A | E5: 4Q23A | F5: 1Q24A | G5: 2Q24A | H5: 3Q24A | I5: 4Q24A | J5: 1Q25A | K5: 2Q25A | L5: 3Q25A | M5: 4Q25A | N5: 1Q26A | O5: 2Q26A | P5: 3Q26E | Q5: 4Q26E | R5: 1Q27E | S5: 2Q27E | T5: 3Q27E | U5: 4Q27E | W5: FY23 | X5: FY24 | Y5: FY25 | Z5: FY26E | AA5: FY27E
A6: 1. Base path: volume, price, FX and take rate | B6: team baseline; comparison scenarios are in section 2
B7: 121.1 | C7: 115.1 | D7: 113.2 | E7: 98.8 | F7: 132.6 | G7: 125.1 | H7: 122.8 | I7: 111 | J7: 143.1 | K7: 134.4 | L7: 133.6 | M7: 121.9 | N7: 156.2 | O7: 148.3 | P7: 146.813 | Q7: 131.7983 | R7: 169.0178 | S7: 157.1001 | T7: 155.958 | U7: 139.7655 | W7: =SUM(B7:E7) -> 448.2 | X7: =SUM(F7:I7) -> 491.5 | Y7: =SUM(J7:M7) -> 533 | Z7: =SUM(N7:O7,P7:Q7) -> 583.1113 | AA7: =SUM(R7:U7) -> 621.8414
A8: y/y | F8: =IFERROR(F7/B7-1,"") -> 0.094962841 | G8: =IFERROR(G7/C7-1,"") -> 0.086880973 | H8: =IFERROR(H7/D7-1,"") -> 0.084805654 | I8: =IFERROR(I7/E7-1,"") -> 0.12348178 | J8: =IFERROR(J7/F7-1,"") -> 0.07918552 | K8: =IFERROR(K7/G7-1,"") -> 0.074340528 | L8: =IFERROR(L7/H7-1,"") -> 0.087947883 | M8: =IFERROR(M7/I7-1,"") -> 0.098198198 | ... U8: =IFERROR(U7/Q7-1,"") -> 0.060449945 | X8: =IFERROR(X7/W7-1,"") -> 0.096608657 | Y8: =IFERROR(Y7/X7-1,"") -> 0.084435402 | Z8: =IFERROR(Z7/Y7-1,"") -> 0.094017448 | AA8: =IFERROR(AA7/Z7-1,"") -> 0.066419738
A9: NA nights y/y (regional build) | N9: 0.08 | O9: 0.08 | P9: 0.11 | Q9: 0.11 | AC9: 1H26 from letters/10-Q commentary; 2H26 = WS10 regional build re-based (h2_bridge_2026_projection.csv). No regional 2027 build.
A10: EMEA nights y/y (regional build) | N10: 0.05 | O10: 0.08 | P10: 0.065 | Q10: 0.095
A11: LatAm nights y/y (regional build) | N11: 0.18 | O11: 0.2 | P11: 0.19333333 | Q11: 0.19666667
A12: APAC nights y/y (regional build) | N12: 0.18 | O12: 0.18 | P12: 0.14666667 | Q12: 0.14
B14: 168.43 | C14: 166.01 | D14: 161.38 | E14: 156.73 | F14: 172.88 | G14: 169.53 | H14: 163.64 | I14: 158.13 | J14: 171.34 | K14: 174.48 | L14: 171.29 | M14: 167.51 | N14: 186.82 | O14: 183.73 | P14: 177.1652 | Q14: 174.5789 | R14: 192.7534 | S14: 189.0471 | T14: 181.9168 | U14: 177.854
A15: ADR y/y reported | F15: =IFERROR(F14/B14-1,"") -> 0.026420471 | G15: =IFERROR(G14/C14-1,"") -> 0.021203542 | H15: =IFERROR(H14/D14-1,"") -> 0.014004214 | I15: =IFERROR(I14/E14-1,"") -> 0.0089325592 | J15: =IFERROR(J14/F14-1,"") -> -0.008907913 | K15: =IFERROR(K14/G14-1,"") -> 0.029198372 | L15: =IFERROR(L14/H14-1,"") -> 0.046748961 | M15: =IFERROR(M14/I14-1,"") -> 0.059318282 | ... U15: =IFERROR(U14/Q14-1,"") -> 0.018759999 | X15: =IFERROR(X14/W14-1,"") | Y15: =IFERROR(Y14/X14-1,"") | Z15: =IFERROR(Z14/Y14-1,"") | AA15: =IFERROR(AA14/Z14-1,"")
A16: ADR y/y ex-FX | L16: =L15-L17 -> 0.019748961 | M16: =M15-M17 -> 0.030318282 | N16: =N15-N17 -> 0.040346679 | O16: =O15-O17 -> 0.040014672 | P16: 0.0386 | Q16: 0.0407 | R16: 0.03478 | S16: 0.03087 | T16: 0.02648 | U16: 0.02161 | AC16: Forecast: ADR card v3 (3Q26 +3.9%, 4Q26 +4.1%) then the WS06 ADR build (residual + K line + geo mix + party size + LOS + seats).
A17: FX contribution to ADR y/y (pts) | L17: 0.027 | M17: 0.029 | N17: 0.05 | O17: 0.013 | P17: -0.0043 | Q17: 0.0015 | R17: -0.00301 | S17: -0.00193 | T17: 0.00034 | U17: -0.00285 | AC17: History: disclosed in the letters (3Q25-2Q26). Forecast: ADR v3 midpoint of the EUR fit and regional baskets (3Q26 -0.4pt, 4Q26 +0.2pt), then the FX kernel.
B19: 20.4 | C19: 19.1 | D19: 18.3 | E19: 15.5 | F19: 22.9 | G19: 21.2 | H19: 20.1 | I19: 17.6 | J19: 24.5 | K19: 23.5 | L19: 22.9 | M19: 20.4 | N19: 29.2 | O19: 27.2 | P19: =P7*P14/1000 -> 26.010155 | Q19: =Q7*Q14/1000 -> 23.009202 | R19: =R7*R14/1000 -> 32.578756 | S19: =S7*S14/1000 -> 29.699318 | T19: =T7*T14/1000 -> 28.37138 | U19: =U7*U14/1000 -> 24.857853 | W19: =SUM(B19:E19) -> 73.3 | X19: =SUM(F19:I19) -> 81.8 | Y19: =SUM(J19:M19) -> 91.3 | Z19: =SUM(N19:O19,P19:Q19) -> 105.41936 | AA19: =SUM(R19:U19) -> 115.50731 | AC19: Forecast GBV = nights x ADR (the 06 path carries a <0.2% identity gap to its own GBV line).
A20: y/y | F20: =IFERROR(F19/B19-1,"") -> 0.12254902 | G20: =IFERROR(G19/C19-1,"") -> 0.10994764 | H20: =IFERROR(H19/D19-1,"") -> 0.098360656 | I20: =IFERROR(I19/E19-1,"") -> 0.13548387 | J20: =IFERROR(J19/F19-1,"") -> 0.069868996 | K20: =IFERROR(K19/G19-1,"") -> 0.10849057 | L20: =IFERROR(L19/H19-1,"") -> 0.13930348 | M20: =IFERROR(M19/I19-1,"") -> 0.15909091 | ... U20: =IFERROR(U19/Q19-1,"") -> 0.080343985 | X20: =IFERROR(X19/W19-1,"") -> 0.1159618 | Y20: =IFERROR(Y19/X19-1,"") -> 0.11613692 | Z20: =IFERROR(Z19/Y19-1,"") -> 0.15464794 | AA20: =IFERROR(AA19/Z19-1,"") -> 0.095693533
A22: Take rate, prior-year quarter (%) | P22: 0.178821 | Q22: 0.136176 | R22: 0.091712 | S22: 0.132647 | T22: 0.184572 | U22: 0.138255
A23: Take rate change y/y (pts) | P23: 0.005751 | Q23: 0.002079 | R23: 0.001943 | S23: 0.003247 | T23: 0.001429 | U23: 0.001301 | AC23: 3Q26 +0.58pt: FX timing (revenue recognised at check-in on bookings made when the dollar was weaker) and the fee changes; 2027 +0.1-0.3pt.
A24: Lagged GBV used by the bridge ($bn) | P24: 27.8667 | Q24: 26.4186 | R24: 24.0008 | S24: 29.3955 | T24: 30.6318 | U24: 28.8098 | AC24: Revenue converts from bookings made earlier: the bridge kernel maps a lagged GBV mix to revenue at a seasonal conversion rate.
A25: Conversion: revenue / lagged GBV | P25: =IFERROR(P26/(P24*1000),"") -> 0.17239341 | Q25: =IFERROR(Q26/(Q24*1000),"") -> 0.12029812 | R25: =IFERROR(R26/(R24*1000),"") -> 0.12720948 | S25: =IFERROR(S26/(S24*1000),"") -> 0.13706114 | T25: =IFERROR(T26/(T24*1000),"") -> 0.1723938 | U25: =IFERROR(U26/(U24*1000),"") -> 0.1202981
B26: 1818 | C26: 2484 | D26: 3397 | E26: 2218 | F26: 2142 | G26: 2748 | H26: 3732 | I26: 2480 | J26: 2272 | K26: 3096 | L26: 4095 | M26: 2778 | N26: 2678 | O26: 3608 | P26: 4804.0355 | Q26: 3178.1078 | R26: 3053.1293 | S26: 4028.9807 | T26: 5280.7325 | U26: 3465.7641 | W26: =SUM(B26:E26) -> 9917 | X26: =SUM(F26:I26) -> 11102 | Y26: =SUM(J26:M26) -> 12241 | Z26: =SUM(N26:O26,P26:Q26) -> 14268.143 | AA26: =SUM(R26:U26) -> 15828.607
A27: Revenue y/y reported | F27: =IFERROR(F26/B26-1,"") -> 0.17821782 | G27: =IFERROR(G26/C26-1,"") -> 0.10628019 | H27: =IFERROR(H26/D26-1,"") -> 0.098616426 | I27: =IFERROR(I26/E26-1,"") -> 0.11812444 | J27: =IFERROR(J26/F26-1,"") -> 0.060690943 | K27: =IFERROR(K26/G26-1,"") -> 0.12663755 | L27: =IFERROR(L26/H26-1,"") -> 0.097266881 | M27: =IFERROR(M26/I26-1,"") -> 0.12016129 | ... U27: =IFERROR(U26/Q26-1,"") -> 0.090511813 | X27: =IFERROR(X26/W26-1,"") -> 0.11949178 | Y27: =IFERROR(Y26/X26-1,"") -> 0.10259413 | Z27: =IFERROR(Z26/Y26-1,"") -> 0.16560275 | AA27: =IFERROR(AA26/Z26-1,"") -> 0.10936695
A28: FX contribution to revenue y/y (pts) | B28: -0.04 | C28: -0.01 | D28: 0.04 | E28: 0.03 | F28: 0 | G28: 0 | H28: 0 | J28: -0.02 | K28: 0 | L28: 0 | M28: 0.01 | N28: 0.03 | O28: 0.04 | P28: 0.03 | Q28: 0.0098 | R28: 0.0093 | S28: 0.0062 | T28: 0.0031 | U28: 0.0038 | AC28: History: reported less constant-currency growth from the letters. 3Q26 = management's ~3pt after hedging; 4Q26+ = FX-lag kernel (0.98, 0.93, 0.62, 0.31, 0.38pt).
A29: Revenue y/y ex-FX | B29: =IFERROR(B27-B28,"") -> 0.04 | C29: =IFERROR(C27-C28,"") -> 0.01 | D29: =IFERROR(D27-D28,"") -> -0.04 | E29: =IFERROR(E27-E28,"") -> -0.03 | F29: =IFERROR(F27-F28,"") -> 0.17821782 | G29: =IFERROR(G27-G28,"") -> 0.10628019 | H29: =IFERROR(H27-H28,"") -> 0.098616426 | I29: =IFERROR(I27-I28,"") -> 0.11812444 | ... O29: =IFERROR(O27-O28,"") -> 0.12537468 | P29: =P27-P28 -> 0.14314664 | Q29: =Q27-Q28 -> 0.13422729 | R29: =R27-R28 -> 0.13077816 | S29: =S27-S28 -> 0.11047979 | T29: =T27-T28 -> 0.096128451 | U29: =U27-U28 -> 0.086711813
A30: Take rate printed (revenue / GBV) | B30: =IFERROR(B26/(B19*1000),"") -> 0.089117647 | C30: =IFERROR(C26/(C19*1000),"") -> 0.13005236 | D30: =IFERROR(D26/(D19*1000),"") -> 0.18562842 | E30: =IFERROR(E26/(E19*1000),"") -> 0.14309677 | F30: =IFERROR(F26/(F19*1000),"") -> 0.093537118 | G30: =IFERROR(G26/(G19*1000),"") -> 0.12962264 | H30: =IFERROR(H26/(H19*1000),"") -> 0.18567164 | I30: =IFERROR(I26/(I19*1000),"") -> 0.14090909 | ... U30: =IFERROR(U26/(U19*1000),"") -> 0.13942331 | W30: =IFERROR(W26/(W19*1000),"") -> 0.13529332 | X30: =IFERROR(X26/(X19*1000),"") -> 0.13572127 | Y30: =IFERROR(Y26/(Y19*1000),"") -> 0.13407448 | Z30: =IFERROR(Z26/(Z19*1000),"") -> 0.13534652 | AA30: =IFERROR(AA26/(AA19*1000),"") -> 0.13703554
A31: Revenue band low (conversion band) | P31: 4777.8744 | Q31: 3156.008 | R31: 2958.2216 | S31: 3953.2896 | T31: 5251.9755 | U31: 3441.6639
A32: Revenue band high (conversion band) | P32: 4846.2321 | Q32: 3201.2166 | R32: 3128.384 | S32: 4099.4831 | T32: 5327.1162 | U32: 3490.9644 | AC32: Conversion min/max over the fitted years; it is not the nights band (section 2 has that).
A34: 2. Revenue scenarios: nights, ADR and revenue by case | B34: bear/bull = WS06 v2b on the bridge v3 bands; Short = the pitch case (lap + RNPL cancellations)
A35: Nights y/y: Bear | P35: 0.085 | Q35: 0.08 | R35: 0.04707 | S35: 0.03026 | T35: 0.03405 | U35: 0.03327 | Z35: 0.090259 | AA35: 0.036406
A36: Nights y/y: Base | P36: 0.0989 | Q36: 0.0812 | R36: 0.08206 | S36: 0.05934 | T36: 0.06229 | U36: 0.06045 | Z36: 0.094017 | AA36: 0.06642
A37: Nights y/y: Bull | P37: 0.11 | Q37: 0.0886 | R37: 0.10524 | S37: 0.0882 | T37: 0.08684 | U37: 0.08571 | Z37: 0.098492 | AA37: 0.091837
A38: Nights y/y: Short (pitch) | P38: 0.085 | Q38: 0.05 | R38: 0.04 | S38: 0.02 | T38: 0.03 | U38: 0.04 | AC38: Short: nights +8.5% in 3Q26 (guide low; July still has the World Cup) then +5/+4/+2/+3/+4% as the 4Q25-1Q26 bundle and World Cup lap and RNPL cancellations land; ADR ex-FX +2.5% then flat.
A40: ADR y/y reported: Bear | P40: 0.0203 | Q40: 0.0277 | R40: -0.00875 | S40: -0.00798 | T40: -0.00198 | U40: 0.00723 | Z40: 0.048749 | AA40: -0.003331
A41: ADR y/y reported: Base | P41: 0.0343 | Q41: 0.0422 | R41: 0.03176 | S41: 0.02894 | T41: 0.02682 | U41: 0.01876 | Z41: 0.055379 | AA41: 0.027181
A42: ADR y/y reported: Bull | P42: 0.0484 | Q42: 0.0566 | R42: 0.0573 | S42: 0.05801 | T42: 0.05268 | U42: 0.03174 | Z42: 0.062032 | AA42: 0.050872
A43: ADR y/y reported: Short (pitch) | P43: 0.0207 | Q43: 0.0015 | R43: -0.00302 | S43: -0.00193 | T43: 0.00034 | U43: -0.00285
A45: Revenue ($m): Bear | P45: 4755 | Q45: 3123.807 | R45: 2995.1629 | S45: 3803.7239 | T45: 4936.538 | U45: 3212.9091 | Z45: 14164.807 | AA45: 14948.334
A46: Revenue ($m): Base | P46: 4804.0355 | Q46: 3178.1078 | R46: 3053.1293 | S46: 4028.9807 | T46: 5280.7325 | U46: 3465.7641 | Z46: 14268.143 | AA46: 15828.607
A47: Revenue ($m): Bull | P47: 4878 | Q47: 3227.9366 | R47: 3119.9376 | S47: 4189.9054 | T47: 5559.9477 | U47: 3700.9529 | Z47: 14391.937 | AA47: 16570.744
A48: Revenue ($m): Short (pitch) | P48: 4680.9 | Q48: 2965.8677 | R48: 2835.5346 | S48: 3762.9716 | T48: 4988.1742 | U48: 3326.8311 | Z48: 13932.768 | AA48: 14913.512
A50: Revenue y/y: Bear | P50: 0.16117216 | Q50: 0.124481 | R50: 0.118433 | S50: 0.054247 | T50: 0.027581 | U50: 0.028524 | Z50: 0.15716093 | AA50: 0.055315042
A51: Revenue y/y: Base | P51: 0.173147 | Q51: 0.144027 | R51: 0.140078 | S51: 0.11668 | T51: 0.099228 | U51: 0.090512 | Z51: 0.165603 | AA51: 0.109367
A52: Revenue y/y: Bull | P52: 0.19120879 | Q52: 0.161964 | R52: 0.165025 | S52: 0.161282 | T52: 0.157349 | U52: 0.146538 | Z52: 0.17571576 | AA52: 0.15139082
A53: Revenue y/y: Short (pitch) | P53: =IFERROR(P48/L26-1,"") -> 0.14307692 | Q53: =IFERROR(Q48/M26-1,"") -> 0.067626954 | R53: =IFERROR(R48/N26-1,"") -> 0.058825471 | S53: =IFERROR(S48/O26-1,"") -> 0.042952212 | T53: =IFERROR(T48/P26-1,"") -> 0.038330014 | U53: =IFERROR(U48/Q26-1,"") -> 0.046796173 | Z53: =Z48/Y26-1 -> 0.13820502 | AA53: =AA48/Z48-1 -> 0.070391172
A55: 2b. Nights lap arithmetic for 2H26 (bridge v3 scenarios)
A56: Scenario | B56: 3Q26 nights y/y | C56: 4Q26 nights y/y | D56: 3Q26 GBV y/y | E56: 4Q26 GBV y/y | F56: 3Q26 vs guide (10-12%) | G56: 3Q26 accel vs 2Q26 (pts) | H56: 4Q26 accel vs 3Q26 (pts)
A57: v3 baseline band LOW (3Q26 reviews-index low; 4Q26 case B low) | B57: 0.085 | C57: 0.08 | D57: 0.1222155 | E57: 0.125576 | F57: below | G57: -1.84 | H57: -0.5
A58: v3 BASELINE (3Q26 team baseline; 4Q26 case B global lap) | B58: 0.0989 | C58: 0.0812 | D58: 0.13659227 | E58: 0.12682664 | F58: below | G58: -0.45 | H58: -1.77
A59: v3 baseline band HIGH (3Q26 reviews-index high; 4Q26 case A NA-only lap) | B59: 0.11 | C59: 0.0886 | D59: 0.148073 | E59: 0.13453892 | F59: inside 10-12 | G59: 0.66 | H59: -2.14
A60: COMPARISON v1/v2: no lap (international RNPL adoption offsets the US anniversary) | B60: 0.099916667 | C60: 0.10618333 | D60: 0.13764381 | E60: 0.15286427 | F60: below | G60: -0.34833333 | H60: 0.62666667
A61: COMPARISON v1/v2: half lap | B61: 0.084916667 | C61: 0.081183333 | D61: 0.12212931 | E61: 0.12680927 | F61: below | G61: -1.8483333 | H61: -0.37333333
A62: COMPARISON v1/v2: full lap (all ~3 pts of 1Q26 RNPL lift laps) | B62: 0.069916667 | C62: 0.076183333 | D62: 0.10661481 | E62: 0.12159827 | F62: below | G62: -3.3483333 | H62: 0.62666667
A63: 2Q26 printed nights +10.3%; management guided 3Q26 'low double digits'. The team baseline (+9.9%) sits below the guide and decelerates; the 4Q26 case B applies the RNPL/bundle lap to ex-NA nights at a 45% split. The 2027 nights build (06_nights_build.csv) carries NA +2.3% and ex-NA +10-11% pre-lap, less 0.74pt fee-cancellation lap and 0.36-0.91pt RNPL lap, for +6.0-8.2% total.
A65: 3. Street consensus on the KPIs, and where the team sits | B65: Bloomberg estimate distribution (pull 5-12 Sep 2026) for 3Q26/4Q26; LSEG revenue means 11 Sep 2026 for 3Q26-FY28
A66: Quarter | B66: Metric | C66: n | D66: Street low | E66: Street mean | F66: Street high | G66: Prior-year actual | H66: Street mean y/y | I66: Team value | J66: Team y/y | K66: Team position in the range
A67: 3Q26 | B67: Nights (m) | C67: 28 | D67: 147 | E67: 149 | F67: 151 | G67: 133.6 | H67: 0.11527 | I67: 146.8 | J67: 0.0988 | K67: below the lowest estimate
A68: 3Q26 | B68: GBV ($m) | C68: 28 | D68: 25992 | E68: 26375 | F68: 26723 | G68: 22892 | H68: 0.15215 | I68: 25900 | J68: 0.1314 | K68: below the lowest estimate
A69: 3Q26 | B69: ADR ($) | C69: 26 | D69: 173.71 | E69: 177.06 | F69: 179.12 | G69: 171.29 | H69: 0.03369 | I69: 176.9 | J69: 0.03275 | K69: inside the range
A70: 3Q26 | B70: Take rate (%) | C70: 28 | D70: 17.82 | E70: 18 | F70: 18.44 | G70: 17.88 | H70: 0.0012 | I70: 18.4 | J70: 0.0052 | K70: inside the range
A71: 4Q26 | B71: Nights (m) | C71: 28 | D71: 130 | E71: 134 | F71: 136 | G71: 121.9 | H71: 0.09926 | I71: 132.7 | J71: 0.0886 | K71: inside the range
A72: 4Q26 | B72: GBV ($m) | C72: 28 | D72: 22177 | E72: 23003 | F72: 23565 | G72: 20400 | H72: 0.1276 | I72: 23100 | J72: 0.13235 | K72: inside the range
A73: 4Q26 | B73: ADR ($) | C73: 25 | D73: 167.79 | E73: 171.33 | F73: 174.21 | G73: 167.51 | H73: 0.0228 | I73: 174.1 | J73: 0.03934 | K73: inside the range
A74: 4Q26 | B74: Take rate (%) | C74: 28 | D74: 13.6 | E74: 13.76 | F74: 14 | G74: 13.62 | H74: 0.0014 | I74: 13.5 | J74: -0.0012 | K74: below the lowest estimate
A75: 4Q26 | B75: Revenue ($m) | C75: 37 | D75: 3052 | E75: 3157 | F75: 3223 | G75: 2778 | H75: 0.13643 | I75: 3111 | J75: 0.11987 | K75: inside the range
A76: 4Q26 | B76: EPS ($) | C76: 29 | D76: 0.67 | E76: 0.87 | F76: 1.36 | G76: 0.56 | H76: 0.55357 | I76: 0.81 | J76: 0.44643 | K76: inside the range
A77: Team values in this Bloomberg comparison are the reverse-DCF run's snapshot (12 Sep): 3Q26 nights 146.8m / +9.9% and revenue $4,771m; the live bridge v3 revenue is $4,804m (section 1). The point that matters: every one of the 28 Street nights estimates for 3Q26 is at or above 2Q26's growth rate; the team's is below the lowest.
A79: Revenue: Street (LSEG mean) | P79: 4744.3221 | Q79: 3161.8163 | R79: 3010.3238 | S79: 4036.9356 | T79: 5269.9673 | U79: 3528.9194 | Z79: 14189.557 | AA79: 15819.339
A80: n estimates | P80: 36 | Q80: 36 | R80: 19 | S80: 19 | T80: 17 | U80: 17 | Z80: 44 | AA80: 44
A81: sd of estimates ($m) | P81: 24.27626 | Q81: 48.55902 | R81: 49.4461 | S81: 120.0081 | T81: 94.58991 | U81: 72.37043 | Z81: 59.21929 | AA81: 258.17766
A82: Team base vs Street (%) | P82: =P26/P79-1 -> 0.012586283 | Q82: =Q26/Q79-1 -> 0.0051525859 | R82: =R26/R79-1 -> 0.014219584 | S82: =S26/S79-1 -> -0.0019705194 | T82: =T26/T79-1 -> 0.002042747 | U82: =U26/U79-1 -> -0.017896487 | Z82: =Z26/Z79-1 -> 0.0055383159 | AA82: =AA26/AA79-1 -> 0.00058582472
A83: Short case vs Street (%) | P83: =P48/P79-1 -> -0.013368005 | Q83: =Q48/Q79-1 -> -0.061973428 | R83: =R48/R79-1 -> -0.058063236 | S83: =S48/S79-1 -> -0.067864343 | T83: =T48/T79-1 -> -0.053471497 | U83: =U48/U79-1 -> -0.057266335 | Z83: =Z48/Z79-1 -> -0.018097068 | AA83: =AA48/AA79-1 -> -0.057260781
A84: Team base gap in Street sd's | P84: =IFERROR((P26-P79)/P81,"") -> 2.4597438 | Q84: =IFERROR((Q26-Q79)/Q81,"") -> 0.33549956 | R84: =IFERROR((R26-R79)/R81,"") -> 0.86570124 | S84: =IFERROR((S26-S79)/S81,"") -> -0.066286026 | T84: =IFERROR((T26-T79)/T81,"") -> 0.11380928 | U84: =IFERROR((U26-U79)/U81,"") -> -0.87266664 | Z84: =(Z26-Z79)/Z81 -> 1.327038 | AA84: =(AA26-AA79)/AA81 -> 0.035895282
A86: 4. Management guidance: the 3Q26 guide in force, and what the model implies for the 5 Nov 4Q26 guide
A87: 3Q26 item | B87: Guide text (6 Aug 2026 letter) | C87: Guide low | D87: Guide high | E87: Guide mid | F87: Team base | G87: Base vs mid | H87: Short case | I87: Short vs mid | J87: Street
A88: Revenue ($m) | B88: $4.69-4.77bn, +15-17% incl. ~3pt FX | C88: 4690 | D88: 4770 | E88: =AVERAGE(C88:D88) -> 4730 | F88: 4804.0355 | G88: =F88/E88-1 -> 0.015652326 | H88: 4680.9 | I88: =H88/E88-1 -> -0.01038055 | J88: 4744.3221
A89: Nights & seats y/y | B89: low double digits | C89: 0.1 | D89: 0.12 | E89: =AVERAGE(C89:D89) -> 0.11 | F89: 0.0989 | G89: =F89-E89 -> -0.0111 | H89: 0.085 | I89: =H89-E89 -> -0.025 | J89: 0.11527
A90: GBV y/y | B90: mid teens | C90: 0.14 | D90: 0.16 | E90: =AVERAGE(C90:D90) -> 0.15 | F90: 0.136592 | G90: =F90-E90 -> -0.013408 | J90: 0.15215
A91: FX pts on revenue | B91: ~3 | C91: 0.03 | D91: 0.03 | E91: =AVERAGE(C91:D91) -> 0.03 | F91: 0.03 | G91: =F91-E91 -> 0 | H91: 0.03 | I91: =H91-E91 -> 0
A92: Take rate | B92: in line y/y (3Q25 17.9) | C92: 0.179 | D92: 0.179 | E92: =AVERAGE(C92:D92) -> 0.179 | F92: 0.184572 | G92: =F92-E92 -> 0.005572 | J92: 0.18
A93: Adj. EBITDA margin | B93: down slightly vs 50.1 | C93: 0.485 | D93: 0.499 | E93: =AVERAGE(C93:D93) -> 0.492 | J93: 0.49775747
A94: Margin margin-sentence rows are on the Margins tab (3Q26 'down slightly' vs 3Q25's 50.1%; FY26 'at least 35.5%'). The team base sits above the 3Q26 revenue guide's top end (as the last 19 prints did, mean +2.5% vs the midpoint), and below its nights guide.
A96: Expected 4Q26 guide (given 5 Nov) | B96: 4Q26 | C96: How it is derived
A97: Historical Q4 actual vs guide midpoint (mean, 4 Q4 guides) | B97: 0.0388 | C97: abnb_revenue_guidance_vs_actual.csv: 4Q22 +3.4%, 4Q23 +3.2%, 4Q24 +2.7%, 4Q25 +3.3%
A98: Historical actual vs midpoint, all 19 guided quarters (mean) | B98: 0.025526316 | C98: every print since 4Q21 landed above the midpoint; 15 of 19 above the top end
A99: Guide range width, % of midpoint (mean of the last 6) | B99: 0.0185
A100: Team base 4Q26 revenue ($m) | B100: =Q26 -> 3178.1078 | C100: bridge v3
A101: Implied 4Q26 guide midpoint if the Q4 cushion holds ($m) | B101: =B100/(1+B97) -> 3059.403 | C101: team base / (1 + historical Q4 cushion). Bridge v3 quotes $3,059m on the same arithmetic.
A102: Implied guide range ($m, low / high) | B102: =B101*(1-B99/2) -> 3031.1035 | C102: =B101*(1+B99/2) -> 3087.7024
A103: Implied guide midpoint y/y | B103: =B101/M26-1 -> 0.10129696 | C103: vs 4Q25 actual $2,778m
A104: Street 4Q26 revenue (LSEG mean) | B104: =Q79 -> 3161.8163
A105: Implied guide midpoint vs Street (%) | B105: =B101/B104-1 -> -0.032390657 | C105: a guide midpoint below the Street is the base case even on the team's own path: the market prices the guide plus the cushion
A106: Short case 4Q26 revenue ($m) | B106: =Q48 -> 2965.8677
A107: Short case implied guide midpoint ($m) | B107: =B106/(1+B97) -> 2855.0902
A108: Short case implied guide midpoint vs Street (%) | B108: =B107/B104-1 -> -0.097009461 | C108: the pitch's 5 Nov sequence: a Q3 print near the sentence, a Q4 guide well below the Street
A109: Nights guide direction for 4Q26 (expected wording) | B109: decelerating vs 3Q26 print; 'high single digits' on the base path, 'mid single digits' on the short path
A110: FX in the 4Q26 revenue guide (pts) | B110: 0.0098 | C110: kernel: about +1pt; management's own sentence has been the hedged number
A111: Take rate wording | B111: 'in line' y/y (4Q25 13.6%); team 13.8%
A113: 4b. Revenue guide history: every quarterly guide since 4Q21 and how the print landed
A114: Guided quarter | B114: Issued on call | C114: Guide low | D114: Guide high | E114: Guide mid | F114: Range width % of mid | G114: Actual | H114: Actual vs mid | I114: Actual vs high
A115: 2021Q4 | B115: 2021Q3 | C115: 1390 | D115: 1480 | E115: 1435 | F115: 0.063 | G115: 1532 | H115: 0.068 | I115: 0.035
...

Sheet Margins
A1: Margins: the cost stack line by line, the 3Q26 sentence, the 5 Nov card and the FY26/FY27 margin view
A2: Cash cost lines = GAAP less SBC and add-backs (management's adjusted EBITDA definition). Forecast columns follow the scenario dropdown on the Income Statement tab (B3). Blue = source value, black = formula, green = link.
A3: Scenario in the forecast columns: | B3: ='Income Statement'!B3 -> Base (team model)
B4: 1Q23 | C4: 2Q23 | D4: 3Q23 | E4: 4Q23 | F4: 1Q24 | G4: 2Q24 | H4: 3Q24 | I4: 4Q24 | J4: 1Q25 | K4: 2Q25 | L4: 3Q25 | M4: 4Q25 | N4: 1Q26 | O4: 2Q26 | P4: 3Q26 | Q4: 4Q26 | R4: 1Q27 | S4: 2Q27 | T4: 3Q27 | U4: 4Q27
A5: Quarter | B5: 1Q23A | C5: 2Q23A | D5: 3Q23A | E5: 4Q23A | F5: 1Q24A | G5: 2Q24A | H5: 3Q24A | I5: 4Q24A | J5: 1Q25A | K5: 2Q25A | L5: 3Q25A | M5: 4Q25A | N5: 1Q26A | O5: 2Q26A | P5: 3Q26E | Q5: 4Q26E | R5: 1Q27E | S5: 2Q27E | T5: 3Q27E | U5: 4Q27E | W5: FY23 | X5: FY24 | Y5: FY25 | Z5: FY26E | AA5: FY27E
A6: 1. The cost stack, cash basis (what adjusted EBITDA is made of)
A7: Revenue | B7: 1818 | C7: 2484 | D7: 3397 | E7: 2218 | F7: 2142 | G7: 2748 | H7: 3732 | I7: 2480 | J7: 2272 | K7: 3096 | L7: 4095 | M7: 2778 | N7: 2678 | O7: 3608 | P7: =INDEX('Scenario Data'!$D$5:$I$345,MATCH('Income Statement'!$G$3&"|revenue",'Scenario Data'!$A$5:$A$345,0),MATCH(P$4,'Scenario Data'!$D$4:$I$4,0)) -> 4804.0355 | Q7: =INDEX('Scenario Data'!$D$5:$I$345,MATCH('Income Statement'!$G$3&"|revenue",'Scenario Data'!$A$5:$A$345,0),MATCH(Q$4,'Scenario Data'!$D$4:$I$4,0)) -> 3178.1078 | R7: =INDEX('Scenario Data'!$D$5:$I$345,MATCH('Income Statement'!$G$3&"|revenue",'Scenario Data'!$A$5:$A$345,0),MATCH(R$4,'Scenario Data'!$D$4:$I$4,0)) -> 3053.1293 | S7: =INDEX('Scenario Data'!$D$5:$I$345,MATCH('Income Statement'!$G$3&"|revenue",'Scenario Data'!$A$5:$A$345,0),MATCH(S$4,'Scenario Data'!$D$4:$I$4,0)) -> 4028.9807 | T7: =INDEX('Scenario Data'!$D$5:$I$345,MATCH('Income Statement'!$G$3&"|revenue",'Scenario Data'!$A$5:$A$345,0),MATCH(T$4,'Scenario Data'!$D$4:$I$4,0)) -> 5280.7325 | U7: =INDEX('Scenario Data'!$D$5:$I$345,MATCH('Income Statement'!$G$3&"|revenue",'Scenario Data'!$A$5:$A$345,0),MATCH(U$4,'Scenario Data'!$D$4:$I$4,0)) -> 3465.7641 | W7: 9917 | X7: 11102 | Y7: 12241 | Z7: =SUM(N7:O7,P7:Q7) -> 14268.143 | AA7: =SUM(R7:U7) -> 15828.607
A8: Cost of revenue | B8: 428 | C8: 432 | D8: 459 | E8: 384 | F8: 480 | G8: 506 | H8: 465 | I8: 427 | J8: 506 | K8: 544 | L8: 549 | M8: 487 | N8: 581 | O8: 633 | P8: =INDEX('Scenario Data'!$D$5:$I$345,MATCH('Income Statement'!$G$3&"|cor_cash",'Scenario Data'!$A$5:$A$345,0),MATCH(P$4,'Scenario Data'!$D$4:$I$4,0)) -> 640.78412 | Q8: =INDEX('Scenario Data'!$D$5:$I$345,MATCH('Income Statement'!$G$3&"|cor_cash",'Scenario Data'!$A$5:$A$345,0),MATCH(Q$4,'Scenario Data'!$D$4:$I$4,0)) -> 578.03946 | R8: =INDEX('Scenario Data'!$D$5:$I$345,MATCH('Income Statement'!$G$3&"|cor_cash",'Scenario Data'!$A$5:$A$345,0),MATCH(R$4,'Scenario Data'!$D$4:$I$4,0)) -> 706.00359 | S8: =INDEX('Scenario Data'!$D$5:$I$345,MATCH('Income Statement'!$G$3&"|cor_cash",'Scenario Data'!$A$5:$A$345,0),MATCH(S$4,'Scenario Data'!$D$4:$I$4,0)) -> 727.29954 | T8: =INDEX('Scenario Data'!$D$5:$I$345,MATCH('Income Statement'!$G$3&"|cor_cash",'Scenario Data'!$A$5:$A$345,0),MATCH(T$4,'Scenario Data'!$D$4:$I$4,0)) -> 699.45368 | U8: =INDEX('Scenario Data'!$D$5:$I$345,MATCH('Income Statement'!$G$3&"|cor_cash",'Scenario Data'!$A$5:$A$345,0),MATCH(U$4,'Scenario Data'!$D$4:$I$4,0)) -> 626.85228 | W8: 1703 | X8: 1878 | Y8: 2086 | Z8: =SUM(N8:O8,P8:Q8) -> 2432.8236 | AA8: =SUM(R8:U8) -> 2759.6091
A9: % of revenue | B9: =IFERROR(B8/B7,"") -> 0.23542354 | C9: =IFERROR(C8/C7,"") -> 0.17391304 | D9: =IFERROR(D8/D7,"") -> 0.13511922 | E9: =IFERROR(E8/E7,"") -> 0.17312894 | F9: =IFERROR(F8/F7,"") -> 0.22408964 | G9: =IFERROR(G8/G7,"") -> 0.18413392 | H9: =IFERROR(H8/H7,"") -> 0.12459807 | I9: =IFERROR(I8/I7,"") -> 0.17217742 | ... U9: =IFERROR(U8/U7,"") -> 0.18086986 | W9: =IFERROR(W8/W7,"") -> 0.17172532 | X9: =IFERROR(X8/X7,"") -> 0.16915871 | Y9: =IFERROR(Y8/Y7,"") -> 0.17041091 | Z9: =IFERROR(Z8/Z7,"") -> 0.17050737 | AA9: =IFERROR(AA8/AA7,"") -> 0.17434315
A10: y/y | F10: =IFERROR(F8/B8-1,"") -> 0.12149533 | G10: =IFERROR(G8/C8-1,"") -> 0.1712963 | H10: =IFERROR(H8/D8-1,"") -> 0.013071895 | I10: =IFERROR(I8/E8-1,"") -> 0.11197917 | J10: =IFERROR(J8/F8-1,"") -> 0.054166667 | K10: =IFERROR(K8/G8-1,"") -> 0.075098814 | L10: =IFERROR(L8/H8-1,"") -> 0.18064516 | M10: =IFERROR(M8/I8-1,"") -> 0.14051522 | ... U10: =IFERROR(U8/Q8-1,"") -> 0.084445489 | X10: =IFERROR(X8/W8-1,"") -> 0.10275984 | Y10: =IFERROR(Y8/X8-1,"") -> 0.11075612 | Z10: =IFERROR(Z8/Y8-1,"") -> 0.1662625 | AA10: =IFERROR(AA8/Z8-1,"") -> 0.13432356
A11: Merchant / payment fees | P11: =INDEX('Scenario Data'!$D$5:$I$345,MATCH('Income Statement'!$G$3&"|cor_fees",'Scenario Data'!$A$5:$A$345,0),MATCH(P$4,'Scenario Data'!$D$4:$I$4,0)) -> 458.76313 | Q11: =INDEX('Scenario Data'!$D$5:$I$345,MATCH('Income Statement'!$G$3&"|cor_fees",'Scenario Data'!$A$5:$A$345,0),MATCH(Q$4,'Scenario Data'!$D$4:$I$4,0)) -> 404.38557 | R11: =INDEX('Scenario Data'!$D$5:$I$345,MATCH('Income Statement'!$G$3&"|cor_fees",'Scenario Data'!$A$5:$A$345,0),MATCH(R$4,'Scenario Data'!$D$4:$I$4,0)) -> 499.64569 | S11: =INDEX('Scenario Data'!$D$5:$I$345,MATCH('Income Statement'!$G$3&"|cor_fees",'Scenario Data'!$A$5:$A$345,0),MATCH(S$4,'Scenario Data'!$D$4:$I$4,0)) -> 527.61555 | T11: =INDEX('Scenario Data'!$D$5:$I$345,MATCH('Income Statement'!$G$3&"|cor_fees",'Scenario Data'!$A$5:$A$345,0),MATCH(T$4,'Scenario Data'!$D$4:$I$4,0)) -> 500.40927 | U11: =INDEX('Scenario Data'!$D$5:$I$345,MATCH('Income Statement'!$G$3&"|cor_fees",'Scenario Data'!$A$5:$A$345,0),MATCH(U$4,'Scenario Data'!$D$4:$I$4,0)) -> 436.87567 | AC11: 1.70% of GBV annual-equivalent, seasonal factors 0.90/1.045/1.035/1.033; 1H26 rate 1.68% after processor rebates
A12: Chargebacks | P12: =INDEX('Scenario Data'!$D$5:$I$345,MATCH('Income Statement'!$G$3&"|cor_chargebacks",'Scenario Data'!$A$5:$A$345,0),MATCH(P$4,'Scenario Data'!$D$4:$I$4,0)) -> 28.960373 | Q12: =INDEX('Scenario Data'!$D$5:$I$345,MATCH('Income Statement'!$G$3&"|cor_chargebacks",'Scenario Data'!$A$5:$A$345,0),MATCH(Q$4,'Scenario Data'!$D$4:$I$4,0)) -> 25.998569 | R12: =INDEX('Scenario Data'!$D$5:$I$345,MATCH('Income Statement'!$G$3&"|cor_chargebacks",'Scenario Data'!$A$5:$A$345,0),MATCH(R$4,'Scenario Data'!$D$4:$I$4,0)) -> 33.80356 | S12: =INDEX('Scenario Data'!$D$5:$I$345,MATCH('Income Statement'!$G$3&"|cor_chargebacks",'Scenario Data'!$A$5:$A$345,0),MATCH(S$4,'Scenario Data'!$D$4:$I$4,0)) -> 31.42002 | T12: =INDEX('Scenario Data'!$D$5:$I$345,MATCH('Income Statement'!$G$3&"|cor_chargebacks",'Scenario Data'!$A$5:$A$345,0),MATCH(T$4,'Scenario Data'!$D$4:$I$4,0)) -> 31.1916 | U12: =INDEX('Scenario Data'!$D$5:$I$345,MATCH('Income Statement'!$G$3&"|cor_chargebacks",'Scenario Data'!$A$5:$A$345,0),MATCH(U$4,'Scenario Data'!$D$4:$I$4,0)) -> 27.9531 | AC12: $0.72 per booking (1H26 +$25M y/y); short case adds $0.15 per booking
A13: Hosting | P13: =INDEX('Scenario Data'!$D$5:$I$345,MATCH('Income Statement'!$G$3&"|cor_hosting",'Scenario Data'!$A$5:$A$345,0),MATCH(P$4,'Scenario Data'!$D$4:$I$4,0)) -> 100.20793 | Q13: =INDEX('Scenario Data'!$D$5:$I$345,MATCH('Income Statement'!$G$3&"|cor_hosting",'Scenario Data'!$A$5:$A$345,0),MATCH(Q$4,'Scenario Data'!$D$4:$I$4,0)) -> 100.20793 | R13: =INDEX('Scenario Data'!$D$5:$I$345,MATCH('Income Statement'!$G$3&"|cor_hosting",'Scenario Data'!$A$5:$A$345,0),MATCH(R$4,'Scenario Data'!$D$4:$I$4,0)) -> 111.70793 | S13: =INDEX('Scenario Data'!$D$5:$I$345,MATCH('Income Statement'!$G$3&"|cor_hosting",'Scenario Data'!$A$5:$A$345,0),MATCH(S$4,'Scenario Data'!$D$4:$I$4,0)) -> 111.70793 | T13: =INDEX('Scenario Data'!$D$5:$I$345,MATCH('Income Statement'!$G$3&"|cor_hosting",'Scenario Data'!$A$5:$A$345,0),MATCH(T$4,'Scenario Data'!$D$4:$I$4,0)) -> 111.70793 | U13: =INDEX('Scenario Data'!$D$5:$I$345,MATCH('Income Statement'!$G$3&"|cor_hosting",'Scenario Data'!$A$5:$A$345,0),MATCH(U$4,'Scenario Data'!$D$4:$I$4,0)) -> 111.70793 | AC13: $224M/yr FY25 + $30M per half step in 2H26 + AI reconciliation step; $330M/yr FY27. The least-sourced number in the build.
A14: Other cost of revenue | P14: =INDEX('Scenario Data'!$D$5:$I$345,MATCH('Income Statement'!$G$3&"|cor_other",'Scenario Data'!$A$5:$A$345,0),MATCH(P$4,'Scenario Data'!$D$4:$I$4,0)) -> 52.85268 | Q14: =INDEX('Scenario Data'!$D$5:$I$345,MATCH('Income Statement'!$G$3&"|cor_other",'Scenario Data'!$A$5:$A$345,0),MATCH(Q$4,'Scenario Data'!$D$4:$I$4,0)) -> 47.447388 | R14: =INDEX('Scenario Data'!$D$5:$I$345,MATCH('Income Statement'!$G$3&"|cor_other",'Scenario Data'!$A$5:$A$345,0),MATCH(R$4,'Scenario Data'!$D$4:$I$4,0)) -> 60.846408 | S14: =INDEX('Scenario Data'!$D$5:$I$345,MATCH('Income Statement'!$G$3&"|cor_other",'Scenario Data'!$A$5:$A$345,0),MATCH(S$4,'Scenario Data'!$D$4:$I$4,0)) -> 56.556036 | T14: =INDEX('Scenario Data'!$D$5:$I$345,MATCH('Income Statement'!$G$3&"|cor_other",'Scenario Data'!$A$5:$A$345,0),MATCH(T$4,'Scenario Data'!$D$4:$I$4,0)) -> 56.14488 | U14: =INDEX('Scenario Data'!$D$5:$I$345,MATCH('Income Statement'!$G$3&"|cor_other",'Scenario Data'!$A$5:$A$345,0),MATCH(U$4,'Scenario Data'!$D$4:$I$4,0)) -> 50.31558 | AC14: $0.36 per night
A15: Operations & support | B15: 267 | C15: 298 | D15: 299 | E15: 254 | F15: 266 | G15: 314 | H15: 347 | I15: 265 | J15: 282 | K15: 309 | L15: 343 | M15: 303 | N15: 301 | O15: 323 | P15: =INDEX('Scenario Data'!$D$5:$I$345,MATCH('Income Statement'!$G$3&"|ops_cash",'Scenario Data'!$A$5:$A$345,0),MATCH(P$4,'Scenario Data'!$D$4:$I$4,0)) -> 361.44309 | Q15: =INDEX('Scenario Data'!$D$5:$I$345,MATCH('Income Statement'!$G$3&"|ops_cash",'Scenario Data'!$A$5:$A$345,0),MATCH(Q$4,'Scenario Data'!$D$4:$I$4,0)) -> 318.28709 | R15: =INDEX('Scenario Data'!$D$5:$I$345,MATCH('Income Statement'!$G$3&"|ops_cash",'Scenario Data'!$A$5:$A$345,0),MATCH(R$4,'Scenario Data'!$D$4:$I$4,0)) -> 319.08609 | S15: =INDEX('Scenario Data'!$D$5:$I$345,MATCH('Income Statement'!$G$3&"|ops_cash",'Scenario Data'!$A$5:$A$345,0),MATCH(S$4,'Scenario Data'!$D$4:$I$4,0)) -> 340.96824 | T15: =INDEX('Scenario Data'!$D$5:$I$345,MATCH('Income Statement'!$G$3&"|ops_cash",'Scenario Data'!$A$5:$A$345,0),MATCH(T$4,'Scenario Data'!$D$4:$I$4,0)) -> 381.7591 | U15: =INDEX('Scenario Data'!$D$5:$I$345,MATCH('Income Statement'!$G$3&"|ops_cash",'Scenario Data'!$A$5:$A$345,0),MATCH(U$4,'Scenario Data'!$D$4:$I$4,0)) -> 336.06248 | W15: 1118 | X15: 1192 | Y15: 1237 | Z15: =SUM(N15:O15,P15:Q15) -> 1303.7302 | AA15: =SUM(R15:U15) -> 1377.8759
A16: % of revenue | B16: =IFERROR(B15/B7,"") -> 0.14686469 | C16: =IFERROR(C15/C7,"") -> 0.11996779 | D16: =IFERROR(D15/D7,"") -> 0.08801884 | E16: =IFERROR(E15/E7,"") -> 0.11451758 | F16: =IFERROR(F15/F7,"") -> 0.12418301 | G16: =IFERROR(G15/G7,"") -> 0.11426492 | H16: =IFERROR(H15/H7,"") -> 0.092979636 | I16: =IFERROR(I15/I7,"") -> 0.10685484 | ... U16: =IFERROR(U15/U7,"") -> 0.096966346 | W16: =IFERROR(W15/W7,"") -> 0.11273571 | X16: =IFERROR(X15/X7,"") -> 0.10736804 | Y16: =IFERROR(Y15/Y7,"") -> 0.10105384 | Z16: =IFERROR(Z15/Z7,"") -> 0.091373499 | AA16: =IFERROR(AA15/AA7,"") -> 0.087049729
A17: y/y | F17: =IFERROR(F15/B15-1,"") -> -0.0037453184 | G17: =IFERROR(G15/C15-1,"") -> 0.053691275 | H17: =IFERROR(H15/D15-1,"") -> 0.16053512 | I17: =IFERROR(I15/E15-1,"") -> 0.043307087 | J17: =IFERROR(J15/F15-1,"") -> 0.060150376 | K17: =IFERROR(K15/G15-1,"") -> -0.015923567 | L17: =IFERROR(L15/H15-1,"") -> -0.011527378 | M17: =IFERROR(M15/I15-1,"") -> 0.14339623 | ... U17: =IFERROR(U15/Q15-1,"") -> 0.055847024 | X17: =IFERROR(X15/W15-1,"") -> 0.066189624 | Y17: =IFERROR(Y15/X15-1,"") -> 0.037751678 | Z17: =IFERROR(Z15/Y15-1,"") -> 0.053945175 | AA17: =IFERROR(AA15/Z15-1,"") -> 0.05687199
A18: Variable part (AI-addressable, 21.5% of the line) | P18: =INDEX('Scenario Data'!$D$5:$I$345,MATCH('Income Statement'!$G$3&"|ops_variable",'Scenario Data'!$A$5:$A$345,0),MATCH(P$4,'Scenario Data'!$D$4:$I$4,0)) -> 70.647687 | Q18: =INDEX('Scenario Data'!$D$5:$I$345,MATCH('Income Statement'!$G$3&"|ops_variable",'Scenario Data'!$A$5:$A$345,0),MATCH(Q$4,'Scenario Data'!$D$4:$I$4,0)) -> 61.403694 | R18: =INDEX('Scenario Data'!$D$5:$I$345,MATCH('Income Statement'!$G$3&"|ops_variable",'Scenario Data'!$A$5:$A$345,0),MATCH(R$4,'Scenario Data'!$D$4:$I$4,0)) -> 63.898291 | S18: =INDEX('Scenario Data'!$D$5:$I$345,MATCH('Income Statement'!$G$3&"|ops_variable",'Scenario Data'!$A$5:$A$345,0),MATCH(S$4,'Scenario Data'!$D$4:$I$4,0)) -> 67.128844 | T18: =INDEX('Scenario Data'!$D$5:$I$345,MATCH('Income Statement'!$G$3&"|ops_variable",'Scenario Data'!$A$5:$A$345,0),MATCH(T$4,'Scenario Data'!$D$4:$I$4,0)) -> 75.327647 | U18: =INDEX('Scenario Data'!$D$5:$I$345,MATCH('Income Statement'!$G$3&"|ops_variable",'Scenario Data'!$A$5:$A$345,0),MATCH(U$4,'Scenario Data'!$D$4:$I$4,0)) -> 66.218683 | AC18: per booking -14% y/y in 2H26, -10% in FY27 (management: support cost per booking -10% and -16% in 1H26)
A19: Fixed part (payroll, customer relations, insurance) | P19: =INDEX('Scenario Data'!$D$5:$I$345,MATCH('Income Statement'!$G$3&"|ops_fixed",'Scenario Data'!$A$5:$A$345,0),MATCH(P$4,'Scenario Data'!$D$4:$I$4,0)) -> 290.7954 | Q19: =INDEX('Scenario Data'!$D$5:$I$345,MATCH('Income Statement'!$G$3&"|ops_fixed",'Scenario Data'!$A$5:$A$345,0),MATCH(Q$4,'Scenario Data'!$D$4:$I$4,0)) -> 256.8834 | R19: =INDEX('Scenario Data'!$D$5:$I$345,MATCH('Income Statement'!$G$3&"|ops_fixed",'Scenario Data'!$A$5:$A$345,0),MATCH(R$4,'Scenario Data'!$D$4:$I$4,0)) -> 255.1878 | S19: =INDEX('Scenario Data'!$D$5:$I$345,MATCH('Income Statement'!$G$3&"|ops_fixed",'Scenario Data'!$A$5:$A$345,0),MATCH(S$4,'Scenario Data'!$D$4:$I$4,0)) -> 273.8394 | T19: =INDEX('Scenario Data'!$D$5:$I$345,MATCH('Income Statement'!$G$3&"|ops_fixed",'Scenario Data'!$A$5:$A$345,0),MATCH(T$4,'Scenario Data'!$D$4:$I$4,0)) -> 306.43145 | U19: =INDEX('Scenario Data'!$D$5:$I$345,MATCH('Income Statement'!$G$3&"|ops_fixed",'Scenario Data'!$A$5:$A$345,0),MATCH(U$4,'Scenario Data'!$D$4:$I$4,0)) -> 269.8438 | AC19: +8% y/y
A20: Ops & support per booking ($) | P20: =INDEX('Scenario Data'!$D$5:$I$345,MATCH('Income Statement'!$G$3&"|ops_per_booking",'Scenario Data'!$A$5:$A$345,0),MATCH(P$4,'Scenario Data'!$D$4:$I$4,0)) -> 8.9860385 | Q20: =INDEX('Scenario Data'!$D$5:$I$345,MATCH('Income Statement'!$G$3&"|ops_per_booking",'Scenario Data'!$A$5:$A$345,0),MATCH(Q$4,'Scenario Data'!$D$4:$I$4,0)) -> 8.8145894 | R20: =INDEX('Scenario Data'!$D$5:$I$345,MATCH('Income Statement'!$G$3&"|ops_per_booking",'Scenario Data'!$A$5:$A$345,0),MATCH(R$4,'Scenario Data'!$D$4:$I$4,0)) -> 6.7963843 | S20: =INDEX('Scenario Data'!$D$5:$I$345,MATCH('Income Statement'!$G$3&"|ops_per_booking",'Scenario Data'!$A$5:$A$345,0),MATCH(S$4,'Scenario Data'!$D$4:$I$4,0)) -> 7.8133984 | T20: =INDEX('Scenario Data'!$D$5:$I$345,MATCH('Income Statement'!$G$3&"|ops_per_booking",'Scenario Data'!$A$5:$A$345,0),MATCH(T$4,'Scenario Data'!$D$4:$I$4,0)) -> 8.8121978 | U20: =INDEX('Scenario Data'!$D$5:$I$345,MATCH('Income Statement'!$G$3&"|ops_per_booking",'Scenario Data'!$A$5:$A$345,0),MATCH(U$4,'Scenario Data'!$D$4:$I$4,0)) -> 8.6561056
A21: Product development | B21: 271 | C21: 260 | D21: 244 | E21: 253 | F21: 290 | G21: 280 | H21: 294 | I21: 306 | J21: 338 | K21: 331 | L21: 333 | M21: 335 | N21: 375 | O21: 374 | P21: =INDEX('Scenario Data'!$D$5:$I$345,MATCH('Income Statement'!$G$3&"|pd_cash",'Scenario Data'!$A$5:$A$345,0),MATCH(P$4,'Scenario Data'!$D$4:$I$4,0)) -> 359.09488 | Q21: =INDEX('Scenario Data'!$D$5:$I$345,MATCH('Income Statement'!$G$3&"|pd_cash",'Scenario Data'!$A$5:$A$345,0),MATCH(Q$4,'Scenario Data'!$D$4:$I$4,0)) -> 369.02512 | R21: =INDEX('Scenario Data'!$D$5:$I$345,MATCH('Income Statement'!$G$3&"|pd_cash",'Scenario Data'!$A$5:$A$345,0),MATCH(R$4,'Scenario Data'!$D$4:$I$4,0)) -> 414.12379 | S21: =INDEX('Scenario Data'!$D$5:$I$345,MATCH('Income Statement'!$G$3&"|pd_cash",'Scenario Data'!$A$5:$A$345,0),MATCH(S$4,'Scenario Data'!$D$4:$I$4,0)) -> 400.79642 | T21: =INDEX('Scenario Data'!$D$5:$I$345,MATCH('Income Statement'!$G$3&"|pd_cash",'Scenario Data'!$A$5:$A$345,0),MATCH(T$4,'Scenario Data'!$D$4:$I$4,0)) -> 399.65871 | U21: =INDEX('Scenario Data'!$D$5:$I$345,MATCH('Income Statement'!$G$3&"|pd_cash",'Scenario Data'!$A$5:$A$345,0),MATCH(U$4,'Scenario Data'!$D$4:$I$4,0)) -> 410.71068 | W21: 1028 | X21: 1170 | Y21: 1337 | Z21: =SUM(N21:O21,P21:Q21) -> 1477.12 | AA21: =SUM(R21:U21) -> 1625.2896 | AC21: 2H26 +9% y/y, FY27 +8% + $30M AI tooling; 1H26 ran +12%/+10%, all payroll
A22: % of revenue | B22: =IFERROR(B21/B7,"") -> 0.14906491 | C22: =IFERROR(C21/C7,"") -> 0.10466989 | D22: =IFERROR(D21/D7,"") -> 0.071828084 | E22: =IFERROR(E21/E7,"") -> 0.11406673 | F22: =IFERROR(F21/F7,"") -> 0.13538749 | G22: =IFERROR(G21/G7,"") -> 0.10189229 | H22: =IFERROR(H21/H7,"") -> 0.078778135 | I22: =IFERROR(I21/I7,"") -> 0.1233871 | ... U22: =IFERROR(U21/U7,"") -> 0.11850509 | W22: =IFERROR(W21/W7,"") -> 0.10366038 | X22: =IFERROR(X21/X7,"") -> 0.10538642 | Y22: =IFERROR(Y21/Y7,"") -> 0.1092231 | Z22: =IFERROR(Z21/Z7,"") -> 0.10352573 | AA22: =IFERROR(AA21/AA7,"") -> 0.10268052
A23: y/y | F23: =IFERROR(F21/B21-1,"") -> 0.070110701 | G23: =IFERROR(G21/C21-1,"") -> 0.076923077 | H23: =IFERROR(H21/D21-1,"") -> 0.20491803 | I23: =IFERROR(I21/E21-1,"") -> 0.20948617 | J23: =IFERROR(J21/F21-1,"") -> 0.16551724 | K23: =IFERROR(K21/G21-1,"") -> 0.18214286 | L23: =IFERROR(L21/H21-1,"") -> 0.13265306 | M23: =IFERROR(M21/I21-1,"") -> 0.094771242 | ... U23: =IFERROR(U21/Q21-1,"") -> 0.11296132 | X23: =IFERROR(X21/W21-1,"") -> 0.1381323 | Y23: =IFERROR(Y21/X21-1,"") -> 0.14273504 | Z23: =IFERROR(Z21/Y21-1,"") -> 0.1048018 | AA23: =IFERROR(AA21/Z21-1,"") -> 0.10030979
A24: Sales & marketing | B24: 422 | C24: 450 | D24: 370 | E24: 391 | F24: 479 | G24: 527 | H24: 471 | I24: 501 | J24: 519 | K24: 639 | L24: 585 | M24: 633 | N24: 696 | O24: 808 | P24: =INDEX('Scenario Data'!$D$5:$I$345,MATCH('Income Statement'!$G$3&"|sm_cash",'Scenario Data'!$A$5:$A$345,0),MATCH(P$4,'Scenario Data'!$D$4:$I$4,0)) -> 778.31581 | Q24: =INDEX('Scenario Data'!$D$5:$I$345,MATCH('Income Statement'!$G$3&"|sm_cash",'Scenario Data'!$A$5:$A$345,0),MATCH(Q$4,'Scenario Data'!$D$4:$I$4,0)) -> 758.10753 | R24: =INDEX('Scenario Data'!$D$5:$I$345,MATCH('Income Statement'!$G$3&"|sm_cash",'Scenario Data'!$A$5:$A$345,0),MATCH(R$4,'Scenario Data'!$D$4:$I$4,0)) -> 829.27179 | S24: =INDEX('Scenario Data'!$D$5:$I$345,MATCH('Income Statement'!$G$3&"|sm_cash",'Scenario Data'!$A$5:$A$345,0),MATCH(S$4,'Scenario Data'!$D$4:$I$4,0)) -> 935.13627 | T24: =INDEX('Scenario Data'!$D$5:$I$345,MATCH('Income Statement'!$G$3&"|sm_cash",'Scenario Data'!$A$5:$A$345,0),MATCH(T$4,'Scenario Data'!$D$4:$I$4,0)) -> 819.9308 | U24: =INDEX('Scenario Data'!$D$5:$I$345,MATCH('Income Statement'!$G$3&"|sm_cash",'Scenario Data'!$A$5:$A$345,0),MATCH(U$4,'Scenario Data'!$D$4:$I$4,0)) -> 875.28478 | W24: 1633 | X24: 1978 | Y24: 2376 | Z24: =SUM(N24:O24,P24:Q24) -> 3040.4233 | AA24: =SUM(R24:U24) -> 3459.6236 | AC24: THE line that carries the margin call: FY25 19.4% of revenue, FY26 21.3%, FY27 21.9% (line build) / 23.5% (run allocation)
A25: % of revenue | B25: =IFERROR(B24/B7,"") -> 0.23212321 | C25: =IFERROR(C24/C7,"") -> 0.18115942 | D25: =IFERROR(D24/D7,"") -> 0.10891963 | E25: =IFERROR(E24/E7,"") -> 0.17628494 | F25: =IFERROR(F24/F7,"") -> 0.22362278 | G25: =IFERROR(G24/G7,"") -> 0.19177584 | H25: =IFERROR(H24/H7,"") -> 0.12620579 | I25: =IFERROR(I24/I7,"") -> 0.20201613 | ... U25: =IFERROR(U24/U7,"") -> 0.25255175 | W25: =IFERROR(W24/W7,"") -> 0.16466673 | X25: =IFERROR(X24/X7,"") -> 0.1781661 | Y25: =IFERROR(Y24/Y7,"") -> 0.19410179 | Z25: =IFERROR(Z24/Z7,"") -> 0.21309173 | AA25: =IFERROR(AA24/AA7,"") -> 0.2185678
A26: y/y | F26: =IFERROR(F24/B24-1,"") -> 0.13507109 | G26: =IFERROR(G24/C24-1,"") -> 0.17111111 | H26: =IFERROR(H24/D24-1,"") -> 0.27297297 | I26: =IFERROR(I24/E24-1,"") -> 0.28132992 | J26: =IFERROR(J24/F24-1,"") -> 0.083507307 | K26: =IFERROR(K24/G24-1,"") -> 0.21252372 | L26: =IFERROR(L24/H24-1,"") -> 0.24203822 | M26: =IFERROR(M24/I24-1,"") -> 0.26347305 | ... U26: =IFERROR(U24/Q24-1,"") -> 0.15456548 | X26: =IFERROR(X24/W24-1,"") -> 0.21126761 | Y26: =IFERROR(Y24/X24-1,"") -> 0.20121335 | Z26: =IFERROR(Z24/Y24-1,"") -> 0.27963945 | AA26: =IFERROR(AA24/Z24-1,"") -> 0.13787564
A27: Brand + performance marketing | P27: =INDEX('Scenario Data'!$D$5:$I$345,MATCH('Income Statement'!$G$3&"|sm_marketing",'Scenario Data'!$A$5:$A$345,0),MATCH(P$4,'Scenario Data'!$D$4:$I$4,0)) -> 540.67059 | Q27: =INDEX('Scenario Data'!$D$5:$I$345,MATCH('Income Statement'!$G$3&"|sm_marketing",'Scenario Data'!$A$5:$A$345,0),MATCH(Q$4,'Scenario Data'!$D$4:$I$4,0)) -> 504.41875 | R27: =INDEX('Scenario Data'!$D$5:$I$345,MATCH('Income Statement'!$G$3&"|sm_marketing",'Scenario Data'!$A$5:$A$345,0),MATCH(R$4,'Scenario Data'!$D$4:$I$4,0)) -> 584.06976 | S27: =INDEX('Scenario Data'!$D$5:$I$345,MATCH('Income Statement'!$G$3&"|sm_marketing",'Scenario Data'!$A$5:$A$345,0),MATCH(S$4,'Scenario Data'!$D$4:$I$4,0)) -> 658.63186 | T27: =INDEX('Scenario Data'!$D$5:$I$345,MATCH('Income Statement'!$G$3&"|sm_marketing",'Scenario Data'!$A$5:$A$345,0),MATCH(T$4,'Scenario Data'!$D$4:$I$4,0)) -> 577.49075 | U27: =INDEX('Scenario Data'!$D$5:$I$345,MATCH('Income Statement'!$G$3&"|sm_marketing",'Scenario Data'!$A$5:$A$345,0),MATCH(U$4,'Scenario Data'!$D$4:$I$4,0)) -> 616.47747 | AC27: FY25 $1,595M (10-K split); 1H26 +32% reported; 2H26 +25% plus the $67M 3Q26 reconciliation step; FY27 +15%
A28: Field operations & policy | P28: =INDEX('Scenario Data'!$D$5:$I$345,MATCH('Income Statement'!$G$3&"|sm_field",'Scenario Data'!$A$5:$A$345,0),MATCH(P$4,'Scenario Data'!$D$4:$I$4,0)) -> 237.64522 | Q28: =INDEX('Scenario Data'!$D$5:$I$345,MATCH('Income Statement'!$G$3&"|sm_field",'Scenario Data'!$A$5:$A$345,0),MATCH(Q$4,'Scenario Data'!$D$4:$I$4,0)) -> 253.68878 | R28: =INDEX('Scenario Data'!$D$5:$I$345,MATCH('Income Statement'!$G$3&"|sm_field",'Scenario Data'!$A$5:$A$345,0),MATCH(R$4,'Scenario Data'!$D$4:$I$4,0)) -> 245.20203 | S28: =INDEX('Scenario Data'!$D$5:$I$345,MATCH('Income Statement'!$G$3&"|sm_field",'Scenario Data'!$A$5:$A$345,0),MATCH(S$4,'Scenario Data'!$D$4:$I$4,0)) -> 276.50441 | T28: =INDEX('Scenario Data'!$D$5:$I$345,MATCH('Income Statement'!$G$3&"|sm_field",'Scenario Data'!$A$5:$A$345,0),MATCH(T$4,'Scenario Data'!$D$4:$I$4,0)) -> 242.44005 | U28: =INDEX('Scenario Data'!$D$5:$I$345,MATCH('Income Statement'!$G$3&"|sm_field",'Scenario Data'!$A$5:$A$345,0),MATCH(U$4,'Scenario Data'!$D$4:$I$4,0)) -> 258.80731 | AC28: FY25 $781M incl. ~$200M of Services/Experiences launch spend; +18% FY26, +11% FY27
A29: General & administrative (ex lodging-tax reserves) | B29: 191 | C29: 219 | D29: 202 | E29: 211 | F29: 223 | G29: 242 | H29: 210 | I29: 226 | J29: 235 | K29: 244 | L29: 257 | M29: 259 | N29: 226 | O29: 227 | P29: =INDEX('Scenario Data'!$D$5:$I$345,MATCH('Income Statement'!$G$3&"|ga_cash",'Scenario Data'!$A$5:$A$345,0),MATCH(P$4,'Scenario Data'!$D$4:$I$4,0)) -> 265.38907 | Q29: =INDEX('Scenario Data'!$D$5:$I$345,MATCH('Income Statement'!$G$3&"|ga_cash",'Scenario Data'!$A$5:$A$345,0),MATCH(Q$4,'Scenario Data'!$D$4:$I$4,0)) -> 276.41093 | R29: =INDEX('Scenario Data'!$D$5:$I$345,MATCH('Income Statement'!$G$3&"|ga_cash",'Scenario Data'!$A$5:$A$345,0),MATCH(R$4,'Scenario Data'!$D$4:$I$4,0)) -> 249.22724 | S29: =INDEX('Scenario Data'!$D$5:$I$345,MATCH('Income Statement'!$G$3&"|ga_cash",'Scenario Data'!$A$5:$A$345,0),MATCH(S$4,'Scenario Data'!$D$4:$I$4,0)) -> 271.5804 | T29: =INDEX('Scenario Data'!$D$5:$I$345,MATCH('Income Statement'!$G$3&"|ga_cash",'Scenario Data'!$A$5:$A$345,0),MATCH(T$4,'Scenario Data'!$D$4:$I$4,0)) -> 256.53902 | U29: =INDEX('Scenario Data'!$D$5:$I$345,MATCH('Income Statement'!$G$3&"|ga_cash",'Scenario Data'!$A$5:$A$345,0),MATCH(U$4,'Scenario Data'!$D$4:$I$4,0)) -> 267.19333 | W29: 823 | X29: 901 | Y29: 995 | Z29: =SUM(N29:O29,P29:Q29) -> 994.8 | AA29: =SUM(R29:U29) -> 1044.54 | AC29: 4Q23 excludes the ~$1bn lodging-tax reserve, which management adds back; 2H26 +5%, FY27 +5% (1H26 ran -5.4% on a $38M drop in non-income taxes)
A30: % of revenue | B30: =IFERROR(B29/B7,"") -> 0.10506051 | C30: =IFERROR(C29/C7,"") -> 0.088164251 | D30: =IFERROR(D29/D7,"") -> 0.059464233 | E30: =IFERROR(E29/E7,"") -> 0.095130748 | F30: =IFERROR(F29/F7,"") -> 0.10410831 | G30: =IFERROR(G29/G7,"") -> 0.088064047 | H30: =IFERROR(H29/H7,"") -> 0.056270096 | I30: =IFERROR(I29/I7,"") -> 0.091129032 | ... U30: =IFERROR(U29/U7,"") -> 0.077095072 | W30: =IFERROR(W29/W7,"") -> 0.082988807 | X30: =IFERROR(X29/X7,"") -> 0.081156548 | Y30: =IFERROR(Y29/Y7,"") -> 0.081284209 | Z30: =IFERROR(Z29/Z7,"") -> 0.069721756 | AA30: =IFERROR(AA29/AA7,"") -> 0.065990648
A31: y/y | F31: =IFERROR(F29/B29-1,"") -> 0.16753927 | G31: =IFERROR(G29/C29-1,"") -> 0.10502283 | H31: =IFERROR(H29/D29-1,"") -> 0.03960396 | I31: =IFERROR(I29/E29-1,"") -> 0.071090047 | J31: =IFERROR(J29/F29-1,"") -> 0.053811659 | K31: =IFERROR(K29/G29-1,"") -> 0.0082644628 | L31: =IFERROR(L29/H29-1,"") -> 0.22380952 | M31: =IFERROR(M29/I29-1,"") -> 0.1460177 | ... U31: =IFERROR(U29/Q29-1,"") -> -0.033347442 | X31: =IFERROR(X29/W29-1,"") -> 0.094775213 | Y31: =IFERROR(Y29/X29-1,"") -> 0.10432852 | Z31: =IFERROR(Z29/Y29-1,"") -> -0.00020100503 | AA31: =IFERROR(AA29/Z29-1,"") -> 0.05
A32: Total cash costs | B32: =B8+B15+B21+B24+B29 -> 1579 | C32: =C8+C15+C21+C24+C29 -> 1659 | D32: =D8+D15+D21+D24+D29 -> 1574 | E32: =E8+E15+E21+E24+E29 -> 1493 | F32: =F8+F15+F21+F24+F29 -> 1738 | G32: =G8+G15+G21+G24+G29 -> 1869 | H32: =H8+H15+H21+H24+H29 -> 1787 | I32: =I8+I15+I21+I24+I29 -> 1725 | ... U32: =U8+U15+U21+U24+U29 -> 2516.1036 | W32: =W8+W15+W21+W24+W29 -> 6305 | X32: =X8+X15+X21+X24+X29 -> 7119 | Y32: =Y8+Y15+Y21+Y24+Y29 -> 8031 | Z32: =Z8+Z15+Z21+Z24+Z29 -> 9248.8971 | AA32: =AA8+AA15+AA21+AA24+AA29 -> 10266.938
A33: % of revenue | B33: =IFERROR(B32/B7,"") -> 0.86853685 | C33: =IFERROR(C32/C7,"") -> 0.6678744 | D33: =IFERROR(D32/D7,"") -> 0.46335001 | E33: =IFERROR(E32/E7,"") -> 0.67312894 | F33: =IFERROR(F32/F7,"") -> 0.81139122 | G33: =IFERROR(G32/G7,"") -> 0.680131 | H33: =IFERROR(H32/H7,"") -> 0.47883173 | I33: =IFERROR(I32/I7,"") -> 0.69556452 | ... U33: =IFERROR(U32/U7,"") -> 0.72598812 | W33: =IFERROR(W32/W7,"") -> 0.63577695 | X33: =IFERROR(X32/X7,"") -> 0.64123581 | Y33: =IFERROR(Y32/Y7,"") -> 0.65607385 | Z33: =IFERROR(Z32/Z7,"") -> 0.64822009 | AA33: =IFERROR(AA32/AA7,"") -> 0.64863184
A34: y/y | F34: =IFERROR(F32/B32-1,"") -> 0.10069664 | G34: =IFERROR(G32/C32-1,"") -> 0.12658228 | H34: =IFERROR(H32/D32-1,"") -> 0.13532402 | I34: =IFERROR(I32/E32-1,"") -> 0.15539183 | J34: =IFERROR(J32/F32-1,"") -> 0.081703107 | K34: =IFERROR(K32/G32-1,"") -> 0.105939 | L34: =IFERROR(L32/H32-1,"") -> 0.15668719 | M34: =IFERROR(M32/I32-1,"") -> 0.16927536 | ... U34: =IFERROR(U32/Q32-1,"") -> 0.094019844 | X34: =IFERROR(X32/W32-1,"") -> 0.12910389 | Y34: =IFERROR(Y32/X32-1,"") -> 0.12810788 | Z34: =IFERROR(Z32/Y32-1,"") -> 0.1516495 | AA34: =IFERROR(AA32/Z32-1,"") -> 0.11007163
A35: D&A (inside the lines, added back) | B35: 11 | C35: 9 | D35: 8 | E35: 16 | F35: 14 | G35: 14 | H35: 15 | I35: 22 | J35: 25 | K35: 21 | L35: 22 | M35: 23 | N35: 22 | O35: 17 | P35: =INDEX('Scenario Data'!$D$5:$I$345,MATCH('Income Statement'!$G$3&"|da",'Scenario Data'!$A$5:$A$345,0),MATCH(P$4,'Scenario Data'!$D$4:$I$4,0)) -> 20.633971 | Q35: =INDEX('Scenario Data'!$D$5:$I$345,MATCH('Income Statement'!$G$3&"|da",'Scenario Data'!$A$5:$A$345,0),MATCH(Q$4,'Scenario Data'!$D$4:$I$4,0)) -> 20.633971 | R35: =INDEX('Scenario Data'!$D$5:$I$345,MATCH('Income Statement'!$G$3&"|da",'Scenario Data'!$A$5:$A$345,0),MATCH(R$4,'Scenario Data'!$D$4:$I$4,0)) -> 20.633971 | S35: =INDEX('Scenario Data'!$D$5:$I$345,MATCH('Income Statement'!$G$3&"|da",'Scenario Data'!$A$5:$A$345,0),MATCH(S$4,'Scenario Data'!$D$4:$I$4,0)) -> 20.633971 | T35: =INDEX('Scenario Data'!$D$5:$I$345,MATCH('Income Statement'!$G$3&"|da",'Scenario Data'!$A$5:$A$345,0),MATCH(T$4,'Scenario Data'!$D$4:$I$4,0)) -> 20.633971 | U35: =INDEX('Scenario Data'!$D$5:$I$345,MATCH('Income Statement'!$G$3&"|da",'Scenario Data'!$A$5:$A$345,0),MATCH(U$4,'Scenario Data'!$D$4:$I$4,0)) -> 20.633971 | W35: 44 | X35: 65 | Y35: 91 | Z35: =SUM(N35:O35,P35:Q35) -> 80.267941 | AA35: =SUM(R35:U35) -> 82.535882
A36: Other add-backs (history) | B36: 12 | C36: -15 | D36: 3 | E36: -3 | F36: 6 | G36: 1 | H36: -2 | I36: -12 | J36: 0 | K36: -7 | L36: 1 | M36: 2 | N36: -2 | O36: 1 | W36: -3 | X36: -7 | Y36: -4 | Z36: =SUM(N36:O36,P36:Q36) -> -1 | AA36: =SUM(R36:U36) -> 0 | AC36: reported adjusted EBITDA less the stack identity; nil in the forecast
A37: Adjusted EBITDA | B37: =B7-B32+B35+B36 -> 262 | C37: =C7-C32+C35+C36 -> 819 | D37: =D7-D32+D35+D36 -> 1834 | E37: =E7-E32+E35+E36 -> 738 | F37: =F7-F32+F35+F36 -> 424 | G37: =G7-G32+G35+G36 -> 894 | H37: =H7-H32+H35+H36 -> 1958 | I37: =I7-I32+I35+I36 -> 765 | ... O37: =O7-O32+O35+O36 -> 1261 | P37: =P7-P32+P35 -> 2419.6425 | Q37: =Q7-Q32+Q35 -> 898.87164 | R37: =R7-R32+R35 -> 556.05077 | S37: =S7-S32+S35 -> 1373.8338 | T37: =T7-T32+T35 -> 2744.0252 | U37: =U7-U32+U35 -> 970.29451 | W37: =W7-W32+W35+IF(ISNUMBER(W36),W36,0) -> 3653 | X37: =X7-X32+X35+IF(ISNUMBER(X36),X36,0) -> 4041 | Y37: =Y7-Y32+Y35+IF(ISNUMBER(Y36),Y36,0) -> 4297 | Z37: =Z7-Z32+Z35+IF(ISNUMBER(Z36),Z36,0) -> 5098.5141 | AA37: =AA7-AA32+AA35+IF(ISNUMBER(AA36),AA36,0) -> 5644.2042
A38: Adjusted EBITDA margin | B38: =IFERROR(B37/B7,"") -> 0.14411441 | C38: =IFERROR(C37/C7,"") -> 0.32971014 | D38: =IFERROR(D37/D7,"") -> 0.53988814 | E38: =IFERROR(E37/E7,"") -> 0.33273219 | F38: =IFERROR(F37/F7,"") -> 0.19794585 | G38: =IFERROR(G37/G7,"") -> 0.32532751 | H38: =IFERROR(H37/H7,"") -> 0.52465166 | I38: =IFERROR(I37/I7,"") -> 0.30846774 | ... U38: =IFERROR(U37/U7,"") -> 0.27996554 | W38: =IFERROR(W37/W7,"") -> 0.36835737 | X38: =IFERROR(X37/X7,"") -> 0.36398847 | Y38: =IFERROR(Y37/Y7,"") -> 0.35103341 | Z38: =IFERROR(Z37/Z7,"") -> 0.3573355 | AA38: =IFERROR(AA37/AA7,"") -> 0.35658251
A39: Adjusted EBITDA y/y | F39: =IFERROR(F37/B37-1,"") -> 0.61832061 | G39: =IFERROR(G37/C37-1,"") -> 0.091575092 | H39: =IFERROR(H37/D37-1,"") -> 0.067611778 | I39: =IFERROR(I37/E37-1,"") -> 0.036585366 | J39: =IFERROR(J37/F37-1,"") -> -0.016509434 | K39: =IFERROR(K37/G37-1,"") -> 0.16666667 | L39: =IFERROR(L37/H37-1,"") -> 0.047497446 | M39: =IFERROR(M37/I37-1,"") -> 0.02745098 | ... U39: =IFERROR(U37/Q37-1,"") -> 0.079458364 | X39: =IFERROR(X37/W37-1,"") -> 0.10621407 | Y39: =IFERROR(Y37/X37-1,"") -> 0.063350656 | Z39: =IFERROR(Z37/Y37-1,"") -> 0.18652877 | AA39: =IFERROR(AA37/Z37-1,"") -> 0.10702924
A40: Incremental margin y/y (d EBITDA / d revenue) | F40: =IFERROR((F37-B37)/(F7-B7),"") -> 0.5 | G40: =IFERROR((G37-C37)/(G7-C7),"") -> 0.28409091 | H40: =IFERROR((H37-D37)/(H7-D7),"") -> 0.37014925 | I40: =IFERROR((I37-E37)/(I7-E7),"") -> 0.10305344 | J40: =IFERROR((J37-F37)/(J7-F7),"") -> -0.053846154 | K40: =IFERROR((K37-G37)/(K7-G7),"") -> 0.42816092 | L40: =IFERROR((L37-H37)/(L7-H7),"") -> 0.25619835 | M40: =IFERROR((M37-I37)/(M7-I7),"") -> 0.070469799 | ... U40: =IFERROR((U37-Q37)/(U7-Q7),"") -> 0.24829239 | X40: =IFERROR((X37-W37)/(X7-W7),"") -> 0.32742616 | Y40: =IFERROR((Y37-X37)/(Y7-X7),"") -> 0.22475856 | Z40: =IFERROR((Z37-Y37)/(Z7-Y7),"") -> 0.39539096 | AA40: =IFERROR((AA37-Z37)/(AA7-Z7),"") -> 0.34969749 | AC40: Street-implied FY27 incremental margin is 43.7%; the line build's is 34.8%, the run's 24.7%
A41: Stock-based compensation (below adjusted EBITDA) | B41: 240 | C41: 304 | D41: 286 | E41: 290 | F41: 295 | G41: 382 | H41: 362 | I41: 368 | J41: 358 | K41: 424 | L41: 399 | M41: 411 | N41: 410 | O41: 487 | P41: =INDEX('Scenario Data'!$D$5:$I$345,MATCH('Income Statement'!$G$3&"|sbc",'Scenario Data'!$A$5:$A$345,0),MATCH(P$4,'Scenario Data'!$D$4:$I$4,0)) -> 451.57919 | Q41: =INDEX('Scenario Data'!$D$5:$I$345,MATCH('Income Statement'!$G$3&"|sbc",'Scenario Data'!$A$5:$A$345,0),MATCH(Q$4,'Scenario Data'!$D$4:$I$4,0)) -> 465.16051 | R41: =INDEX('Scenario Data'!$D$5:$I$345,MATCH('Income Statement'!$G$3&"|sbc",'Scenario Data'!$A$5:$A$345,0),MATCH(R$4,'Scenario Data'!$D$4:$I$4,0)) -> 464.02874 | S41: =INDEX('Scenario Data'!$D$5:$I$345,MATCH('Income Statement'!$G$3&"|sbc",'Scenario Data'!$A$5:$A$345,0),MATCH(S$4,'Scenario Data'!$D$4:$I$4,0)) -> 551.1756 | T41: =INDEX('Scenario Data'!$D$5:$I$345,MATCH('Income Statement'!$G$3&"|sbc",'Scenario Data'!$A$5:$A$345,0),MATCH(T$4,'Scenario Data'!$D$4:$I$4,0)) -> 511.08712 | U41: =INDEX('Scenario Data'!$D$5:$I$345,MATCH('Income Statement'!$G$3&"|sbc",'Scenario Data'!$A$5:$A$345,0),MATCH(U$4,'Scenario Data'!$D$4:$I$4,0)) -> 526.45816 | W41: 1120 | X41: 1407 | Y41: 1592 | Z41: =SUM(N41:O41,P41:Q41) -> 1813.7397 | AA41: =SUM(R41:U41) -> 2052.7496 | AC41: +13.2% y/y on the year-ago quarter (M7); management: SBC growth below FY25's +13%
A42: % of revenue | B42: =IFERROR(B41/B7,"") -> 0.1320132 | C42: =IFERROR(C41/C7,"") -> 0.12238325 | D42: =IFERROR(D41/D7,"") -> 0.084191934 | E42: =IFERROR(E41/E7,"") -> 0.13074842 | F42: =IFERROR(F41/F7,"") -> 0.13772176 | G42: =IFERROR(G41/G7,"") -> 0.13901019 | H42: =IFERROR(H41/H7,"") -> 0.096998928 | I42: =IFERROR(I41/I7,"") -> 0.1483871 | ... U42: =IFERROR(U41/U7,"") -> 0.15190248 | W42: =IFERROR(W41/W7,"") -> 0.11293738 | X42: =IFERROR(X41/X7,"") -> 0.12673392 | Y42: =IFERROR(Y41/Y7,"") -> 0.13005473 | Z42: =IFERROR(Z41/Z7,"") -> 0.12711813 | AA42: =IFERROR(AA41/AA7,"") -> 0.12968606
A44: 2. Adjusted EBITDA and margin: line build vs the calibrated run vs Street vs the short case | B44: LSEG 11 Sep 2026; run = 23_final_model (backtested combination); line build = 40_line_build (composition); short = pitch
A45: Adj. EBITDA ($m) / margin | B45: 3Q26 | C45: 4Q26 | D45: FY26 | E45: FY27 | F45: FY28 (roll)
A46: EBITDA: Street (LSEG mean) | B46: 2361.5218 | C46: 913.68388 | D46: 5053.7221 | E46: 5766.0992 | F46: 6602.7173
A47: EBITDA: line build base (this workbook's IS) | B47: 2419.6425 | C47: 898.87164 | D47: 5098.5141 | E47: 5644.2042 | F47: 6110.9117
A48: EBITDA: calibrated run (backtested; the 5 Nov card object) | B48: 2399.1324 | C48: 918.3917 | D48: 5097.5241 | E48: 5483.3298 | F48: 5936.7348
A49: EBITDA: short case (pitch, costs at budget) | B49: 2289.8152 | C49: 699.60784 | D49: 4769.4231 | E49: 4761.4354
A50: Margin: Street | B50: 0.49775747 | C50: 0.28897437 | D50: 0.35615785 | E50: 0.36449684 | F50: 0.37654299
A51: Margin: line build base | B51: 0.50366874 | C51: 0.28283233 | D51: 0.3573355 | E51: 0.35658251 | F51: 0.35658251
A52: Margin: calibrated run | B52: 0.49939939 | C52: 0.28897437 | D52: 0.35726611 | E52: 0.34641898 | F52: 0.34641898
A53: Margin: short case | B53: 0.48918268 | C53: 0.2358864 | D53: 0.34231699 | E53: 0.3192699
A54: EPS: Street | B54: 2.84539 | C54: 0.86154 | D54: 5.31259 | E54: 6.22753 | F54: 7.51977
A55: EPS: line build base | B55: 2.9071599 | C55: 0.7625519 | D55: 5.276011 | E55: 5.9331363 | F55: 6.4237349
A56: EPS: calibrated run | D56: 5.2808869 | E56: 5.7301115 | F56: 6.2685428
A57: EPS: short case | B57: 2.7144969 | C57: 0.47084354 | E57: 4.5839264
A58: Line build base vs Street, EBITDA ($m) | B58: =B47-B46 -> 58.12071 | C58: =C47-C46 -> -14.812239 | D58: =D47-D46 -> 44.792001 | E58: =E47-E46 -> -121.89493 | F58: =F47-F46 -> -491.80566
A59: Short case vs Street, EBITDA ($m) | B59: =IF(ISNUMBER(B49),B49-B46,"") -> -71.706562 | C59: =IF(ISNUMBER(C49),C49-C46,"") -> -214.07604 | D59: =IF(ISNUMBER(D49),D49-D46,"") -> -284.29907 | E59: =IF(ISNUMBER(E49),E49-E46,"") -> -1004.6638 | F59: =IF(ISNUMBER(F49),F49-F46,"")
A60: FY28 in the line build is the FY27 margin rolled flat, not a forecast. The run's FY27 (34.6%) and the line build's FY27 (35.7%) differ by one point, all in S&M: the run carried the 1H26 marketing growth rate forward, the line build applies management's stated deceleration to a base that already includes the 3Q26 step. Both sit below the Street's 36.5%, which needs the marketing ramp to stop (43.7% incremental margin).
A62: 3. 3Q26: management's 'margin down slightly' sentence used as the cost budget
A63: 3Q25 actual margin | B63: 0.5009
A64: 'down slightly' target used (3Q25 - 0.5pt) | B64: 49.59
A65: evidence-only build: 3Q26 margin | B65: 0.52393499
A66: evidence-only build: 3Q26 total cash cost growth y/y % | B66: 0.11427677
A67: reconciled base: 3Q26 margin at the GUIDE midpoint revenue (by construction = target) | B67: 0.4959
A68: reconciled base: 3Q26 margin at OUR revenue ($4,804M; the forecast) | B68: 0.50366874
A69: reconciled base: 3Q26 total cash cost growth y/y % | B69: 0.16128777
A70: reconciled base: cost gap assigned in 3Q26, USD m | B70: 97.359775
A71: 2H26 marketing growth % that lands the sentence AT OUR revenue with no hosting step (evidence build) | B71: 0.60628499
A72: 3Q26 S&M at that growth, USD m | B72: 844.84504
A73: 3Q26 S&M y/y % at that growth | B73: 0.44417956
A74: 3Q26 total cash cost growth y/y % at that growth | B74: 0.17930868
A75: FY26 margin at that growth | B75: 0.34669033
A76: Built from the evidence alone, 3Q26 costs grow 11.5% against revenue +17% and the margin would be 52.4%, contradicting the sentence. The base takes management at its word and adds $97M of cost to 3Q26 (70% marketing as a timing step, 30% hosting as a run-rate step). The quarterly sentence has not been sandbagged: the realised gap averaged -0.19pp, above the sentence in 4 of 10 quarters. The 5 Nov 10-Q S&M split (brand vs performance) is what settles whether the ramp is a fixed commitment or a dial.
A78: 4. The 5 November margin card (calibrated run, audited; the object with the backtest record)
A79: Item | B79: Value | C79: Unit | D79: 80% band | E79: Versus | F79: Note
A80: 3Q26 adj EBITDA margin | B80: 0.49939939 | C80: % | D80: 47.86 - 52.02 | E80: Street 49.78% | F80: combination stack_clip, h=0; bias-corrected on the last 5 PIT errors -> 50.21%, which the 'down slightly' sentence caps at 50.09%
A81: 3Q26 adj EBITDA | B81: 2399.1324 | C81: USD m | D81: 2337 - 2462 | E81: Street 2362 (n 36, EBITDA sd 20.0) | F81: final-margin|combined_dollar_from_margin (the margin combination x bridge-v3 revenue 4,804), band = its OWN conformal qhat80 62.6 on the 2024Q1+ calibration; W1/W2 h=0 MAE 30.7 / 2
A82: 3Q26 beat vs Street, $ | B82: 37.610612 | C82: USD m | F82: M5 flow-through arithmetic: 0.464 x (4,804 - 4,744) + 16 = +$44M
A83: P(3Q26 adj EBITDA beats Street) | B83: 0.77940809 | C83: probability | F83: Gaussian, sd = qhat80/1.2816 = 48.8, on the SAME object as the band (WS31 audit 04). The previously published 0.77 mixed a band from the margin route with an sd from the four-membe
A84: P(3Q26 margin beats Street margin) | B84: 0.54028618 | C84: probability | F84: Gaussian on the margin object's own conformal sd; same caveat
A85: 3Q26 EPS (GAAP diluted) | B85: 2.8789064 | C85: USD | D85: 2.70 - 3.05 | E85: Street 2.85 | F85: M7 bridge, ETR 18.0%, 591.7m shares; $0.001386 of EPS per $M of EBITDA. Band is JOINT (WS31 audit 06): EBITDA conformal term and M7's measured bridge sd $0.083 in quadrature, not E
A86: 4Q26 adj EBITDA margin | B86: 0.28897437 | C86: % | E86: Street 28.90% | F86: h=1 rule: the Street is unbeaten; combination 29.04%, M3 sentence path 29.90%
A87: FY26 adj EBITDA margin | B87: 0.35726611 | C87: % | E87: floor 35.5%, Street 35.62% | F87: 1H26 actual + 3Q26 combination + 4Q26 Street, on bridge v3 revenue
A88: FY26 adj EBITDA | B88: 5097.5241 | C88: USD m | E88: Street 5,053.7
A89: 5 Nov FY26 margin sentence (forecast) | B89: 0.36 | C89: % | F89: M3: the November sentence has been the numeric floor + 50bp, exact 2 of 2; p ~0.45-0.50. 'Approximately 36%'
A90: 4Q26 margin implied by the 36.0% sentence at our 3Q26 | B90: 0.30124819 | C90: % | E90: Street 28.90% | F90: M3 budget identity: 1pp of FY26 = 4.49pp of 4Q26; 1pp of 3Q26 = -1.51pp of 4Q26
A91: FY27 adj EBITDA margin (SCENARIO) | B91: 0.34641898 | C91: % | E91: Street 36.45% | F91: h>=2 fails its test; this is a spending scenario, not a forecast
A92: The beat is dollars, not points: the team's revenue is $60M above the Street's; at the Street's own revenue the margin view is worth about $8M (P(margin beats) 0.54). Backtest: at h=0 the combination's MAE is 0.50x/0.40x the seasonal naive and 0.71x/0.60x the Street (W1 n 14 / W2 n 10); at h=1 it loses to the raw Street, so 4Q26 is quoted from the Street. The pool was chosen after seeing the scoreboard; 5 Nov is the first true out-of-sample observation.
A94: 5. What the FY26 margin sentence should look like on 5 Nov, and what it forces on 4Q26
A95: FY | B95: Call | C95: Guide date | D95: Type | E95: Guide level | F95: FY actual margin | G95: Cushion (actual - guide) | H95: Quote
A96: 2022 | B96: FEB | C96: 2022-02-15 | D96: point | E96: 0.26592123 | F96: 0.3456177 | G96: 0.079696475 | H96: we would expect Adjusted EBITDA margin to be directionally in-line with 2021
A97: 2022 | B97: MAY | C97: 2022-05-03 | D97: floor | E97: 0.26592123 | F97: 0.3456177 | G97: 0.079696475 | H97: We currently anticipate delivering modest Adjusted EBITDA margin expansion for the full-year 2022 relative to 2021
A98: 2022 | B98: AUG | C98: 2022-08-02 | D98: floor | E98: 0.26592123 | F98: 0.3456177 | G98: 0.079696475 | H98: We continue to forecast delivering Adjusted EBITDA margin expansion for the full-year 2022 relative to 2021
A99: 2023 | B99: FEB | C99: 2023-02-14 | D99: point | E99: 0.3456177 | F99: 0.36835737 | G99: 0.022739663 | H99: For the full year 2023, we expect to maintain the strong Adjusted EBITDA margin we delivered in 2022
A100: 2023 | B100: MAY | C100: 2023-05-09 | D100: point | E100: 0.3456177 | F100: 0.36835737 | G100: 0.022739663 | H100: We continue to anticipate a full year Adjusted EBITDA margin that is broadly in-line with full-year 2022
A101: 2023 | B101: AUG | C101: 2023-08-03 | D101: floor | E101: 0.3456177 | F101: 0.36835737 | G101: 0.022739663 | H101: For the full-year 2023, we expect an Adjusted EBITDA margin that is modestly higher than the full-year 2022
A102: 2023 | B102: NOV | C102: 2023-11-01 | D102: point | E102: 0.3606177 | F102: 0.36835737 | G102: 0.0077396629 | H102: we expect an Adjusted EBITDA margin for full-year 2023 that is approximately 150 bps higher than full-year 2022
A103: 2024 | B103: FEB | C103: 2024-02-13 | D103: floor | E103: 0.35 | F103: 0.36398847 | G103: 0.013988471 | H103: For the full-year 2024, we expect to maintain an Adjusted EBITDA Margin of at least 35%
A104: 2024 | B104: MAY | C104: 2024-05-08 | D104: floor | E104: 0.35 | F104: 0.36398847 | G104: 0.013988471 | H104: For the full-year 2024, consistent with our prior guidance, we expect to grow Adjusted EBITDA on a nominal basis and to
...

Sheet Operating Schedules
A1: Operating schedules: volume, unit economics, regional mix, the 2027 nights and ADR builds, FX, below-EBITDA items, parameters
A2: Forecast columns follow the scenario dropdown on the Income Statement tab where the line exists per scenario (green links); builds that exist only for the base path are shown as blue source values.
B4: 1Q23 | C4: 2Q23 | D4: 3Q23 | E4: 4Q23 | F4: 1Q24 | G4: 2Q24 | H4: 3Q24 | I4: 4Q24 | J4: 1Q25 | K4: 2Q25 | L4: 3Q25 | M4: 4Q25 | N4: 1Q26 | O4: 2Q26 | P4: 3Q26 | Q4: 4Q26 | R4: 1Q27 | S4: 2Q27 | T4: 3Q27 | U4: 4Q27
A5: Quarter | B5: 1Q23A | C5: 2Q23A | D5: 3Q23A | E5: 4Q23A | F5: 1Q24A | G5: 2Q24A | H5: 3Q24A | I5: 4Q24A | J5: 1Q25A | K5: 2Q25A | L5: 3Q25A | M5: 4Q25A | N5: 1Q26A | O5: 2Q26A | P5: 3Q26E | Q5: 4Q26E | R5: 1Q27E | S5: 2Q27E | T5: 3Q27E | U5: 4Q27E
A6: A. Volume and unit economics
A7: Nights & seats booked (m) | B7: 121.1 | C7: 115.1 | D7: 113.2 | E7: 98.8 | F7: 132.6 | G7: 125.1 | H7: 122.8 | I7: 111 | J7: 143.1 | K7: 134.4 | L7: 133.6 | M7: 121.9 | N7: 156.2 | O7: 148.3 | P7: =INDEX('Scenario Data'!$D$5:$I$345,MATCH('Income Statement'!$G$3&"|nights_m",'Scenario Data'!$A$5:$A$345,0),MATCH(P$4,'Scenario Data'!$D$4:$I$4,0)) -> 146.813 | Q7: =INDEX('Scenario Data'!$D$5:$I$345,MATCH('Income Statement'!$G$3&"|nights_m",'Scenario Data'!$A$5:$A$345,0),MATCH(Q$4,'Scenario Data'!$D$4:$I$4,0)) -> 131.7983 | R7: =INDEX('Scenario Data'!$D$5:$I$345,MATCH('Income Statement'!$G$3&"|nights_m",'Scenario Data'!$A$5:$A$345,0),MATCH(R$4,'Scenario Data'!$D$4:$I$4,0)) -> 169.0178 | S7: =INDEX('Scenario Data'!$D$5:$I$345,MATCH('Income Statement'!$G$3&"|nights_m",'Scenario Data'!$A$5:$A$345,0),MATCH(S$4,'Scenario Data'!$D$4:$I$4,0)) -> 157.1001 | T7: =INDEX('Scenario Data'!$D$5:$I$345,MATCH('Income Statement'!$G$3&"|nights_m",'Scenario Data'!$A$5:$A$345,0),MATCH(T$4,'Scenario Data'!$D$4:$I$4,0)) -> 155.958 | U7: =INDEX('Scenario Data'!$D$5:$I$345,MATCH('Income Statement'!$G$3&"|nights_m",'Scenario Data'!$A$5:$A$345,0),MATCH(U$4,'Scenario Data'!$D$4:$I$4,0)) -> 139.7655
A8: Bookings (m) | P8: =INDEX('Scenario Data'!$D$5:$I$345,MATCH('Income Statement'!$G$3&"|bookings_m",'Scenario Data'!$A$5:$A$345,0),MATCH(P$4,'Scenario Data'!$D$4:$I$4,0)) -> 40.22274 | Q8: =INDEX('Scenario Data'!$D$5:$I$345,MATCH('Income Statement'!$G$3&"|bookings_m",'Scenario Data'!$A$5:$A$345,0),MATCH(Q$4,'Scenario Data'!$D$4:$I$4,0)) -> 36.109123 | R8: =INDEX('Scenario Data'!$D$5:$I$345,MATCH('Income Statement'!$G$3&"|bookings_m",'Scenario Data'!$A$5:$A$345,0),MATCH(R$4,'Scenario Data'!$D$4:$I$4,0)) -> 46.949389 | S8: =INDEX('Scenario Data'!$D$5:$I$345,MATCH('Income Statement'!$G$3&"|bookings_m",'Scenario Data'!$A$5:$A$345,0),MATCH(S$4,'Scenario Data'!$D$4:$I$4,0)) -> 43.638917 | T8: =INDEX('Scenario Data'!$D$5:$I$345,MATCH('Income Statement'!$G$3&"|bookings_m",'Scenario Data'!$A$5:$A$345,0),MATCH(T$4,'Scenario Data'!$D$4:$I$4,0)) -> 43.321667 | U8: =INDEX('Scenario Data'!$D$5:$I$345,MATCH('Income Statement'!$G$3&"|bookings_m",'Scenario Data'!$A$5:$A$345,0),MATCH(U$4,'Scenario Data'!$D$4:$I$4,0)) -> 38.82375 | W8: nights / nights per booking (3.65 in 2026, 3.60 in 2027, continuing 3.9 / 3.8 / 3.7)
A9: Nights per booking | P9: =IFERROR(P7/P8,"") -> 3.65 | Q9: =IFERROR(Q7/Q8,"") -> 3.65 | R9: =IFERROR(R7/R8,"") -> 3.6 | S9: =IFERROR(S7/S8,"") -> 3.6 | T9: =IFERROR(T7/T8,"") -> 3.6 | U9: =IFERROR(U7/U8,"") -> 3.6
A10: Gross booking value ($bn) | B10: 20.4 | C10: 19.1 | D10: 18.3 | E10: 15.5 | F10: 22.9 | G10: 21.2 | H10: 20.1 | I10: 17.6 | J10: 24.5 | K10: 23.5 | L10: 22.9 | M10: 20.4 | N10: 29.2 | O10: 27.2 | P10: =INDEX('Scenario Data'!$D$5:$I$345,MATCH('Income Statement'!$G$3&"|gbv_busd",'Scenario Data'!$A$5:$A$345,0),MATCH(P$4,'Scenario Data'!$D$4:$I$4,0)) -> 26.028 | Q10: =INDEX('Scenario Data'!$D$5:$I$345,MATCH('Income Statement'!$G$3&"|gbv_busd",'Scenario Data'!$A$5:$A$345,0),MATCH(Q$4,'Scenario Data'!$D$4:$I$4,0)) -> 22.9873 | R10: =INDEX('Scenario Data'!$D$5:$I$345,MATCH('Income Statement'!$G$3&"|gbv_busd",'Scenario Data'!$A$5:$A$345,0),MATCH(R$4,'Scenario Data'!$D$4:$I$4,0)) -> 32.5996 | S10: =INDEX('Scenario Data'!$D$5:$I$345,MATCH('Income Statement'!$G$3&"|gbv_busd",'Scenario Data'!$A$5:$A$345,0),MATCH(S$4,'Scenario Data'!$D$4:$I$4,0)) -> 29.6479 | T10: =INDEX('Scenario Data'!$D$5:$I$345,MATCH('Income Statement'!$G$3&"|gbv_busd",'Scenario Data'!$A$5:$A$345,0),MATCH(T$4,'Scenario Data'!$D$4:$I$4,0)) -> 28.3908 | U10: =INDEX('Scenario Data'!$D$5:$I$345,MATCH('Income Statement'!$G$3&"|gbv_busd",'Scenario Data'!$A$5:$A$345,0),MATCH(U$4,'Scenario Data'!$D$4:$I$4,0)) -> 24.8342
A11: ADR ($) | B11: 168.43 | C11: 166.01 | D11: 161.38 | E11: 156.73 | F11: 172.88 | G11: 169.53 | H11: 163.64 | I11: 158.13 | J11: 171.34 | K11: 174.48 | L11: 171.29 | M11: 167.51 | N11: 186.82 | O11: 183.73 | P11: =IFERROR(P10*1000/P7,"") -> 177.28675 | Q11: =IFERROR(Q10*1000/Q7,"") -> 174.41272 | R11: =IFERROR(R10*1000/R7,"") -> 192.87673 | S11: =IFERROR(S10*1000/S7,"") -> 188.7198 | T11: =IFERROR(T10*1000/T7,"") -> 182.04132 | U11: =IFERROR(U10*1000/U7,"") -> 177.68476
A12: Revenue ($m) | B12: 1818 | C12: 2484 | D12: 3397 | E12: 2218 | F12: 2142 | G12: 2748 | H12: 3732 | I12: 2480 | J12: 2272 | K12: 3096 | L12: 4095 | M12: 2778 | N12: 2678 | O12: 3608 | P12: =INDEX('Scenario Data'!$D$5:$I$345,MATCH('Income Statement'!$G$3&"|revenue",'Scenario Data'!$A$5:$A$345,0),MATCH(P$4,'Scenario Data'!$D$4:$I$4,0)) -> 4804.0355 | Q12: =INDEX('Scenario Data'!$D$5:$I$345,MATCH('Income Statement'!$G$3&"|revenue",'Scenario Data'!$A$5:$A$345,0),MATCH(Q$4,'Scenario Data'!$D$4:$I$4,0)) -> 3178.1078 | R12: =INDEX('Scenario Data'!$D$5:$I$345,MATCH('Income Statement'!$G$3&"|revenue",'Scenario Data'!$A$5:$A$345,0),MATCH(R$4,'Scenario Data'!$D$4:$I$4,0)) -> 3053.1293 | S12: =INDEX('Scenario Data'!$D$5:$I$345,MATCH('Income Statement'!$G$3&"|revenue",'Scenario Data'!$A$5:$A$345,0),MATCH(S$4,'Scenario Data'!$D$4:$I$4,0)) -> 4028.9807 | T12: =INDEX('Scenario Data'!$D$5:$I$345,MATCH('Income Statement'!$G$3&"|revenue",'Scenario Data'!$A$5:$A$345,0),MATCH(T$4,'Scenario Data'!$D$4:$I$4,0)) -> 5280.7325 | U12: =INDEX('Scenario Data'!$D$5:$I$345,MATCH('Income Statement'!$G$3&"|revenue",'Scenario Data'!$A$5:$A$345,0),MATCH(U$4,'Scenario Data'!$D$4:$I$4,0)) -> 3465.7641
A13: Revenue per night ($) | B13: =B12/B7 -> 15.012386 | C13: =C12/C7 -> 21.581234 | D13: =D12/D7 -> 30.008834 | E13: =E12/E7 -> 22.449393 | F13: =F12/F7 -> 16.153846 | G13: =G12/G7 -> 21.966427 | H13: =H12/H7 -> 30.390879 | I13: =I12/I7 -> 22.342342 | ... U13: =U12/U7 -> 24.796993
A14: Take rate (revenue / GBV) | B14: =B12/(B10*1000) -> 0.089117647 | C14: =C12/(C10*1000) -> 0.13005236 | D14: =D12/(D10*1000) -> 0.18562842 | E14: =E12/(E10*1000) -> 0.14309677 | F14: =F12/(F10*1000) -> 0.093537118 | G14: =G12/(G10*1000) -> 0.12962264 | H14: =H12/(H10*1000) -> 0.18567164 | I14: =I12/(I10*1000) -> 0.14090909 | ... U14: =U12/(U10*1000) -> 0.1395561
A15: Cash cost per night ($) | B15: =1579/B7 -> 13.038811 | C15: =1659/C7 -> 14.413553 | D15: =1574/D7 -> 13.904594 | E15: =1493/E7 -> 15.111336 | F15: =1738/F7 -> 13.107089 | G15: =1869/G7 -> 14.940048 | H15: =1787/H7 -> 14.552117 | I15: =1725/I7 -> 15.540541 | J15: =1880/J7 -> 13.137666 | K15: =2067/K7 -> 15.379464 | L15: =2067/L7 -> 15.471557 | M15: =2017/M7 -> 16.546349 | N15: =2179/N7 -> 13.950064 | O15: =2365/O7 -> 15.947404 | P15: =INDEX('Scenario Data'!$D$5:$I$345,MATCH('Income Statement'!$G$3&"|total_cash_costs",'Scenario Data'!$A$5:$A$345,0),MATCH(P$4,'Scenario Data'!$D$4:$I$4,0))/P7 -> 16.381567 | Q15: =INDEX('Scenario Data'!$D$5:$I$345,MATCH('Income Statement'!$G$3&"|total_cash_costs",'Scenario Data'!$A$5:$A$345,0),MATCH(Q$4,'Scenario Data'!$D$4:$I$4,0))/Q7 -> 17.449923 | R15: =INDEX('Scenario Data'!$D$5:$I$345,MATCH('Income Statement'!$G$3&"|total_cash_costs",'Scenario Data'!$A$5:$A$345,0),MATCH(R$4,'Scenario Data'!$D$4:$I$4,0))/R7 -> 14.896138 | S15: =INDEX('Scenario Data'!$D$5:$I$345,MATCH('Income Statement'!$G$3&"|total_cash_costs",'Scenario Data'!$A$5:$A$345,0),MATCH(S$4,'Scenario Data'!$D$4:$I$4,0))/S7 -> 17.032331 | T15: =INDEX('Scenario Data'!$D$5:$I$345,MATCH('Income Statement'!$G$3&"|total_cash_costs",'Scenario Data'!$A$5:$A$345,0),MATCH(T$4,'Scenario Data'!$D$4:$I$4,0))/T7 -> 16.397628 | U15: =INDEX('Scenario Data'!$D$5:$I$345,MATCH('Income Statement'!$G$3&"|total_cash_costs",'Scenario Data'!$A$5:$A$345,0),MATCH(U$4,'Scenario Data'!$D$4:$I$4,0))/U7 -> 18.002322
A17: B. Revenue by region (10-Q geographic split; Q4 derived from the 10-K)
A18: North America ($m) | B18: 925 | C18: 1192 | D18: 1478 | E18: 1043 | F18: 1015 | G18: 1308 | H18: 1572 | I18: 1111 | J18: 1054 | K18: 1377 | L18: 1619 | M18: 1146 | N18: 1138 | O18: 1594
A19: EMEA ($m) | B19: 458 | C19: 941 | D19: 1533 | E19: 683 | F19: 567 | G19: 1048 | H19: 1726 | I19: 794 | J19: 597 | K19: 1233 | L19: 1969 | M19: 930 | N19: 747 | O19: 1425
A20: Latin America ($m) | B20: 235 | C20: 163 | D20: 178 | E20: 248 | F20: 307 | G20: 185 | H20: 199 | I20: 278 | J20: 343 | K20: 231 | L20: 235 | M20: 351 | N20: 451 | O20: 291
A21: Asia Pacific ($m) | B21: 200 | C21: 188 | D21: 208 | E21: 244 | F21: 253 | G21: 207 | H21: 235 | I21: 297 | J21: 278 | K21: 255 | L21: 272 | M21: 351 | N21: 342 | O21: 298
A22: North America share of revenue | B22: =IFERROR(B18/B12,"") -> 0.50880088 | C22: =IFERROR(C18/C12,"") -> 0.47987118 | D22: =IFERROR(D18/D12,"") -> 0.43508979 | E22: =IFERROR(E18/E12,"") -> 0.47024346 | F22: =IFERROR(F18/F12,"") -> 0.47385621 | G22: =IFERROR(G18/G12,"") -> 0.47598253 | H22: =IFERROR(H18/H12,"") -> 0.42122186 | I22: =IFERROR(I18/I12,"") -> 0.44798387 | ... O22: =IFERROR(O18/O12,"") -> 0.44179601
A23: EMEA share of revenue | B23: =IFERROR(B19/B12,"") -> 0.25192519 | C23: =IFERROR(C19/C12,"") -> 0.37882448 | D23: =IFERROR(D19/D12,"") -> 0.45128054 | E23: =IFERROR(E19/E12,"") -> 0.30793508 | F23: =IFERROR(F19/F12,"") -> 0.26470588 | G23: =IFERROR(G19/G12,"") -> 0.38136827 | H23: =IFERROR(H19/H12,"") -> 0.4624866 | I23: =IFERROR(I19/I12,"") -> 0.32016129 | ... O23: =IFERROR(O19/O12,"") -> 0.39495565
A24: Latin America share of revenue | B24: =IFERROR(B20/B12,"") -> 0.12926293 | C24: =IFERROR(C20/C12,"") -> 0.065619968 | D24: =IFERROR(D20/D12,"") -> 0.052399176 | E24: =IFERROR(E20/E12,"") -> 0.11181244 | F24: =IFERROR(F20/F12,"") -> 0.143324 | G24: =IFERROR(G20/G12,"") -> 0.067321689 | H24: =IFERROR(H20/H12,"") -> 0.053322615 | I24: =IFERROR(I20/I12,"") -> 0.11209677 | ... O24: =IFERROR(O20/O12,"") -> 0.080654102
A25: Asia Pacific share of revenue | B25: =IFERROR(B21/B12,"") -> 0.110011 | C25: =IFERROR(C21/C12,"") -> 0.07568438 | D25: =IFERROR(D21/D12,"") -> 0.061230497 | E25: =IFERROR(E21/E12,"") -> 0.11000902 | F25: =IFERROR(F21/F12,"") -> 0.11811391 | G25: =IFERROR(G21/G12,"") -> 0.075327511 | H25: =IFERROR(H21/H12,"") -> 0.062968917 | I25: =IFERROR(I21/I12,"") -> 0.11975806 | ... O25: =IFERROR(O21/O12,"") -> 0.082594235
A26: North America revenue y/y | F26: =IFERROR(F18/B18-1,"") -> 0.097297297 | G26: =IFERROR(G18/C18-1,"") -> 0.097315436 | H26: =IFERROR(H18/D18-1,"") -> 0.063599459 | I26: =IFERROR(I18/E18-1,"") -> 0.065196548 | J26: =IFERROR(J18/F18-1,"") -> 0.038423645 | K26: =IFERROR(K18/G18-1,"") -> 0.052752294 | L26: =IFERROR(L18/H18-1,"") -> 0.029898219 | M26: =IFERROR(M18/I18-1,"") -> 0.03150315 | ... O26: =IFERROR(O18/K18-1,"") -> 0.15758896
A27: EMEA revenue y/y | F27: =IFERROR(F19/B19-1,"") -> 0.23799127 | G27: =IFERROR(G19/C19-1,"") -> 0.11370882 | H27: =IFERROR(H19/D19-1,"") -> 0.12589693 | I27: =IFERROR(I19/E19-1,"") -> 0.1625183 | J27: =IFERROR(J19/F19-1,"") -> 0.052910053 | K27: =IFERROR(K19/G19-1,"") -> 0.17652672 | L27: =IFERROR(L19/H19-1,"") -> 0.14078795 | M27: =IFERROR(M19/I19-1,"") -> 0.17128463 | ... O27: =IFERROR(O19/K19-1,"") -> 0.15571776
A28: Latin America revenue y/y | F28: =IFERROR(F20/B20-1,"") -> 0.30638298 | G28: =IFERROR(G20/C20-1,"") -> 0.13496933 | H28: =IFERROR(H20/D20-1,"") -> 0.11797753 | I28: =IFERROR(I20/E20-1,"") -> 0.12096774 | J28: =IFERROR(J20/F20-1,"") -> 0.11726384 | K28: =IFERROR(K20/G20-1,"") -> 0.24864865 | L28: =IFERROR(L20/H20-1,"") -> 0.18090452 | M28: =IFERROR(M20/I20-1,"") -> 0.26258993 | ... O28: =IFERROR(O20/K20-1,"") -> 0.25974026
A29: Asia Pacific revenue y/y | F29: =IFERROR(F21/B21-1,"") -> 0.265 | G29: =IFERROR(G21/C21-1,"") -> 0.10106383 | H29: =IFERROR(H21/D21-1,"") -> 0.12980769 | I29: =IFERROR(I21/E21-1,"") -> 0.21721311 | J29: =IFERROR(J21/F21-1,"") -> 0.098814229 | K29: =IFERROR(K21/G21-1,"") -> 0.23188406 | L29: =IFERROR(L21/H21-1,"") -> 0.15744681 | M29: =IFERROR(M21/I21-1,"") -> 0.18181818 | ... O29: =IFERROR(O21/K21-1,"") -> 0.16862745
A30: Regional nights growth used by the 2026 build (WS10, re-based): NA +8% in 1H26 and +11% in 2H26; EMEA +5/+8/+6.5/+9.5%; LatAm +18-20%; APAC +14-18%. The pitch's lap thesis is NA-centred: the 4Q25-1Q26 bundle and the June-July World Cup flattered 1H26 NA nights. Revenue Model tab section 1 has the quarterly rows.
A32: C. The 2027 nights build (WS06 v2b, base): NA plus ex-NA less the laps
A33: NA share of prior-year nights | R33: 0.291 | S33: 0.291 | T33: 0.288 | U33: 0.282
A34: NA nights y/y | R34: 0.0231 | S34: 0.0231 | T34: 0.0231 | U34: 0.0231 | W34: PR #32 three-feature lap: NA +2.3% base (bear +1.3%, bull +4.7%)
A35: Ex-NA nights y/y, pre-lap (WS10) | R35: 0.10773 | S35: 0.10452 | T35: 0.10131 | U35: 0.0981
A36: NA contribution (pts) | R36: 0.00672 | S36: 0.00672 | T36: 0.00665 | U36: 0.00651
A37: Ex-NA contribution pre-lap (pts) | R37: 0.07638 | S37: 0.07411 | T37: 0.07213 | U37: 0.07043
A38: Ex-NA fee-cancellation lap (pts) | R38: -0.00742 | S38: -0.00742 | T38: -0.00742 | U38: -0.00742
A39: Ex-NA RNPL lap (pts) | R39: -0.00363 | S39: -0.00907 | T39: -0.00907 | U39: -0.00907
A40: Events (World Cup lap etc., pts) | R40: 0.01 | S40: -0.005 | T40: 0 | U40: 0
A41: Total nights y/y (base) | R41: 0.08206 | S41: 0.05934 | T41: 0.06229 | U41: 0.06045 | W41: = NA contribution + ex-NA contribution + laps + events
A43: D. The 2027 ADR build (WS06 v2b, base): ex-FX terms then FX
A44: Pricing residual (pts) | R44: 0.04372 | S44: 0.04016 | T44: 0.0375 | U44: 0.03551 | W44: the unobserved same-listing price term; ADR v3 rule = last quarter's residual, decaying
A45: K mechanics line (pts) | R45: 0.00345 | S45: 0.00311 | T45: 0.00138 | U45: -0.0015 | W45: fee-structure mechanics from ADR v3 workstream K
A46: Geographic mix (pts) | R46: -0.01428 | S46: -0.01428 | T46: -0.01428 | U46: -0.01428 | W46: faster growth in lower-ADR regions (LatAm/APAC) dilutes ADR
A47: Party size (pts) | R47: 0.00797 | S47: 0.00797 | T47: 0.00797 | U47: 0.00797
A48: Length of stay (pts) | R48: 0.00056 | S48: 0.00056 | T48: 0.00056 | U48: 0.00056
A49: New-business seats dilution (pts) | R49: -0.00565 | S49: -0.00565 | T49: -0.00565 | U49: -0.00565 | W49: Services/Experiences seats are counted in 'nights & seats' at a lower price
A50: Interaction (pts) | R50: -0.001 | S50: -0.001 | T50: -0.001 | U50: -0.001
A51: ADR y/y ex-FX | R51: 0.03478 | S51: 0.03087 | T51: 0.02648 | U51: 0.02161
A52: FX on ADR (pts, kernel) | R52: -0.00301 | S52: -0.00193 | T52: 0.00034 | U52: -0.00285
A53: ADR y/y reported | R53: 0.03176 | S53: 0.02894 | T53: 0.02682 | U53: 0.01876
A55: E. FX: EUR/USD paths and the fitted effects on ADR and revenue (WS05 kernel; three USD paths)
A56: Consensus FX path: EUR/USD average | L56: 1.17 | M56: 1.16 | N56: 1.17 | O56: 1.16 | P56: 1.15 | Q56: 1.16 | R56: 1.16 | S56: 1.17 | T56: 1.18 | U56: 1.18
A57: EUR/USD y/y | L57: 0.0636 | M57: 0.0913 | N57: 0.1111 | O57: 0.0256 | P57: -0.0156 | Q57: -0.0036 | R57: -0.0044 | S57: 0.0059 | T57: 0.0214 | U57: 0.0172
A58: FX effect on ADR (pts): fit (EUR) / actual where disclosed | L58: 0.027 | M58: 0.029 | N58: 0.05 | O58: 0.013 | P58: -0.0127 | Q58: -0.0073 | R58: -0.0077 | S58: -0.003 | T58: 0.004 | U58: 0.0021
A59: FX effect on revenue (pts): lagged fit / actual where disclosed | L59: 0 | M59: 0.01 | N59: 0.03 | O59: 0.04 | P59: 0.0219 | Q59: -0.0043 | R59: -0.0103 | S59: -0.008 | T59: -0.0061 | U59: -0.0007
A60: Strong-USD path: EUR/USD average | L60: 1.17 | M60: 1.16 | N60: 1.17 | O60: 1.16 | P60: 1.15 | Q60: 1.13 | R60: 1.1 | S60: 1.09 | T60: 1.09 | U60: 1.1
A61: EUR/USD y/y | L61: 0.0636 | M61: 0.0913 | N61: 0.1111 | O61: 0.0256 | P61: -0.0156 | Q61: -0.0293 | R61: -0.0599 | S61: -0.0629 | T61: -0.0525 | U61: -0.0265
A62: FX effect on ADR (pts): fit (EUR) / actual where disclosed | L62: 0.027 | M62: 0.029 | N62: 0.05 | O62: 0.013 | P62: -0.0127 | Q62: -0.0189 | R62: -0.0327 | S62: -0.0341 | T62: -0.0294 | U62: -0.0177
A63: FX effect on revenue (pts): lagged fit / actual where disclosed | L63: 0 | M63: 0.01 | N63: 0.03 | O63: 0.04 | P63: 0.0219 | Q63: -0.0043 | R63: -0.0156 | S63: -0.0248 | T63: -0.0318 | U63: -0.0302
A64: Weak-USD path: EUR/USD average | L64: 1.17 | M64: 1.16 | N64: 1.17 | O64: 1.16 | P64: 1.15 | Q64: 1.19 | R64: 1.21 | S64: 1.23 | T64: 1.24 | U64: 1.25
A65: EUR/USD y/y | L65: 0.0636 | M65: 0.0913 | N65: 0.1111 | O65: 0.0256 | P65: -0.0156 | Q65: 0.0222 | R65: 0.0341 | S65: 0.0574 | T65: 0.0779 | U65: 0.0504
A66: FX effect on ADR (pts): fit (EUR) / actual where disclosed | L66: 0.027 | M66: 0.029 | N66: 0.05 | O66: 0.013 | P66: -0.0127 | Q66: 0.0043 | R66: 0.0097 | S66: 0.0202 | T66: 0.0295 | U66: 0.0171
A67: FX effect on revenue (pts): lagged fit / actual where disclosed | L67: 0 | M67: 0.01 | N67: 0.03 | O67: 0.04 | P67: 0.0219 | Q67: -0.0043 | R67: -0.005 | S67: 0.0053 | T67: 0.0125 | U67: 0.0216
A68: Revenue FX lags ADR FX because revenue is recognised at check-in on bookings made one to two quarters earlier (fit: -0.64 + 0.41 x mean EUR/USD y/y at t-1, t-2; n 17, r 0.80). The base path in the Revenue Model uses management's ~3pt for 3Q26 and the kernel thereafter (+1.0, +0.9, +0.6, +0.3, +0.4pt); ADR FX uses the ADR v3 midpoint (EUR fit and regional baskets).
A70: F. Unit-cost drivers (follow the scenario dropdown)
A71: Merchant fee rate (% of GBV, quarterly) | P71: =INDEX('Scenario Data'!$D$5:$I$345,MATCH('Income Statement'!$G$3&"|merchant_fee_rate_q_pct",'Scenario Data'!$A$5:$A$345,0),MATCH(P$4,'Scenario Data'!$D$4:$I$4,0)) -> 0.017625754 | Q71: =INDEX('Scenario Data'!$D$5:$I$345,MATCH('Income Statement'!$G$3&"|merchant_fee_rate_q_pct",'Scenario Data'!$A$5:$A$345,0),MATCH(Q$4,'Scenario Data'!$D$4:$I$4,0)) -> 0.017591695 | R71: =INDEX('Scenario Data'!$D$5:$I$345,MATCH('Income Statement'!$G$3&"|merchant_fee_rate_q_pct",'Scenario Data'!$A$5:$A$345,0),MATCH(R$4,'Scenario Data'!$D$4:$I$4,0)) -> 0.015326743 | S71: =INDEX('Scenario Data'!$D$5:$I$345,MATCH('Income Statement'!$G$3&"|merchant_fee_rate_q_pct",'Scenario Data'!$A$5:$A$345,0),MATCH(S$4,'Scenario Data'!$D$4:$I$4,0)) -> 0.017796051 | T71: =INDEX('Scenario Data'!$D$5:$I$345,MATCH('Income Statement'!$G$3&"|merchant_fee_rate_q_pct",'Scenario Data'!$A$5:$A$345,0),MATCH(T$4,'Scenario Data'!$D$4:$I$4,0)) -> 0.017625754 | U71: =INDEX('Scenario Data'!$D$5:$I$345,MATCH('Income Statement'!$G$3&"|merchant_fee_rate_q_pct",'Scenario Data'!$A$5:$A$345,0),MATCH(U$4,'Scenario Data'!$D$4:$I$4,0)) -> 0.017591695 | W71: annual-equivalent 1.70% x seasonal factor; +1bp per point of non-NA revenue share
A72: Merchant / payment fees ($m) | P72: =INDEX('Scenario Data'!$D$5:$I$345,MATCH('Income Statement'!$G$3&"|cor_fees",'Scenario Data'!$A$5:$A$345,0),MATCH(P$4,'Scenario Data'!$D$4:$I$4,0)) -> 458.76313 | Q72: =INDEX('Scenario Data'!$D$5:$I$345,MATCH('Income Statement'!$G$3&"|cor_fees",'Scenario Data'!$A$5:$A$345,0),MATCH(Q$4,'Scenario Data'!$D$4:$I$4,0)) -> 404.38557 | R72: =INDEX('Scenario Data'!$D$5:$I$345,MATCH('Income Statement'!$G$3&"|cor_fees",'Scenario Data'!$A$5:$A$345,0),MATCH(R$4,'Scenario Data'!$D$4:$I$4,0)) -> 499.64569 | S72: =INDEX('Scenario Data'!$D$5:$I$345,MATCH('Income Statement'!$G$3&"|cor_fees",'Scenario Data'!$A$5:$A$345,0),MATCH(S$4,'Scenario Data'!$D$4:$I$4,0)) -> 527.61555 | T72: =INDEX('Scenario Data'!$D$5:$I$345,MATCH('Income Statement'!$G$3&"|cor_fees",'Scenario Data'!$A$5:$A$345,0),MATCH(T$4,'Scenario Data'!$D$4:$I$4,0)) -> 500.40927 | U72: =INDEX('Scenario Data'!$D$5:$I$345,MATCH('Income Statement'!$G$3&"|cor_fees",'Scenario Data'!$A$5:$A$345,0),MATCH(U$4,'Scenario Data'!$D$4:$I$4,0)) -> 436.87567
A73: Chargebacks ($m) | P73: =INDEX('Scenario Data'!$D$5:$I$345,MATCH('Income Statement'!$G$3&"|cor_chargebacks",'Scenario Data'!$A$5:$A$345,0),MATCH(P$4,'Scenario Data'!$D$4:$I$4,0)) -> 28.960373 | Q73: =INDEX('Scenario Data'!$D$5:$I$345,MATCH('Income Statement'!$G$3&"|cor_chargebacks",'Scenario Data'!$A$5:$A$345,0),MATCH(Q$4,'Scenario Data'!$D$4:$I$4,0)) -> 25.998569 | R73: =INDEX('Scenario Data'!$D$5:$I$345,MATCH('Income Statement'!$G$3&"|cor_chargebacks",'Scenario Data'!$A$5:$A$345,0),MATCH(R$4,'Scenario Data'!$D$4:$I$4,0)) -> 33.80356 | S73: =INDEX('Scenario Data'!$D$5:$I$345,MATCH('Income Statement'!$G$3&"|cor_chargebacks",'Scenario Data'!$A$5:$A$345,0),MATCH(S$4,'Scenario Data'!$D$4:$I$4,0)) -> 31.42002 | T73: =INDEX('Scenario Data'!$D$5:$I$345,MATCH('Income Statement'!$G$3&"|cor_chargebacks",'Scenario Data'!$A$5:$A$345,0),MATCH(T$4,'Scenario Data'!$D$4:$I$4,0)) -> 31.1916 | U73: =INDEX('Scenario Data'!$D$5:$I$345,MATCH('Income Statement'!$G$3&"|cor_chargebacks",'Scenario Data'!$A$5:$A$345,0),MATCH(U$4,'Scenario Data'!$D$4:$I$4,0)) -> 27.9531
A74: Chargebacks per booking ($) | P74: =IFERROR(P73/P8,"") -> 0.72 | Q74: =IFERROR(Q73/Q8,"") -> 0.72 | R74: =IFERROR(R73/R8,"") -> 0.72 | S74: =IFERROR(S73/S8,"") -> 0.72 | T74: =IFERROR(T73/T8,"") -> 0.72 | U74: =IFERROR(U73/U8,"") -> 0.72
A75: Hosting ($m) | P75: =INDEX('Scenario Data'!$D$5:$I$345,MATCH('Income Statement'!$G$3&"|cor_hosting",'Scenario Data'!$A$5:$A$345,0),MATCH(P$4,'Scenario Data'!$D$4:$I$4,0)) -> 100.20793 | Q75: =INDEX('Scenario Data'!$D$5:$I$345,MATCH('Income Statement'!$G$3&"|cor_hosting",'Scenario Data'!$A$5:$A$345,0),MATCH(Q$4,'Scenario Data'!$D$4:$I$4,0)) -> 100.20793 | R75: =INDEX('Scenario Data'!$D$5:$I$345,MATCH('Income Statement'!$G$3&"|cor_hosting",'Scenario Data'!$A$5:$A$345,0),MATCH(R$4,'Scenario Data'!$D$4:$I$4,0)) -> 111.70793 | S75: =INDEX('Scenario Data'!$D$5:$I$345,MATCH('Income Statement'!$G$3&"|cor_hosting",'Scenario Data'!$A$5:$A$345,0),MATCH(S$4,'Scenario Data'!$D$4:$I$4,0)) -> 111.70793 | T75: =INDEX('Scenario Data'!$D$5:$I$345,MATCH('Income Statement'!$G$3&"|cor_hosting",'Scenario Data'!$A$5:$A$345,0),MATCH(T$4,'Scenario Data'!$D$4:$I$4,0)) -> 111.70793 | U75: =INDEX('Scenario Data'!$D$5:$I$345,MATCH('Income Statement'!$G$3&"|cor_hosting",'Scenario Data'!$A$5:$A$345,0),MATCH(U$4,'Scenario Data'!$D$4:$I$4,0)) -> 111.70793 | W75: $1.7bn of cloud commitments through 2031 (10-K); 'material increase in AI spend' (Mertz)
A76: Ops & support per booking ($) | P76: =INDEX('Scenario Data'!$D$5:$I$345,MATCH('Income Statement'!$G$3&"|ops_per_booking",'Scenario Data'!$A$5:$A$345,0),MATCH(P$4,'Scenario Data'!$D$4:$I$4,0)) -> 8.9860385 | Q76: =INDEX('Scenario Data'!$D$5:$I$345,MATCH('Income Statement'!$G$3&"|ops_per_booking",'Scenario Data'!$A$5:$A$345,0),MATCH(Q$4,'Scenario Data'!$D$4:$I$4,0)) -> 8.8145894 | R76: =INDEX('Scenario Data'!$D$5:$I$345,MATCH('Income Statement'!$G$3&"|ops_per_booking",'Scenario Data'!$A$5:$A$345,0),MATCH(R$4,'Scenario Data'!$D$4:$I$4,0)) -> 6.7963843 | S76: =INDEX('Scenario Data'!$D$5:$I$345,MATCH('Income Statement'!$G$3&"|ops_per_booking",'Scenario Data'!$A$5:$A$345,0),MATCH(S$4,'Scenario Data'!$D$4:$I$4,0)) -> 7.8133984 | T76: =INDEX('Scenario Data'!$D$5:$I$345,MATCH('Income Statement'!$G$3&"|ops_per_booking",'Scenario Data'!$A$5:$A$345,0),MATCH(T$4,'Scenario Data'!$D$4:$I$4,0)) -> 8.8121978 | U76: =INDEX('Scenario Data'!$D$5:$I$345,MATCH('Income Statement'!$G$3&"|ops_per_booking",'Scenario Data'!$A$5:$A$345,0),MATCH(U$4,'Scenario Data'!$D$4:$I$4,0)) -> 8.6561056 | W76: management: support cost per booking -10% (1Q26) and -16% (2Q26) y/y with AI; applies to ~22% of the line
A77: Brand + performance marketing ($m) | P77: =INDEX('Scenario Data'!$D$5:$I$345,MATCH('Income Statement'!$G$3&"|sm_marketing",'Scenario Data'!$A$5:$A$345,0),MATCH(P$4,'Scenario Data'!$D$4:$I$4,0)) -> 540.67059 | Q77: =INDEX('Scenario Data'!$D$5:$I$345,MATCH('Income Statement'!$G$3&"|sm_marketing",'Scenario Data'!$A$5:$A$345,0),MATCH(Q$4,'Scenario Data'!$D$4:$I$4,0)) -> 504.41875 | R77: =INDEX('Scenario Data'!$D$5:$I$345,MATCH('Income Statement'!$G$3&"|sm_marketing",'Scenario Data'!$A$5:$A$345,0),MATCH(R$4,'Scenario Data'!$D$4:$I$4,0)) -> 584.06976 | S77: =INDEX('Scenario Data'!$D$5:$I$345,MATCH('Income Statement'!$G$3&"|sm_marketing",'Scenario Data'!$A$5:$A$345,0),MATCH(S$4,'Scenario Data'!$D$4:$I$4,0)) -> 658.63186 | T77: =INDEX('Scenario Data'!$D$5:$I$345,MATCH('Income Statement'!$G$3&"|sm_marketing",'Scenario Data'!$A$5:$A$345,0),MATCH(T$4,'Scenario Data'!$D$4:$I$4,0)) -> 577.49075 | U77: =INDEX('Scenario Data'!$D$5:$I$345,MATCH('Income Statement'!$G$3&"|sm_marketing",'Scenario Data'!$A$5:$A$345,0),MATCH(U$4,'Scenario Data'!$D$4:$I$4,0)) -> 616.47747
A78: Marketing per night ($) | P78: =IFERROR(P77/P7,"") -> 3.6827161 | Q78: =IFERROR(Q77/Q7,"") -> 3.8272022 | R78: =IFERROR(R77/R7,"") -> 3.4556701 | S78: =IFERROR(S77/S7,"") -> 4.1924344 | T78: =IFERROR(T77/T7,"") -> 3.7028607 | U78: =IFERROR(U77/U7,"") -> 4.4107986
A79: Field operations & policy ($m) | P79: =INDEX('Scenario Data'!$D$5:$I$345,MATCH('Income Statement'!$G$3&"|sm_field",'Scenario Data'!$A$5:$A$345,0),MATCH(P$4,'Scenario Data'!$D$4:$I$4,0)) -> 237.64522 | Q79: =INDEX('Scenario Data'!$D$5:$I$345,MATCH('Income Statement'!$G$3&"|sm_field",'Scenario Data'!$A$5:$A$345,0),MATCH(Q$4,'Scenario Data'!$D$4:$I$4,0)) -> 253.68878 | R79: =INDEX('Scenario Data'!$D$5:$I$345,MATCH('Income Statement'!$G$3&"|sm_field",'Scenario Data'!$A$5:$A$345,0),MATCH(R$4,'Scenario Data'!$D$4:$I$4,0)) -> 245.20203 | S79: =INDEX('Scenario Data'!$D$5:$I$345,MATCH('Income Statement'!$G$3&"|sm_field",'Scenario Data'!$A$5:$A$345,0),MATCH(S$4,'Scenario Data'!$D$4:$I$4,0)) -> 276.50441 | T79: =INDEX('Scenario Data'!$D$5:$I$345,MATCH('Income Statement'!$G$3&"|sm_field",'Scenario Data'!$A$5:$A$345,0),MATCH(T$4,'Scenario Data'!$D$4:$I$4,0)) -> 242.44005 | U79: =INDEX('Scenario Data'!$D$5:$I$345,MATCH('Income Statement'!$G$3&"|sm_field",'Scenario Data'!$A$5:$A$345,0),MATCH(U$4,'Scenario Data'!$D$4:$I$4,0)) -> 258.80731
A81: G. Below adjusted EBITDA (M7 bridge conventions)
A82: Stock-based compensation ($m) | B82: 240 | C82: 304 | D82: 286 | E82: 290 | F82: 295 | G82: 382 | H82: 362 | I82: 368 | J82: 358 | K82: 424 | L82: 399 | M82: 411 | N82: 410 | O82: 487 | P82: =INDEX('Scenario Data'!$D$5:$I$345,MATCH('Income Statement'!$G$3&"|sbc",'Scenario Data'!$A$5:$A$345,0),MATCH(P$4,'Scenario Data'!$D$4:$I$4,0)) -> 451.57919 | Q82: =INDEX('Scenario Data'!$D$5:$I$345,MATCH('Income Statement'!$G$3&"|sbc",'Scenario Data'!$A$5:$A$345,0),MATCH(Q$4,'Scenario Data'!$D$4:$I$4,0)) -> 465.16051 | R82: =INDEX('Scenario Data'!$D$5:$I$345,MATCH('Income Statement'!$G$3&"|sbc",'Scenario Data'!$A$5:$A$345,0),MATCH(R$4,'Scenario Data'!$D$4:$I$4,0)) -> 464.02874 | S82: =INDEX('Scenario Data'!$D$5:$I$345,MATCH('Income Statement'!$G$3&"|sbc",'Scenario Data'!$A$5:$A$345,0),MATCH(S$4,'Scenario Data'!$D$4:$I$4,0)) -> 551.1756 | T82: =INDEX('Scenario Data'!$D$5:$I$345,MATCH('Income Statement'!$G$3&"|sbc",'Scenario Data'!$A$5:$A$345,0),MATCH(T$4,'Scenario Data'!$D$4:$I$4,0)) -> 511.08712 | U82: =INDEX('Scenario Data'!$D$5:$I$345,MATCH('Income Statement'!$G$3&"|sbc",'Scenario Data'!$A$5:$A$345,0),MATCH(U$4,'Scenario Data'!$D$4:$I$4,0)) -> 526.45816 | W82: +13.2% y/y on the year-ago quarter
A83: D&A ($m) | B83: 11 | C83: 9 | D83: 8 | E83: 16 | F83: 14 | G83: 14 | H83: 15 | I83: 22 | J83: 25 | K83: 21 | L83: 22 | M83: 23 | N83: 22 | O83: 17 | P83: =INDEX('Scenario Data'!$D$5:$I$345,MATCH('Income Statement'!$G$3&"|da",'Scenario Data'!$A$5:$A$345,0),MATCH(P$4,'Scenario Data'!$D$4:$I$4,0)) -> 20.633971 | Q83: =INDEX('Scenario Data'!$D$5:$I$345,MATCH('Income Statement'!$G$3&"|da",'Scenario Data'!$A$5:$A$345,0),MATCH(Q$4,'Scenario Data'!$D$4:$I$4,0)) -> 20.633971 | R83: =INDEX('Scenario Data'!$D$5:$I$345,MATCH('Income Statement'!$G$3&"|da",'Scenario Data'!$A$5:$A$345,0),MATCH(R$4,'Scenario Data'!$D$4:$I$4,0)) -> 20.633971 | S83: =INDEX('Scenario Data'!$D$5:$I$345,MATCH('Income Statement'!$G$3&"|da",'Scenario Data'!$A$5:$A$345,0),MATCH(S$4,'Scenario Data'!$D$4:$I$4,0)) -> 20.633971 | T83: =INDEX('Scenario Data'!$D$5:$I$345,MATCH('Income Statement'!$G$3&"|da",'Scenario Data'!$A$5:$A$345,0),MATCH(T$4,'Scenario Data'!$D$4:$I$4,0)) -> 20.633971 | U83: =INDEX('Scenario Data'!$D$5:$I$345,MATCH('Income Statement'!$G$3&"|da",'Scenario Data'!$A$5:$A$345,0),MATCH(U$4,'Scenario Data'!$D$4:$I$4,0)) -> 20.633971 | W83: $20.6M per quarter
A84: Interest income ($m) | B84: 146 | C84: 191 | D84: 192 | E84: 192 | F84: 202 | G84: 226 | H84: 207 | I84: 183 | J84: 173 | K84: 190 | L84: 180 | M84: 162 | N84: 155 | O84: 183 | P84: =INDEX('Scenario Data'!$D$5:$I$345,MATCH('Income Statement'!$G$3&"|interest_income",'Scenario Data'!$A$5:$A$345,0),MATCH(P$4,'Scenario Data'!$D$4:$I$4,0)) -> 183.54893 | Q84: =INDEX('Scenario Data'!$D$5:$I$345,MATCH('Income Statement'!$G$3&"|interest_income",'Scenario Data'!$A$5:$A$345,0),MATCH(Q$4,'Scenario Data'!$D$4:$I$4,0)) -> 165.49547 | R84: =INDEX('Scenario Data'!$D$5:$I$345,MATCH('Income Statement'!$G$3&"|interest_income",'Scenario Data'!$A$5:$A$345,0),MATCH(R$4,'Scenario Data'!$D$4:$I$4,0)) -> 180.26226 | S84: =INDEX('Scenario Data'!$D$5:$I$345,MATCH('Income Statement'!$G$3&"|interest_income",'Scenario Data'!$A$5:$A$345,0),MATCH(S$4,'Scenario Data'!$D$4:$I$4,0)) -> 202.84769 | T84: =INDEX('Scenario Data'!$D$5:$I$345,MATCH('Income Statement'!$G$3&"|interest_income",'Scenario Data'!$A$5:$A$345,0),MATCH(T$4,'Scenario Data'!$D$4:$I$4,0)) -> 191.14509 | U84: =INDEX('Scenario Data'!$D$5:$I$345,MATCH('Income Statement'!$G$3&"|interest_income",'Scenario Data'!$A$5:$A$345,0),MATCH(U$4,'Scenario Data'!$D$4:$I$4,0)) -> 171.15508 | W84: rule: 0.876 x 3m T-bill (3.76% held) x average earning base (cash + STI $12.1bn + funds held, previous quarter) / 4; reproduces 2Q26 $183M. Short case: funds held -10%
A85: Interest expense ($m) | B85: 4 | C85: 2 | D85: 6 | E85: 71 | G85: 9 | H85: 2 | I85: 10 | J85: 5 | K85: 6 | L85: 6 | M85: 26 | N85: 21 | O85: 37 | P85: =INDEX('Scenario Data'!$D$5:$I$345,MATCH('Income Statement'!$G$3&"|interest_expense",'Scenario Data'!$A$5:$A$345,0),MATCH(P$4,'Scenario Data'!$D$4:$I$4,0)) -> 37 | Q85: =INDEX('Scenario Data'!$D$5:$I$345,MATCH('Income Statement'!$G$3&"|interest_expense",'Scenario Data'!$A$5:$A$345,0),MATCH(Q$4,'Scenario Data'!$D$4:$I$4,0)) -> 37 | R85: =INDEX('Scenario Data'!$D$5:$I$345,MATCH('Income Statement'!$G$3&"|interest_expense",'Scenario Data'!$A$5:$A$345,0),MATCH(R$4,'Scenario Data'!$D$4:$I$4,0)) -> 37 | S85: =INDEX('Scenario Data'!$D$5:$I$345,MATCH('Income Statement'!$G$3&"|interest_expense",'Scenario Data'!$A$5:$A$345,0),MATCH(S$4,'Scenario Data'!$D$4:$I$4,0)) -> 37 | T85: =INDEX('Scenario Data'!$D$5:$I$345,MATCH('Income Statement'!$G$3&"|interest_expense",'Scenario Data'!$A$5:$A$345,0),MATCH(T$4,'Scenario Data'!$D$4:$I$4,0)) -> 37 | U85: =INDEX('Scenario Data'!$D$5:$I$345,MATCH('Income Statement'!$G$3&"|interest_expense",'Scenario Data'!$A$5:$A$345,0),MATCH(U$4,'Scenario Data'!$D$4:$I$4,0)) -> 37 | W85: $37M per quarter on the $2.5bn 2026 senior notes
A86: Effective tax rate | B86: =IFERROR(13.4/130,"") -> 0.10307692 | C86: =IFERROR(26/676,"") -> 0.038461538 | D86: =IFERROR(-2695/1679,"") -> -1.6051221 | E86: =IFERROR(-34/-383,"") -> 0.088772846 | F86: =IFERROR(29/293,"") -> 0.098976109 | G86: =IFERROR(126/681,"") -> 0.18502203 | H86: =IFERROR(367/1735,"") -> 0.21152738 | I86: =IFERROR(161/622,"") -> 0.25884244 | J86: =IFERROR(19/173,"") -> 0.10982659 | K86: =IFERROR(137/779,"") -> 0.1758665 | L86: =IFERROR(418/1792,"") -> 0.23325893 | M86: =IFERROR(52/393,"") -> 0.13231552 | N86: =IFERROR(121/281,"") -> 0.43060498 | O86: =IFERROR(81/897,"") -> 0.090301003 | P86: =INDEX('Scenario Data'!$D$5:$I$345,MATCH('Income Statement'!$G$3&"|etr_pct",'Scenario Data'!$A$5:$A$345,0),MATCH(P$4,'Scenario Data'!$D$4:$I$4,0)) -> 0.18 | Q86: =INDEX('Scenario Data'!$D$5:$I$345,MATCH('Income Statement'!$G$3&"|etr_pct",'Scenario Data'!$A$5:$A$345,0),MATCH(Q$4,'Scenario Data'!$D$4:$I$4,0)) -> 0.18 | R86: =INDEX('Scenario Data'!$D$5:$I$345,MATCH('Income Statement'!$G$3&"|etr_pct",'Scenario Data'!$A$5:$A$345,0),MATCH(R$4,'Scenario Data'!$D$4:$I$4,0)) -> 0.175 | S86: =INDEX('Scenario Data'!$D$5:$I$345,MATCH('Income Statement'!$G$3&"|etr_pct",'Scenario Data'!$A$5:$A$345,0),MATCH(S$4,'Scenario Data'!$D$4:$I$4,0)) -> 0.175 | T86: =INDEX('Scenario Data'!$D$5:$I$345,MATCH('Income Statement'!$G$3&"|etr_pct",'Scenario Data'!$A$5:$A$345,0),MATCH(T$4,'Scenario Data'!$D$4:$I$4,0)) -> 0.175 | U86: =INDEX('Scenario Data'!$D$5:$I$345,MATCH('Income Statement'!$G$3&"|etr_pct",'Scenario Data'!$A$5:$A$345,0),MATCH(U$4,'Scenario Data'!$D$4:$I$4,0)) -> 0.175 | W86: 18.0% for 2H26 (1H26 printed 17.1%), 17.5% for FY27; management guides 'high teens'
A87: Diluted shares (m) | B87: 670 | C87: 665 | D87: 660 | E87: 640 | F87: 654 | G87: 649 | H87: 642 | I87: 636 | J87: 632 | K87: 626 | L87: 621 | M87: 614 | N87: 608 | O87: 597 | P87: =INDEX('Scenario Data'!$D$5:$I$345,MATCH('Income Statement'!$G$3&"|diluted_shares_m",'Scenario Data'!$A$5:$A$345,0),MATCH(P$4,'Scenario Data'!$D$4:$I$4,0)) -> 591.67581 | Q87: =INDEX('Scenario Data'!$D$5:$I$345,MATCH('Income Statement'!$G$3&"|diluted_shares_m",'Scenario Data'!$A$5:$A$345,0),MATCH(Q$4,'Scenario Data'!$D$4:$I$4,0)) -> 586.35163 | R87: =INDEX('Scenario Data'!$D$5:$I$345,MATCH('Income Statement'!$G$3&"|diluted_shares_m",'Scenario Data'!$A$5:$A$345,0),MATCH(R$4,'Scenario Data'!$D$4:$I$4,0)) -> 581.02744 | S87: =INDEX('Scenario Data'!$D$5:$I$345,MATCH('Income Statement'!$G$3&"|diluted_shares_m",'Scenario Data'!$A$5:$A$345,0),MATCH(S$4,'Scenario Data'!$D$4:$I$4,0)) -> 575.70325 | T87: =INDEX('Scenario Data'!$D$5:$I$345,MATCH('Income Statement'!$G$3&"|diluted_shares_m",'Scenario Data'!$A$5:$A$345,0),MATCH(T$4,'Scenario Data'!$D$4:$I$4,0)) -> 570.37907 | U87: =INDEX('Scenario Data'!$D$5:$I$345,MATCH('Income Statement'!$G$3&"|diluted_shares_m",'Scenario Data'!$A$5:$A$345,0),MATCH(U$4,'Scenario Data'!$D$4:$I$4,0)) -> 565.05488 | W87: -5.3M per quarter (the 2023-26 run rate of buybacks net of RSU issuance)
A88: Share repurchases ($m, history) | B88: 493 | C88: 507 | D88: 500 | E88: 752 | F88: 750 | G88: 749 | H88: 1093 | I88: 838 | J88: 807 | K88: 1010 | L88: 877 | M88: 1095 | N88: 1088 | O88: 1051 | W88: FY24 $3.4bn, FY25 $3.8bn, 1H26 $2.1bn; $3.4bn authorisation left (Aug 2026)
A89: Free cash flow ($m, history) | B89: 1581 | C89: 900 | D89: 1310 | E89: 46 | F89: 1909 | G89: 1043 | H89: 1074 | I89: 458 | J89: 1781 | K89: 962 | L89: 1349 | M89: 521 | N89: 1704 | O89: 1253 | W89: conversion above 100% of EBITDA is guest-float growth and interest income
A91: H. The line build's parameter sheet (40_params.csv): change a value there and re-run to regenerate
A92: Line | B92: Parameter | C92: Base | D92: Bear | E92: Bull | F92: Unit | G92: Source
A93: volume | B93: nights_per_booking_fy26 | C93: 3.65 | D93: 3.65 | E93: 3.65 | F93: nights per booking | G93: WS02 nights_per_booking_fy 3.9 (2023), 3.8 (2024), 3.7 (2025); trend continued
A94: volume | B94: nights_per_booking_fy27 | C94: 3.6 | D94: 3.6 | E94: 3.6 | F94: nights per booking | G94: same trend
A95: cor | B95: merchant_fee_pct_gbv | C95: 1.7 | D95: 1.76 | E95: 1.64 | F95: % of GBV, annual-equivalent rate | G95: FY24 1.69%, FY25 1.76% (cost of revenue less chargebacks, hosting, other per night; 07_cost_components payment processing $1,665M incl. $67M chargebacks); 1H26 fits 1.68% annual-equivalent after 'higher payment processor rebates and incentives' (1Q26 10-Q). Base 1.70 = rebates persist, do not widen.
A96: cor | B96: chargeback_per_booking | C96: 0.72 | D96: 0.85 | E96: 0.6 | F96: USD per booking | G96: FY25 $67M / 144M bookings = $0.47; 1H26 +$12M and +$13M y/y (10-Q MD&A) implies ~$0.72 on 1H26 bookings; held flat
A97: cor | B97: hosting_fy25 | C97: 224 | D97: 224 | E97: 224 | F97: USD m per year | G97: Run-rate of the $672M hosting commitment through 2027 in the FY24 10-K (~$224M a year); FY25 10-K re-cut to $1.7bn through 2031 (~$283M a year)
A98: cor | B98: hosting_step_2h26 | C98: 30 | D98: 45 | E98: 20 | F98: USD m per half vs 2H25 | G98: 1H26 server costs +$12M y/y (2Q26 10-Q) and reserved-instance amortisation +$12-15M (WS05 H14); Mertz 2Q26 'a material increase in AI spend' ramping in 2H
A99: cor | B99: hosting_fy27 | C99: 330 | D99: 400 | E99: 290 | F99: USD m per year | G99: Between the old run-rate ($224M) and the new commitment ($283M a year) plus the unsized AI inference ramp; WS05 H03 total purchase obligations ~$465M a year in 2027-28
A100: cor | B100: cor_other_per_night | C100: 0.36 | D100: 0.36 | E100: 0.36 | F100: USD per night | G100: FY25 residual: 2,086 - 1,598 fees - 67 chargebacks - 224 hosting = $197M on 533M nights (AirCover claims, payment operations)
A101: cor | B101: xborder_fee_bp_per_pt | C101: 1 | D101: 1 | E101: 1 | F101: bp of GBV per +1pt non-NA revenue share | G101: Cross-border card volume carries higher interchange and FX cost; non-NA share of revenue 2Q26 55.8% vs 55.5% 2Q25 (WS02). Small at current drift.
A102: ops | B102: ops_variable_share | C102: 0.215 | D102: 0.17 | E102: 0.27 | F102: share of the line that behaves like mgmt's 'support cost per booking' | G102: Calibrated on 1H26 with the rule itself: ops 1H26/1H25 = 624/591 = 1.056 = v x (1 - 0.13) x 1.112 (bookings) + (1 - v) x 1.08 -> v = 0.215; mgmt's metric fell -10% (1Q26) and -16% (2Q26). Consistent with the metric being third-party contact cost (13,000 contingent workers, FY25 10-K), not the whole line.
A103: ops | B103: ops_variable_decline_2h26 | C103: -14 | D103: -8 | E103: -18 | F103: % y/y per booking, 2H26 | G103: Support cost per booking -10% (1Q26 call), -16% (2Q26 call); >40% of issues resolved without an agent
A104: ops | B104: ops_variable_decline_fy27 | C104: -10 | D104: -4 | E104: -14 | F104: % y/y per booking, FY27 | G104: Chesky 4Q25/2Q26: 'continue to decline' as AI moves to voice; no number (31a: medium confidence)
... A138: below | B138: diluted_shares_delta_per_q | C138: -5.3241866 | D138: -5.3241866 | E138: -5.3241866 | F138: m per quarter | G138: M7: -buyback/price + issuance; authorisation runs out ~1Q27 (WS05 H11)
A140: Sources (paths relative to the repo root)
A141: Volume, unit costs, below-EBITDA forecast lines | B141: data/processed/margin_build/40_line_build/40_lines_quarterly.csv, 40_short_case_quarterly.csv, 40_params.csv
A142: Regional revenue | B142: data/processed/airbnb_regional_revenue_quarterly.csv (10-Q / 10-K)
...

Sheet 5 Nov & Street
A1: 5 November and the Street: where the team sits on every key item, the guide we expect, and what it implies for the stock
A2: Street = LSEG mean 11 Sep 2026 (revenue/EBITDA/EPS) and Bloomberg estimate distribution 5-12 Sep (nights/GBV/ADR). Team base = this workbook's base scenario. Short = the pitch case. Blue = source value, black = formula.
A4: 1. Key items: Street, team base, short case, management delivered
A5: Item | B5: Street | C5: n | D5: Team base | E5: Base vs Street | F5: Short (pitch) | G5: Short vs Street | H5: Mgmt delivered | I5: Notes
A6: 3Q26 (prints 5 Nov)
A7: Revenue ($m) | B7: 4744.3221 | C7: 37 | D7: 4804.0355 | E7: =IFERROR(D7/B7-1,"") -> 0.012586283 | F7: 4680.9 | G7: =IFERROR(F7/B7-1,"") -> -0.013368005 | I7: guide $4,690-4,770m; the base sits above the top end, as 15 of the last 19 prints did
A8: Nights & seats y/y | B8: 0.11527 | C8: 28 | D8: 0.0989 | E8: =IFERROR(D8-B8,"") -> -0.01637 | F8: 0.085 | G8: =IFERROR(F8-B8,"") -> -0.03027 | H8: 0.115 | I8: guide 'low double digits'; 2Q26 printed +10.3%. Every Street estimate is at or above 2Q26's rate; the team is below the lowest
A9: ADR y/y reported | B9: 0.03369 | C9: 26 | D9: 0.0343 | E9: =IFERROR(D9-B9,"") -> 0.00061 | F9: 0.0207 | G9: =IFERROR(F9-B9,"") -> -0.01299 | I9: ADR card v3 +3.9% ex-FX, FX -0.4pt
A10: GBV y/y | B10: 0.15215 | C10: 28 | D10: 0.136592 | E10: =IFERROR(D10-B10,"") -> -0.015558 | I10: guide 'mid teens'
A11: Adj. EBITDA ($m) | B11: 2361.5218 | C11: 36 | D11: 2419.6425 | E11: =IFERROR(D11/B11-1,"") -> 0.024611549 | F11: 2289.8152 | G11: =IFERROR(F11/B11-1,"") -> -0.030364556 | I11: calibrated run $2,399m, 80% band $2,337-2,462m, P(beat) 0.78; line build $2,420m
A12: Adj. EBITDA margin | B12: 0.49775747 | C12: 36 | D12: 0.50366874 | E12: =IFERROR(D12-B12,"") -> 0.0059112654 | F12: 0.48918268 | G12: =IFERROR(F12-B12,"") -> -0.0085747881 | I12: sentence 'down slightly' vs 50.1%; ceiling 50.085%; P(margin beats) 0.54
A13: Diluted EPS ($) | B13: 2.84539 | C13: 34 | D13: 2.9071599 | E13: =IFERROR(D13/B13-1,"") -> 0.021708758 | F13: 2.7144969 | G13: =IFERROR(F13/B13-1,"") -> -0.046001803 | I13: run $2.88 (band $2.70-3.05)
A14: 4Q26 (guided 5 Nov, prints Feb 2027)
A15: Revenue ($m) | B15: 3161.8163 | C15: 37 | D15: 3178.1078 | E15: =IFERROR(D15/B15-1,"") -> 0.0051525859 | F15: 2965.8677 | G15: =IFERROR(F15/B15-1,"") -> -0.061973428 | I15: the guide will sit below the print by the cushion (about 3.9% in Q4s): see section 2
A16: Nights & seats y/y | B16: 0.09926 | C16: 28 | D16: 0.0812 | E16: =IFERROR(D16-B16,"") -> -0.01806 | F16: 0.05 | G16: =IFERROR(F16-B16,"") -> -0.04926 | I16: ex-NA lap adopted (case B); NA-only lap would be +8.9%
A17: ADR y/y reported | B17: 0.0228 | C17: 25 | D17: 0.0422 | E17: =IFERROR(D17-B17,"") -> 0.0194 | F17: 0.0015 | G17: =IFERROR(F17-B17,"") -> -0.0213
A18: Adj. EBITDA ($m) | B18: 913.68388 | C18: 36 | D18: 898.87164 | E18: =IFERROR(D18/B18-1,"") -> -0.016211557 | F18: 699.60784 | G18: =IFERROR(F18/B18-1,"") -> -0.2342999 | I18: no h=1 edge: the run quotes the Street ($918m); line build $899m; short $700m at budget / $876m with the marketing cut
A19: Adj. EBITDA margin | B19: 0.28897437 | C19: 36 | D19: 0.28283233 | E19: =IFERROR(D19-B19,"") -> -0.0061420426 | F19: 0.2358864 | G19: =IFERROR(F19-B19,"") -> -0.053087978 | I19: 'approximately 36%' FY sentence at the run's 3Q26 implies 30.1%
A20: Diluted EPS ($) | B20: 0.86154 | C20: 34 | D20: 0.7625519 | E20: =IFERROR(D20/B20-1,"") -> -0.11489669 | F20: 0.47084354 | G20: =IFERROR(F20/B20-1,"") -> -0.45348615
A21: FY26
A22: Revenue ($m) | B22: 14189.557 | C22: 44 | D22: 14268.143 | E22: =IFERROR(D22/B22-1,"") -> 0.0055383159 | F22: 13932.768 | G22: =IFERROR(F22/B22-1,"") -> -0.018097068 | H22: 14231.303
A23: Adj. EBITDA ($m) | B23: 5053.7221 | C23: 44 | D23: 5098.5141 | E23: =IFERROR(D23/B23-1,"") -> 0.0088631706 | F23: 4769.4231 | G23: =IFERROR(F23/B23-1,"") -> -0.056255383 | H23: 5151.732 | I23: floor 'at least 35.5%' breaks on a 2H26 revenue miss of $50m held / $75m flexed
A24: Adj. EBITDA margin | B24: 0.35615785 | C24: 44 | D24: 0.3573355 | E24: =IFERROR(D24-B24,"") -> 0.0011776509 | F24: 0.34231699 | G24: =IFERROR(F24-B24,"") -> -0.013840862 | H24: 0.362 | I24: short case: 34.2% at budget (floor broken) or 35.5% with a $177m Q4 marketing cut
A25: Diluted EPS ($) | B25: 5.31259 | C25: 43 | D25: 5.276011 | E25: =IFERROR(D25/B25-1,"") -> -0.0068853453 | H25: 5.369
A26: FY27 (the trade)
A27: Revenue ($m) | B27: 15819.339 | C27: 44 | D27: 15828.607 | E27: =IFERROR(D27/B27-1,"") -> 0.00058582472 | F27: 14913.512 | G27: =IFERROR(F27/B27-1,"") -> -0.057260781 | H27: 16024.742 | I27: Street FY27 = management's delivered case; the price pays for $15.7-15.9bn
A28: Revenue growth | B28: 0.11485786 | C28: 44 | D28: 0.109367 | E28: =IFERROR(D28-B28,"") -> -0.0054908623 | F28: 0.070391172 | G28: =IFERROR(F28-B28,"") -> -0.04446669 | H28: 0.12602072
A29: Nights growth | D29: 0.06642 | F29: 0.03235336 | H29: 0.09999932 | I29: no direct Street nights consensus for FY27; the joint solve backs out +8 to +9% at the price
A30: Adj. EBITDA ($m) | B30: 5766.0992 | C30: 44 | D30: 5644.2042 | E30: =IFERROR(D30/B30-1,"") -> -0.02113993 | F30: 4761.4354 | G30: =IFERROR(F30/B30-1,"") -> -0.1742363 | H30: 5800.957 | I30: calibrated run $5,483m (34.6%, a spending scenario); Street needs a 43.7% incremental margin
A31: Adj. EBITDA margin | B31: 0.36449684 | C31: 44 | D31: 0.35658251 | E31: =IFERROR(D31-B31,"") -> -0.0079143327 | F31: 0.3192699 | G31: =IFERROR(F31-B31,"") -> -0.045226937 | H31: 0.362 | I31: S&M 19.4% (FY25) -> 21.3% (FY26) -> 21.9% (FY27) of revenue
A32: Diluted EPS ($) | B32: 6.22753 | C32: 43 | D32: 5.9331363 | E32: =IFERROR(D32/B32-1,"") -> -0.04727295 | F32: 4.5839264 | G32: =IFERROR(F32/B32-1,"") -> -0.26392544 | H32: 6.078
A34: 2. The 5 November sequence the model expects (links to the Revenue Model and Margins tabs)
A35: Item | B35: Base path | C35: Short path | D35: Street / prior | E35: Comment
A36: 3Q26 revenue print vs guide midpoint ($4,730m) | B36: ='Revenue Model'!P26/4730-1 -> 0.015652326 | C36: ='Revenue Model'!P48/4730-1 -> -0.01038055 | D36: 0.0125 | E36: prior: Q3 prints landed +1.3% above the midpoint on average
A37: 3Q26 nights y/y print | B37: ='Revenue Model'!P8 -> 0.098899701 | C37: ='Revenue Model'!P38 -> 0.085 | D37: 0.11527 | E37: Street bar +11.5%; a decelerating print vs 2Q26's +10.3% is the differentiated call
A38: 3Q26 adj. EBITDA margin | B38: =Margins!P38 -> 0.50366874 | C38: 0.48918268 | D38: 0.49775747 | E38: at or just under the 'down slightly' ceiling; the beat is dollars
A39: 4Q26 revenue guide midpoint we expect ($m) | B39: ='Revenue Model'!B101 -> 3059.403 | C39: ='Revenue Model'!B107 -> 2855.0902 | D39: 3161.8163 | E39: team revenue / (1 + historical Q4 cushion); Street column = LSEG 4Q26 revenue mean
A40: ... vs Street 4Q26 revenue | B40: =B39/D39-1 -> -0.032390657 | C40: =C39/D39-1 -> -0.097009461 | E40: the market prices the guide plus the cushion; a guide below the Street is the base case even on the team path
A41: 4Q26 nights guide direction | B41: decelerating ('high single digits') | C41: decelerating ('mid single digits') | D41: Street 4Q26 +9.9% | E41: management's bar has matched the Street's sign in 12 of 13 guided prints; this is a bet on the first downside miss of a nights guide
A42: FY26 margin sentence we expect | B42: approximately 36% | C42: at least 35.5% held (or floor at risk) | D42: in force: at least 35.5% | E42: M3: November sentence = August floor + 50bp, 2 of 2; p about 0.45-0.50
A43: 4Q26 margin that sentence implies at the run's 3Q26 | B43: 0.30125 | C43: 0.2358864 | D43: 0.28897437 | E43: 1pp of the FY sentence = 4.49pp of 4Q26; an unchanged floor only says 4Q26 >= ~27.6%
A45: 3. What each path implies for the share price (reverse DCF run, 12-13 Sep 2026; details on the two Reverse DCF tabs)
A46: Reference price (12 Sep 2026) | B46: 170.19
A47: Diluted shares (m) | B47: 597
A48: Net cash ex float ($m, 30 Jun 2026) | B48: 9593
A49: Fixed EV / FY27 EBITDA multiple used for the cross-check | B49: 16.5
A50: Joint-solve multiple rule: EV / NTM EBITDA = a + b x NTM growth (%) | B50: 12.533 | C50: 0.3955 | D50: t 3.1, R2 0.23, about 16 independent observations; the price pays 16x for 12.9% NTM growth
A52: Case | B52: FY27 revenue ($m) | C52: FY27 growth | D52: FY27 EBITDA ($m) | E52: Joint-solve price | F52: Upside vs ref | G52: Price at 16.5x own EBITDA | H52: Upside vs ref | I52: P(above in 12M, options)
A53: Management literal | B53: 15630.397 | C53: 0.098311 | D53: 5548.792 | E53: 162.1901 | F53: =E53/$B$46-1 -> -0.0470057 | G53: 169.4272 | H53: =G53/$B$46-1 -> -0.0044820495 | I53: 0.5103
A54: Management delivered | B54: 16024.746 | C54: 0.126021 | D54: 5800.957 | E54: 175.4934 | F54: =E54/$B$46-1 -> 0.031161643 | G54: 176.3966 | H54: =G54/$B$46-1 -> 0.036468653 | I54: 0.4318
A55: Management ambition | B55: 16790.632 | C55: 0.179838 | D55: 6212.536 | E55: 202.6734 | F55: =E55/$B$46-1 -> 0.1908655 | G55: 187.7719 | H55: =G55/$B$46-1 -> 0.10330748 | I55: 0.2965
A56: Street FY27 $15,745m | B56: 15745.001 | C56: 0.106364 | D56: 5699.69 | E56: 166.0077 | F56: =E56/$B$46-1 -> -0.024574299 | G56: 173.5978 | H56: =G56/$B$46-1 -> 0.020023503 | I56: 0.4868
A57: Team base (WS29/30) $15,804m | B57: 15803.691 | C57: 0.110488 | D57: 5757.93 | E57: 167.9782 | F57: =E57/$B$46-1 -> -0.012996063 | G57: 175.2074 | H57: =G57/$B$46-1 -> 0.029481168 | I57: 0.475
A58: Team bear (WS29) $14,318m | B58: 14318.327 | C58: 0.006115 | D58: 4375 | E58: 121.3079 | F58: =E58/$B$46-1 -> -0.28722075 | G58: 136.9858 | H58: =G58/$B$46-1 -> -0.19510077 | I58: 0.761
A59: Team bull (WS29) $16,910m | B59: 16909.762 | C59: 0.188209 | D59: 6977.35 | E59: 207.06 | F59: =E59/$B$46-1 -> 0.21664023 | G59: 208.91 | H59: =G59/$B$46-1 -> 0.22751043 | I59: 0.2784
A60: Short case (pitch): 15 Sep, not in the run; derived here | B60: 14913.512 | C60: =B60/13932.7676741855-1 -> 0.070391172 | D60: 4761.4354 | E60: =E58+(B60-B58)/(B56-B58)*(E56-E58) -> 139.9559 | F60: =E60/$B$46-1 -> -0.17764912 | G60: =($B$49*D60+$B$48)/$B$47 -> 147.66614 | H60: =G60/$B$46-1 -> -0.13234539
A61: Short-case joint-solve price is a linear interpolation between the team bear and Street rows on FY27 revenue (indicative, JUDGEMENT); the 16.5x column is the arithmetic (multiple x own FY27 EBITDA + net cash) / shares, the same convention as the run's fixed-multiple cross-check. The joint solve is the primary lens in the run; the fixed multiple is the cross-check.
A63: Print scenario (reaction function C) | B63: 3Q26 nights y/y | C63: Accel sign vs 2Q26 | D63: 3Q26 revenue ($m) | E63: 4Q26 revenue guide ($m) | F63: Guide vs Street | G63: Expected day-1 excess (sign rule, post-2022) | H63: Expected (S2 with guide term)
A64: Team base (WS29/30) | B64: 0.099 | C64: -1 | D64: 4771 | E64: 3111 | F64: -0.0136 | G64: -0.0611 | H64: -0.0823
A65: Team base, ex-NA lap adopted (4Q26 8.1%) | B65: 0.099 | C65: -1 | D65: 4771 | E65: 3102 | F65: -0.0166 | G65: -0.0611 | H65: -0.0863
A66: Street (Bloomberg FA 4 Sep) | B66: 0.111 | C66: 1 | D66: 4744 | E66: 3154 | F66: 0 | G66: 0.0521 | H66: 0.045
A67: Management delivered | B67: 0.115 | C67: 1 | D67: 4815 | E67: 3130 | F67: -0.0076 | G67: 0.0521 | H67: 0.0349
A68: Q3 nowcast central (reviews index 9.75) with stable 4Q guide | B68: 0.0975 | C68: -1 | D68: 4815 | E68: 3121 | F68: -0.0104 | G68: -0.0611 | H68: -0.0781
A69: Flat print: 3Q26 = 2Q26 rate, 4Q26 guided stable, revenue at Street | B69: 0.1034 | C69: 0 | D69: 4744 | E69: 3154 | F69: 0 | G69: -0.0045 | H69: -0.0096
A70: Accelerating print, 4Q26 guide at Street revenue | B70: 0.11 | C70: 1 | D70: 4815 | E70: 3154 | F70: 0 | G70: 0.0521 | H70: 0.045
A71: Team base, UNCONDITIONAL over the nowcast band (nowcast centre 9.9,... | B71: 0.099 | D71: 4771 | E71: 3111 | F71: -0.0136 | G71: -0.026 | H71: -0.0484
A72: Options-implied 5 Nov event standard deviation | B72: 9.5 (range 8.5-10.5; identified specs 8.3-11.0)% | C72: expected absolute move 7.6 (range 6.8-8.4)%; realised print rms 8.92% raw / 8.48% excess
A73: Nights-acceleration sign rule, post-2022 (n 14) | B73: accelerating +6.0%, decelerating -5.6% day-1 excess; 0 of 8 decelerating prints positive on excess, 2 of 8 raw; Fisher p 0.007
A74: 12-month options distribution (lognormal p25 / p50 / p75) | B74: 125.5 | C74: 163.8 | D74: 213.9 | E74: P(above $179.5) 0.41-0.43; P(below $150) 0.40-0.41
A76: Outcome on 5 Nov (positioning card E) | B76: NTM revenue ($m) | C76: NTM growth | D76: Joint-solve price | E76: Fundamental repricing | F76: Accel sign | G76: Sign-rule reaction
A77: Street path prints (3Q26 +11.45%, 4Q26 at Street $3,177m; 1H27 at Street FY27, delivered FY26 base) | B77: 14875.605 | C77: 0.13045 | D77: 170.745 | E77: 0.00326 | F77: 1 | G77: 0.05205
A78: Street path, 1H27 on the Street's own FY26 base | B78: 14925.464 | C78: 0.13424 | D78: 172.577 | E78: 0.01403 | F78: 1 | G78: 0.05205
A79: Management delivered prints (3Q26 +11.5%, 4Q26 $3,130m) | B79: 15004.296 | C79: 0.14023 | D79: 175.493 | E79: 0.03116 | F79: 1 | G79: 0.05205
A80: Team pnl bridge prints (3Q26 +10.3%, 4Q26 +9.9%, revenue $4,771m / $3,111m) | B80: 14818.354 | C80: 0.1261 | D80: 168.651 | E80: -0.00904 | F80: -1 | G80: -0.06109
A81: Team pivot baseline prints (3Q26 +9.9%, 4Q26 +8.9%, 1H27 as pnl) | B81: 14773.492 | C81: 0.12269 | D81: 167.018 | E81: -0.01864 | F81: -1 | G81: -0.06109
A82: Team pivot baseline with the ex-NA lap: 4Q26 +8.1% one-for-one, 1H27 unchanged | B82: 14751.268 | C82: 0.121 | D82: 166.212 | E82: -0.02337 | F82: -1 | G82: -0.06109
A83: Team pivot baseline with the ex-NA lap also hitting 1H27 by 0.8pt | B83: 14700.98 | C83: 0.11718 | D83: 164.394 | E83: -0.03405 | F83: -1 | G83: -0.06109
A84: Reading: the differentiated claim is the 3Q26 nights print, not FY27. The price is within 1-3% of the team's own revenue path (fundamental repricing -1 to -3%); the reaction is the sign rule (-4 to -6% conditional on deceleration, -2 to -3.5% probability-weighted over the nowcast band) against a 9.5% options-implied dispersion. The short case adds a second leg: a 4Q26 guide 6-10% below the Street and FY27 EBITDA about $1.0bn below, which on the multiple arithmetic above is worth $20-30 a share.
A86: Sources (paths relative to the repo root)
A87: Street | B87: data/processed/margin_build/03_consensus_pit/03_current_consensus.csv (LSEG 11 Sep 2026); reverse_dcf/E/E_street_distribution_vs_team.csv (Bloomberg)
A88: Team base / short | B88: this workbook's Income Statement, Revenue Model and Margins tabs; 40_line_build outputs
A89: Management delivered | B89: data/processed/reverse_dcf/mgmt_implied_summary.csv
A90: Price implications | B90: data/processed/reverse_dcf/market/market_implied_cases.csv, market_implied_comparison.csv, market_implied_params.json; C/C_scenarios.csv; B/B_headline.csv; E/E_repricing_ladder.csv; docs/reverse_dcf/SYNTHESIS.md

Sheet Stock Chart
A1: ABNB stock chart: what moves the stock, Dec 2020 IPO to Sep 2026
A2: Earnings prints are the dominant driver of ABNB's largest days: 11 of the 41 moves of 7% or more since IPO are earnings days, and they are the biggest (mean 12.1% absolute vs 8.6% for macro days). The chart labels which prints moved the stock and why; the tables below give every print and every 7%+ day, and the read-across to the 5 Nov 2026 print.
A36: Earnings-day reactions, all 23 prints | B36: reaction day = first session after the print; close-to-close; excess = ABNB minus QQQ
A37: Mean absolute 1-day move (n = 23) | B37: =SUMPRODUCT(ABS(C43:C65))/COUNT(C43:C65) -> 0.070608696
A38: Share of prints with |move| >= 7% | B38: =SUMPRODUCT(--(ABS(C43:C65)>=0.07))/COUNT(C43:C65) -> 0.47826087
A39: Prints up / down (1-day) | B39: =COUNTIF(C43:C65,">0") -> 13 | C39: =COUNTIF(C43:C65,"<0") -> 10
A40: Mean 1-day excess vs QQQ | B40: =AVERAGE(E43:E65) -> 0.0050869565
A42: quarter | B42: reaction_date | C42: abnb_1d_pct | D42: qqq_1d_pct | E42: excess_1d_pct | F42: abnb_5d_pct | G42: excess_5d_pct | H42: abnb_20d_pct | I42: excess_20d_pct
A43: 2020Q4 | B43: 44253 | C43: 0.133 | D43: 0.004 | E43: 0.129 | F43: -0.01 | G43: 0.018 | H43: -0.032 | I43: -0.028
A44: 2021Q1 | B44: 44330 | C44: 0.04 | D44: 0.022 | E44: 0.018 | F44: 0.003 | G44: -0.026 | H44: 0.093 | I44: 0.025
A45: 2021Q2 | B45: 44421 | C45: 0.011 | D45: 0.004 | E45: 0.007 | F45: -0.056 | G45: -0.047 | H45: 0.093 | I45: 0.068
A46: 2021Q3 | B46: 44505 | C46: 0.13 | D46: 0.001 | E46: 0.129 | F46: 0.074 | G46: 0.093 | H46: -0.066 | I46: -0.028
A47: 2021Q4 | B47: 44608 | C47: 0.036 | D47: 0 | E47: 0.037 | F47: -0.167 | G47: -0.092 | H47: -0.135 | I47: -0.091
A48: 2022Q1 | B48: 44685 | C48: 0.077 | D48: 0.034 | E48: 0.043 | F48: -0.199 | G48: -0.142 | H48: -0.195 | I48: -0.155
A49: 2022Q2 | B49: 44776 | C49: -0.011 | D49: 0.027 | E49: -0.039 | F49: -0.016 | G49: -0.025 | H49: -0.032 | I49: 0.01
A50: 2022Q3 | B50: 44867 | C50: -0.134 | D50: -0.034 | E50: -0.1 | F50: -0.093 | G50: -0.073 | H50: -0.063 | I50: -0.13
A51: 2022Q4 | B51: 44972 | C51: 0.134 | D51: 0.008 | E51: 0.126 | F51: 0.052 | G51: 0.093 | H51: -0.06 | I51: -0.035
A52: 2023Q1 | B52: 45056 | C52: -0.109 | D52: 0.011 | E52: -0.12 | F52: -0.17 | G52: -0.188 | H52: -0.083 | I52: -0.167
A53: 2023Q2 | B53: 45142 | C53: -0.005 | D53: -0.005 | E53: 0 | F53: -0.035 | G53: -0.021 | H53: -0.066 | I53: -0.077
A54: 2023Q3 | B54: 45232 | C54: -0.033 | D54: 0.018 | E54: -0.051 | F54: -0.015 | G54: -0.06 | H54: 0.058 | I54: -0.032
... A64: 2026Q1 | B64: 46150 | C64: 0.007 | D64: 0.023 | E64: -0.016 | F64: -0.048 | G64: -0.084 | H64: -0.049 | I64: -0.064
A65: 2026Q2 | B65: 46241 | C65: 0.174 | D65: 0.012 | E65: 0.163 | F65: 0.221 | G65: 0.196
A66: Missing: 20-day returns for the 7 Aug 2026 print (2026Q2) were not yet available in the source file. Row highlighting is not applied; large moves are readable from the values.
A68: What moved the stock on each earnings day (the 11 prints with a 7%+ move) | B68: same-day moves of QQQ, BKNG, EXPE for context; trigger and notes from the big-moves file
A69: date | B69: ABNB move | C69: QQQ same day | D69: BKNG same day | E69: EXPE same day | F69: trigger | J69: notes
A70: 44253 | B70: 0.133 | C70: 0.004 | D70: 0.024 | E70: 0.024 | F70: Q4'20 (first print as a public company) | J70: Revenue $859M (-22% YoY) beat ~$748M est; nights 46.3M (-39%); GBV $5.9B (-31%); ADR $128 (+13%); net loss $3.9B on IPO charges
A71: 44505 | B71: 0.13 | C71: 0.001 | D71: 0.075 | E71: 0.156 | F71: Q3'21 record quarter (Expedia also reported) | J71: Revenue $2.24B (+67% YoY; +36% vs 2019); nights 79.7M (+29%); GBV $11.9B (+48%); net income $834M; adj EBITDA $1.1B (49% margin); Expedia +15.6% same day on its own beat
A72: 44685 | B72: 0.077 | C72: 0.034 | D72: -0.001 | E72: -0.005 | F72: Q1'22 first-ever profitable Q1 (plus Fed-day rally) | J72: Revenue $1.51B (+70%); nights 102.1M (+59%; first 100M quarter); GBV $17.2B (+67%); adj EBITDA $229M; Q2 guide $2.03-2.13B above est; Nasdaq +3.4% on Powell
A73: 44867 | B73: -0.134 | C73: -0.034 | D73: -0.059 | E73: -0.056 | F73: Q3'22: beat but Q4 nights guided to moderate | J73: Revenue $2.88B (+29%) at top of guide; adj EBITDA $1.46B (51% margin); nights 99.7M (+25%); Q4 guide nights growth to slow to ~20% ADR flat revenue +17-23%; Fed hiked 75 bp same day
A74: 44972 | B74: 0.134 | C74: 0.008 | D74: 0.018 | E74: 0.009 | F74: Q4'22: first profitable full year; Q1 guide beat | J74: Revenue $1.90B (+24%) vs $1.86B; adj EBITDA $506M vs $435M; nights 88.2M (+20%) slightly below 90.1M est; FY22 net income $1.9B FCF $3.4B; Q1'23 guide $1.75-1.82B vs $1.68B est
A75: 45056 | B75: -0.109 | C75: 0.011 | D75: 0.004 | E75: -0.024 | F75: Q1'23: first profitable Q1 on GAAP but nights guided below revenue | J75: Revenue $1.82B (+20%); nights 121.1M (+19%); GBV $20.4B (+19%); net income $117M; Q2 guide $2.35-2.45B (+12-16%) with nights growth below revenue growth; tough pandemic comps
A76: 45511 | B76: -0.134 | C76: -0.011 | D76: -0.033 | E76: -0.037 | F76: Q2'24: shorter lead times and slowing US demand | J76: Revenue $2.75B (+11%); nights 125.1M (+9%); GBV $21.2B (+11%); EPS $0.86 vs $0.92 est; adj EBITDA $894M (33%); Q3 guide $3.67-3.73B and nights growth to moderate; flagged shorter booking lead times
A77: 45604 | B77: -0.087 | C77: 0.001 | D77: 0.005 | E77: 0.038 | F77: Q3'24: EPS miss and expense growth | J77: Revenue $3.73B (+10%) beat; nights 122.8M (+8%); GBV $20.1B (+10%); EPS $2.13 vs $2.17; S&M +27.5% product dev +25%; adj EBITDA margin 52% (-200 bp)
A78: 45702 | B78: 0.144 | C78: 0.004 | D78: 0.007 | E78: -0.004 | F78: Q4'24: nights beat (best day on record) | J78: Revenue $2.48B (+12%) vs $2.42B; nights 111.0M (+12%) vs 108.7M est; GBV $17.6B (+13%); EPS $0.73 vs $0.58; adj EBITDA $765M vs $654M; Q1 guide $2.23-2.27B below $2.30B est but ignored
A79: 45876 | B79: -0.08 | C79: 0.003 | D79: -0.019 | E79: 0.013 | F79: Q2'25: beat but H2 nights to moderate and $200M new-business spend | J79: Revenue $3.10B (+13%) vs $3.04B; nights 134.4M (+7%) vs 133.4M; GBV $23.5B (+11%); EPS $1.03 vs $0.94; adj EBITDA $1.04B (34%); Q3 guide $4.02-4.10B; nights growth to slow into Q4; Services/Experiences to weigh on margin
A80: 46241 | B80: 0.174 | C80: 0.012 | D80: 0.034 | E80: 0.013 | F80: Q2'26: beat on every KPI and FY guide raised | J80: Revenue $3.61B (+17%) vs $3.58B; nights 148.3M (+10%) accelerating; GBV $27.2B (+16%); EPS $1.37 vs $1.26; adj EBITDA $1.26B (35%); first-time bookers +11%; hotels ~3x homes; FY26 revenue at least mid-teens and margin at least 35.5%; highest close since Apr 2022
A82: All moves of 7% or more since IPO, by driver | B82: 41 days; percentages are absolute close-to-close moves; excess = ABNB minus the peer
A83: driver | B83: n | C83: n_up | D83: n_down | E83: mean_abs_move | F83: median_abs_move | G83: max_up | H83: max_down | I83: mean_abs_qqq_same_day | J83: mean_abs_excess_vs_qqq | K83: mean_abs_excess_vs_bkng | L83: mean_abs_excess_vs_expe | M83: n_since_2023
A84: Company/other | B84: 9 | C84: 8 | D84: 1 | E84: 0.088 | F84: 0.086 | G84: 0.115 | H84: -0.072 | I84: 0.007 | J84: 0.081 | K84: 0.084 | L84: 0.085 | M84: 1
A85: Competitor/industry | B85: 1 | C85: 0 | D85: 1 | E85: 0.07 | F85: 0.07 | G85: -0.07 | H85: -0.07 | I85: 0.015 | J85: 0.055 | K85: 0.023 | L85: 0.083 | M85: 1
A86: Earnings | B86: 11 | C86: 6 | D86: 5 | E86: 0.121 | F86: 0.133 | G86: 0.174 | H86: -0.134 | I86: 0.011 | J86: 0.113 | K86: 0.098 | L86: 0.103 | M86: 7
A87: Macro/market | B87: 20 | C87: 9 | D87: 11 | E87: 0.086 | F87: 0.081 | G87: 0.148 | H87: -0.121 | I87: 0.036 | J87: 0.051 | K87: 0.042 | L87: 0.036 | M87: 2
A88: ALL | B88: 41 | C88: 23 | D88: 18 | E88: 0.096 | F88: 0.085 | G88: 0.174 | H88: -0.134 | I88: 0.023 | J88: 0.074 | K88: 0.066 | L88: 0.066 | M88: 11
A89: Earnings days are fewer than macro days but larger on average, and almost all of the move is stock-specific (mean absolute excess vs QQQ 11.3% on earnings days vs 5.1% on macro days).
A91: Full list, 41 days (chronological)
A92: date | B92: ABNB move | C92: driver | D92: QQQ same day | E92: BKNG same day | F92: EXPE same day | G92: trigger
A93: 44181 | B93: 0.106 | C93: Company/other | D93: 0.005 | E93: 0 | F93: -0.008 | G93: Post-IPO momentum
A94: 44208 | B94: 0.086 | C94: Company/other | D94: -0.002 | E94: -0.011 | F94: -0.014 | G94: Tigress Financial initiates Buy
A95: 44217 | B95: 0.115 | C95: Company/other | D95: 0.008 | E95: -0.023 | F95: -0.02 | G95: Analyst-initiation and reopening momentum
A96: 44222 | B96: 0.086 | C96: Company/other | D96: 0.001 | E96: -0.017 | F96: -0.033 | G96: Momentum into Feb 11 all-time high ($216.84)
A97: 44252 | B97: -0.091 | C97: Macro/market | D97: -0.035 | E97: -0.07 | F97: -0.034 | G97: Rates spike hits growth
A98: 44253 | B98: 0.133 | C98: Earnings | D98: 0.004 | E98: 0.024 | F98: 0.024 | G98: Q4'20 (first print as a public company)
A99: 44266 | B99: 0.077 | C99: Macro/market | D99: 0.023 | E99: -0.003 | F99: 0.021 | G99: Growth rebound after rates scare
A100: 44432 | B100: 0.1 | C100: Company/other | D100: 0.003 | E100: 0.045 | F100: 0.027 | G100: Afghan refugee housing pledge; DA Davidson reiterates Buy
A101: 44505 | B101: 0.13 | C101: Earnings | D101: 0.001 | E101: 0.075 | F101: 0.156 | G101: Q3'21 record quarter (Expedia also reported)
A102: 44512 | B102: 0.078 | C102: Company/other | D102: 0.011 | E102: -0.011 | F102: -0.02 | G102: Post-earnings momentum
A103: 44522 | B103: -0.075 | C103: Macro/market | D103: -0.012 | E103: -0.018 | F103: -0.011 | G103: Growth rotation on Powell renomination
A104: 44536 | B104: 0.085 | C104: Macro/market | D104: 0.008 | E104: 0.053 | F104: 0.067 | G104: Omicron-is-milder relief rally
... A133: 46241 | B133: 0.174 | C133: Earnings | D133: 0.012 | E133: 0.034 | F133: 0.013 | G133: Q2'26: beat on every KPI and FY guide raised
A135: Read-across to 5 Nov 2026 (3Q26 print) | B135: numbers from data/processed/reverse_dcf/{B,C,E} and docs/reverse_dcf/SYNTHESIS.md section 1
A136: • Sign rule on printed nights acceleration (workstream C, post-2022 prints, n = 14, +/-0.25pt dead band): accelerating prints average +6.0% day-1 excess vs QQQ (4 of 5 positive); decelerating prints average -5.6% (0 of 8 positive); flat: 3Q24; Fisher p 0.007. Regression form: excess = -0.45 + 5.66 x sign, R2 0.41 (C_coefficients_used.csv, S1_post2022; C_deadband_sensitivity.csv).
A137: • On the raw (not QQQ-excess) return the split is 6 up / 2 down accel; 3 up / 8 down decel; on excess it is 6 up / 2 down accel; 1 up / 10 down decel (B_headline.csv). The rule gives the sign of the reaction, not its size, and does not clear a multiplicity correction (C_multiplicity_holm.csv): 14 prints.
A138: • Where the Street sits for 3Q26: the consensus nights bar is 148.9M (+11.45% y/y vs +10.34% in 2Q26), i.e. positioned for acceleration, for only the 4th time in 17 prints. The 3 prior times the Street was positioned for acceleration, all 3 printed acceleration, mean day-1 excess +4.2%; the 12 times it was positioned for deceleration averaged +0.38% (E_street_sign_summary.csv, E_street_sign_history.csv).
A139: • Options-implied 5 Nov event: standard deviation 9.5% (range 8.5-10.5; identified specs 8.3-11.0), expected absolute move 7.6%; spot $170.19 on 2026-09-12 (B_headline.csv, JUDGEMENT rows built from the measured 16 Oct / 20 Nov straddle pair 9.88% and least-squares 9.16-9.73%).
A140: • Realised print history for scale: raw close-to-close rms 8.92%, 48% of the 23 prints moved 7% or more, 13 up / 10 down (B_headline.csv, hist_realised_raw_* rows); this tab's table above gives the same 23 prints.
A141: • Team read (SYNTHESIS.md section 1): the team's nowcast is a decelerating 3Q26 nights print (+9.5 to 10.0%) against a Street bar that implies acceleration; on the sign rule that implies a -4 to -6% day conditional on deceleration and -2 to -3.5% unconditionally, against a 9.5% options-implied dispersion. The trade is the print reaction, not an estimate revision.
A143: Sources (paths relative to the repo root)
A144: Daily close (Yahoo, Dec 2020 to 4 Sep 2026) | B144: data/processed/abnb_daily_close.csv
A145: 7%+ days with driver, trigger, notes, peer moves (41 rows) | B145: data/processed/abnb_big_moves_7pct.csv
A146: Earnings-day reactions, 23 prints | B146: data/processed/abnb_earnings_reactions.csv
A147: 7%+ move statistics by driver | B147: data/processed/abnb_big_move_stats_by_driver.csv
A148: Sign rule, dead-band sensitivity (post-2022, 0.25pt row) | B148: data/processed/reverse_dcf/C/C_deadband_sensitivity.csv
A149: Sign rule, coefficients used (S1_post2022) | B149: data/processed/reverse_dcf/C/C_coefficients_used.csv
A150: Multiplicity check | B150: data/processed/reverse_dcf/C/C_multiplicity_holm.csv
A151: Street positioning summary | B151: data/processed/reverse_dcf/E/E_street_sign_summary.csv
A152: Street positioning history (16 prints + 3Q26E) | B152: data/processed/reverse_dcf/E/E_street_sign_history.csv
A153: Options headline (event sd, realised history) | B153: data/processed/reverse_dcf/B/B_headline.csv
A154: Reverse DCF synthesis, section 1 | B154: docs/reverse_dcf/SYNTHESIS.md
A155: Chart image | B155: model/figures/abnb_annotated_stock_chart.png

Sheet Reverse DCF - Mgmt
A1: Reverse DCF - Management-implied: what management's words are worth
A2: Three readings of the guide (Literal / Delivered / Ambition), FY26E-FY27E by quarter, implied prices at the team's multiples, and a reverse DCF on management's own FCF. Source: management-implied model, 12 Sep 2026.
A4: What this tab says
A5: • LITERAL = the guide taken at its word: range midpoints, floors as points, buckets ('low double digits') at the low end; FY27 is the guide management would give in Feb 2027 on its own pattern (floor carried).
A6: • DELIVERED = the guide plus management's own cushion: quarterly revenue +1.8% vs the midpoint (median of the last eight prints; 19 of 19 ranges beaten), nights one point above the bucket top (3 of 3 bucket guides since 4Q25 printed above range), FY margin floor +70bp (FY24 +140, FY25 +60); FY27 holds the FY26 exit rate with margin flat.
A7: • AMBITION = the 8 Sep 2026 CEO framing ('almost every market is accelerating', hotels 3x homes, India +60%, sponsored listings 'a straight shot to $1bn'): take rate +20bp in FY27, margin drifting to 37%.
A8: • Headline (Delivered, FY27E): revenue $16,025m (+12.6%), nights 647.0m (+10.0%), adj. EBITDA $5,801m at a 36.2% margin, GAAP EPS $6.08, FCF $5,941m. The Street's FY27 revenue ($15,745m) is the Delivered case; the sell-side mean target (~$182) is the Delivered case at 16-17x EBITDA.
A9: • At the team's mid multiples (16.5x EV/EBITDA, 27x P/E, 17x EV/FCF) the three cases are worth $174 / $182 / $196 (Literal / Delivered / Ambition) against $170.19, i.e. +2% / +7% / +15%. The multiple matters more than the case: 13.5x to 18.5x moves the Delivered case by about $51, the three cases at a fixed 16.5x span about $30.
A10: • Reverse DCF on the Delivered FCF ($5,941m, WACC 10%, ten-year fade to 3%): at $170.19 (EV $92.0bn) the price needs FY28+ FCF growth of 4.6% on reported FCF and 15.9% on SBC-adjusted FCF ($4,005m): the SBC debate.
A12: The three cases side by side: annual (FY25A actual, FY26E-FY27E by case) | B12: USD millions unless stated; blue = model output from the CSV, black = growth formulas
B13: Actual | C13: Literal | E13: Delivered | G13: Ambition
A14: Metric | B14: FY25A | C14: FY26E | D14: FY27E | E14: FY26E | F14: FY27E | G14: FY26E | H14: FY27E
A15: Nights & seats booked (m) | B15: 533 | C15: 583.722 | D15: 636.256 | E15: 588.164 | F15: 646.98 | G15: 591.328 | H15: 662.287
A16: Gross booking value ($m) | B16: 91292 | C16: 105045.05 | D16: 117434.59 | E16: 106056.58 | F16: 120239.98 | G16: 106851.08 | H16: 123345.66
A17: ADR ($) | B17: 171.28 | C17: 179.957 | D17: 184.571 | E17: 180.318 | F17: 185.848 | G17: 180.697 | H17: 186.242
A18: Revenue ($m) | B18: 12241 | C18: 14077.15 | D18: 15630.4 | E18: 14231.303 | F18: 16024.742 | G18: 14356.237 | H18: 16790.638
A19: Take rate (revenue / GBV) | B19: 0.13409 | C19: 0.13401 | D19: 0.1331 | E19: 0.13419 | F19: 0.13327 | G19: 0.13436 | H19: 0.13613
A20: Adj. EBITDA ($m) | B20: 4297 | C20: 4997.388 | D20: 5548.792 | E20: 5151.732 | F20: 5800.957 | G20: 5240.026 | H20: 6212.536
A21: Adj. EBITDA margin | B21: 0.35103 | C21: 0.355 | D21: 0.355 | E21: 0.362 | F21: 0.362 | G21: 0.365 | H21: 0.37
A22: Stock-based compensation ($m) | B22: 1581 | C22: 1775.9 | D22: 1935.731 | E22: 1775.9 | F22: 1935.731 | G22: 1775.9 | H22: 1917.972
A23: GAAP net income ($m) | B23: 2511 | C23: 3075.894 | D23: 3302.52 | E23: 3201.633 | F23: 3507.193 | G23: 3273.369 | H23: 3855.168
A24: Diluted shares (m) | B24: 623 | C24: 596.341 | D24: 577.051 | E24: 596.341 | F24: 577.051 | G24: 596.341 | H24: 577.051
A25: GAAP diluted EPS | B25: 4.03 | C25: 5.158 | D25: 5.723 | E25: 5.369 | F25: 6.078 | G25: 5.489 | H25: 6.681
A26: Free cash flow ($m) | B26: 4613 | C26: 5209.172 | D26: 5738.124 | E26: 5317.212 | F26: 5940.573 | G26: 5379.019 | H26: 6346.656
A27: Net cash ($m) | B27: 11014 | C27: 9437.557 | D27: 10298.175 | E27: 9545.597 | F27: 10608.664 | G27: 9607.404 | H27: 11082.769
A28: Revenue growth y/y | C28: =C18/$B$18-1 -> 0.15 | D28: =D18/C18-1 -> 0.11033839 | E28: =E18/$B$18-1 -> 0.16259317 | F28: =F18/E18-1 -> 0.12602072 | G28: =G18/$B$18-1 -> 0.17279936 | H28: =H18/G18-1 -> 0.16957097
A29: Nights growth y/y | C29: =C15/$B$15-1 -> 0.095163227 | D29: =D15/C15-1 -> 0.089998321 | E29: =E15/$B$15-1 -> 0.10349719 | F29: =F15/E15-1 -> 0.09999932 | G29: =G15/$B$15-1 -> 0.1094334 | H29: =H15/G15-1 -> 0.11999939
A30: Adj. EBITDA growth y/y | C30: =C20/$B$20-1 -> 0.16299465 | D30: =D20/C20-1 -> 0.11033844 | E30: =E20/$B$20-1 -> 0.19891366 | F30: =F20/E20-1 -> 0.12602072 | G30: =G20/$B$20-1 -> 0.21946148 | H30: =H20/G20-1 -> 0.18559259
A31: EPS growth y/y | C31: =C25/$B$25-1 -> 0.27990074 | D31: =D25/C25-1 -> 0.10953858 | E31: =E25/$B$25-1 -> 0.33225806 | F31: =F25/E25-1 -> 0.13205439 | G31: =G25/$B$25-1 -> 0.36203474 | H31: =H25/G25-1 -> 0.2171616
A33: The three cases side by side: quarterly, 3Q26E-4Q27E
B34: Literal | H34: Delivered | N34: Ambition
A35: Metric | B35: 3Q26 | C35: 4Q26 | D35: 1Q27 | E35: 2Q27 | F35: 3Q27 | G35: 4Q27 | H35: 3Q26 | I35: 4Q26 | J35: 1Q27 | K35: 2Q27 | L35: 3Q27 | M35: 4Q27 | N35: 3Q26 | O35: 4Q26 | P35: 1Q27 | Q35: 2Q27 | R35: 3Q27 | S35: 4Q27
A36: Nights & seats booked (m) | B36: 146.96 | C36: 132.262 | D36: 170.258 | E36: 161.647 | F36: 160.186 | G36: 144.165 | H36: 148.964 | I36: 134.7 | J36: 171.82 | K36: 163.13 | L36: 163.86 | M36: 148.169 | N36: 150.3 | O36: 136.528 | P36: 174.944 | Q36: 166.096 | R36: 168.336 | S36: 152.911
A37: Gross booking value ($m) | B37: 26014.446 | C37: 22596.601 | D37: 32478.739 | E37: 30441.711 | F37: 29268.092 | G37: 25246.052 | H37: 26497.194 | I37: 23125.387 | J37: 32936.596 | K37: 30870.851 | L37: 30231.47 | M37: 26201.063 | N37: 26863.991 | O37: 23553.089 | P37: 33535.443 | Q37: 31432.139 | R37: 31207.232 | S37: 27170.844
A38: ADR ($) | B38: 177.017 | C38: 170.848 | D38: 190.762 | E38: 188.322 | F38: 182.713 | G38: 175.119 | H38: 177.876 | I38: 171.681 | J38: 191.692 | K38: 189.241 | L38: 184.495 | M38: 176.832 | N38: 178.736 | O38: 172.515 | P38: 191.692 | Q38: 189.241 | R38: 185.387 | S38: 177.69
A39: Revenue ($m) | B39: 4730 | C39: 3061.15 | D39: 2962.076 | E39: 3998.79 | F39: 5252.885 | G39: 3416.65 | H39: 4815.14 | I39: 3130.163 | J39: 3003.832 | K39: 4055.161 | L39: 5422.82 | M39: 3542.928 | N39: 4882.182 | O39: 3188.055 | P39: 3120.003 | Q39: 4211.948 | R39: 5710.85 | S39: 3747.838
A40: Take rate (revenue / GBV) | B40: 0.18182 | C40: 0.13547 | D40: 0.0912 | E40: 0.13136 | F40: 0.17947 | G40: 0.13533 | H40: 0.18172 | I40: 0.13536 | J40: 0.0912 | K40: 0.13136 | L40: 0.17938 | M40: 0.13522 | N40: 0.18174 | O40: 0.13536 | P40: 0.09304 | Q40: 0.134 | R40: 0.183 | S40: 0.13794
A41: Adj. EBITDA ($m) | B41: 2340.663 | C41: 876.726 | D41: 573.903 | E41: 1397.377 | F41: 2599.146 | G41: 978.367 | H41: 2406.87 | I41: 964.861 | J41: 581.924 | K41: 1416.982 | L41: 2710.219 | M41: 1091.831 | N41: 2459.91 | O41: 1000.116 | P41: 620.015 | Q41: 1492.809 | R41: 2905.543 | S41: 1194.169
A42: Adj. EBITDA margin | B42: 0.49485 | C42: 0.2864 | D42: 0.19375 | E42: 0.34945 | F42: 0.4948 | G42: 0.28635 | H42: 0.49985 | I42: 0.30825 | J42: 0.19373 | K42: 0.34943 | L42: 0.49978 | M42: 0.30817 | N42: 0.50385 | O42: 0.31371 | P42: 0.19872 | Q42: 0.35442 | R42: 0.50878 | S42: 0.31863
A43: Stock-based compensation ($m) | B43: 438.9 | C43: 440 | D43: 446.9 | E43: 530.83 | F43: 478.401 | G43: 479.6 | H43: 438.9 | I43: 440 | J43: 446.9 | K43: 530.83 | L43: 478.401 | M43: 479.6 | N43: 438.9 | O43: 440 | P43: 442.8 | Q43: 525.96 | R43: 474.012 | S43: 475.2
A44: GAAP net income ($m) | B44: 1648.215 | C44: 451.679 | D44: 194.134 | E44: 795.035 | F44: 1816.793 | G44: 496.558 | H44: 1702.051 | I44: 523.582 | J44: 200.489 | K44: 810.811 | L44: 1906.967 | M44: 588.926 | N44: 1745.186 | O44: 552.183 | P44: 234.467 | Q44: 876.146 | R44: 2069.197 | S44: 675.358
A45: Diluted shares (m) | B45: 592.43 | C45: 587.934 | D45: 583.51 | E45: 579.157 | F45: 574.875 | G45: 570.663 | H45: 592.43 | I45: 587.934 | J45: 583.51 | K45: 579.157 | L45: 574.875 | M45: 570.663 | N45: 592.43 | O45: 587.934 | P45: 583.51 | Q45: 579.157 | R45: 574.875 | S45: 570.663
A46: GAAP diluted EPS | B46: 2.782 | C46: 0.768 | D46: 0.333 | E46: 1.373 | F46: 3.16 | G46: 0.87 | H46: 2.873 | I46: 0.891 | J46: 0.344 | K46: 1.4 | L46: 3.317 | M46: 1.032 | N46: 2.946 | O46: 0.939 | P46: 0.402 | Q46: 1.513 | R46: 3.599 | S46: 1.183
A47: Free cash flow ($m) | B47: 1638.464 | C47: 613.708 | D47: 1836.488 | E47: 1397.377 | F47: 1819.402 | G47: 684.857 | H47: 1684.809 | I47: 675.403 | J47: 1862.155 | K47: 1416.982 | L47: 1897.154 | M47: 764.282 | N47: 1721.937 | O47: 700.081 | P47: 1984.049 | Q47: 1492.809 | R47: 2033.88 | S47: 835.918
A48: Net cash ($m) | B48: 10027.849 | C48: 9437.557 | D48: 10067.63 | E48: 10229.216 | F48: 10831.178 | G48: 10298.175 | H48: 10074.194 | I48: 9545.597 | J48: 10201.338 | K48: 10382.529 | L48: 11062.242 | M48: 10608.664 | N48: 10111.322 | O48: 9607.404 | P48: 10386.472 | Q48: 10645.195 | R48: 11463.171 | S48: 11082.769
A50: Inputs by case and quarter (the assumptions behind each case) | B50: pp rows are percentage points; FX and timing rows are common across cases (WS29 consensus-EUR schedule)
B51: Literal | H51: Delivered | N51: Ambition
A52: Input | B52: 3Q26 | C52: 4Q26 | D52: 1Q27 | E52: 2Q27 | F52: 3Q27 | G52: 4Q27 | H52: 3Q26 | I52: 4Q26 | J52: 1Q27 | K52: 2Q27 | L52: 3Q27 | M52: 4Q27 | N52: 3Q26 | O52: 4Q26 | P52: 1Q27 | Q52: 2Q27 | R52: 3Q27 | S52: 4Q27
A53: Nights growth y/y | B53: 0.1 | C53: 0.085 | D53: 0.09 | E53: 0.09 | F53: 0.09 | G53: 0.09 | H53: 0.115 | I53: 0.105 | J53: 0.1 | K53: 0.1 | L53: 0.1 | M53: 0.1 | N53: 0.125 | O53: 0.12 | P53: 0.12 | Q53: 0.12 | R53: 0.12 | S53: 0.12
A54: ADR growth ex-FX y/y | B54: 0.03 | C54: 0.025 | D54: 0.025 | E54: 0.025 | F54: 0.025 | G54: 0.025 | H54: 0.035 | I54: 0.03 | J54: 0.03 | K54: 0.03 | L54: 0.03 | M54: 0.03 | N54: 0.04 | O54: 0.035 | P54: 0.03 | Q54: 0.03 | R54: 0.03 | S54: 0.03
A55: ADR FX effect (pp) | B55: 0.3 | C55: -0.4 | D55: -0.4 | E55: 0 | F55: 0.7 | G55: 0 | H55: 0.3 | I55: -0.4 | J55: -0.4 | K55: 0 | L55: 0.7 | M55: 0 | N55: 0.3 | O55: -0.4 | P55: -0.4 | Q55: 0 | R55: 0.7 | S55: 0
A56: Take-rate change vs prior year (pp) | B56: 0 | C56: 0 | D56: 0 | E56: 0 | F56: 0 | G56: 0 | H56: 0 | I56: 0 | J56: 0 | K56: 0 | L56: 0 | M56: 0 | N56: 0 | O56: 0 | P56: 1.5 | Q56: 1.5 | R56: 1.5 | S56: 1.5
A57: Revenue FX after hedging (pp) | B57: 3 | C57: -0.4 | D57: -1 | E57: -0.8 | F57: -0.6 | G57: -0.1 | H57: 3 | I57: -0.4 | J57: -1 | K57: -0.8 | L57: -0.6 | M57: -0.1 | N57: 3 | O57: -0.4 | P57: -1 | Q57: -0.8 | R57: -0.6 | S57: -0.1
A58: Timing / RNPL residual (pp of revenue growth) | B58: -1.0523 | C58: -0.5171 | D58: 0 | E58: 0 | F58: 0 | G58: 0 | H58: -1.1081 | I58: -0.6 | J58: 0 | K58: 0 | L58: 0 | M58: 0 | N58: -1.1 | O58: -0.6 | P58: 0.5 | Q58: 0.5 | R58: 0.5 | S58: 0.5
A59: SBC growth y/y | B59: 0.1 | C59: 0.1 | D59: 0.09 | E59: 0.09 | F59: 0.09 | G59: 0.09 | H59: 0.1 | I59: 0.1 | J59: 0.09 | K59: 0.09 | L59: 0.09 | M59: 0.09 | N59: 0.1 | O59: 0.1 | P59: 0.08 | Q59: 0.08 | R59: 0.08 | S59: 0.08
A60: D&A (% of revenue) | B60: 0.0065 | C60: 0.0065 | D60: 0.0065 | E60: 0.0065 | F60: 0.0065 | G60: 0.0065 | H60: 0.0065 | I60: 0.0065 | J60: 0.0065 | K60: 0.0065 | L60: 0.0065 | M60: 0.0065 | N60: 0.0065 | O60: 0.0065 | P60: 0.0065 | Q60: 0.0065 | R60: 0.0065 | S60: 0.0065
A61: Interest income ($m) | B61: 170 | C61: 165 | D61: 160 | E61: 160 | F61: 160 | G61: 160 | H61: 170 | I61: 165 | J61: 160 | K61: 160 | L61: 160 | M61: 160 | N61: 170 | O61: 165 | P61: 160 | Q61: 160 | R61: 160 | S61: 160
A62: Interest expense ($m) | B62: 31 | C62: 31 | D62: 31 | E62: 31 | F62: 31 | G62: 31 | H62: 31 | I62: 31 | J62: 31 | K62: 31 | L62: 31 | M62: 31 | N62: 31 | O62: 31 | P62: 31 | Q62: 31 | R62: 31 | S62: 31
A63: Effective tax rate | B63: 0.18 | C63: 0.18 | D63: 0.18 | E63: 0.18 | F63: 0.18 | G63: 0.18 | H63: 0.18 | I63: 0.18 | J63: 0.18 | K63: 0.18 | L63: 0.18 | M63: 0.18 | N63: 0.18 | O63: 0.18 | P63: 0.18 | Q63: 0.18 | R63: 0.18 | S63: 0.18
A64: Buybacks ($m) | B64: 1050 | C64: 1050 | D64: 1050 | E64: 1050 | F64: 1050 | G64: 1050 | H64: 1050 | I64: 1050 | J64: 1050 | K64: 1050 | L64: 1050 | M64: 1050 | N64: 1050 | O64: 1050 | P64: 1050 | Q64: 1050 | R64: 1050 | S64: 1050
... A68: Adj. EBITDA margin change y/y (pp) | B68: -0.6 | C68: 0.3467 | D68: -0.0051 | E68: -0.0051 | F68: -0.0051 | G68: -0.0051 | H68: -0.1 | I68: 2.5309 | J68: -0.0074 | K68: -0.0074 | L68: -0.0074 | M68: -0.0074 | N68: 0.3 | O68: 3.077 | P68: 0.4921 | Q68: 0.4921 | R68: 0.4921 | S68: 0.4921
A70: Implied share price by lens and case (team multiples: EV/EBITDA 13.5 / 16.5 / 18.5x; P/E 22 / 27 / 30x; EV/FCF 14 / 17 / 20x)
A71: Reference share price ($, close 11 Sep 2026) | B71: 170.19 | D71: input: the upside columns reference this cell
A72: Lens (multiple) | B72: Literal | C72: Delivered | D72: Ambition | E72: Literal upside | F72: Delivered upside | G72: Ambition upside
A73: EV / FY27E adj. EBITDA x Low | B73: 149.31227 | C73: 155.8217 | D73: 166.38888 | E73: =B73/$B$71-1 -> -0.12267308 | F73: =C73/$B$71-1 -> -0.084425061 | G73: =D73/$B$71-1 -> -0.022334591
A74: EV / FY27E adj. EBITDA x Mid | B74: 178.48255 | C74: 186.31761 | D74: 199.04843 | E74: =B74/$B$71-1 -> 0.04872525 | F74: =C74/$B$71-1 -> 0.094762399 | G74: =D74/$B$71-1 -> 0.16956598
A75: EV / FY27E adj. EBITDA x High | B75: 197.9294 | C75: 206.64822 | D75: 220.82147 | E75: =B75/$B$71-1 -> 0.1629908 | F75: =C75/$B$71-1 -> 0.21422071 | G75: =D75/$B$71-1 -> 0.2974997
A76: P / FY27E GAAP EPS x Low | B76: 125.90829 | C76: 133.71138 | D76: 146.97761 | E76: =B76/$B$71-1 -> -0.26018982 | F76: =C76/$B$71-1 -> -0.21434055 | G76: =D76/$B$71-1 -> -0.13639103
A77: P / FY27E GAAP EPS x Mid | B77: 154.52382 | C77: 164.10033 | D77: 180.38161 | E77: =B77/$B$71-1 -> -0.092051141 | F77: =C77/$B$71-1 -> -0.035781581 | G77: =D77/$B$71-1 -> 0.059883735
A78: P / FY27E GAAP EPS x High | B78: 171.69313 | C78: 182.3337 | D78: 200.42401 | E78: =B78/$B$71-1 -> 0.0088320657 | F78: =C78/$B$71-1 -> 0.071353799 | G78: =D78/$B$71-1 -> 0.17764859
A79: EV / FY27E FCF x Low | B79: 158.81884 | C79: 164.32958 | D79: 175.12245 | E79: =B79/$B$71-1 -> -0.066814495 | F79: =C79/$B$71-1 -> -0.034434557 | G79: =D79/$B$71-1 -> 0.028982021
A80: EV / FY27E FCF x Mid | B80: 188.98445 | C80: 195.55947 | D80: 208.48708 | E80: =B80/$B$71-1 -> 0.11043216 | F80: =C80/$B$71-1 -> 0.1490656 | G80: =D80/$B$71-1 -> 0.22502542
A81: EV / FY27E FCF x High | B81: 219.15006 | C81: 226.78937 | D81: 241.8517 | E81: =B81/$B$71-1 -> 0.28767881 | F81: =C81/$B$71-1 -> 0.33256576 | G81: =D81/$B$71-1 -> 0.42106881
A82: Average of the three mid multiples | B82: 173.99694 | C82: 181.99247 | D82: 195.97237 | E82: =B82/$B$71-1 -> 0.022368756 | F82: =C82/$B$71-1 -> 0.069348807 | G82: =D82/$B$71-1 -> 0.15149171
A83: Average of all nine cells | B83: 171.64476 | C83: 179.51238 | D83: 193.27814 | E83: =B83/$B$71-1 -> 0.0085478399 | F83: =C83/$B$71-1 -> 0.05477628 | G83: =D83/$B$71-1 -> 0.13566096
A85: Reverse DCF on management's own FCF (EV $92.0bn at $170.19; WACC 10%; growth fades to 3% over ten years)
A86: Item | B86: Literal | C86: Delivered | D86: Ambition
A87: FY27E free cash flow, reported ($m) | B87: 5738.124 | C87: 5940.573 | D87: 6346.656
A88: FY27E free cash flow less SBC ($m) | B88: 3802.393 | C88: 4004.842 | D88: 4428.684
A89: FY27E FCF growth y/y | B89: 0.10154 | C89: 0.11723 | D89: 0.17989
A90: Implied FCF growth FY28+ on reported FCF (price = $170.19) | B90: 0.05598 | C90: 0.04614 | D90: 0.02742
A91: Implied FCF growth FY28+ on SBC-adjusted FCF | B91: 0.17465 | C91: 0.15948 | D91: 0.13024
A92: Value per share if FY27 FCF growth were sustained ($) | B92: 196.839 | C92: 213.703 | D92: 277.955
A93: The seven-turn gap between the reported and SBC-adjusted readings is the SBC debate: on reported FCF the market asks for little; on FCF after SBC it asks for mid-teens growth.
A95: What management is looking at, by area: near term, mid term, the number used in the Delivered case, and the line's track record
A96: Area | B96: Near term: what they said (3Q26 / FY26) | C96: Mid term: what they said (FY27 and beyond) | D96: Number used (Delivered case) | E96: Track record of this line | F96: Source
A97: Nights & Seats Booked | B97: 3Q26 'low double-digit growth'; FY26 'accelerated pace of Nights and Seats Booked we've observed'; 2Q26 +10.3% with every region up, expansion markets ~2x core, first-time bookers +11% (highest in four years), app nights +23% = 64% of total | C97: No number. 8 Sep: 'almost every market is accelerating', 'four of the five countries [70% of the business] are accelerating', India +60%; core business 'could probably be double the size' | D97: 3Q26 +11.5%, 4Q26 +10.5%, FY27 +10.0% | E97: Bucket guides: 3 of 3 since 4Q25 printed ABOVE the range (+1 to +5pts). Directional guides 92% met (n=13) | F97: 2Q26 letter p.6; 2Q26 call; Communacopia 8 Sep 2026
A98: ADR | B98: 3Q26 'moderate increase in ADR due to mix shift and price appreciation'; 2Q26 +5% (+4% ex-FX), 'noticeable strength in North America and Europe'; bedroom nights +12% vs nights +10% (larger homes keep growing fastest) | C98: AI pricing model 'one of the biggest single levers for growth', 'many multiples bigger than RNPL' -> aimed at affordability, i.e. it argues for LOWER host prices over time, not higher; ADR ex-FX above ~3% is mix, not price | D98: ex-FX +3.5% 3Q26, +3.0% thereafter; FX +0.3 / -0.4 / -0.4 / 0 / +0.7 / 0 pp | E98: ADR floors/points 16 of 18 met or beaten | F98: 2Q26 letter p.10; 2Q26 call (pricing answer)
A99: GBV | B99: 3Q26 'mid teens' (nights low double digits + moderate ADR); 2Q26 +16% (+15% ex-FX); RNPL >20% of GBV, eligibility expanded in July | C99: 'approaching $100 billion in GBV' (8 Sep); FY25 was $91.3bn, FY26 lands ~$106bn in the Delivered case | D99: 3Q26 +15.4%, 4Q26 +13.4%, FY27 +13.3% | E99: Bucket guides beaten by 4-6pts in all three cases since 4Q25 | F99: 2Q26 letter; Communacopia
A100: Take rate / monetisation | B100: FY26 'relatively flat compared to 2025' (13.41%) after RNPL timing and 'higher customer incentives related to new businesses'; 'absent these incentives... slightly higher'; 3Q26 'relatively in-line'; single fee to be completed by year-end (half of listings already) | C100: Sponsored listings 'a pretty easy straight shot to $1 billion incremental high margin revenue' (8 Sep, undated); travel insurance 'very high margin... does quite well'; advertising deferred behind AI search | D100: flat in Literal/Delivered; +20bp FY27 in Ambition | E100: The weak line: 59% kept (n=17). FY25 promised +20bp, printed -16bp. 1Q26 'lift full-year take rate' withdrawn at 2Q26 | F100: 2Q26 call prepared remarks; 31a S165/S166/S110
A101: Cancellations / RNPL | B101: Not disclosed. Nights and GBV are reported net of cancellations. RNPL defers payment to near check-in; 2Q26: 'absent RNPL... unearned fees would have grown y/y'; 1Q26 letter predicted unearned fees higher y/y in 3Q26 (forward-testable on 5 Nov). 1Q26: Middle East cancellations cost ~1pt of nights | C101: Nothing. The team's own RNPL ledger (overnight2 D) models a -0.1 to -1.4pt cancellation drag on 3Q26/4Q26 nights; management has never sized it | D101: Inside the -0.6 to -1.1pp timing residual | E101: n/a (never guided) | F101: 2Q26 call CFO; 1Q26 letter; docs/overnight2/SYNTHESIS.md
A102: Revenue | B102: 3Q26 $4.69-4.77bn (+15-17%) incl. ~3pp FX after hedging; FY26 'at least mid teens' (raised from 'low double digits' in Feb and 'low-to-mid teens' in May) | C102: No FY27 number ('I'm not going to give you a specific guide for 2027 and beyond'). Pattern: Feb guide is a floor, raised twice, printed 1-3pp above | D102: 3Q26 $4,815M (+17.6%), 4Q26 $3,131M (+12.7%), FY26 $14.23bn (+16.3%), FY27 $15.99bn (+12.4%) | E102: 19 of 19 quarterly ranges beaten at the midpoint (median +2.5%, last eight +1.8%); 15 of 19 above the top | F102: 2Q26 letter p.6; 02_guidance_ledger.csv
A103: FX | B103: ~3pp tailwind to 3Q26 revenue after hedging (was 0 / +3 / +4 in 4Q25-2Q26); ADR FX 'significantly lower in Q2 than Q1' | C103: Silent; hedging programme unchanged. Consensus EUR path turns FX to a -0.4 to -1.0pp headwind from 4Q26 | D103: WS29 schedule | E103: FX statements 100% kept but they only ever guide one quarter | F103: 2Q26 letter; 28_fx-hedge-disclosures.md
A104: Adj. EBITDA margin | B104: FY26 'at least 35.5%' (raised from 'stable' -> '>=35%' -> '>=35.5%'); 3Q26 'down slightly compared to Q3 2025' (50.1%) 'due to timing of investments'; 2Q26 printed 35.0% (+1.3pts) on ops & support and product-dev efficiency, offset by S&M | C104: 'There's a relative floor in our ability to continue to invest against that' (2Q26); 'we basically have remained pretty steady, 35% margins' (8 Sep); rule: find variable-cost efficiencies every year and reinvest most of them | D104: 3Q26 50.0%, 4Q26 30.8%, FY26 36.2%, FY27 36.2% | E104: Total-margin statements 91% kept (n=43). Floors beaten by +140bp (FY24), +60bp (FY25). Floor becomes a point ('approximately X') at the Q3 print | F104: 2Q26 letter; 31a note
A105: Cost lines | B105: Cost of revenue 'scale somewhat linearly'; ops & support cost per booking -16% y/y (AI resolves ~45% of tickets); product dev: 'we don't need to grow our head count at levels that we did in the past'; S&M: 'where you will see some incremental investment'; AI spend: guidance 'assumes a material increase' (unsized) | C105: No FY27 line has a number. Brand marketing is fixed per market ('surgical topper' for performance); hotels build-out unbudgeted; services are partnerships ('we do not see a big incurring of cost') | D105: Not modelled line by line here (margin is the policy variable per 31a); WS30/31 hold the line build | E105: Ops & support 100% kept (n=13); brand marketing 63% (n=35); product dev 60%; SBC 40% | F105: 31a_mgmt-margin-statements.md
A106: SBC / share count | B106: FY26 SBC growth 'lower than 2025'; 1H26 +14.7%; 37.8M RSUs + 5.7M options outstanding; diluted WA 597M in 2Q26 (-4.6% y/y) | C106: Silent; the SBC-equals-headcount promise was withdrawn at 4Q25 | D106: SBC +10% H2-26, +9% FY27; shares -4.5M/q net | E106: SBC guides 40% kept (n=5) | F106: 4Q25 letter; 2Q26 10-Q
A107: Capital return | B107: $1.1bn repurchased in 2Q26, $2.1bn in 1H26; $3.4bn authorisation remaining (2Q26 call); 'returning capital to shareholders remains a core component' | C107: Nothing beyond the authorisation; at the current pace it is exhausted by ~2Q27, so a new programme is the likely 4Q26/1Q27 announcement | D107: $1,050M/q through FY27 ($4.2bn/yr) | E107: FY24 $3.4bn, FY25 $3.8bn delivered; never guided | F107: 2Q26 call CFO; 10-Q
... A112: Regulation | B112: Not in guidance. 2Q26 letter: usual risk-factor language only | C112: Nothing | D112: Zero; the team's regulatory Monte Carlo (PR #15) is the only quantification | E112: n/a | F112: regulatory package, PR #19
A114: Sources (paths relative to the repo root)
A115: Three cases, quarterly and annual | B115: data/processed/reverse_dcf/mgmt_implied_summary.csv
...

Sheet Reverse DCF - Market
A1: Reverse DCF - Market-implied: what the price, the options and the sell-side imply
A2: Joint solve (multiple endogenous to growth) at $170.19, the options-implied distribution and 5 Nov event move, the sell-side tape, the print reaction function and the positioning card. Run of 12-13 Sep 2026.
A4: What this tab says
