Workbook

Sheet Cover
A1: Airbnb (ABNB) — official model, built line by line. Line 1: nights. Line 2: ADR.
A3: What this is | B3: The nights engine (reviews_index_v2, v2.1) laid out cell by cell, and the income-statement scaffold with nights as its first line. Everything derivable is an Excel formula; every input carries its source.
A4: How to trace | B4: Nights_Engine, blocks A–H: printed nights → regional stays growth × stay-mix weights = index → INTERCEPT/SLOPE on 1Q23–2Q25 = the frozen mapping → walk-forward W1/W2 reproduced row by row → 3Q26 read → the option term (scenarios, y/y lap, kernel landing) → forward path as sums of sourced components → Street, guidance, tail probability → unearned fees vs GBV → Stage A statistics.
A5: Colours | B5: Header fill FF385C = section; fill 222222 = block title; blue text = input with source; black = formula; green = link to another sheet or block; pink fill = a headline number; yellow fill = to be built.
A6: Engine | B6: analysis/src/forecast_methods/reviews_index_v2 — python3 run.py --stage all (≈15 s), then python3 workbook.py rebuilds this file. Spec, pre-registration and results: docs/revenue-forecast-strategy/05_backtests/REVIEWS_INDEX_v2.md; rationale: REVIEWS_INDEX_v2_RATIONALE.md.
A7: Status | B7: Nights: built (DEC-0029 base 146.8m). ADR: built (ADR_Engine; pre-registered FX identity promoted, ex-FX mechanism with the bundle lapping on filed dates; proposed DEC-0034/0035 pending Theo), then extended with the v2 geo-mix layer and hardened by the four mitigations of 22 Sep (block G; DEC-0037–0041 pending Theo). Base ADR path unchanged by the mitigations: 3Q26 $177.68, 4Q26 $173.03. GBV = nights × ADR on Income_Statement row 8. Income statement: history 1Q23-2Q26 plugged from the reconciled financial panel; forecast cost lines, SBC, D&A and below-the-line plugged from the 40_line_build base (DEC-0022); take rate Street-implied for 3Q26-4Q26 (DEC-0018) and seasonal naive thereafter, so the margin is an output of our own nights x ADR. Open: DEC-0023 hosting step.
A8: Verification | B8: Nights: formulas recalculated in Excel and checked against the engine (block 'Engine reference values'). ADR: formulas written by adr_engine/workbook.py; open in Excel to recalculate, then tie out block E (walk-forward ratios, FX pp, ADR $).

Sheet Nights_Engine
A1: Airbnb — nights engine (reviews_index_v2, v2.1 stay-quarter mix). Blue = input with source; black = formula; green = link.
A2: Every number below can be traced: inputs carry their file path; every derived cell is an Excel formula on the cells above it. Engine: analysis/src/forecast_methods/reviews_index_v2 (run.py --stage all); note: docs/revenue-forecast-strategy/05_backtests/REVIEWS_INDEX_v2.md
A4: Quarter | B4: A = printed, E = engine | C4: 1Q21A | D4: 2Q21A | E4: 3Q21A | F4: 4Q21A | G4: 1Q22A | H4: 2Q22A | I4: 3Q22A | J4: 4Q22A | K4: 1Q23A | L4: 2Q23A | M4: 3Q23A | N4: 4Q23A | O4: 1Q24A | P4: 2Q24A | Q4: 3Q24A | R4: 4Q24A | S4: 1Q25A | T4: 2Q25A | U4: 3Q25A | V4: 4Q25A | W4: 1Q26A | X4: 2Q26A | Y4: 3Q26E | Z4: 4Q26E | AA4: 1Q27E | AB4: 2Q27E | AC4: 3Q27E | AD4: 4Q27E
A6: A. Printed nights (the KPI, booking-dated)
A7: Nights & seats booked (m) | B7: data/processed/abnb_driver_history_quarterly.csv (10-Q/10-K) | C7: 64.4 | D7: 83.1 | E7: 79.7 | F7: 73.4 | G7: 102.1 | H7: 103.7 | I7: 99.7 | J7: 88.2 | K7: 121.1 | L7: 115.1 | M7: 113.2 | N7: 98.8 | O7: 132.6 | P7: 125.1 | Q7: 122.8 | R7: 111 | S7: 143.1 | T7: 134.4 | U7: 133.6 | V7: 121.9 | W7: 156.2 | X7: 148.3
A8: y/y | B8: → nights / nights four quarters earlier − 1 | G8: =G7/C7-1 -> 0.58540373 | H8: =H7/D7-1 -> 0.2478941 | I8: =I7/E7-1 -> 0.25094103 | J8: =J7/F7-1 -> 0.20163488 | K8: =K7/G7-1 -> 0.18609207 | L8: =L7/H7-1 -> 0.1099325 | M8: =M7/I7-1 -> 0.13540622 | N8: =N7/J7-1 -> 0.12018141 | ... X8: =X7/T7-1 -> 0.10342262
A10: B. Stays index — regional stays growth (same-age two-vintage review counts) × stay-quarter mix weights
A11: Stays y/y, NAM (%) | B11: index_regional_vmatch_pct.csv (Inside Airbnb reviews, vmatch) | C11: -30.009186 | D11: 256.22579 | E11: 84.267421 | F11: 86.208477 | G11: 67.324547 | H11: 46.571018 | I11: 22.732978 | J11: 11.322568 | K11: 9.7224684 | L11: 3.9560507 | M11: 4.3760435 | N11: 1.61386 | O11: 1.4023741 | P11: 0.11141141 | Q11: 2.569901 | R11: 2.7347428 | S11: -2.6372923 | T11: -0.91095634 | U11: -0.38243552 | V11: 0.059808764 | W11: 5.4096747 | X11: 6.8959656
A12: Stays y/y, EMEA (%) | B12: index_regional_vmatch_pct.csv (Inside Airbnb reviews, vmatch) | C12: -74.978465 | D12: 408.42535 | E12: 76.402152 | F12: 266.06162 | G12: 324.38397 | H12: 256.4864 | I12: 55.237057 | J12: 34.48634 | K12: 36.693192 | L12: 23.201082 | M12: 11.821018 | N12: 14.612667 | O12: 9.2353198 | P12: 8.8281243 | Q12: 5.5260003 | R12: 6.7601096 | S12: 4.2529156 | T12: 2.9855344 | U12: 2.1806637 | V12: 5.5190956 | W12: 4.7307413 | X12: 1.4823409
A13: Stays y/y, LatAm (%) | B13: index_regional_vmatch_pct.csv (Inside Airbnb reviews, vmatch) | C13: -50.559682 | D13: 384.87718 | E13: 131.73399 | F13: 101.51506 | G13: 128.20255 | H13: 134.69878 | I13: 102.44056 | J13: 67.420907 | K13: 50.234582 | L13: 35.123094 | M13: 33.380883 | N13: 38.083971 | O13: 24.186325 | P13: 16.542043 | Q13: 24.111263 | R13: 13.35591 | S13: 27.15945 | T13: 34.005572 | U13: 18.44378 | V13: 24.824748 | W13: 18.22158 | X13: 20.395825
A14: Stays y/y, APAC (%) | B14: index_regional_vmatch_pct.csv (Inside Airbnb reviews, vmatch) | C14: -24.215632 | D14: 231.83258 | E14: -3.9807107 | F14: -2.6257212 | G14: 12.215553 | H14: 16.689583 | I14: 95.7677 | J14: 74.884346 | K14: 53.345968 | L14: 18.132796 | M14: 14.799396 | N14: 16.516761 | O14: 21.770867 | P14: 4.8761296 | Q14: 2.0800717 | R14: 8.6573671 | S14: -0.82253826 | T14: 4.7150993 | U14: 4.9485043 | V14: 6.2442451 | W14: 8.8637261 | X14: 2.3029909
A15: Stay-mix weight, NAM | B15: mix_weights_stay_quarter.csv (regional revenue ÷ ADR index; drift rule fwd) | G15: 0.39766449 | H15: 0.39419766 | I15: 0.34525404 | J15: 0.36554987 | K15: 0.36026345 | L15: 0.35450833 | M15: 0.32168886 | N15: 0.33132229 | O15: 0.32794356 | P15: 0.35097958 | Q15: 0.30945651 | R15: 0.31131842 | S15: 0.31811106 | T15: 0.32187024 | U15: 0.28670938 | V15: 0.28052526 | W15: 0.28475207 | X15: 0.31848284 | Y15: 0.26492132 | Z15: 0.25327854 | AA15: 0.25205453 | AB15: 0.28037536 | AC15: 0.22127536 | AD15: 0.20414601
A16: Stay-mix weight, EMEA | B16: mix_weights_stay_quarter.csv (regional revenue ÷ ADR index; drift rule fwd) | G16: 0.26416206 | H16: 0.38471524 | I16: 0.48141011 | J16: 0.30864625 | K16: 0.26113228 | L16: 0.409691 | M16: 0.48845027 | N16: 0.31761694 | O16: 0.26818392 | P16: 0.41167264 | Q16: 0.49739852 | R16: 0.32570758 | S16: 0.26377225 | T16: 0.42191656 | U16: 0.51045491 | V16: 0.33326286 | W16: 0.27362882 | X16: 0.41680142 | Y16: 0.5148668 | Z16: 0.33860146 | AA16: 0.27996478 | AB16: 0.42439557 | AC16: 0.52370473 | AD16: 0.34822828
A17: Stay-mix weight, LatAm | B17: mix_weights_stay_quarter.csv (regional revenue ÷ ADR index; drift rule fwd) | G17: 0.17982266 | H17: 0.10270976 | I17: 0.075576971 | J17: 0.14966176 | K17: 0.19112864 | L17: 0.10123186 | M17: 0.080902329 | N17: 0.16451195 | O17: 0.20713375 | P17: 0.10366336 | Q17: 0.081804952 | R17: 0.16267281 | S17: 0.21617811 | T17: 0.11275565 | U17: 0.086904517 | V17: 0.17942126 | W17: 0.23565714 | X17: 0.12141438 | Y17: 0.10018467 | Z17: 0.19611738 | AA17: 0.25576405 | AB17: 0.14471699 | AC17: 0.12678753 | AD17: 0.22622459
A18: Stay-mix weight, APAC | B18: mix_weights_stay_quarter.csv (regional revenue ÷ ADR index; drift rule fwd) | G18: 0.15835079 | H18: 0.11837735 | I18: 0.097758872 | J18: 0.17614213 | K18: 0.18747562 | L18: 0.1345688 | M18: 0.10895854 | N18: 0.18654882 | O18: 0.19673876 | P18: 0.13368442 | Q18: 0.11134002 | R18: 0.20030119 | S18: 0.20193858 | T18: 0.14345755 | U18: 0.11593119 | V18: 0.20679061 | W18: 0.20596198 | X18: 0.14330136 | Y18: 0.12002721 | Z18: 0.21200261 | AA18: 0.21221664 | AB18: 0.15051208 | AC18: 0.12823238 | AD18: 0.22140113
A19: Global stays index, y/y (%) | B19: → SUMPRODUCT(regional growth, weights) | G19: =SUMPRODUCT(G11:G14,G15:G18) -> 137.45058 | H19: =SUMPRODUCT(H11:H14,H15:H18) -> 132.84296 | I19: =SUMPRODUCT(I11:I14,I15:I18) -> 51.54462 | J19: =SUMPRODUCT(J11:J14,J15:J18) -> 38.063662 | K19: =SUMPRODUCT(K11:K14,K15:K18) -> 32.686763 | L19: =SUMPRODUCT(L11:L14,L15:L18) -> 16.903412 | M19: =SUMPRODUCT(M11:M14,M15:M18) -> 11.494816 | N19: =SUMPRODUCT(N11:N14,N15:N18) -> 14.522389 | ... X19: =SUMPRODUCT(X11:X14,X15:X18) -> 5.6204567
A21: C. Mapping to the KPI — nights y/y = a + b × index, fitted 1Q23–2Q25 and frozen; scored walk-forward
A22: Intercept a (frozen, 1Q23–2Q25) | B22: → INTERCEPT(nights y/y, index) — pre-RNPL quarters only | C22: =INTERCEPT(K8:T8,K19:T19)*100 -> 6.8246002 | D22: pp
A23: Slope b (frozen, 1Q23–2Q25) | B23: → SLOPE(nights y/y, index) | C23: =SLOPE(K8:T8,K19:T19)*100 -> 0.34969 | D23: pp of nights per index point
A25: Stays-implied nights y/y (%) | B25: → a + b × index (frozen mapping) | K25: =$C$22+$C$23*K19 -> 18.254834 | L25: =$C$22+$C$23*L19 -> 12.735555 | M25: =$C$22+$C$23*M19 -> 10.844222 | N25: =$C$22+$C$23*N19 -> 11.902934 | O25: =$C$22+$C$23*O19 -> 11.101184 | P25: =$C$22+$C$23*P19 -> 8.9367511 | Q25: =$C$22+$C$23*Q19 -> 8.8345879 | R25: =$C$22+$C$23*R19 -> 9.2584143 | ... X25: =$C$22+$C$23*X19 -> 8.7900177
A26: Gap: printed − stays-implied (pp) | B26: the option term I, observed (3Q25 onward) | K26: =K8*100-K25 -> 0.35437224 | L26: =L8*100-L25 -> -1.7423048 | M26: =M8*100-M25 -> 2.6963996 | N26: =N8*100-N25 -> 0.11520611 | O26: =O8*100-O25 -> -1.6048994 | P26: =P8*100-P25 -> -0.24865384 | Q26: =Q8*100-Q25 -> -0.35402249 | R26: =R8*100-R25 -> 3.0897638 | ... X26: =X8*100-X25 -> 1.5522442
A28: C1. Walk-forward W1 — window 1Q22+, scored 1Q23–2Q26
A29: prediction (refit on quarters before t) | B29: → INTERCEPT(prior y, prior x) + SLOPE(prior y, prior x) × index_t | K29: =(INTERCEPT(G8:J8,G19:J19)+SLOPE(G8:J8,G19:J19)*K19)*100 -> 19.454303 | L29: =(INTERCEPT(G8:K8,G19:K19)+SLOPE(G8:K8,G19:K19)*L19)*100 -> 15.569258 | M29: =(INTERCEPT(G8:L8,G19:L19)+SLOPE(G8:L8,G19:L19)*M19)*100 -> 12.640135 | N29: =(INTERCEPT(G8:M8,G19:M19)+SLOPE(G8:M8,G19:M19)*N19)*100 -> 13.619791 | O29: =(INTERCEPT(G8:N8,G19:N19)+SLOPE(G8:N8,G19:N19)*O19)*100 -> 12.726287 | P29: =(INTERCEPT(G8:O8,G19:O19)+SLOPE(G8:O8,G19:O19)*P19)*100 -> 10.603466 | Q29: =(INTERCEPT(G8:P8,G19:P19)+SLOPE(G8:P8,G19:P19)*Q19)*100 -> 10.203171 | R29: =(INTERCEPT(G8:Q8,G19:Q19)+SLOPE(G8:Q8,G19:Q19)*R19)*100 -> 10.259625 | S29: =(INTERCEPT(G8:R8,G19:R19)+SLOPE(G8:R8,G19:R19)*S19)*100 -> 10.275645 | T29: =(INTERCEPT(G8:S8,G19:S19)+SLOPE(G8:S8,G19:S19)*T19)*100 -> 9.8788874 | U29: =(INTERCEPT(G8:T8,G19:T19)+SLOPE(G8:T8,G19:T19)*U19)*100 -> 9.0365752 | V29: =(INTERCEPT(G8:U8,G19:U19)+SLOPE(G8:U8,G19:U19)*V19)*100 -> 10.15263 | W29: =(INTERCEPT(G8:V8,G19:V19)+SLOPE(G8:V8,G19:V19)*W19)*100 -> 10.47465 | X29: =(INTERCEPT(G8:W8,G19:W19)+SLOPE(G8:W8,G19:W19)*X19)*100 -> 9.514287
A30: error: prediction − printed (pp) | K30: =K29-K8*100 -> 0.84509657 | L30: =L29-L8*100 -> 4.576008 | M30: =M29-M8*100 -> -0.90048698 | N30: =N29-N8*100 -> 1.6016503 | O30: =O29-O8*100 -> 3.2300026 | P30: =P29-P8*100 -> 1.9153685 | Q30: =Q29-Q8*100 -> 1.7226053 | R30: =R29-R8*100 -> -2.0885532 | ... X30: =X29-X8*100 -> -0.82797486
A31: naive error: last quarter's y/y − printed (pp) | K31: =(J8-K8)*100 -> 1.5542811 | L31: =(K8-L8)*100 -> 7.6159569 | M31: =(L8-M8)*100 -> -2.5473721 | N31: =(M8-N8)*100 -> 1.5224813 | O31: =(N8-O8)*100 -> 2.5218565 | P31: =(O8-P8)*100 -> 0.80818676 | Q31: =(P8-Q8)*100 -> 0.20753194 | R31: =(Q8-R8)*100 -> -3.8676128 | ... X31: =(W8-X8)*100 -> -1.1878244
A32: RMSE engine / RMSE naive | B32: scored 1Q23–2Q26, n 14 | C32: =SQRT(SUMSQ(K30:X30)/COUNT(K30:X30)) -> 2.0803847 | D32: =SQRT(SUMSQ(K31:X31)/COUNT(K31:X31)) -> 2.8766591 | E32: =C32/D32 -> 0.72319473 | F32: ratio (pass line ≤ 0.75)
A33: mean error (pp) | C33: =AVERAGE(K30:X30) -> 1.1978896
A34: C2. Walk-forward W2 — window 1Q23+, scored 1Q24–2Q26
A35: prediction (refit on quarters before t) | B35: → INTERCEPT(prior y, prior x) + SLOPE(prior y, prior x) × index_t | O35: =(INTERCEPT(K8:N8,K19:N19)+SLOPE(K8:N8,K19:N19)*O19)*100 -> 11.758526 | P35: =(INTERCEPT(K8:O8,K19:O19)+SLOPE(K8:O8,K19:O19)*P19)*100 -> 8.9628958 | Q35: =(INTERCEPT(K8:P8,K19:P19)+SLOPE(K8:P8,K19:P19)*Q19)*100 -> 8.753463 | R35: =(INTERCEPT(K8:Q8,K19:Q19)+SLOPE(K8:Q8,K19:Q19)*R19)*100 -> 9.1056806 | S35: =(INTERCEPT(K8:R8,K19:R19)+SLOPE(K8:R8,K19:R19)*S19)*100 -> 9.4435499 | T35: =(INTERCEPT(K8:S8,K19:S19)+SLOPE(K8:S8,K19:S19)*T19)*100 -> 8.9939625 | U35: =(INTERCEPT(K8:T8,K19:T19)+SLOPE(K8:T8,K19:T19)*U19)*100 -> 7.9366202 | V35: =(INTERCEPT(K8:U8,K19:U19)+SLOPE(K8:U8,K19:U19)*V19)*100 -> 9.5934136 | W35: =(INTERCEPT(K8:V8,K19:V19)+SLOPE(K8:V8,K19:V19)*W19)*100 -> 10.07429 | X35: =(INTERCEPT(K8:W8,K19:W19)+SLOPE(K8:W8,K19:W19)*X19)*100 -> 8.8623061
A36: error: prediction − printed (pp) | O36: =O35-O8*100 -> 2.2622421 | P36: =P35-P8*100 -> 0.2747985 | Q36: =Q35-Q8*100 -> 0.27289762 | R36: =R35-R8*100 -> -3.2424975 | S36: =S35-S8*100 -> 1.5249979 | T36: =T35-T8*100 -> 1.5599098 | U36: =U35-U8*100 -> -0.8581681 | V36: =V35-V8*100 -> -0.22640621 | ... X36: =X35-X8*100 -> -1.4799558
A37: naive error: last quarter's y/y − printed (pp) | O37: =(N8-O8)*100 -> 2.5218565 | P37: =(O8-P8)*100 -> 0.80818676 | Q37: =(P8-Q8)*100 -> 0.20753194 | R37: =(Q8-R8)*100 -> -3.8676128 | S37: =(R8-S8)*100 -> 4.4296261 | T37: =(S8-T8)*100 -> 0.48449928 | U37: =(T8-U8)*100 -> -1.3607355 | V37: =(U8-V8)*100 -> -1.0250315 | ... X37: =(W8-X8)*100 -> -1.1878244
A38: RMSE engine / RMSE naive | B38: scored 1Q24–2Q26, n 10 | C38: =SQRT(SUMSQ(O36:X36)/COUNT(O36:X36)) -> 1.5609152 | D38: =SQRT(SUMSQ(O37:X37)/COUNT(O37:X37)) -> 2.1593217 | E38: =C38/D38 -> 0.72287293 | F38: ratio (pass line ≤ 0.75)
A39: mean error (pp) | C39: =AVERAGE(O36:X36) -> 0.10076703
A40: C3. Band — W2 walk-forward on the pre-RNPL quarters only, scored 1Q24–2Q25
A41: prediction (refit on quarters before t) | B41: → INTERCEPT(prior y, prior x) + SLOPE(prior y, prior x) × index_t | O41: =(INTERCEPT(K8:N8,K19:N19)+SLOPE(K8:N8,K19:N19)*O19)*100 -> 11.758526 | P41: =(INTERCEPT(K8:O8,K19:O19)+SLOPE(K8:O8,K19:O19)*P19)*100 -> 8.9628958 | Q41: =(INTERCEPT(K8:P8,K19:P19)+SLOPE(K8:P8,K19:P19)*Q19)*100 -> 8.753463 | R41: =(INTERCEPT(K8:Q8,K19:Q19)+SLOPE(K8:Q8,K19:Q19)*R19)*100 -> 9.1056806 | S41: =(INTERCEPT(K8:R8,K19:R19)+SLOPE(K8:R8,K19:R19)*S19)*100 -> 9.4435499 | T41: =(INTERCEPT(K8:S8,K19:S19)+SLOPE(K8:S8,K19:S19)*T19)*100 -> 8.9939625
A42: error: prediction − printed (pp) | O42: =O41-O8*100 -> 2.2622421 | P42: =P41-P8*100 -> 0.2747985 | Q42: =Q41-Q8*100 -> 0.27289762 | R42: =R41-R8*100 -> -3.2424975 | S42: =S41-S8*100 -> 1.5249979 | T42: =T41-T8*100 -> 1.5599098
A43: naive error: last quarter's y/y − printed (pp) | O43: =(N8-O8)*100 -> 2.5218565 | P43: =(O8-P8)*100 -> 0.80818676 | Q43: =(P8-Q8)*100 -> 0.20753194 | R43: =(Q8-R8)*100 -> -3.8676128 | S43: =(R8-S8)*100 -> 4.4296261 | T43: =(S8-T8)*100 -> 0.48449928
A44: RMSE engine / RMSE naive | B44: scored 1Q24–2Q25, n 6 | C44: =SQRT(SUMSQ(O42:T42)/COUNT(O42:T42)) -> 1.8502457 | D44: =SQRT(SUMSQ(O43:T43)/COUNT(O43:T43)) -> 2.6416772 | E44: =C44/D44 -> 0.70040565 | F44: ratio (pass line ≤ 0.75) | G44: ← the RMSE in the first cell of this row is the band (±pp) on every read
A45: mean error (pp) | C45: =AVERAGE(O42:T42) -> 0.44205806
A47: D. The 3Q26 read — quarter-to-date, day-matched, same-age two vintages, through the frozen mapping
A48: 3Q26 QTD stays y/y, NAM (%) | B48: q3nowcast/E/vintage_matched_nowcast.csv (E6, 3q26_to_date, vmatch_cw) | C48: 6.8501694 | D48: =Y15 -> 0.26492132 | E48: ← 3Q26 stay-mix weight (block B)
A49: 3Q26 QTD stays y/y, EMEA (%) | B49: q3nowcast/E/vintage_matched_nowcast.csv (E6, 3q26_to_date, vmatch_cw) | C49: 0.86249526 | D49: =Y16 -> 0.5148668 | E49: ← 3Q26 stay-mix weight (block B)
A50: 3Q26 QTD stays y/y, LatAm (%) | B50: q3nowcast/E/vintage_matched_nowcast.csv (E6, 3q26_to_date, vmatch_cw) | C50: 27.534173 | D50: =Y17 -> 0.10018467 | E50: ← 3Q26 stay-mix weight (block B)
A51: 3Q26 QTD stays y/y, APAC (%) | B51: q3nowcast/E/vintage_matched_nowcast.csv (E6, 3q26_to_date, vmatch_cw) | C51: 7.34947 | D51: =Y18 -> 0.12002721 | E51: ← 3Q26 stay-mix weight (block B)
A52: Composite QTD index (%) | B52: → SUMPRODUCT(regional, weights)/SUM(weights) | C52: =SUMPRODUCT(C48:C51,D48:D51)/SUM(D48:D51) -> 5.8994644
A53: Partial-to-full-quarter gap (pp) | B53: q3nowcast/E/q3_2026_nowcast.csv gap_mean_pp (measured 2023–25) | C53: 0.087243539
A54: Full-quarter index (%) | B54: → composite + gap | C54: =C52+C53 -> 5.986708
A55: 3Q26 STAYS READ, nights y/y (%) | B55: → a + b × full index | C55: =$C$22+$C$23*C54 -> 8.9180921 | D55: =$C$44 -> 1.8502457 | E55: ± band (block C3)
A56: 3Q26 stays level (m) [lo, hi] | B56: → 3Q25 printed × (1 + read) | C56: =U7*(1+C55/100) -> 145.51457 | D56: =U7*(1+(C55-$C$44)/100) -> 143.04264 | E56: =U7*(1+(C55+$C$44)/100) -> 147.9865
A58: E. The option term — print = stays + I; I observed 3Q25–2Q26, scenarios for 3Q26, y/y lap and kernel landing
A59: I scenario: 0 (exercise keeps pace with writing) | C59: 0 | D59: =$C$55+C59 -> 8.9180921 | E59: =U7*(1+D59/100) -> 145.51457 | F59: ← print y/y and level under each scenario
A60: I scenario: mean observed gap | B60: → AVERAGE(gaps 3Q25–2Q26) | C60: =AVERAGE(U26:X26) -> 0.48650511 | D60: =$C$55+C60 -> 9.4045973 | E60: =U7*(1+D60/100) -> 146.16454
A61: I scenario: largest observed gap (a writing wave) | B61: → MAX(gaps) | C61: =MAX(U26:X26) -> 1.5522442 | D61: =$C$55+C61 -> 10.470336 | E61: =U7*(1+D61/100) -> 147.58837
A63: y/y option term = I_t − I_{t−4} (pp) | B63: what the KPI laps; 3Q26 uses the base print minus the stays read | Y63: =(Y64-$C$55)-U26 -> 0.10973976 | Z63: =0-V26 -> -0.33707681 | AA63: =0-W26 -> 0.80146861 | AB63: =0-X26 -> -1.5522442
A64: Base print y/y (%) — mechanism (DEC-0029/0019/0025) | B64: final_nights.md; components in block F | Y64: =Y84 -> 9.886 | Z64: =Z84 -> 8.12 | AA64: =AA84 -> 8.205 | AB64: =AB84 -> 5.933
A66: K2 kernel: share of a stay quarter's stays booked 0..3 quarters earlier | B66: kernel_leadtime_v2/K2_M_matrix.csv
A67: stays in Q1: lag 0 / 1 / 2 / 3 | C67: 0.55836405 | D67: 0.31449942 | E67: 0.099987084 | F67: 0.027149452
A68: stays in Q2: lag 0 / 1 / 2 / 3 | C68: 0.49807942 | D68: 0.3606152 | E68: 0.082123964 | F68: 0.059181417
A69: stays in Q3: lag 0 / 1 / 2 / 3 | C69: 0.46338217 | D69: 0.38937815 | E69: 0.095450002 | F69: 0.05178968
A70: stays in Q4: lag 0 / 1 / 2 / 3 | C70: 0.50173952 | D70: 0.35284184 | E70: 0.11743769 | F70: 0.027980962
A71: Landing of each writing wave's cancellations, pp (cohort gap × normalised kernel share by stay quarter)
A72: written 3Q25 (gap 3Q25) | U72: =MAX(U26,0)*C69/(C69+D70+E67+F68) -> 0.40769207 | V72: =MAX(U26,0)*D70/(C69+D70+E67+F68) -> 0.31043668 | W72: =MAX(U26,0)*E67/(C69+D70+E67+F68) -> 0.087970459 | X72: =MAX(U26,0)*F68/(C69+D70+E67+F68) -> 0.052068889
A73: written 4Q25 (gap 4Q25) | V73: =MAX(V26,0)*C70/(C70+D67+E68+F69) -> 0.17799747 | W73: =MAX(V26,0)*D67/(C70+D67+E68+F69) -> 0.11157204 | X73: =MAX(V26,0)*E68/(C70+D67+E68+F69) -> 0.029134356 | Y73: =MAX(V26,0)*F69/(C70+D67+E68+F69) -> 0.018372944
A74: written 1Q26 (gap 1Q26) | W74: =MAX(W26,0)*C67/(C67+D68+E69+F70) -> 0 | X74: =MAX(W26,0)*D68/(C67+D68+E69+F70) -> 0 | Y74: =MAX(W26,0)*E69/(C67+D68+E69+F70) -> 0 | Z74: =MAX(W26,0)*F70/(C67+D68+E69+F70) -> 0
A75: written 2Q26 (gap 2Q26) | X75: =MAX(X26,0)*C68/(C68+D69+E70+F67) -> 0.74913505 | Y75: =MAX(X26,0)*D69/(C68+D69+E70+F67) -> 0.5856432 | Z75: =MAX(X26,0)*E70/(C68+D69+E70+F67) -> 0.17663185 | AA75: =MAX(X26,0)*F67/(C68+D69+E70+F67) -> 0.040834063
A76: written 3Q26 (base I) | Y76: =MAX(Y64-$C$55,0)*C69/(C69+D70+E67+F68) -> 0.45982642 | Z76: =MAX(Y64-$C$55,0)*D70/(C69+D70+E67+F68) -> 0.35013432 | AA76: =MAX(Y64-$C$55,0)*E67/(C69+D70+E67+F68) -> 0.099219837 | AB76: =MAX(Y64-$C$55,0)*F68/(C69+D70+E67+F68) -> 0.05872729
A77: cancellations landing, pp | B77: column sums | U77: =SUM(U72:U76) -> 0.40769207 | V77: =SUM(V72:V76) -> 0.48843415 | W77: =SUM(W72:W76) -> 0.1995425 | X77: =SUM(X72:X76) -> 0.8303383 | Y77: =SUM(Y72:Y76) -> 1.0638426 | Z77: =SUM(Z72:Z76) -> 0.52676616 | AA77: =SUM(AA72:AA76) -> 0.1400539 | AB77: =SUM(AB72:AB76) -> 0.05872729
A79: F. Forward path — base y/y as the sum of sourced components; levels; Street; guidance; the stays path
A80: underlying growth (pp) | B80: 3Q26: mechanism 0.288×NA 5.60 + 0.712×ex-NA 11.62; 4Q26: ref 8.90; 2027: NA 0.291×2.31 + ex-NA 0.709×g | Y80: 9.886 | Z80: 8.9 | AA80: 8.31 | AB80: 8.082 | AC80: 7.855 | AD80: 7.627
A81: fee / cancellation lap (pp) | B81: components per final_nights.md §4–6 | Y81: 0 | Z81: -0.78 | AA81: -0.742 | AB81: -0.742 | AC81: -0.742 | AD81: -0.742
A82: ex-NA RNPL lap (pp) | B82: components per final_nights.md §4–6 | Y82: 0 | Z82: 0 | AA82: -0.363 | AB82: -0.907 | AC82: -0.907 | AD82: -0.907
A83: events (pp) | B83: components per final_nights.md §4–6 | Y83: 0 | Z83: 0 | AA83: 1 | AB83: -0.5 | AC83: 0 | AD83: 0
A84: BASE PRINT y/y (%) | B84: → sum of components | Y84: =SUM(Y80:Y83) -> 9.886 | Z84: =SUM(Z80:Z83) -> 8.12 | AA84: =SUM(AA80:AA83) -> 8.205 | AB84: =SUM(AB80:AB83) -> 5.933 | AC84: =SUM(AC80:AC83) -> 6.206 | AD84: =SUM(AD80:AD83) -> 5.978
A85: Base print level (m) | B85: → prior-year level × (1 + y/y) | Y85: =U7*(1+Y84/100) -> 146.8077 | Z85: =V7*(1+Z84/100) -> 131.79828 | AA85: =W7*(1+AA84/100) -> 169.01621 | AB85: =X7*(1+AB84/100) -> 157.09864 | AC85: =Y85*(1+AC84/100) -> 155.91858 | AD85: =Z85*(1+AD84/100) -> 139.67718
A86: Stays path y/y (%) | B86: 3Q26 = stays read; 4Q26 on = base (I = 0 at the ceiling) | Y86: =$C$55 -> 8.9180921 | Z86: =Z84 -> 8.12 | AA86: =AA84 -> 8.205 | AB86: =AB84 -> 5.933 | AC86: =AC84 -> 6.206 | AD86: =AD84 -> 5.978
A87: FY26 / FY27 nights (m) and FY27 y/y | B87: FY26 = 1Q26A + 2Q26A + 3Q26E + 4Q26E; FY27 = sum of 2027 | C87: =W7+X7+Y85+Z85 -> 583.10598 | D87: =AA85+AB85+AC85+AD85 -> 621.71061 | E87: =D87/C87-1 -> 0.066205179 | F87: FY26 · FY27 · FY27 y/y
A88: Street consensus nights (m) | B88: Bloomberg MODL 12 Sep 2026 (DEC-0005); 4Q26 per final_nights §4.6 | Y88: 149 | Z88: 134
A89: Street y/y (%) | B89: → Street level / prior-year printed − 1 | Y89: =(Y88/U7-1)*100 -> 11.526946 | Z89: =(Z88/V7-1)*100 -> 9.926169
A90: Airbnb guidance, nights y/y (low–high, %) | B90: overnight/02_guidance_ledger.csv (shareholder letters) | V90: 4–6 | W90: 7–9 | Y90: 10–12
A91: P(3Q26 print ≥ Street | stays read, band) | B91: → 1 − NORMDIST(Street y/y, read, band, TRUE) | Y91: =1-NORMDIST(Y89,$C$55,$C$44,TRUE) -> 0.079269236
A93: G. RNPL written: unearned fees y/y vs GBV y/y (the option collects no cash until its deadline)
A94: Unearned fees y/y (%) | B94: overnight/02_kpi_panel_quarterly.csv (10-Q balance sheet) | K94: 24.28 | L94: 18.48 | M94: 20.22 | N94: 20.73 | O94: 12.06 | P94: 11.67 | Q94: 12.95 | R94: 13.24 | S94: 11.87 | T94: 9 | U94: 9.84 | V94: 7.86 | W94: 0.37 | X94: -0.91
A95: GBV y/y, reported (%) | B95: same file | K95: 18.6 | L95: 12.35 | M95: 17.31 | N95: 14.81 | O95: 12.25 | P95: 10.99 | Q95: 9.84 | R95: 13.55 | S95: 6.99 | T95: 10.85 | U95: 13.93 | V95: 15.91 | W95: 19.18 | X95: 15.74
A96: Spread: unearned fees − GBV (pp) | B96: → UF − GBV | K96: =K94-K95 -> 5.68 | L96: =L94-L95 -> 6.13 | M96: =M94-M95 -> 2.91 | N96: =N94-N95 -> 5.92 | O96: =O94-O95 -> -0.19 | P96: =P94-P95 -> 0.68 | Q96: =Q94-Q95 -> 3.11 | R96: =R94-R95 -> -0.31 | ... X96: =X94-X95 -> -16.65
A97: z vs pre-RNPL spread (1Q23–2Q25) | B97: pre mean / sd in B: | U97: =(U96-AVERAGE(K96:T96))/STDEV(K96:T96) -> -2.302534 | V97: =(V96-AVERAGE(K96:T96))/STDEV(K96:T96) -> -3.6461878 | W97: =(W96-AVERAGE(K96:T96))/STDEV(K96:T96) -> -7.2971259 | X97: =(X96-AVERAGE(K96:T96))/STDEV(K96:T96) -> -6.5642238
A99: H. The instrument is validated where nights are observed — Eurostat panel (computed in the engine; values, sourced)
A100: β, country fixed effects (se, wild-cluster p, n, clusters) | B100: stage_a_tests.csv | C100: 0.49364297 | D100: 0.06962927 | E100: 0.001 | F100: 702 | G100: within-R2 0.358
A101: β in first differences (p) | B101: stage_a_tests.csv | C101: 0.70340927 | D101: 0.10295847 | E101: 0.001 | F101: 684 | G101: nan
A102: median walk-forward ratio vs naive (countries ≤ 0.75) | B102: stage_a_tests.csv | C102: 0.59031327 | F102: 486 | G102: countries<=0.75: 17/18
A104: Engine reference values (Python run) — the checker compares the formulas above to these
A105: W1 ratio | B105: reviews_index_v2 outputs | C105: 0.72319612
A106: W2 ratio | B106: reviews_index_v2 outputs | C106: 0.72291903
A107: band | B107: reviews_index_v2 outputs | C107: 1.8518455
A108: 3Q26 read | B108: reviews_index_v2 outputs | C108: 8.9181858
A109: a | B109: reviews_index_v2 outputs | C109: 6.8247849
A110: b | B110: reviews_index_v2 outputs | C110: 0.34967479
A112: chart helper: printed nights y/y (%) | B112: → y/y × 100 | K112: =K8*100 -> 18.609207 | L112: =L8*100 -> 10.99325 | M112: =M8*100 -> 13.540622 | N112: =N8*100 -> 12.018141 | O112: =O8*100 -> 9.4962841 | P112: =P8*100 -> 8.6880973 | Q112: =Q8*100 -> 8.4805654 | R112: =R8*100 -> 12.348178 | ... X112: =X8*100 -> 10.342262
A113: chart helper: our view (printed, then base print path) | K113: =K112 -> 18.609207 | L113: =L112 -> 10.99325 | M113: =M112 -> 13.540622 | N113: =N112 -> 12.018141 | O113: =O112 -> 9.4962841 | P113: =P112 -> 8.6880973 | Q113: =Q112 -> 8.4805654 | R113: =R112 -> 12.348178 | ... X113: =X112 -> 10.342262 | Y113: =Y84 -> 9.886 | Z113: =Z84 -> 8.12 | AA113: =AA84 -> 8.205 | AB113: =AB84 -> 5.933 | AC113: =AC84 -> 6.206 | AD113: =AD84 -> 5.978
A114: chart helper: Street y/y | Y114: =Y89 -> 11.526946 | Z114: =Z89 -> 9.926169
A115: chart helper: stays-implied / stays path | K115: =K25 -> 18.254834 | L115: =L25 -> 12.735555 | M115: =M25 -> 10.844222 | N115: =N25 -> 11.902934 | O115: =O25 -> 11.101184 | P115: =P25 -> 8.9367511 | Q115: =Q25 -> 8.8345879 | R115: =R25 -> 9.2584143 | ... X115: =X25 -> 8.7900177 | Y115: =Y86 -> 8.9180921 | Z115: =Z86 -> 8.12 | AA115: =AA86 -> 8.205 | AB115: =AB86 -> 5.933 | AC115: =AC86 -> 6.206 | AD115: =AD86 -> 5.978

Sheet ADR_Engine
A1: Airbnb — ADR engine (line 2). reported ADR y/y = ex-FX mechanism + FX translation identity (ex ante, spot held). Blue = input with source; black = formula; green = link.
A2: Engine: analysis/src/pitch_model_v2/adr_engine (python3 -m pitch_model_v2.adr_engine.run); pre-registration docs/pitch-model-v2/lines/adr_fx_prereg.md; design adr_v1_design.md; rationale final_adr.md. FX through FRED 2026-09-18; forward quarters hold the last print (spot held).
A4: Quarter | B4: A = printed, E = engine | C4: 1Q21A | D4: 2Q21A | E4: 3Q21A | F4: 4Q21A | G4: 1Q22A | H4: 2Q22A | I4: 3Q22A | J4: 4Q22A | K4: 1Q23A | L4: 2Q23A | M4: 3Q23A | N4: 4Q23A | O4: 1Q24A | P4: 2Q24A | Q4: 3Q24A | R4: 4Q24A | S4: 1Q25A | T4: 2Q25A | U4: 3Q25A | V4: 4Q25A | W4: 1Q26A | X4: 2Q26A | Y4: 3Q26E | Z4: 4Q26E | AA4: 1Q27E | AB4: 2Q27E | AC4: 3Q27E | AD4: 4Q27E
A6: A. Printed ADR and the disclosed identity: reported y/y − ex-FX y/y = FX effect (closes to ≤0.04pp)
A7: ADR ($, GBV ÷ nights, printed; forward = engine path) | B7: data/processed/overnight/02_kpi_panel_quarterly.csv adr_usd (letters / 10-Q) | C7: 159.82 | D7: 161.45 | E7: 149.15 | F7: 153.61 | G7: 168.07 | H7: 163.74 | I7: 156.44 | J7: 152.81 | K7: 168.43 | L7: 166.01 | M7: 161.38 | N7: 156.73 | O7: 172.88 | P7: 169.53 | Q7: 163.64 | R7: 158.13 | S7: 171.34 | T7: 174.48 | U7: 171.29 | V7: 167.51 | W7: 186.82 | X7: 183.73 | Y7: =Y96 -> 177.68122 | Z7: =Z96 -> 173.03405 | AA7: =AA96 -> 190.64582 | AB7: =AB96 -> 188.37762 | AC7: =AC96 -> 182.52209 | AD7: =AD96 -> 178.11165
A8: reported y/y | B8: → ADR / ADR four quarters earlier − 1 | G8: =G7/C7-1 -> 0.051620573 | H8: =H7/D7-1 -> 0.014183958 | I8: =I7/E7-1 -> 0.048876969 | J8: =J7/F7-1 -> -0.0052079943 | K8: =K7/G7-1 -> 0.0021419647 | L8: =L7/H7-1 -> 0.013863442 | M8: =M7/I7-1 -> 0.031577602 | N8: =N7/J7-1 -> 0.025652771 | ... AD8: =AD7/Z7-1 -> 0.02934449
A9: ex-FX y/y, as stated in the letter (whole points; 3Q23/4Q23 'less than 1%' → 0.5) | B9: 02_kpi_panel_quarterly.csv adr_yoy_exfx_pct; 2Q22 onward | H9: 7 | I9: 12 | J9: 5 | K9: 3 | L9: 2 | M9: 0.5 | N9: 0.5 | O9: 2 | P9: 3 | Q9: 2 | R9: 2 | S9: 1 | T9: 1 | U9: 2 | V9: 3 | W9: 4 | X9: 4
A10: FX effect on ADR (pp) — the disclosed target | B10: → reported y/y × 100 − ex-FX y/y | H10: =H8*100-H9 -> -5.5816042 | I10: =I8*100-I9 -> -7.1123031 | J10: =J8*100-J9 -> -5.5207994 | K10: =K8*100-K9 -> -2.7858035 | L10: =L8*100-L9 -> -0.6136558 | M10: =M8*100-M9 -> 2.6577602 | N10: =N8*100-N9 -> 2.0652771 | O10: =O8*100-O9 -> 0.64204714 | ... X10: =X8*100-X9 -> 1.3014672
A12: B. FX translation identity (ex ante): FX pp = Σ_region GBV share × Σ_currency κ × (avg rate / avg rate a year earlier − 1) — zero fitted parameters
A13: Quarterly average USD per EUR (business days; forward = spot held from 2026-09-18) | B13: FRED DEXUSEU → adr_engine/fx_daily_2026-09-21.csv (fetch_fx.py) | C13: 1.2051578 | D13: 1.2052631 | E13: 1.1786621 | F13: 1.1432652 | G13: 1.1220844 | H13: 1.0644092 | I13: 1.0070318 | J13: 1.0219185 | K13: 1.0729677 | L13: 1.0886154 | M13: 1.0883215 | N13: 1.0763308 | O13: 1.0858477 | P13: 1.07668 | Q13: 1.0985045 | R13: 1.0666939 | S13: 1.0523953 | T13: 1.1344462 | U13: 1.1686682 | V13: 1.1640894 | W13: 1.1703063 | X13: 1.1628877 | Y13: 1.1515591 | Z13: 1.1464 | AA13: 1.1464 | AB13: 1.1464 | AC13: 1.1464 | AD13: 1.1464
A14: Quarterly average USD per GBP (business days; forward = spot held from 2026-09-18) | B14: FRED DEXUSUK → adr_engine/fx_daily_2026-09-21.csv (fetch_fx.py) | C14: 1.3790891 | D14: 1.3984477 | E14: 1.3780667 | F14: 1.3484455 | G14: 1.3413922 | H14: 1.2559246 | I14: 1.176797 | J14: 1.1751738 | K14: 1.2150692 | L14: 1.2521308 | M14: 1.2662 | N14: 1.2419846 | O14: 1.2682554 | P14: 1.2621554 | Q14: 1.3003091 | R14: 1.2814455 | S14: 1.2597047 | T14: 1.3357262 | U14: 1.3486742 | V14: 1.3304591 | W14: 1.3478812 | X14: 1.34264 | Y14: 1.3456939 | Z14: 1.3372 | AA14: 1.3372 | AB14: 1.3372 | AC14: 1.3372 | AD14: 1.3372
A15: Quarterly average USD per BRL (business days; forward = spot held from 2026-09-18) | B15: FRED DEXBZUS → adr_engine/fx_daily_2026-09-21.csv (fetch_fx.py) | C15: 0.1828723 | D15: 0.1892938 | E15: 0.19140422 | F15: 0.17901789 | G15: 0.19180331 | H15: 0.20348532 | I15: 0.19074296 | J15: 0.19031259 | K15: 0.19255919 | L15: 0.20206913 | M15: 0.20494515 | N15: 0.20197053 | O15: 0.20203222 | P15: 0.19200767 | Q15: 0.18034804 | R15: 0.17142182 | S15: 0.1709568 | T15: 0.17648985 | U15: 0.18360546 | V15: 0.18528564 | W15: 0.19021328 | X15: 0.19812416 | Y15: 0.19477107 | Z15: 0.19381347 | AA15: 0.19381347 | AB15: 0.19381347 | AC15: 0.19381347 | AD15: 0.19381347
A16: Quarterly average USD per MXN (business days; forward = spot held from 2026-09-18) | B16: FRED DEXMXUS → adr_engine/fx_daily_2026-09-21.csv (fetch_fx.py) | C16: 0.049188327 | D16: 0.049977378 | E16: 0.049941177 | F16: 0.048211633 | G16: 0.048790826 | H16: 0.049882551 | I16: 0.049438854 | J16: 0.050840307 | K16: 0.053601005 | L16: 0.056587911 | M16: 0.058640683 | N16: 0.057045653 | O16: 0.058894717 | P16: 0.05812609 | Q16: 0.052918776 | R16: 0.049783664 | S16: 0.048979898 | T16: 0.051289124 | U16: 0.053691549 | V16: 0.054659442 | W16: 0.056955797 | X16: 0.057533585 | Y16: 0.058112133 | Z16: 0.057986478 | AA16: 0.057986478 | AB16: 0.057986478 | AC16: 0.057986478 | AD16: 0.057986478
A17: Quarterly average USD per JPY (business days; forward = spot held from 2026-09-18) | B17: FRED DEXJPUS → adr_engine/fx_daily_2026-09-21.csv (fetch_fx.py) | C17: 0.0094349051 | D17: 0.0091381254 | E17: 0.0090842013 | F17: 0.0087968935 | G17: 0.0086023215 | H17: 0.007712152 | I17: 0.0072346139 | J17: 0.007089682 | K17: 0.0075563288 | L17: 0.0072794962 | M17: 0.0069207958 | N17: 0.0067688001 | O17: 0.0067398721 | P17: 0.0064187659 | Q17: 0.0067138749 | R17: 0.006564705 | S17: 0.0065592852 | T17: 0.0069232239 | U17: 0.0067818577 | V17: 0.0064909558 | W17: 0.0063765536 | X17: 0.0062743757 | Y17: 0.0062864113 | Z17: 0.0063747052 | AA17: 0.0063747052 | AB17: 0.0063747052 | AC17: 0.0063747052 | AD17: 0.0063747052
A18: Quarterly average USD per AUD (business days; forward = spot held from 2026-09-18) | B18: FRED DEXUSAL → adr_engine/fx_daily_2026-09-21.csv (fetch_fx.py) | C18: 0.77284219 | D18: 0.77006615 | E18: 0.73476667 | F18: 0.72878939 | G18: 0.72470469 | H18: 0.71404769 | I18: 0.68325606 | J18: 0.65758769 | K18: 0.68345538 | L18: 0.6681 | M18: 0.65481231 | N18: 0.65147231 | O18: 0.65780462 | P18: 0.65907231 | Q18: 0.66993485 | R18: 0.65226515 | S18: 0.62754219 | T18: 0.64107231 | U18: 0.6543197 | V18: 0.65672576 | W18: 0.69493594 | X18: 0.70997385 | Y18: 0.7071303 | Z18: 0.7111 | AA18: 0.7111 | AB18: 0.7111 | AC18: 0.7111 | AD18: 0.7111
A19: Quarterly average USD per KRW (business days; forward = spot held from 2026-09-18) | B19: FRED DEXKOUS → adr_engine/fx_daily_2026-09-21.csv (fetch_fx.py) | C19: 0.00089805741 | D19: 0.00089194501 | E19: 0.00086250124 | F19: 0.00084489755 | G19: 0.00082949308 | H19: 0.00079350424 | I19: 0.00074657344 | J19: 0.00073713865 | K19: 0.00078425692 | L19: 0.00076050865 | M19: 0.00076178375 | N19: 0.00075699545 | O19: 0.00075258659 | P19: 0.00072983185 | Q19: 0.00073789966 | R19: 0.00071545038 | S19: 0.00068861141 | T19: 0.00071531199 | U19: 0.00072120431 | V19: 0.00069039611 | W19: 0.00068276249 | X19: 0.00066626241 | Y19: 0.00070476994 | Z19: 0.00072047667 | AA19: 0.00072047667 | AB19: 0.00072047667 | AC19: 0.00072047667 | AD19: 0.00072047667
A20: Quarterly average USD per CAD (business days; forward = spot held from 2026-09-18) | B20: FRED DEXCAUS → adr_engine/fx_daily_2026-09-21.csv (fetch_fx.py) | C20: 0.78993696 | D20: 0.8144081 | E20: 0.79401148 | F20: 0.79344988 | G20: 0.78974132 | H20: 0.78333727 | I20: 0.76598682 | J20: 0.73679988 | K20: 0.73938089 | L20: 0.74472729 | M20: 0.7457969 | N20: 0.73473312 | O20: 0.74185751 | P20: 0.73094942 | Q20: 0.73325029 | R20: 0.71493814 | S20: 0.69696586 | T20: 0.72265336 | U20: 0.72630067 | V20: 0.71747374 | W20: 0.72912713 | X20: 0.72266251 | Y20: 0.71533732 | Z20: 0.71387778 | AA20: 0.71387778 | AB20: 0.71387778 | AC20: 0.71387778 | AD20: 0.71387778
A21: Quarterly average USD per INR (business days; forward = spot held from 2026-09-18) | B21: FRED DEXINUS → adr_engine/fx_daily_2026-09-21.csv (fetch_fx.py) | C21: 0.013716405 | D21: 0.013558294 | E21: 0.013498359 | F21: 0.013348796 | G21: 0.013297218 | H21: 0.012954458 | I21: 0.012537862 | J21: 0.012175212 | K21: 0.012165732 | L21: 0.012169914 | M21: 0.012095919 | N21: 0.012012913 | O21: 0.012044004 | P21: 0.011989327 | Q21: 0.011940174 | R21: 0.01184369 | S21: 0.011549405 | T21: 0.011686775 | U21: 0.011453966 | V21: 0.01122424 | W21: 0.010931728 | X21: 0.010567997 | Y21: 0.010461347 | Z21: 0.010430792 | AA21: 0.010430792 | AB21: 0.010430792 | AC21: 0.010430792 | AD21: 0.010430792
A22: share of the quarter's business days printed at 18 Sep 2026 | B22: engine fx_forecast_asof.csv obs_frac_at_asof | C22: 1 | D22: 1 | E22: 1 | F22: 1 | G22: 1 | H22: 1 | I22: 1 | J22: 1 | K22: 1 | L22: 1 | M22: 1 | N22: 1 | O22: 1 | P22: 1 | Q22: 1 | R22: 1 | S22: 1 | T22: 1 | U22: 1 | V22: 1 | W22: 1 | X22: 1 | Y22: 0.87878788 | Z22: 0 | AA22: 0 | AB22: 0 | AC22: 0 | AD22: 0
A24: EUR y/y of the quarterly average (%) | B24: → (avg / avg four quarters earlier − 1) × 100 | G24: =(G13/C13-1)*100 -> -6.8931584 | H24: =(H13/D13-1)*100 -> -11.686564 | I24: =(I13/E13-1)*100 -> -14.561451 | J24: =(J13/F13-1)*100 -> -10.614046 | K24: =(K13/G13-1)*100 -> -4.3772718 | L24: =(L13/H13-1)*100 -> 2.2741398 | M24: =(M13/I13-1)*100 -> 8.0722097 | N24: =(N13/J13-1)*100 -> 5.3245254 | ... AD24: =(AD13/Z13-1)*100 -> 0
A25: GBP y/y of the quarterly average (%) | B25: → (avg / avg four quarters earlier − 1) × 100 | G25: =(G14/C14-1)*100 -> -2.733462 | H25: =(H14/D14-1)*100 -> -10.19152 | I25: =(I14/E14-1)*100 -> -14.605222 | J25: =(J14/F14-1)*100 -> -12.849731 | K25: =(K14/G14-1)*100 -> -9.4173023 | L25: =(L14/H14-1)*100 -> -0.30207595 | M25: =(M14/I14-1)*100 -> 7.5971499 | N25: =(N14/J14-1)*100 -> 5.6851818 | ... AD25: =(AD14/Z14-1)*100 -> 0
A26: BRL y/y of the quarterly average (%) | B26: → (avg / avg four quarters earlier − 1) × 100 | G26: =(G15/C15-1)*100 -> 4.8837417 | H26: =(H15/D15-1)*100 -> 7.4970888 | I26: =(I15/E15-1)*100 -> -0.34547466 | J26: =(J15/F15-1)*100 -> 6.3092573 | K26: =(K15/G15-1)*100 -> 0.39409243 | L26: =(L15/H15-1)*100 -> -0.69596721 | M26: =(M15/I15-1)*100 -> 7.4457166 | N26: =(N15/J15-1)*100 -> 6.1256803 | ... AD26: =(AD15/Z15-1)*100 -> 0
A27: MXN y/y of the quarterly average (%) | B27: → (avg / avg four quarters earlier − 1) × 100 | G27: =(G16/C16-1)*100 -> -0.80811973 | H27: =(H16/D16-1)*100 -> -0.18974069 | I27: =(I16/E16-1)*100 -> -1.0058289 | J27: =(J16/F16-1)*100 -> 5.4523649 | K27: =(K16/G16-1)*100 -> 9.858778 | L27: =(L16/H16-1)*100 -> 13.442295 | M27: =(M16/I16-1)*100 -> 18.612544 | N27: =(N16/J16-1)*100 -> 12.205564 | ... AD27: =(AD16/Z16-1)*100 -> 0
A28: JPY y/y of the quarterly average (%) | B28: → (avg / avg four quarters earlier − 1) × 100 | G28: =(G17/C17-1)*100 -> -8.8245043 | H28: =(H17/D17-1)*100 -> -15.60466 | I28: =(I17/E17-1)*100 -> -20.360484 | J28: =(J17/F17-1)*100 -> -19.406981 | K28: =(K17/G17-1)*100 -> -12.159423 | L28: =(L17/H17-1)*100 -> -5.6100523 | M28: =(M17/I17-1)*100 -> -4.3377316 | N28: =(N17/J17-1)*100 -> -4.5260402 | ... AD28: =(AD17/Z17-1)*100 -> 0
A29: AUD y/y of the quarterly average (%) | B29: → (avg / avg four quarters earlier − 1) × 100 | G29: =(G18/C18-1)*100 -> -6.2286325 | H29: =(H18/D18-1)*100 -> -7.2744999 | I29: =(I18/E18-1)*100 -> -7.0104713 | J29: =(J18/F18-1)*100 -> -9.7698597 | K29: =(K18/G18-1)*100 -> -5.6918775 | L29: =(L18/H18-1)*100 -> -6.4348212 | M29: =(M18/I18-1)*100 -> -4.1629712 | N29: =(N18/J18-1)*100 -> -0.92997249 | ... AD29: =(AD18/Z18-1)*100 -> 0
A30: KRW y/y of the quarterly average (%) | B30: → (avg / avg four quarters earlier − 1) × 100 | G30: =(G19/C19-1)*100 -> -7.6347376 | H30: =(H19/D19-1)*100 -> -11.036641 | I30: =(I19/E19-1)*100 -> -13.440885 | J30: =(J19/F19-1)*100 -> -12.754078 | K30: =(K19/G19-1)*100 -> -5.45347 | L30: =(L19/H19-1)*100 -> -4.1582117 | M30: =(M19/I19-1)*100 -> 2.0373483 | N30: =(N19/J19-1)*100 -> 2.6937669 | ... AD30: =(AD19/Z19-1)*100 -> 0
A31: CAD y/y of the quarterly average (%) | B31: → (avg / avg four quarters earlier − 1) × 100 | G31: =(G20/C20-1)*100 -> -0.024765877 | H31: =(H20/D20-1)*100 -> -3.8151426 | I31: =(I20/E20-1)*100 -> -3.529504 | J31: =(J20/F20-1)*100 -> -7.1397079 | K31: =(K20/G20-1)*100 -> -6.3768263 | L31: =(L20/H20-1)*100 -> -4.9289085 | M31: =(M20/I20-1)*100 -> -2.6358046 | N31: =(N20/J20-1)*100 -> -0.28050398 | ... AD31: =(AD20/Z20-1)*100 -> 0
A32: INR y/y of the quarterly average (%) | B32: → (avg / avg four quarters earlier − 1) × 100 | G32: =(G21/C21-1)*100 -> -3.0560932 | H32: =(H21/D21-1)*100 -> -4.4536226 | I32: =(I21/E21-1)*100 -> -7.1156601 | J32: =(J21/F21-1)*100 -> -8.7916896 | K32: =(K21/G21-1)*100 -> -8.5091983 | L32: =(L21/H21-1)*100 -> -6.0561763 | M32: =(M21/I21-1)*100 -> -3.5248667 | N32: =(N21/J21-1)*100 -> -1.3330265 | ... AD32: =(AD21/Z21-1)*100 -> 0
A34: Destination-currency basket weights κ (frozen judgement, 01b_basket_weights_used.csv; USD legs carry 0) | B34: rows = region; columns C..K = EUR GBP BRL MXN JPY AUD KRW CAD INR; L = USD | C34: EUR | D34: GBP | E34: BRL | F34: MXN | G34: JPY | H34: AUD | I34: KRW | J34: CAD | K34: INR | L34: USD
A35: κ na | C35: 0 | D35: 0 | E35: 0 | F35: 0.02 | G35: 0 | H35: 0 | I35: 0 | J35: 0.08 | K35: 0 | L35: 0.9
A36: κ emea | C36: 0.7 | D36: 0.25 | E36: 0 | F36: 0 | G36: 0 | H36: 0 | I36: 0 | J36: 0 | K36: 0 | L36: 0.05
A37: κ latam | C37: 0 | D37: 0 | E37: 0.55 | F37: 0.38 | G37: 0 | H37: 0 | I37: 0 | J37: 0 | K37: 0 | L37: 0.07
A38: κ apac | C38: 0 | D38: 0 | E38: 0 | F38: 0 | G38: 0.2 | H38: 0.55 | I38: 0.1 | J38: 0 | K38: 0.07 | L38: 0.08
A40: basket y/y, na (%) | B40: → Σ_currency κ × currency y/y | G40: =$F$35*G27+$J$35*G31 -> -0.018143665 | H40: =$F$35*H27+$J$35*H31 -> -0.30900622 | I40: =$F$35*I27+$J$35*I31 -> -0.3024769 | J40: =$F$35*J27+$J$35*J31 -> -0.46212933 | K40: =$F$35*K27+$J$35*K31 -> -0.31297055 | L40: =$F$35*L27+$J$35*L31 -> -0.12546678 | M40: =$F$35*M27+$J$35*M31 -> 0.16138651 | N40: =$F$35*N27+$J$35*N31 -> 0.22167095 | ... AD40: =$F$35*AD27+$J$35*AD31 -> 0
A41: basket y/y, emea (%) | B41: → Σ_currency κ × currency y/y | G41: =$C$36*G24+$D$36*G25 -> -5.5085764 | H41: =$C$36*H24+$D$36*H25 -> -10.728475 | I41: =$C$36*I24+$D$36*I25 -> -13.844321 | J41: =$C$36*J24+$D$36*J25 -> -10.642265 | K41: =$C$36*K24+$D$36*K25 -> -5.4184158 | L41: =$C$36*L24+$D$36*L25 -> 1.5163789 | M41: =$C$36*M24+$D$36*M25 -> 7.5498343 | N41: =$C$36*N24+$D$36*N25 -> 5.1484632 | ... AD41: =$C$36*AD24+$D$36*AD25 -> 0
A42: basket y/y, latam (%) | B42: → Σ_currency κ × currency y/y | G42: =$E$37*G26+$F$37*G27 -> 2.3789724 | H42: =$E$37*H26+$F$37*H27 -> 4.0512974 | I42: =$E$37*I26+$F$37*I27 -> -0.57222604 | J42: =$E$37*J26+$F$37*J27 -> 5.5419902 | K42: =$E$37*K26+$F$37*K27 -> 3.9630865 | L42: =$E$37*L26+$F$37*L27 -> 4.7252902 | M42: =$E$37*M26+$F$37*M27 -> 11.167911 | N42: =$E$37*N26+$F$37*N27 -> 8.0072383 | ... AD42: =$E$37*AD26+$F$37*AD27 -> 0
A43: basket y/y, apac (%) | B43: → Σ_currency κ × currency y/y | G43: =$G$38*G28+$H$38*G29+$I$38*G30+$K$38*G32 -> -6.168049 | H43: =$G$38*H28+$H$38*H29+$I$38*H30+$K$38*H32 -> -8.5373246 | I43: =$G$38*I28+$H$38*I29+$I$38*I30+$K$38*I32 -> -9.7700407 | J43: =$G$38*J28+$H$38*J29+$I$38*J30+$K$38*J32 -> -11.145645 | K43: =$G$38*K28+$H$38*K29+$I$38*K30+$K$38*K32 -> -6.7034081 | L43: =$G$38*L28+$H$38*L29+$I$38*L30+$K$38*L32 -> -5.5009156 | M43: =$G$38*M28+$H$38*M29+$I$38*M30+$K$38*M32 -> -3.2001863 | N43: =$G$38*N28+$H$38*N29+$I$38*N30+$K$38*N32 -> -1.2406281 | ... AD43: =$G$38*AD28+$H$38*AD29+$I$38*AD30+$K$38*AD32 -> 0
A44: Regional GBV shares (10-K Geographic Mix, latest fiscal year filed before the quarter's print; FY2025 forward) | B44: data/processed/adr/01_regional_annual.csv gbv_share_pct
A45: GBV share, na | C45: 0.55111332 | D45: 0.55111332 | E45: 0.55111332 | F45: 0.55111332 | G45: 0.53982763 | H45: 0.53982763 | I45: 0.53982763 | J45: 0.53982763 | K45: 0.51012466 | L45: 0.51012466 | M45: 0.51012466 | N45: 0.51012466 | O45: 0.47699722 | P45: 0.47699722 | Q45: 0.47699722 | R45: 0.47699722 | S45: 0.46238873 | T45: 0.46238873 | U45: 0.46238873 | V45: 0.46238873 | W45: 0.44147776 | X45: 0.44147776 | Y45: 0.44147776 | Z45: 0.44147776 | AA45: 0.44147776 | AB45: 0.44147776 | AC45: 0.44147776 | AD45: 0.44147776
A46: GBV share, emea | C46: 0.27870142 | D46: 0.27870142 | E46: 0.27870142 | F46: 0.27870142 | G46: 0.31160057 | H46: 0.31160057 | I46: 0.31160057 | J46: 0.31160057 | K46: 0.33990382 | L46: 0.33990382 | M46: 0.33990382 | N46: 0.33990382 | O46: 0.35822913 | P46: 0.35822913 | Q46: 0.35822913 | R46: 0.35822913 | S46: 0.36376308 | T46: 0.36376308 | U46: 0.36376308 | V46: 0.36376308 | W46: 0.37428374 | X46: 0.37428374 | Y46: 0.37428374 | Z46: 0.37428374 | AA46: 0.37428374 | AB46: 0.37428374 | AC46: 0.37428374 | AD46: 0.37428374
A47: GBV share, latam | C47: 0.071172411 | D47: 0.071172411 | E47: 0.071172411 | F47: 0.071172411 | G47: 0.07905796 | H47: 0.07905796 | I47: 0.07905796 | J47: 0.07905796 | K47: 0.076536101 | L47: 0.076536101 | M47: 0.076536101 | N47: 0.076536101 | O47: 0.082646208 | P47: 0.082646208 | Q47: 0.082646208 | R47: 0.082646208 | S47: 0.086716228 | T47: 0.086716228 | U47: 0.086716228 | V47: 0.086716228 | W47: 0.09358737 | X47: 0.09358737 | Y47: 0.09358737 | Z47: 0.09358737 | AA47: 0.09358737 | AB47: 0.09358737 | AC47: 0.09358737 | AD47: 0.09358737
A48: GBV share, apac | C48: 0.099012843 | D48: 0.099012843 | E48: 0.099012843 | F48: 0.099012843 | G48: 0.069513834 | H48: 0.069513834 | I48: 0.069513834 | J48: 0.069513834 | K48: 0.073435424 | L48: 0.073435424 | M48: 0.073435424 | N48: 0.073435424 | O48: 0.08212745 | P48: 0.08212745 | Q48: 0.08212745 | R48: 0.08212745 | S48: 0.087131957 | T48: 0.087131957 | U48: 0.087131957 | V48: 0.087131957 | W48: 0.090651124 | X48: 0.090651124 | Y48: 0.090651124 | Z48: 0.090651124 | AA48: 0.090651124 | AB48: 0.090651124 | AC48: 0.090651124 | AD48: 0.090651124
A49: fiscal year of the shares used | C49: 2020 | D49: 2020 | E49: 2020 | F49: 2020 | G49: 2021 | H49: 2021 | I49: 2021 | J49: 2021 | K49: 2022 | L49: 2022 | M49: 2022 | N49: 2022 | O49: 2023 | P49: 2023 | Q49: 2023 | R49: 2023 | S49: 2024 | T49: 2024 | U49: 2024 | V49: 2024 | W49: 2025 | X49: 2025 | Y49: 2025 | Z49: 2025 | AA49: 2025 | AB49: 2025 | AC49: 2025 | AD49: 2025
A51: FX effect on ADR — translation identity (pp) | B51: → SUMPRODUCT(GBV shares, regional basket y/y); the promoted leg (pre-registration §5, V0) | G51: =SUMPRODUCT(G45:G48,G40:G43) -> -1.966958 | H51: =SUMPRODUCT(H45:H48,H40:H43) -> -3.7829839 | I51: =SUMPRODUCT(I45:I48,I40:I43) -> -5.2015757 | J51: =SUMPRODUCT(J45:J48,J40:J43) -> -3.9022441 | K51: =SUMPRODUCT(K45:K48,K40:K43) -> -2.1903426 | L51: =SUMPRODUCT(L45:L48,L40:L43) -> 0.40911248 | M51: =SUMPRODUCT(M45:M48,M40:M43) -> 3.268286 | N51: =SUMPRODUCT(N45:N48,N40:N43) -> 2.3847989 | ... AD51: =SUMPRODUCT(AD45:AD48,AD40:AD43) -> 0
A52: error: identity − disclosed (pp), completed quarters | B52: → identity − row 10 | I52: =I51-I10 -> 1.9107273 | J52: =J51-J10 -> 1.6185553 | K52: =K51-K10 -> 0.59546091 | L52: =L51-L10 -> 1.0227683 | M52: =M51-M10 -> 0.61052588 | N52: =N51-N10 -> 0.31952171 | O52: =O51-O10 -> 0.30584243 | P52: =P51-P10 -> 0.19387478 | ... X52: =X51-X10 -> 0.81835214
A53: naive error: last quarter's disclosed − disclosed (pp) | I53: =H10-I10 -> 1.5306988 | J53: =I10-J10 -> -1.5915036 | K53: =J10-K10 -> -2.7349959 | L53: =K10-L10 -> -2.1721477 | M53: =L10-M10 -> -3.271416 | N53: =M10-N10 -> 0.59248302 | O53: =N10-O10 -> 1.42323 | P53: =O10-P10 -> 1.5216929 | ... X53: =W10-X10 -> 3.7332007
A54: RMSE identity / RMSE naive, 1Q23–2Q26 (n 14; full-quarter rates = origin O3) | B54: → SQRT(SUMSQ)/n; point-in-time O1/O2 ratios are in block E | C54: =SQRT(SUMSQ(K52:X52)/14) -> 0.63704455 | D54: =SQRT(SUMSQ(K53:X53)/14) -> 2.1054162 | E54: =C54/D54 -> 0.30257417 | F54: ratio (pass line ≤ 0.75)
A56: P10 of the ex-ante band (pp) | B56: engine: moving-block bootstrap of daily FX returns on the unobserved days, 4,000 paths | Y56: 0.35548329 | Z56: -1.0564431 | AA56: -3.2000074 | AB56: -3.9016224 | AC56: -4.3383992 | AD56: -4.335432
A57: P50 | Y57: 0.41627241 | Z57: 0.58199844 | AA57: -0.23581807 | AB57: -0.22730493 | AC57: 0.030552077 | AD57: 0.23395893
A58: P90 | Y58: 0.48050927 | Z58: 2.2594723 | AA58: 2.7779556 | AB58: 3.6801854 | AC58: 4.8558389 | AD58: 5.1154117
A60: C. Ex-FX ADR mechanism: ex-FX y/y = core + bundle (laps on filed dates) + geo mix (from the nights line) + unit size + LOS + seats + interaction
A61: Disclosed ex-FX ADR y/y (pp) | B61: → link to row 9 | K61: =K9 -> 3 | L61: =L9 -> 2 | M61: =M9 -> 0.5 | N61: =N9 -> 0.5 | O61: =O9 -> 2 | P61: =P9 -> 3 | Q61: =Q9 -> 2 | R61: =R9 -> 2 | ... X61: =X9 -> 4
A62: geographic mix (pp) | B62: history: H decomposition adr_history_components.csv; forward: block C1 arithmetic on the nights line's regional path | K62: -1.3517979 | L62: -0.90308045 | M62: -1.167208 | N62: -0.93907687 | O62: -1.3250725 | P62: -1.1316446 | Q62: -1.1196158 | R62: -1.7918875 | S62: -1.8943503 | T62: -1.7015904 | U62: -1.5932341 | V62: -1.4573972 | W62: -1.0430677 | X62: -1.2672244 | Y62: =Y91 -> -1.2926338 | Z62: =Z91 -> -1.3356182 | AA62: =AA91 -> -1.6203852 | AB62: =AB91 -> -1.0807337 | AC62: =AC91 -> -1.1660443 | AD62: =AD91 -> -1.1028134
A63: unit size / party size (pp) | B63: history: H; forward: card v3 measured 3Q26 term +0.797 carried (I_mix_terms_3q26.csv) | K63: 0.46209128 | L63: 0.36214403 | M63: 0.40989737 | N63: 0.29065396 | O63: 0.96335054 | P63: 0.77215958 | Q63: 0.89031575 | R63: 0.70667477 | S63: 0.66909918 | T63: 0.73241031 | U63: 0.74815096 | V63: 0.82242274 | W63: 0.94504894 | X63: 0.70046817 | Y63: 0.796672 | Z63: 0.796672 | AA63: 0.796672 | AB63: 0.796672 | AC63: 0.796672 | AD63: 0.796672
A64: length-of-stay mix (pp) | B64: history: H; forward: card +0.056 carried | K64: 0.46262529 | L64: 0.11837515 | M64: 0.30159544 | N64: 0.36393874 | O64: 0.21253021 | P64: 0.23169287 | Q64: 0.25269487 | R64: 0.43155104 | S64: 0.27873472 | T64: 0.34841461 | U64: 0.30764916 | V64: 0.22101848 | W64: 0.3 | X64: 0.3 | Y64: 0.056264 | Z64: 0.056264 | AA64: 0.056264 | AB64: 0.056264 | AC64: 0.056264 | AD64: 0.056264
A65: seats / new business dilution (pp) | B65: history: H 15_seats_dilution; forward: −0.483 (2026), −0.565 (2027), assumed | K65: 0 | L65: 0 | M65: 0 | N65: 0 | O65: 0 | P65: 0 | Q65: 0 | R65: 0 | S65: -0.17653663 | T65: -0.17653663 | U65: -0.17653663 | V65: -0.17653663 | W65: -0.48257015 | X65: -0.48257015 | Y65: -0.48257 | Z65: -0.48257 | AA65: -0.565 | AB65: -0.565 | AC65: -0.565 | AD65: -0.565
A66: interaction (pp) | B66: H, descriptive −0.10 | K66: -0.049478637 | L66: -0.049478637 | M66: -0.049478637 | N66: -0.049478637 | O66: -0.10658345 | P66: -0.10658345 | Q66: -0.10658345 | R66: -0.10658345 | S66: -0.10832061 | T66: -0.10832061 | U66: -0.10832061 | V66: -0.10832061 | W66: -0.1 | X66: -0.1 | Y66: -0.1 | Z66: -0.1 | AA66: -0.1 | AB66: -0.1 | AC66: -0.1 | AD66: -0.1
A67: like-for-like residual (pp) = ex-FX − the five terms above | B67: history: formula; forward: core + bundle | K67: =K61-SUM(K62:K66) -> 3.47656 | L67: =L61-SUM(L62:L66) -> 2.4720399 | M67: =M61-SUM(M62:M66) -> 1.0051938 | N67: =N61-SUM(N62:N66) -> 0.83396281 | O67: =O61-SUM(O62:O66) -> 2.2557752 | P67: =P61-SUM(P62:P66) -> 3.2343756 | Q67: =Q61-SUM(Q62:Q66) -> 2.0831886 | R67: =R61-SUM(R62:R66) -> 2.7602451 | ... X67: =X61-SUM(X62:X66) -> 4.8493264 | Y67: =Y68+Y73 -> 4.3382153 | Z67: =Z68+Z73 -> 3.8493264 | AA67: =AA68+AA73 -> 3.8493264 | AB67: =AB68+AB73 -> 3.8493264 | AC67: =AC68+AC73 -> 3.8493264 | AD67: =AD68+AD73 -> 3.8493264
A68: core (pp) = residual − bundle live in the quarter | B68: history: formula; forward: carried at the last observed value (2Q26) — the same carry rule the card applies to the residual | K68: =K67-K73 -> 3.47656 | L68: =L67-L73 -> 2.4720399 | M68: =M67-M73 -> 1.0051938 | N68: =N67-N73 -> 0.83396281 | O68: =O67-O73 -> 2.2557752 | P68: =P67-P73 -> 3.2343756 | Q68: =Q67-Q73 -> 2.0831886 | R68: =R67-R73 -> 2.7602451 | ... X68: =X67-X73 -> 3.8493264 | Y68: =X68 -> 3.8493264 | Z68: =X68 -> 3.8493264 | AA68: =X68 -> 3.8493264 | AB68: =X68 -> 3.8493264 | AC68: =X68 -> 3.8493264 | AD68: =X68 -> 3.8493264
A70: bundle leg: RNPL North America (larger-home mix), live 3Q25–2Q26, laps 3Q26 | B70: ledger D014/D032 (~1pp bundle ADR, transcript-only) split by K4 residual steps 0.92:0.88 | K70: 0 | L70: 0 | M70: 0 | N70: 0 | O70: 0 | P70: 0 | Q70: 0 | R70: 0 | S70: 0 | T70: 0 | U70: 0.51111111 | V70: 0.51111111 | W70: 0.51111111 | X70: 0.51111111 | Y70: 0 | Z70: 0 | AA70: 0 | AB70: 0 | AC70: 0 | AD70: 0
A71: bundle leg: cancellation redesign + single fee, live 4Q25–3Q26 (global), laps 4Q26 | B71: same sizing; dates ledger D012/D013/D024/D060 | K71: 0 | L71: 0 | M71: 0 | N71: 0 | O71: 0 | P71: 0 | Q71: 0 | R71: 0 | S71: 0 | T71: 0 | U71: 0 | V71: 0.48888889 | W71: 0.48888889 | X71: 0.48888889 | Y71: 0.48888889 | Z71: 0 | AA71: 0 | AB71: 0 | AC71: 0 | AD71: 0
A72: bundle leg: RNPL ex-NA (live 17 Feb 2026), base 0.0 (unsized by management); high 1.15 | B72: alternative in block F | K72: 0 | L72: 0 | M72: 0 | N72: 0 | O72: 0 | P72: 0 | Q72: 0 | R72: 0 | S72: 0 | T72: 0 | U72: 0 | V72: 0 | W72: 0 | X72: 0 | Y72: 0 | Z72: 0 | AA72: 0 | AB72: 0 | AC72: 0 | AD72: 0
A73: bundle live (pp) | B73: → sum of the three legs | K73: =SUM(K70:K72) -> 0 | L73: =SUM(L70:L72) -> 0 | M73: =SUM(M70:M72) -> 0 | N73: =SUM(N70:N72) -> 0 | O73: =SUM(O70:O72) -> 0 | P73: =SUM(P70:P72) -> 0 | Q73: =SUM(Q70:Q72) -> 0 | R73: =SUM(R70:R72) -> 0 | ... AD73: =SUM(AD70:AD72) -> 0
A75: EX-FX ADR y/y — mechanism (pp) | B75: → core + bundle + geo + unit + LOS + seats + interaction; history = disclosed | K75: =K61 -> 3 | L75: =L61 -> 2 | M75: =M61 -> 0.5 | N75: =N61 -> 0.5 | O75: =O61 -> 2 | P75: =P61 -> 3 | Q75: =Q61 -> 2 | R75: =R61 -> 2 | ... X75: =X61 -> 4 | Y75: =Y68+Y73+SUM(Y62:Y66) -> 3.3159475 | Z75: =Z68+Z73+SUM(Z62:Z66) -> 2.7840742 | AA75: =AA68+AA73+SUM(AA62:AA66) -> 2.4168771 | AB75: =AB68+AB73+SUM(AB62:AB66) -> 2.9565286 | AC75: =AC68+AC73+SUM(AC62:AC66) -> 2.8712181 | AD75: =AD68+AD73+SUM(AD62:AD66) -> 2.934449
A77: C1. Geo-mix arithmetic for the forward quarters: regional nights growth from the nights line (nights_v2_design.md §2.1), base-quarter shares and regional ADR levels held | B77: regional_growth_forward.csv; 04_regional_quarterly_wide.csv (disclosed-chained)
A78: nights growth, na (%) | B78: NA = nights line; ex-NA = 2Q26 bucket pattern (EMEA 8 / LatAm 20 / APAC 18) scaled to the line's ex-NA rate | Y78: 5.6 | Z78: 3.31 | AA78: 2.31 | AB78: 2.31 | AC78: 2.31 | AD78: 2.31
A79: nights growth, emea (%) | B79: NA = nights line; ex-NA = 2Q26 bucket pattern (EMEA 8 / LatAm 20 / APAC 18) scaled to the line's ex-NA rate | Y79: 7.0786911 | Z79: 6.3166151 | AA79: 6.5333935 | AB79: 4.6724999 | AC79: 4.6726434 | AD79: 4.6357219
A80: nights growth, latam (%) | B80: NA = nights line; ex-NA = 2Q26 bucket pattern (EMEA 8 / LatAm 20 / APAC 18) scaled to the line's ex-NA rate | Y80: 17.696728 | Z80: 15.791538 | AA80: 16.333484 | AB80: 11.68125 | AC80: 11.681609 | AD80: 11.589305
A81: nights growth, apac (%) | B81: NA = nights line; ex-NA = 2Q26 bucket pattern (EMEA 8 / LatAm 20 / APAC 18) scaled to the line's ex-NA rate | Y81: 15.927055 | Z81: 14.212384 | AA81: 14.700135 | AB81: 10.513125 | AC81: 10.513448 | AD81: 10.430374
A82: base-quarter nights share, na | Y82: 0.313935 | Z82: 0.300561 | AA82: 0.277286 | AB82: 0.282553 | AC82: 0.30168752 | AD82: 0.28709151
A83: base-quarter nights share, emea | Y83: 0.367798 | Z83: 0.402575 | AA83: 0.396427 | AB83: 0.4155 | AC83: 0.35839843 | AD83: 0.39572484
A84: base-quarter nights share, latam | Y84: 0.169649 | Z84: 0.174009 | AA84: 0.179409 | AB84: 0.178621 | AC84: 0.18170604 | AD84: 0.18629187
A85: base-quarter nights share, apac | Y85: 0.148618 | Z85: 0.122855 | AA85: 0.146878 | AB85: 0.123325 | AC85: 0.15678695 | AD85: 0.12973328
A86: base-quarter regional ADR ($, anchored) | Y86: 249.337 | Z86: 247.2078 | AA86: 279.2009 | AB86: 280.7511 | AC86: 280.7511 | AD86: 280.7511
A87: base-quarter regional ADR ($, anchored) | Y87: 162.0721 | Z87: 158.3398 | AA87: 180.3991 | AB87: 169.8482 | AC87: 169.8482 | AD87: 169.8482
A88: base-quarter regional ADR ($, anchored) | Y88: 97.0811 | Z88: 95.5083 | AA88: 102.1656 | AB88: 102.8022 | AC88: 102.8022 | AD88: 102.8022
A89: base-quarter regional ADR ($, anchored) | Y89: 116.0255 | Z89: 115.3398 | AA89: 127.7091 | AB89: 122.0612 | AC89: 122.0612 | AD89: 122.0612
A90: total nights growth (%) | B90: → SUMPRODUCT(shares, growth) | Y90: =SUMPRODUCT(Y82:Y85,Y78:Y81) -> 9.7308436 | Z90: =SUMPRODUCT(Z82:Z85,Z78:Z81) -> 8.0317003 | AA90: =SUMPRODUCT(AA82:AA85,AA78:AA81) -> 8.3200448 | AB90: =SUMPRODUCT(AB82:AB85,AB78:AB81) -> 5.9771688 | AC90: =SUMPRODUCT(AC82:AC85,AC78:AC81) -> 6.1425565 | AD90: =SUMPRODUCT(AD82:AD85,AD78:AD81) -> 6.0098116
A91: geo mix (pp) | B91: → (Σ share×(1+g)×ADR) / ((1+g_tot) × Σ share×ADR) − 1, ×100 | Y91: =(SUMPRODUCT(Y82:Y85,1+Y78:Y81/100,Y86:Y89)/((1+Y90/100)*SUMPRODUCT(Y82:Y85,Y86:Y89))-1)*100 -> -1.2926338 | Z91: =(SUMPRODUCT(Z82:Z85,1+Z78:Z81/100,Z86:Z89)/((1+Z90/100)*SUMPRODUCT(Z82:Z85,Z86:Z89))-1)*100 -> -1.3356182 | AA91: =(SUMPRODUCT(AA82:AA85,1+AA78:AA81/100,AA86:AA89)/((1+AA90/100)*SUMPRODUCT(AA82:AA85,AA86:AA89))-1)*100 -> -1.6203852 | AB91: =(SUMPRODUCT(AB82:AB85,1+AB78:AB81/100,AB86:AB89)/((1+AB90/100)*SUMPRODUCT(AB82:AB85,AB86:AB89))-1)*100 -> -1.0807337 | AC91: =(SUMPRODUCT(AC82:AC85,1+AC78:AC81/100,AC86:AC89)/((1+AC90/100)*SUMPRODUCT(AC82:AC85,AC86:AC89))-1)*100 -> -1.1660443 | AD91: =(SUMPRODUCT(AD82:AD85,1+AD78:AD81/100,AD86:AD89)/((1+AD90/100)*SUMPRODUCT(AD82:AD85,AD86:AD89))-1)*100 -> -1.1028134
A93: D. Reported ADR path — ADR = year-ago ADR × (1 + (ex-FX mechanism + FX identity) / 100); band; the Street; GBV on the nights line
A94: FX effect on ADR (pp) | B94: → block B identity | Y94: =Y51 -> 0.41528142 | Z94: =Z51 -> 0.51366903 | AA94: =AA51 -> -0.36901348 | AB94: =AB51 -> -0.42693615 | AC94: =AC51 -> -0.14674826 | AD94: =AD51 -> 0
A95: reported ADR y/y (%) | B95: → ex-FX mechanism + FX | Y95: =Y75+Y94 -> 3.7312289 | Z95: =Z75+Z94 -> 3.2977432 | AA95: =AA75+AA94 -> 2.0478636 | AB95: =AB75+AB94 -> 2.5295925 | AC95: =AC75+AC94 -> 2.7244698 | AD95: =AD75+AD94 -> 2.934449
A96: ADR ($) — the line | B96: → year-ago ADR × (1 + y/y/100) | Y96: =U7*(1+Y95/100) -> 177.68122 | Z96: =V7*(1+Z95/100) -> 173.03405 | AA96: =W7*(1+AA95/100) -> 190.64582 | AB96: =X7*(1+AB95/100) -> 188.37762 | AC96: =Y7*(1+AC95/100) -> 182.52209 | AD96: =Z7*(1+AD95/100) -> 178.11165
A97: band half-width (pp) | B97: engine exfx_envelope.csv: RSS of parameter half-ranges ⊕ FX bootstrap sd | Y97: 0.97752254 | Z97: 1.9318807 | AA97: 2.7421745 | AB97: 3.2481459 | AC97: 3.7566631 | AD97: 3.9000455
A98: ADR low ($) | Y98: =U7*(1+(Y95-Y97)/100) -> 176.00682 | Z98: =V7*(1+(Z95-Z97)/100) -> 169.79796 | AA98: =W7*(1+(AA95-AA97)/100) -> 185.52289 | AB98: =X7*(1+(AB95-AB97)/100) -> 182.4098 | AC98: =Y7*(1+(AC95-AC97)/100) -> 175.84721 | AD98: =Z7*(1+(AD95-AD97)/100) -> 171.36324
A99: ADR high ($) | Y99: =U7*(1+(Y95+Y97)/100) -> 179.35562 | Z99: =V7*(1+(Z95+Z97)/100) -> 176.27014 | AA99: =W7*(1+(AA95+AA97)/100) -> 195.76875 | AB99: =X7*(1+(AB95+AB97)/100) -> 194.34544 | AC99: =Y7*(1+(AC95+AC97)/100) -> 189.19698 | AD99: =Z7*(1+(AD95+AD97)/100) -> 184.86005
A100: Street ADR ($) | B100: Bloomberg MODL screenshot 12 Sep 2026 (Krish): 3Q26 177.06 n 26 (173.71–179.12), 4Q26 171.33 n 25; no FY row exists | Y100: 177.06 | Z100: 171.33
A101: Street implied y/y (%) | Y101: =(Y100/U7-1)*100 -> 3.3685562 | Z101: =(Z100/V7-1)*100 -> 2.2804609
A102: z: (ours − Street) / band | Y102: =(Y95-Y101)/Y97 -> 0.37101203 | Z102: =(Z95-Z101)/Z97 -> 0.52657616
A103: P(print ≥ Street) | B103: → 1 − NORM.S.DIST((Street y/y − ours)/band, TRUE) | Y103: =1-NORM.S.DIST((Y101-Y95)/Y97,TRUE) -> 0.64468572 | Z103: =1-NORM.S.DIST((Z101-Z95)/Z97,TRUE) -> 0.70075602
A104: nights (m) — line 1 | B104: → Income_Statement row 5 (nights line) | K104: =Income_Statement!C5 -> 121.1 | L104: =Income_Statement!D5 -> 115.1 | M104: =Income_Statement!E5 -> 113.2 | N104: =Income_Statement!F5 -> 98.8 | O104: =Income_Statement!G5 -> 132.6 | P104: =Income_Statement!H5 -> 125.1 | Q104: =Income_Statement!I5 -> 122.8 | R104: =Income_Statement!J5 -> 111 | ... AD104: =Income_Statement!V5 -> 139.67718
A105: GBV ($bn) = nights × ADR | B105: cross-check only; the take-rate line is built next | K105: =K104*K7/1000 -> 20.396873 | L105: =L104*L7/1000 -> 19.107751 | M105: =M104*M7/1000 -> 18.268216 | N105: =N104*N7/1000 -> 15.484924 | O105: =O104*O7/1000 -> 22.923888 | P105: =P104*P7/1000 -> 21.208203 | Q105: =Q104*Q7/1000 -> 20.094992 | R105: =R104*R7/1000 -> 17.55243 | ... X105: =X104*X7/1000 -> 27.247159 | Y105: =Y104*Y96/1000 -> 26.084971 | Z105: =Z104*Z96/1000 -> 22.80559 | AA105: =AA104*AA96/1000 -> 32.222234 | AB105: =AB104*AB96/1000 -> 29.593868 | AC105: =AC104*AC96/1000 -> 28.458586 | AD105: =AD104*AD96/1000 -> 24.878133
A107: E. Engine reference values (Python) — for tie-out after an Excel recalculation
A108: walk-forward RMSE ratio vs naive, V0 identity, W1 O1 / O2 / O3 | C108: 0.43734369 | D108: 0.34372143 | E108: 0.30273258
A109: … W2 O1 / O2 / O3 (pass line ≤ 0.75 at O2 and O3 on both windows) | C109: 0.62480261 | D109: 0.38308644 | E109: 0.3172637
A110: V1 fitted pass-through, W1 O1 / O2 / O3 | C110: 0.49715297 | D110: 0.37498592 | E110: 0.33727461
A111: euro-only OLS (comparator), W1 O1 / O2 / O3 | C111: 0.39910412 | D111: 0.27000123 | E111: 0.28132061
A112: posterior pass-through β (NA / EMEA / LatAm / APAC), prior N(1, 0.25²) | C112: 0.99372204 | D112: 1.1991177 | E112: 0.45952241 | F112: 1.2663928
A113: FX effect 3Q26 / 4Q26 / 1Q27 / 2Q27 (pp, spot held) | C113: 0.41528142 | D113: 0.51366903 | E113: -0.36901348 | F113: -0.42693615
A114: ADR $ 3Q26 / 4Q26 / 1Q27 / 2Q27 (engine) | C114: 177.68122 | D114: 173.03405 | E114: 190.64582 | F114: 188.37761
...

Sheet Income_Statement
A1: Airbnb — income statement, official (built line by line; nights first). USD millions unless stated.
A2: Row 5 nights: green = link to Nights_Engine. Rows 8–11 GBV and ADR: link to ADR_Engine (line 2). Other lines: labels only until built together (yellow = to build). Quarters A = printed, E = engine.
A4: Quarter | C4: 1Q23A | D4: 2Q23A | E4: 3Q23A | F4: 4Q23A | G4: 1Q24A | H4: 2Q24A | I4: 3Q24A | J4: 4Q24A | K4: 1Q25A | L4: 2Q25A | M4: 3Q25A | N4: 4Q25A | O4: 1Q26A | P4: 2Q26A | Q4: 3Q26E | R4: 4Q26E | S4: 1Q27E | T4: 2Q27E | U4: 3Q27E | V4: 4Q27E | X4: FY23 | Y4: FY24 | Z4: FY25 | AA4: FY26 | AB4: FY27
A5: Nights & seats booked (m) | B5: Nights_Engine: printed (A), base print path (E) | C5: =Nights_Engine!K7 -> 121.1 | D5: =Nights_Engine!L7 -> 115.1 | E5: =Nights_Engine!M7 -> 113.2 | F5: =Nights_Engine!N7 -> 98.8 | G5: =Nights_Engine!O7 -> 132.6 | H5: =Nights_Engine!P7 -> 125.1 | I5: =Nights_Engine!Q7 -> 122.8 | J5: =Nights_Engine!R7 -> 111 | ... P5: =Nights_Engine!X7 -> 148.3 | Q5: =Nights_Engine!Y85 -> 146.8077 | R5: =Nights_Engine!Z85 -> 131.79828 | S5: =Nights_Engine!AA85 -> 169.01621 | T5: =Nights_Engine!AB85 -> 157.09864 | U5: =Nights_Engine!AC85 -> 155.91858 | V5: =Nights_Engine!AD85 -> 139.67718 | X5: =C5+D5+E5+F5 -> 448.2 | Y5: =G5+H5+I5+J5 -> 491.5 | Z5: =K5+L5+M5+N5 -> 533 | AA5: =O5+P5+Q5+R5 -> 583.10598 | AB5: =S5+T5+U5+V5 -> 621.71061
A6: y/y | B6: → nights / four quarters earlier − 1 | C6: =Nights_Engine!K8 -> 0.18609207 | D6: =Nights_Engine!L8 -> 0.1099325 | E6: =Nights_Engine!M8 -> 0.13540622 | F6: =Nights_Engine!N8 -> 0.12018141 | G6: =G5/C5-1 -> 0.094962841 | H6: =H5/D5-1 -> 0.086880973 | I6: =I5/E5-1 -> 0.084805654 | J6: =J5/F5-1 -> 0.12348178 | K6: =K5/G5-1 -> 0.07918552 | L6: =L5/H5-1 -> 0.074340528 | M6: =M5/I5-1 -> 0.087947883 | N6: =N5/J5-1 -> 0.098198198 | ... V6: =V5/R5-1 -> 0.05978 | Y6: =Y5/X5-1 -> 0.096608657 | Z6: =Z5/Y5-1 -> 0.084435402 | AA6: =AA5/Z5-1 -> 0.09400746 | AB6: =AB5/AA5-1 -> 0.066205179
A7: Lines to build together (in order) — empty until each has its rationale file | B7: history 1Q23-2Q26 plugged from 02_panel_quarterly.csv (reported); forecast cost lines and below-the-line plugged from 40_line_build base (DEC-0022); blue = plug, black = formula
A8: Gross booking value ($bn) | B8: → nights × ADR ÷ 1000 (line 1 × line 2) | C8: =C5*C10/1000 -> 20.396873 | D8: =D5*D10/1000 -> 19.107751 | E8: =E5*E10/1000 -> 18.268216 | F8: =F5*F10/1000 -> 15.484924 | G8: =G5*G10/1000 -> 22.923888 | H8: =H5*H10/1000 -> 21.208203 | I8: =I5*I10/1000 -> 20.094992 | J8: =J5*J10/1000 -> 17.55243 | ... V8: =V5*V10/1000 -> 24.878133
A9: y/y | G9: =G8/C8-1 -> 0.12389228 | H9: =H8/D8-1 -> 0.1099267 | I9: =I8/E8-1 -> 0.099997504 | J9: =J8/F8-1 -> 0.13351735 | K9: =K8/G8-1 -> 0.06957223 | L9: =L8/H8-1 -> 0.10570952 | M9: =M8/I8-1 -> 0.13880832 | N9: =N8/J8-1 -> 0.16334143 | ... V9: =V8/R8-1 -> 0.090878703
A10: ADR ($ = GBV / nights) | B10: ADR_Engine: printed (A), engine path (E) — line 2 | C10: =ADR_Engine!K7 -> 168.43 | D10: =ADR_Engine!L7 -> 166.01 | E10: =ADR_Engine!M7 -> 161.38 | F10: =ADR_Engine!N7 -> 156.73 | G10: =ADR_Engine!O7 -> 172.88 | H10: =ADR_Engine!P7 -> 169.53 | I10: =ADR_Engine!Q7 -> 163.64 | J10: =ADR_Engine!R7 -> 158.13 | ... V10: =ADR_Engine!AD7 -> 178.11165
A11: y/y | C11: =ADR_Engine!K8 -> 0.0021419647 | D11: =ADR_Engine!L8 -> 0.013863442 | E11: =ADR_Engine!M8 -> 0.031577602 | F11: =ADR_Engine!N8 -> 0.025652771 | G11: =G10/C10-1 -> 0.026420471 | H11: =H10/D10-1 -> 0.021203542 | I11: =I10/E10-1 -> 0.014004214 | J11: =J10/F10-1 -> 0.0089325592 | K11: =K10/G10-1 -> -0.008907913 | L11: =L10/H10-1 -> 0.029198372 | M11: =M10/I10-1 -> 0.046748961 | N11: =N10/J10-1 -> 0.059318282 | ... V11: =V10/R10-1 -> 0.02934449
A12: Revenue | B12: A: reported. E: = GBV x take rate (DEC-0018), so revenue is an output of lines 1-2 | C12: 1818 | D12: 2484 | E12: 3397 | F12: 2218 | G12: 2142 | H12: 2748 | I12: 3732 | J12: 2480 | K12: 2272 | L12: 3096 | M12: 4095 | N12: 2778 | O12: 2678 | P12: 3608 | Q12: =Q8*1000*Q14 -> 4690.9154 | R12: =R8*1000*R14 -> 3140.7997 | S12: =S8*1000*S14 -> 2955.1011 | T12: =T8*1000*T14 -> 3925.6266 | U12: =U8*1000*U14 -> 5117.7676 | V12: =V8*1000*V14 -> 3426.2315 | X12: =SUM(C12:F12) -> 9917 | Y12: =SUM(G12:J12) -> 11102 | Z12: =SUM(K12:N12) -> 12241 | AA12: =SUM(O12:R12) -> 14117.715 | AB12: =SUM(S12:V12) -> 15424.727
A13: y/y | G13: =G12/C12-1 -> 0.17821782 | H13: =H12/D12-1 -> 0.10628019 | I13: =I12/E12-1 -> 0.098616426 | J13: =J12/F12-1 -> 0.11812444 | K13: =K12/G12-1 -> 0.060690943 | L13: =L12/H12-1 -> 0.12663755 | M13: =M12/I12-1 -> 0.097266881 | N13: =N12/J12-1 -> 0.12016129 | ... V13: =V12/R12-1 -> 0.090878703 | Y13: =Y12/X12-1 -> 0.11949178 | Z13: =Z12/Y12-1 -> 0.10259413 | AA13: =AA12/Z12-1 -> 0.15331387 | AB13: =AB12/AA12-1 -> 0.092579544
A14: Take rate (revenue / GBV) | B14: A: = revenue / GBV. E: 3Q26-4Q26 Street-implied; 1Q27+ seasonal naive tau[q-4], no drift | C14: =C12/(C8*1000) -> 0.089131309 | D14: =D12/(D8*1000) -> 0.1299996 | E14: =E12/(E8*1000) -> 0.18595138 | F14: =F12/(F8*1000) -> 0.14323609 | G14: =G12/(G8*1000) -> 0.093439647 | H14: =H12/(H8*1000) -> 0.12957251 | I14: =I12/(I8*1000) -> 0.18571791 | J14: =J12/(J8*1000) -> 0.14129098 | ... P14: =P12/(P8*1000) -> 0.13241748 | Q14: 0.17983211 | R14: 0.13772061 | S14: 0.09171 | T14: 0.13265 | U14: 0.17983211 | V14: 0.13772061 | X14: =X12/(SUM(C8:F8)*1000) -> 0.13537132 | Y14: =Y12/(SUM(G8:J8)*1000) -> 0.13575527 | Z14: =Z12/(SUM(K8:N8)*1000) -> 0.13411461 | AA14: =AA12/(SUM(O8:R8)*1000) -> 0.13404718 | AB14: =AB12/(SUM(S8:V8)*1000) -> 0.13395006
A16: Cost of revenue (cash) | B16: cash = GAAP less SBC. A: 02_panel_quarterly. E: 40_line_build base, carried in dollars (DEC-0022) | C16: 428 | D16: 432 | E16: 459 | F16: 384 | G16: 480 | H16: 506 | I16: 465 | J16: 427 | K16: 506 | L16: 544 | M16: 549 | N16: 487 | O16: 581 | P16: 633 | Q16: 640.78412 | R16: 578.03946 | S16: 706.00359 | T16: 727.29954 | U16: 699.45368 | V16: 626.85228 | X16: =SUM(C16:F16) -> 1703 | Y16: =SUM(G16:J16) -> 1878 | Z16: =SUM(K16:N16) -> 2086 | AA16: =SUM(O16:R16) -> 2432.8236 | AB16: =SUM(S16:V16) -> 2759.6091
A17: Operations & support (cash) | C17: 267 | D17: 298 | E17: 299 | F17: 254 | G17: 266 | H17: 314 | I17: 347 | J17: 265 | K17: 282 | L17: 309 | M17: 343 | N17: 303 | O17: 301 | P17: 323 | Q17: 361.44309 | R17: 318.28709 | S17: 319.08609 | T17: 340.96824 | U17: 381.7591 | V17: 336.06248 | X17: =SUM(C17:F17) -> 1118 | Y17: =SUM(G17:J17) -> 1192 | Z17: =SUM(K17:N17) -> 1237 | AA17: =SUM(O17:R17) -> 1303.7302 | AB17: =SUM(S17:V17) -> 1377.8759
A18: Product development (cash) | C18: 271 | D18: 260 | E18: 244 | F18: 253 | G18: 290 | H18: 280 | I18: 294 | J18: 306 | K18: 338 | L18: 331 | M18: 333 | N18: 335 | O18: 375 | P18: 374 | Q18: 359.09488 | R18: 369.02512 | S18: 414.12379 | T18: 400.79642 | U18: 399.65871 | V18: 410.71068 | X18: =SUM(C18:F18) -> 1028 | Y18: =SUM(G18:J18) -> 1170 | Z18: =SUM(K18:N18) -> 1337 | AA18: =SUM(O18:R18) -> 1477.12 | AB18: =SUM(S18:V18) -> 1625.2896
A19: Sales & marketing (cash) | C19: 422 | D19: 450 | E19: 370 | F19: 391 | G19: 479 | H19: 527 | I19: 471 | J19: 501 | K19: 519 | L19: 639 | M19: 585 | N19: 633 | O19: 696 | P19: 808 | Q19: 778.31581 | R19: 758.10753 | S19: 829.27179 | T19: 935.13627 | U19: 819.9308 | V19: 875.28478 | X19: =SUM(C19:F19) -> 1633 | Y19: =SUM(G19:J19) -> 1978 | Z19: =SUM(K19:N19) -> 2376 | AA19: =SUM(O19:R19) -> 3040.4233 | AB19: =SUM(S19:V19) -> 3459.6236
A20: General & administrative (cash, ex lodging-tax reserves) | B20: ex lodging/withholding-tax reserves (4Q23 carried $931m); reserves sit in the add-back row | C20: 191 | D20: 219 | E20: 202 | F20: 211 | G20: 223 | H20: 242 | I20: 210 | J20: 226 | K20: 235 | L20: 244 | M20: 257 | N20: 259 | O20: 226 | P20: 227 | Q20: 265.38907 | R20: 276.41093 | S20: 249.22724 | T20: 271.5804 | U20: 256.53902 | V20: 267.19333 | X20: =SUM(C20:F20) -> 823 | Y20: =SUM(G20:J20) -> 901 | Z20: =SUM(K20:N20) -> 995 | AA20: =SUM(O20:R20) -> 994.8 | AB20: =SUM(S20:V20) -> 1044.54
A21: Total cash costs | C21: =SUM(C16:C20) -> 1579 | D21: =SUM(D16:D20) -> 1659 | E21: =SUM(E16:E20) -> 1574 | F21: =SUM(F16:F20) -> 1493 | G21: =SUM(G16:G20) -> 1738 | H21: =SUM(H16:H20) -> 1869 | I21: =SUM(I16:I20) -> 1787 | J21: =SUM(J16:J20) -> 1725 | ... V21: =SUM(V16:V20) -> 2516.1036 | X21: =SUM(C21:F21) -> 6305 | Y21: =SUM(G21:J21) -> 7119 | Z21: =SUM(K21:N21) -> 8031 | AA21: =SUM(O21:R21) -> 9248.8971 | AB21: =SUM(S21:V21) -> 10266.938
A22: % of revenue | C22: =C21/C12 -> 0.86853685 | D22: =D21/D12 -> 0.6678744 | E22: =E21/E12 -> 0.46335001 | F22: =F21/F12 -> 0.67312894 | G22: =G21/G12 -> 0.81139122 | H22: =H21/H12 -> 0.680131 | I22: =I21/I12 -> 0.47883173 | J22: =J21/J12 -> 0.69556452 | ... V22: =V21/V12 -> 0.73436472 | X22: =X21/X12 -> 0.63577695 | Y22: =Y21/Y12 -> 0.64123581 | Z22: =Z21/Z12 -> 0.65607385 | AA22: =AA21/AA12 -> 0.65512705 | AB22: =AB21/AB12 -> 0.66561557
A23: Depreciation & amortisation | C23: 11 | D23: 9 | E23: 8 | F23: 16 | G23: 14 | H23: 14 | I23: 15 | J23: 22 | K23: 25 | L23: 21 | M23: 22 | N23: 23 | O23: 22 | P23: 17 | Q23: 20.633971 | R23: 20.633971 | S23: 20.633971 | T23: 20.633971 | U23: 20.633971 | V23: 20.633971 | X23: =SUM(C23:F23) -> 44 | Y23: =SUM(G23:J23) -> 65 | Z23: =SUM(K23:N23) -> 91 | AA23: =SUM(O23:R23) -> 80.267941 | AB23: =SUM(S23:V23) -> 82.535882
A24: Adjusted EBITDA | B24: A: as reported. E: = revenue - cash costs + D&A + add-backs; margin is therefore an OUTPUT | C24: 262 | D24: 819 | E24: 1834 | F24: 738 | G24: 424 | H24: 894 | I24: 1958 | J24: 765 | K24: 417 | L24: 1043 | M24: 2051 | N24: 786 | O24: 519 | P24: 1261 | Q24: =Q12-Q21+Q23+Q26 -> 2306.5224 | R24: =R12-R21+R23+R26 -> 861.56356 | S24: =S12-S21+S23+S26 -> 458.02253 | T24: =T12-T21+T23+T26 -> 1270.4797 | U24: =U12-U21+U23+U26 -> 2581.0603 | V24: =V12-V21+V23+V26 -> 930.76194 | X24: =SUM(C24:F24) -> 3653 | Y24: =SUM(G24:J24) -> 4041 | Z24: =SUM(K24:N24) -> 4297 | AA24: =SUM(O24:R24) -> 4948.086 | AB24: =SUM(S24:V24) -> 5240.3244
A25: Adjusted EBITDA margin | C25: =C24/C12 -> 0.14411441 | D25: =D24/D12 -> 0.32971014 | E25: =E24/E12 -> 0.53988814 | F25: =F24/F12 -> 0.33273219 | G25: =G24/G12 -> 0.19794585 | H25: =H24/H12 -> 0.32532751 | I25: =I24/I12 -> 0.52465166 | J25: =J24/J12 -> 0.30846774 | ... V25: =V24/V12 -> 0.27165763 | X25: =X24/X12 -> 0.36835737 | Y25: =Y24/Y12 -> 0.36398847 | Z25: =Z24/Z12 -> 0.35103341 | AA25: =AA24/AA12 -> 0.35048773 | AB25: =AB24/AB12 -> 0.33973531
B26: memo, feeds Adj. EBITDA: lodging-tax reserves and other add-backs (acquisition, IPO, restructuring) | C26: 12 | D26: -15 | E26: 3 | F26: -3 | G26: 6 | H26: 1 | I26: -2 | J26: -12 | K26: 0 | L26: -7 | M26: 1 | N26: 2 | O26: -2 | P26: 1 | Q26: 0 | R26: 0 | S26: 0 | T26: 0 | U26: 0 | V26: 0 | X26: =SUM(C26:F26) -> -3 | Y26: =SUM(G26:J26) -> -7 | Z26: =SUM(K26:N26) -> -4 | AA26: =SUM(O26:R26) -> -1 | AB26: =SUM(S26:V26) -> 0
A27: Stock-based compensation | B27: A: income-statement footnote total. E: 40_line_build (SBC[q-4] x 1.1318, M7 parameter sheet) | C27: 240 | D27: 304 | E27: 286 | F27: 290 | G27: 295 | H27: 382 | I27: 362 | J27: 368 | K27: 358 | L27: 424 | M27: 399 | N27: 411 | O27: 410 | P27: 487 | Q27: 451.57919 | R27: 465.16051 | S27: 464.02874 | T27: 551.1756 | U27: 511.08712 | V27: 526.45816 | X27: =SUM(C27:F27) -> 1120 | Y27: =SUM(G27:J27) -> 1407 | Z27: =SUM(K27:N27) -> 1592 | AA27: =SUM(O27:R27) -> 1813.7397 | AB27: =SUM(S27:V27) -> 2052.7496
A28: Operating income (GAAP) | B28: A: reported GAAP. E: = Adj. EBITDA - D&A - SBC (holds exactly in the line build) | C28: -5 | D28: 523 | E28: 1496 | F28: -496 | G28: 101 | H28: 497 | I28: 1525 | J28: 430 | K28: 38 | L28: 612 | M28: 1625 | N28: 269 | O28: 86 | P28: 758 | Q28: =Q24-Q23-Q27 -> 1834.3092 | R28: =R24-R23-R27 -> 375.76908 | S28: =S24-S23-S27 -> -26.64018 | T28: =T24-T23-T27 -> 698.67009 | U28: =U24-U23-U27 -> 2049.3392 | V28: =V24-V23-V27 -> 383.66981 | X28: =SUM(C28:F28) -> 1518 | Y28: =SUM(G28:J28) -> 2553 | Z28: =SUM(K28:N28) -> 2544 | AA28: =SUM(O28:R28) -> 3054.0783 | AB28: =SUM(S28:V28) -> 3105.0389
A29: Interest income | C29: 146 | D29: 191 | E29: 192 | F29: 192 | G29: 202 | H29: 226 | I29: 207 | J29: 183 | K29: 173 | L29: 190 | M29: 180 | N29: 162 | O29: 155 | P29: 183 | Q29: 183.54893 | R29: 165.49547 | S29: 180.26226 | T29: 202.84769 | U29: 191.14509 | V29: 171.15508 | X29: =SUM(C29:F29) -> 721 | Y29: =SUM(G29:J29) -> 818 | Z29: =SUM(K29:N29) -> 705 | AA29: =SUM(O29:R29) -> 687.0444 | AB29: =SUM(S29:V29) -> 745.41011
A30: Interest expense | C30: 4 | D30: 2 | E30: 6 | F30: 71 | G30: 0 | H30: 9 | I30: 2 | J30: 10 | K30: 5 | L30: 6 | M30: 6 | N30: 26 | O30: 21 | P30: 37 | Q30: 37 | R30: 37 | S30: 37 | T30: 37 | U30: 37 | V30: 37 | X30: =SUM(C30:F30) -> 83 | Y30: =SUM(G30:J30) -> 21 | Z30: =SUM(K30:N30) -> 43 | AA30: =SUM(O30:R30) -> 132 | AB30: =SUM(S30:V30) -> 148
A31: Other income / (expense), net | C31: -7 | D31: -36 | E31: -3 | F31: -8 | G31: -10 | H31: -33 | I31: 5 | J31: 19 | K31: -33 | L31: -17 | M31: -7 | N31: -12 | O31: 61 | P31: -7 | Q31: 3.7 | R31: 3.7 | S31: 3.7 | T31: 3.7 | U31: 3.7 | V31: 3.7 | X31: =SUM(C31:F31) -> -54 | Y31: =SUM(G31:J31) -> -19 | Z31: =SUM(K31:N31) -> -69 | AA31: =SUM(O31:R31) -> 61.4 | AB31: =SUM(S31:V31) -> 14.8
A32: Pre-tax income | C32: 130 | D32: 676 | E32: 1679 | F32: -383 | G32: 293 | H32: 681 | I32: 1735 | J32: 622 | K32: 173 | L32: 779 | M32: 1792 | N32: 393 | O32: 281 | P32: 897 | Q32: =Q28+Q29-Q30+Q31 -> 1984.5582 | R32: =R28+R29-R30+R31 -> 507.96454 | S32: =S28+S29-S30+S31 -> 120.32208 | T32: =T28+T29-T30+T31 -> 868.21778 | U32: =U28+U29-U30+U31 -> 2207.1843 | V32: =V28+V29-V30+V31 -> 521.52488 | X32: =SUM(C32:F32) -> 2102 | Y32: =SUM(G32:J32) -> 3331 | Z32: =SUM(K32:N32) -> 3137 | AA32: =SUM(O32:R32) -> 3670.5227 | AB32: =SUM(S32:V32) -> 3717.249
A33: Income tax | B33: E: effective rate 18.0% FY26 / 17.5% FY27 (M7 parameter sheet), applied to our own pre-tax | C33: 13.4 | D33: 26 | E33: -2695 | F33: -34 | G33: 29 | H33: 126 | I33: 367 | J33: 161 | K33: 19 | L33: 137 | M33: 418 | N33: 52 | O33: 121 | P33: 81 | Q33: =Q32*0.18 -> 357.22047 | R33: =R32*0.18 -> 91.433618 | S33: =S32*0.175 -> 21.056364 | T33: =T32*0.175 -> 151.93811 | U33: =U32*0.175 -> 386.25725 | V33: =V32*0.175 -> 91.266854 | X33: =SUM(C33:F33) -> -2689.6 | Y33: =SUM(G33:J33) -> 683 | Z33: =SUM(K33:N33) -> 626 | AA33: =SUM(O33:R33) -> 650.65409 | AB33: =SUM(S33:V33) -> 650.51858
A34: Net income | C34: 117 | D34: 650 | E34: 4374 | F34: -349 | G34: 264 | H34: 555 | I34: 1368 | J34: 461 | K34: 154 | L34: 642 | M34: 1374 | N34: 341 | O34: 160 | P34: 816 | Q34: =Q32-Q33 -> 1627.3377 | R34: =R32-R33 -> 416.53092 | S34: =S32-S33 -> 99.265715 | T34: =T32-T33 -> 716.27967 | U34: =U32-U33 -> 1820.927 | V34: =V32-V33 -> 430.25803 | X34: =SUM(C34:F34) -> 4792 | Y34: =SUM(G34:J34) -> 2648 | Z34: =SUM(K34:N34) -> 2511 | AA34: =SUM(O34:R34) -> 3019.8686 | AB34: =SUM(S34:V34) -> 3066.7304
A35: Diluted shares (m) | C35: 670 | D35: 665 | E35: 660 | F35: 640 | G35: 654 | H35: 649 | I35: 642 | J35: 636 | K35: 632 | L35: 626 | M35: 621 | N35: 614 | O35: 608 | P35: 597 | Q35: 591.67581 | R35: 586.35163 | S35: 581.02744 | T35: 575.70325 | U35: 570.37907 | V35: 565.05488 | X35: 662 | Y35: 645 | Z35: 623 | AA35: =AVERAGE(O35:R35) -> 595.75686 | AB35: =AVERAGE(S35:V35) -> 573.04116
A36: Diluted EPS ($) | B36: E: = net income / diluted shares; shares -5.324m per quarter (M7) | C36: 0.18 | D36: 0.98 | E36: 6.63 | F36: -0.55 | G36: 0.41 | H36: 0.86 | I36: 2.13 | J36: 0.73 | K36: 0.24 | L36: 1.03 | M36: 2.21 | N36: 0.56 | O36: 0.26 | P36: 1.37 | Q36: =Q34/Q35 -> 2.7503874 | R36: =R34/R35 -> 0.71037737 | S36: =S34/S35 -> 0.17084514 | T36: =T34/T35 -> 1.2441821 | U36: =U34/U35 -> 3.1924857 | V36: =V34/V35 -> 0.76144467 | X36: 7.24 | Y36: 4.11 | Z36: 4.03 | AA36: =AA34/AA35 -> 5.0689616 | AB36: =AB34/AB35 -> 5.3516757
A38: Cross-checks against the Street, and the open choices this line does not settle (memo rows - none of these feed the statement above)
A39: Street revenue ($m) | B39: LSEG 06_consensus_quarterly_2027.csv, 13 Sep 2026 pull | Q39: 4744.32 | R39: 3161.82 | S39: 3010.32 | T39: 4036.94 | U39: 5269.97 | V39: 3528.92
A40: ours vs Street | B40: negative = our nights/ADR lines sit below consensus | Q40: =Q12/Q39-1 -> -0.011256533 | R40: =R12/R39-1 -> -0.0066481582 | S40: =S12/S39-1 -> -0.018343213 | T40: =T12/T39-1 -> -0.027573717 | U40: =U12/U39-1 -> -0.028881072 | V40: =V12/V39-1 -> -0.029099122
A41: Street adj. EBITDA ($m) | B41: LSEG; n 36-37 for 3Q26/4Q26, n 17-19 for 2027 | Q41: 2361.52 | R41: 913.68 | S41: 610.73 | T41: 1451.71 | U41: 2695.55 | V41: 1068.4
A42: ours vs Street | B42: wider than the revenue gap because cost dollars are carried flat | Q42: =Q24/Q41-1 -> -0.023289066 | R42: =R24/R41-1 -> -0.057040143 | S42: =S24/S41-1 -> -0.25004089 | T42: =T24/T41-1 -> -0.12483922 | U42: =U24/U41-1 -> -0.042473606 | V42: =V24/V41-1 -> -0.12882634
A43: memo: adj. EBITDA if costs flexed to hold the line build's own margin | B43: DEC-0022 carries dollars flat; C4 asks whether management's margin sentence is a budget (costs flex) or a floor | Q43: =Q12*0.5036687385012039 -> 2362.6674 | R43: =R12*0.2828323322844086 -> 888.31971 | S43: =S12*0.18212486768865177 -> 538.19739 | T43: =T12*0.34098793219639467 -> 1338.5913 | U43: =U12*0.5196296453789346 -> 2659.3438 | V43: =V12*0.2799655381693949 -> 959.22675
A44: difference vs the statement above | B44: the cost of the flat-dollar assumption, in EBITDA $m | Q44: =Q43-Q24 -> 56.14504 | R44: =R43-R24 -> 26.756148 | S44: =S43-S24 -> 80.174862 | T44: =T43-T24 -> 68.111626 | U44: =U43-U24 -> 78.283499 | V44: =V43-V24 -> 28.464816
A45: memo: DEC-0023 hosting step, B08 alternative ($85.0m/q vs the $100.21m/$111.71m plugged) | B45: NOT CHOSEN - both sides on record; positive = EBITDA if the lower B08 hosting number is right | Q45: 15.207932 | R45: 15.207932 | S45: 26.707932 | T45: 26.707932 | U45: 26.707932 | V45: 26.707932

Sheet Sources
A1: Sources and decisions
A2: Printed nights | B2: data/processed/abnb_driver_history_quarterly.csv | C2: DEC-0003
A3: Review counts, two vintages | B3: data/processed/q3nowcast/E/market_vintage_monthly.csv; q3nowcast_v2/E | C3: E note; WPK-A
A4: Regional stays growth (vmatch) | B4: data/processed/forecast_methods/reviews_index_v2/index_regional_vmatch_pct.csv | C4: REVIEWS_INDEX_v2 §2
A5: Stay-mix weights | B5: reviews_index_v2/mix_weights_stay_quarter.csv ← overnight/10_regional_panel_quarterly.csv | C5: §5 (v2.1)
A6: 3Q26 quarter-to-date by region | B6: data/processed/q3nowcast/E/vintage_matched_nowcast.csv; q3_2026_nowcast.csv | C6: E6
A7: Lead-time kernel | B7: data/processed/forecast_methods/kernel_leadtime_v2/K2_M_matrix.csv | C7: kernel lane
A8: Base path components | B8: docs/pitch-model-v2/lines/final_nights.md §4–6 | C8: DEC-0019 / 0025 / 0029
A9: Street nights | B9: Bloomberg MODL 12 Sep 2026 | C9: DEC-0005
A10: Guidance | B10: data/processed/overnight/02_guidance_ledger.csv | C10: letters
A11: Unearned fees, GBV | B11: data/processed/overnight/02_kpi_panel_quarterly.csv | C11: RNPL audit
A12: Eurostat panel statistics | B12: reviews_index_v2/stage_a_tests.csv | C12: §2.2
A13: ADR, ex-FX ADR, FX effect (letters) | B13: data/processed/overnight/02_kpi_panel_quarterly.csv (adr_usd, adr_yoy_exfx_pct, fx_pts_adr) | C13: X1 §2a
... A24: Mitigation outputs (block G) | B24: adr_engine/: reconcile_pooled_regressions.csv, sizemix_rebased_plug.csv, market_panel_scores.csv, origin_lang_*.csv | C24: adr_v2_mitigation_A–D
