Workbook

Sheet Inputs
A1: Choice-probability nights driver — INPUTS
A2: Blue = hardcoded input you can change. Black = formula. Green = link to another sheet. Yellow = key levers. Every input carries its source in column G.
A4: AIRBNB 2025 (U.S.)
A5: Airbnb North America nights 2025 (mm) | B5: 158 | G5: Airbnb FY2025 10-K, MD&A regional table — https://www.sec.gov/Archives/edgar/data/1559720/000155972026000004/abnb-20251231.htm
A6: U.S. share of North America (revenue proxy) | B6: 0.92 | G6: U.S. = 39% of FY2025 revenue ($4.76B of $12.2B; 61% non-U.S. per 10-K) ÷ NA revenue $5.196B
A7: Nights per booking, North America | B7: 4.1 | G7: Airbnb FY2025 10-K
A8: Share of Airbnb guests who would have used a hotel absent Airbnb | B8: 0.38 | G8: Farronato & Fradkin (AER 2022): 62% would NOT have switched to a hotel — https://andreyfradkin.com/assets/airbnb_welfare_paper.pdf
A9: HOTELS 2025 (U.S.)
A10: U.S. hotel room nights sold 2024 (mm) | B10: 1300 | G10: STR/CoStar via HospitalityNet — https://www.hospitalitynet.org/news/4127015.html
A11: Room-night growth 2025 (assumed) | B11: 0.01 | G11: Assumption; CoStar/TE 2026 forecast is +1.7%
A12: Business share of room nights | B12: 0.42049808 | G12: AHLA 2024 State of the Industry: 439M business / 605M leisure (2023) — https://www.ahla.com/sites/default/files/SOTI.2024.Final_.Draft_.v4.pdf
A13: Corporate bookings single-occupancy share | B13: 0.795 | G13: Hotel Booking Demand dataset (Antonio et al. 2019), corporate segment, n=4,291 — https://www.sciencedirect.com/science/article/pii/S2352340918315191
A14: SHARE DYNAMICS
A15: Switch rate: Airbnb-hotel switching per % price gap | B15: 5 | G15: Central 5.0; grid 2.5–10.3. Anchor: F&F (AER 2022) online Appendix Table E9 — Airbnb demand rises 3.76% when all hotel prices rise 1%; model reproduces that at beta 10.3 (= 3.76/(0.38×0.955)), discounted for tier-level, 10-city, city-night scope. 2.5 = bull floor (no evidential support as a central)
A16: Rest-of-world nights growth (placeholder, team input) | B16: 0.1 | G16: SUPERSEDED by the Global sheet: EMEA from the measured 4-country calibration, LatAm/APAC explicit fades from disclosed +18%/+15% (choice_nights_driver_global.py)
A18: SEGMENT INPUTS (party size)
A19: Segment | B19: Airbnb booking share | C19: Airbnb relative stay length | D19: Hotel leisure party share | E19: Hotel leisure relative nights | F19: Hotel rooms per party | G19: Price ratio 2025 (Airbnb ÷ hotel) | H19: Mix drift / yr — Airbnb pool | I19: Mix drift / yr — hotel pool | J19: Product shift (logit pts/yr)
A20: solo | B20: 0.16 | C20: 1.5 | D20: 0.2 | E20: 0.7 | F20: 1 | G20: 0.54 | H20: -0.0063 | I20: -0.0027 | J20: 0
A21: pair | B21: 0.358 | C21: 0.95 | D21: 0.54 | E21: 1 | F21: 1 | G21: 1.03 | H21: 0 | I21: 0 | J21: 0
A22: 3-4 | B22: 0.323 | C22: 0.9 | D22: 0.2 | E22: 1 | F22: 1.5 | G22: 0.69 | H22: 0.0127 | I22: 0.0054 | J22: 0
A23: 5+ | B23: 0.159 | C23: 0.8 | D23: 0.06 | E23: 1 | F23: 2.5 | G23: 0.71 | H23: 0.0253 | I23: 0.0107 | J23: 0
A24: Sources: booking share = fitted party-size distribution (research/party_size_distribution.md; anchors: guest arrivals ÷ bookings 2.97, Airbnb '>80% of bookings are group trips'). Relative stay length: solo = 24% of nights ÷ 16% of bookings (Airbnb 2022); others from Inside Airbnb booked-run lengths by capacity. Hotel leisure party share = mean of Hawaii DBEDT 2024 hotel-only (Table 43) and Las Vegas Visitor Profile 2024. Relative nights: Portuguese ledger (solo 2.5 vs 3.6). Rooms per party: 2 people/room, families with small kids 1.5. Price ratio: party_size_cost_crossover.csv - the Jun-2026 Inside Airbnb `price` is a stay quote that ALREADY includes the guest service fee and amortised cleaning, so no fee is added (corrected 7 Sep 2026; the earlier 0.69/1.22/0.80/0.79 counted the 14% fee twice) vs rooms × $158.67 ADR. Descriptive - no formula reads this column. Mix drift SPLIT 8 Sep 2026 into two vectors (was one applied to both pools). Airbnb pool implies mean party size +0.62%/yr, from the Inside Airbnb review-text proxy (74m reviews, 123 markets, 2018-25); hotel pool +0.26%/yr, from the Hawaii DBEDT ratio (rental 2.28->2.49 = +0.80%/yr vs hotel 2.22->2.30 = +0.34%/yr, 2013-24 - the only source observing both in one market). The old single vector implied +0.98%/yr for both and flattered the forecast.
A26: YEAR PATHS
A27: Year | B27: 2025 | C27: 2026 | D27: 2027 | E27: 2028 | F27: 2029 | G27: 2030
A28: U.S. lodging demand growth (hotel-contestable pool) | B28: — | C28: 0.017 | D28: 0.011 | E28: 0.015 | F28: 0.015 | G28: 0.015 | H28: CoStar/Tourism Economics Aug-2026: demand +1.7% 2026, +1.1% 2027 — https://www.hospitalitynet.org/news/4133888/us-hotel-forecast-assumptions-august-2026.html; 1.5% after = assumption
A29: Hotel ADR growth | B29: — | C29: 0.031 | D29: 0.016 | E29: 0.025 | F29: 0.025 | G29: 0.025 | H29: CoStar/TE: ADR +3.1% 2026, +1.6% 2027 (+2.1% ex World Cup); 2.5% after = assumption
A30: Airbnb ADR growth (link to the team's ADR line) | B30: — | C30: 0.035 | D30: 0.025 | E30: 0.025 | F30: 0.025 | G30: 0.025 | H30: WIRED to model/assumptions.md WS13 base, ex-FX: 2H26 +3.0% (FY26 blends ~+3.5%), FY27/28 +2.5%, held after. Ex-FX is the right basis for the US share equation. Bear +2.0% / bull +4.0% 2H26
A31: Stay length, nights per booking (NA) | B31: 4.1 | C31: 4.1 | D31: 4.1 | E31: 4.1 | F31: 4.1 | G31: 4.1 | H31: EXPLICIT LEVER added 8 Sep 2026. FY20-25 10-Ks: NA 4.4/4.3/4.2/4.1/4.1/4.1 - FLAT since 2023, so the U.S. base carries no drag. Global fell 4.1->3.7 (-2.0%/yr, ~58mm nights forgone in 2025) but that is EMEA (4.4->3.8) and LatAm (4.4->3.6); APAC rose 2.8->3.3. Bear = the EMEA pattern reaches NA (-2%/yr -> 2030 nights 154.8mm, CAGR +1.3%); bull = +1%/yr (179.8mm, +4.4%). Caveat: the 2020-22 plateau was COVID long-stay inflation, so part of the global fall is self-limiting normalisation
A32: Own-category nights growth (category adoption) | B32: — | C32: 0.04 | D32: 0.04 | E32: 0.035 | F32: 0.035 | G32: 0.03 | H32: GROUNDED: inverting the model on disclosed NA nights (146/154/158mm FY23-25) implies own-category growth 7.9% (2024) -> 4.5% (2025); 4% entry = observed 2025 exit rate, fade extends the observed deceleration. category_adoption_evidence.csv

Sheet Calibration_2025
A1: 2025 calibration (U.S.) — party-nights, millions
A3: Segment | B3: Airbnb nights | C3: Own-category Airbnb | D3: Contestable Airbnb | E3: Hotel party-nights | F3: Contestable pool | G3: P(Airbnb | pool) | H3: Airbnb share of all lodging
A4: solo | B4: =(Inputs!$B$5*Inputs!$B$6)*Inputs!$B$20*Inputs!$C$20/(Inputs!$B$20*Inputs!$C$20+Inputs!$B$21*Inputs!$C$21+Inputs!$B$22*Inputs!$C$22+Inputs!$B$23*Inputs!$C$23) | C4: =B4*(1-Inputs!$B$8) | D4: =B4-C4 | E4: =((Inputs!$B$10*(1+Inputs!$B$11))*(1-Inputs!$B$12))/(Inputs!$D$20*Inputs!$E$20*Inputs!$F$20+Inputs!$D$21*Inputs!$E$21*Inputs!$F$21+Inputs!$D$22*Inputs!$E$22*Inputs!$F$22+Inputs!$D$23*Inputs!$E$23*Inputs!$F$23)*Inputs!$D$20*Inputs!$E$20+((Inputs!$B$10*(1+Inputs!$B$11))*Inputs!$B$12)*Inputs!$B$13 | F4: =D4+E4 | G4: =D4/F4 | H4: =B4/(B4+E4)
A5: pair | B5: =(Inputs!$B$5*Inputs!$B$6)*Inputs!$B$21*Inputs!$C$21/(Inputs!$B$20*Inputs!$C$20+Inputs!$B$21*Inputs!$C$21+Inputs!$B$22*Inputs!$C$22+Inputs!$B$23*Inputs!$C$23) | C5: =B5*(1-Inputs!$B$8) | D5: =B5-C5 | E5: =((Inputs!$B$10*(1+Inputs!$B$11))*(1-Inputs!$B$12))/(Inputs!$D$20*Inputs!$E$20*Inputs!$F$20+Inputs!$D$21*Inputs!$E$21*Inputs!$F$21+Inputs!$D$22*Inputs!$E$22*Inputs!$F$22+Inputs!$D$23*Inputs!$E$23*Inputs!$F$23)*Inputs!$D$21*Inputs!$E$21+((Inputs!$B$10*(1+Inputs!$B$11))*Inputs!$B$12)*(1-Inputs!$B$13) | F5: =D5+E5 | G5: =D5/F5 | H5: =B5/(B5+E5)
A6: 3-4 | B6: =(Inputs!$B$5*Inputs!$B$6)*Inputs!$B$22*Inputs!$C$22/(Inputs!$B$20*Inputs!$C$20+Inputs!$B$21*Inputs!$C$21+Inputs!$B$22*Inputs!$C$22+Inputs!$B$23*Inputs!$C$23) | C6: =B6*(1-Inputs!$B$8) | D6: =B6-C6 | E6: =((Inputs!$B$10*(1+Inputs!$B$11))*(1-Inputs!$B$12))/(Inputs!$D$20*Inputs!$E$20*Inputs!$F$20+Inputs!$D$21*Inputs!$E$21*Inputs!$F$21+Inputs!$D$22*Inputs!$E$22*Inputs!$F$22+Inputs!$D$23*Inputs!$E$23*Inputs!$F$23)*Inputs!$D$22*Inputs!$E$22 | F6: =D6+E6 | G6: =D6/F6 | H6: =B6/(B6+E6)
A7: 5+ | B7: =(Inputs!$B$5*Inputs!$B$6)*Inputs!$B$23*Inputs!$C$23/(Inputs!$B$20*Inputs!$C$20+Inputs!$B$21*Inputs!$C$21+Inputs!$B$22*Inputs!$C$22+Inputs!$B$23*Inputs!$C$23) | C7: =B7*(1-Inputs!$B$8) | D7: =B7-C7 | E7: =((Inputs!$B$10*(1+Inputs!$B$11))*(1-Inputs!$B$12))/(Inputs!$D$20*Inputs!$E$20*Inputs!$F$20+Inputs!$D$21*Inputs!$E$21*Inputs!$F$21+Inputs!$D$22*Inputs!$E$22*Inputs!$F$22+Inputs!$D$23*Inputs!$E$23*Inputs!$F$23)*Inputs!$D$23*Inputs!$E$23 | F7: =D7+E7 | G7: =D7/F7 | H7: =B7/(B7+E7)
A8: TOTAL | B8: =SUM(B4:B7) | C8: =SUM(C4:C7) | D8: =SUM(D4:D7) | E8: =SUM(E4:E7) | F8: =SUM(F4:F7) | G8: =D8/F8 | H8: =B8/(B8+E8)
A10: Check: Airbnb U.S. nights = NA nights × U.S. share | B10: =(Inputs!$B$5*Inputs!$B$6)
A11: Check: hotel room nights 2025 (mm) | B11: =(Inputs!$B$10*(1+Inputs!$B$11))
A12: Hotel party-nights < room nights because parties of 3+ take 1.5–2.5 rooms. Business room nights are split solo/pair by the corporate single-occupancy share; leisure room nights are converted to parties with the leisure party mix, relative nights and rooms per party.

Sheet Projection
A1: Projection — U.S. Airbnb nights from choice probabilities (millions)
A2: Nights = Σ segments [ own-category nights + contestable pool × P(Airbnb) ]. logit P(t) = logit P(t−1) − β·[ln(1+Airbnb ADR g) − ln(1+hotel ADR g)] + product shift.
A3: YEAR | B3: 2025 | C3: 2026 | D3: 2027 | E3: 2028 | F3: 2029 | G3: 2030
A4: Relative price change: ln(1+Airbnb ADR g) − ln(1+hotel ADR g) | C4: =LN(1+Inputs!C30)-LN(1+Inputs!C29) | D4: =LN(1+Inputs!D30)-LN(1+Inputs!D29) | E4: =LN(1+Inputs!E30)-LN(1+Inputs!E29) | F4: =LN(1+Inputs!F30)-LN(1+Inputs!F29) | G4: =LN(1+Inputs!G30)-LN(1+Inputs!G29)
A6: Segment: solo
A7: Contestable pool M (hotel + contestable Airbnb) | B7: =Calibration_2025!F4 | C7: =B7*(1+Inputs!C28)*(1+Inputs!$H$20) | D7: =C7*(1+Inputs!D28)*(1+Inputs!$H$20) | E7: =D7*(1+Inputs!E28)*(1+Inputs!$H$20) | F7: =E7*(1+Inputs!F28)*(1+Inputs!$H$20) | G7: =F7*(1+Inputs!G28)*(1+Inputs!$H$20)
A8: Own-category Airbnb nights N | B8: =Calibration_2025!C4 | C8: =B8*(1+Inputs!$H$20)*(1+Inputs!C32) | D8: =C8*(1+Inputs!$H$20)*(1+Inputs!D32) | E8: =D8*(1+Inputs!$H$20)*(1+Inputs!E32) | F8: =E8*(1+Inputs!$H$20)*(1+Inputs!F32) | G8: =F8*(1+Inputs!$H$20)*(1+Inputs!G32)
A9: P(Airbnb | contestable pool) | B9: =Calibration_2025!G4 | C9: =1/(1+EXP(-(LN(B9/(1-B9))-Inputs!$B$15*C$4+Inputs!$I$20))) | D9: =1/(1+EXP(-(LN(C9/(1-C9))-Inputs!$B$15*D$4+Inputs!$I$20))) | E9: =1/(1+EXP(-(LN(D9/(1-D9))-Inputs!$B$15*E$4+Inputs!$I$20))) | F9: =1/(1+EXP(-(LN(E9/(1-E9))-Inputs!$B$15*F$4+Inputs!$I$20))) | G9: =1/(1+EXP(-(LN(F9/(1-F9))-Inputs!$B$15*G$4+Inputs!$I$20)))
A10: Airbnb nights — solo | B10: =B8+B7*B9 | C10: =C8+C7*C9 | D10: =D8+D7*D9 | E10: =E8+E7*E9 | F10: =F8+F7*F9 | G10: =G8+G7*G9
A12: Segment: pair
A13: Contestable pool M (hotel + contestable Airbnb) | B13: =Calibration_2025!F5 | C13: =B13*(1+Inputs!C28)*(1+Inputs!$H$21) | D13: =C13*(1+Inputs!D28)*(1+Inputs!$H$21) | E13: =D13*(1+Inputs!E28)*(1+Inputs!$H$21) | F13: =E13*(1+Inputs!F28)*(1+Inputs!$H$21) | G13: =F13*(1+Inputs!G28)*(1+Inputs!$H$21)
A14: Own-category Airbnb nights N | B14: =Calibration_2025!C5 | C14: =B14*(1+Inputs!$H$21)*(1+Inputs!C32) | D14: =C14*(1+Inputs!$H$21)*(1+Inputs!D32) | E14: =D14*(1+Inputs!$H$21)*(1+Inputs!E32) | F14: =E14*(1+Inputs!$H$21)*(1+Inputs!F32) | G14: =F14*(1+Inputs!$H$21)*(1+Inputs!G32)
A15: P(Airbnb | contestable pool) | B15: =Calibration_2025!G5 | C15: =1/(1+EXP(-(LN(B15/(1-B15))-Inputs!$B$15*C$4+Inputs!$I$21))) | D15: =1/(1+EXP(-(LN(C15/(1-C15))-Inputs!$B$15*D$4+Inputs!$I$21))) | E15: =1/(1+EXP(-(LN(D15/(1-D15))-Inputs!$B$15*E$4+Inputs!$I$21))) | F15: =1/(1+EXP(-(LN(E15/(1-E15))-Inputs!$B$15*F$4+Inputs!$I$21))) | G15: =1/(1+EXP(-(LN(F15/(1-F15))-Inputs!$B$15*G$4+Inputs!$I$21)))
A16: Airbnb nights — pair | B16: =B14+B13*B15 | C16: =C14+C13*C15 | D16: =D14+D13*D15 | E16: =E14+E13*E15 | F16: =F14+F13*F15 | G16: =G14+G13*G15
A18: Segment: 3-4
A19: Contestable pool M (hotel + contestable Airbnb) | B19: =Calibration_2025!F6 | C19: =B19*(1+Inputs!C28)*(1+Inputs!$H$22) | D19: =C19*(1+Inputs!D28)*(1+Inputs!$H$22) | E19: =D19*(1+Inputs!E28)*(1+Inputs!$H$22) | F19: =E19*(1+Inputs!F28)*(1+Inputs!$H$22) | G19: =F19*(1+Inputs!G28)*(1+Inputs!$H$22)
A20: Own-category Airbnb nights N | B20: =Calibration_2025!C6 | C20: =B20*(1+Inputs!$H$22)*(1+Inputs!C32) | D20: =C20*(1+Inputs!$H$22)*(1+Inputs!D32) | E20: =D20*(1+Inputs!$H$22)*(1+Inputs!E32) | F20: =E20*(1+Inputs!$H$22)*(1+Inputs!F32) | G20: =F20*(1+Inputs!$H$22)*(1+Inputs!G32)
A21: P(Airbnb | contestable pool) | B21: =Calibration_2025!G6 | C21: =1/(1+EXP(-(LN(B21/(1-B21))-Inputs!$B$15*C$4+Inputs!$I$22))) | D21: =1/(1+EXP(-(LN(C21/(1-C21))-Inputs!$B$15*D$4+Inputs!$I$22))) | E21: =1/(1+EXP(-(LN(D21/(1-D21))-Inputs!$B$15*E$4+Inputs!$I$22))) | F21: =1/(1+EXP(-(LN(E21/(1-E21))-Inputs!$B$15*F$4+Inputs!$I$22))) | G21: =1/(1+EXP(-(LN(F21/(1-F21))-Inputs!$B$15*G$4+Inputs!$I$22)))
A22: Airbnb nights — 3-4 | B22: =B20+B19*B21 | C22: =C20+C19*C21 | D22: =D20+D19*D21 | E22: =E20+E19*E21 | F22: =F20+F19*F21 | G22: =G20+G19*G21
A24: Segment: 5+
A25: Contestable pool M (hotel + contestable Airbnb) | B25: =Calibration_2025!F7 | C25: =B25*(1+Inputs!C28)*(1+Inputs!$H$23) | D25: =C25*(1+Inputs!D28)*(1+Inputs!$H$23) | E25: =D25*(1+Inputs!E28)*(1+Inputs!$H$23) | F25: =E25*(1+Inputs!F28)*(1+Inputs!$H$23) | G25: =F25*(1+Inputs!G28)*(1+Inputs!$H$23)
A26: Own-category Airbnb nights N | B26: =Calibration_2025!C7 | C26: =B26*(1+Inputs!$H$23)*(1+Inputs!C32) | D26: =C26*(1+Inputs!$H$23)*(1+Inputs!D32) | E26: =D26*(1+Inputs!$H$23)*(1+Inputs!E32) | F26: =E26*(1+Inputs!$H$23)*(1+Inputs!F32) | G26: =F26*(1+Inputs!$H$23)*(1+Inputs!G32)
A27: P(Airbnb | contestable pool) | B27: =Calibration_2025!G7 | C27: =1/(1+EXP(-(LN(B27/(1-B27))-Inputs!$B$15*C$4+Inputs!$I$23))) | D27: =1/(1+EXP(-(LN(C27/(1-C27))-Inputs!$B$15*D$4+Inputs!$I$23))) | E27: =1/(1+EXP(-(LN(D27/(1-D27))-Inputs!$B$15*E$4+Inputs!$I$23))) | F27: =1/(1+EXP(-(LN(E27/(1-E27))-Inputs!$B$15*F$4+Inputs!$I$23))) | G27: =1/(1+EXP(-(LN(F27/(1-F27))-Inputs!$B$15*G$4+Inputs!$I$23)))
A28: Airbnb nights — 5+ | B28: =B26+B25*B27 | C28: =C26+C25*C27 | D28: =D26+D25*D27 | E28: =E26+E25*E27 | F28: =F26+F25*F27 | G28: =G26+G25*G27
A30: U.S. AIRBNB NIGHTS (mm) | B30: =B10+B16+B22+B28 | C30: =C10+C16+C22+C28 | D30: =D10+D16+D22+D28 | E30: =E10+E16+E22+E28 | F30: =F10+F16+F22+F28 | G30: =G10+G16+G22+G28
A31: growth | C31: =C30/B30-1 | D31: =D30/C30-1 | E31: =E30/D30-1 | F31: =F30/E30-1 | G31: =G30/F30-1
A32: Airbnb share of hotel-contestable pool | B32: =(B7*B9+B13*B15+B19*B21+B25*B27)/(B7+B13+B19+B25) | C32: =(C7*C9+C13*C15+C19*C21+C25*C27)/(C7+C13+C19+C25) | D32: =(D7*D9+D13*D15+D19*D21+D25*D27)/(D7+D13+D19+D25) | E32: =(E7*E9+E13*E15+E19*E21+E25*E27)/(E7+E13+E19+E25) | F32: =(F7*F9+F13*F15+F19*F21+F25*F27)/(F7+F13+F19+F25) | G32: =(G7*G9+G13*G15+G19*G21+G25*G27)/(G7+G13+G19+G25)
A33: Airbnb share of all U.S. lodging party-nights | B33: =B30/(B8+B7+B14+B13+B20+B19+B26+B25) | C33: =C30/(C8+C7+C14+C13+C20+C19+C26+C25) | D33: =D30/(D8+D7+D14+D13+D20+D19+D26+D25) | E33: =E30/(E8+E7+E14+E13+E20+E19+E26+E25) | F33: =F30/(F8+F7+F14+F13+F20+F19+F26+F25) | G33: =G30/(G8+G7+G14+G13+G20+G19+G26+G25)
A35: PLUG INTO THE REVENUE MODEL (U.S. slice)
A36: Airbnb ADR ($, GBV per night) — team input | B36: 255 | C36: =B36*(1+Inputs!C30) | D36: =C36*(1+Inputs!D30) | E36: =D36*(1+Inputs!E30) | F36: =E36*(1+Inputs!F30) | G36: =F36*(1+Inputs!G30) | H36: 2025 NA GBV $40.3B ÷ 158M nights = $255 (FY2025 10-K); grows with the Airbnb ADR path on Inputs
A37: Take rate — team input (carries the host-only fee migration) | B37: 0.134 | C37: 0.134 | D37: 0.136 | E37: 0.136 | F37: 0.136 | G37: 0.136 | H37: FY2025 revenue ÷ GBV = 13.4% (Q4'25 letter). Steps to 13.6% by FY27: the single 15.5% host fee is ~+58bp on guest spend (~half of listings migrated by 2Q26, all by year end); FY26 is held at 13.4% because incentives for Services/Experiences/hotels are contra-revenue and management guided FY26 flat. Without the migration this line would drift to 12.9-13.1%.
A38: FX factor (1.00 for USD) — team input | B38: 1 | C38: 1 | D38: 1 | E38: 1 | F38: 1 | G38: 1
A39: U.S. GBV ($mm) = nights × ADR × FX | B39: =B30*B36*B38 | C39: =C30*C36*C38 | D39: =D30*D36*D38 | E39: =E30*E36*E38 | F39: =F30*F36*F38 | G39: =G30*G36*G38
A40: U.S. revenue ($mm) = GBV × take rate | B40: =B39*B37 | C40: =C39*C37 | D40: =D39*D37 | E40: =E39*E37 | F40: =F39*F37 | G40: =G39*G37
A42: How to wire it: replace the U.S./North-America nights growth plug in the team model with row 30 (or its growth in row 31). Keep ADR and FX where they are — this sheet only explains NIGHTS. The take-rate row is NOT a constant: it steps 13.4% → 13.6% by FY27 for the host-only fee migration, so reconcile it with the team model rather than overwriting it blind. For other regions, either repeat the calibration with that region's hotel data or apply the rest-of-world growth input.

Sheet Sensitivity
A1: Sensitivity — 2030 U.S. Airbnb nights (mm) and 2025–30 CAGR
A2: Values computed by analysis/src/choice_nights_driver.py (same model); rows = switch rate (share sensitivity to the % price gap; called beta in the F&F paper), columns = Airbnb ADR growth minus hotel ADR growth per year. Static output, not formulas.
A4: switch rate \ ADR premium | B4: -2%/yr | C4: +0%/yr | D4: +2%/yr | E4: +4%/yr
A5: 2.5 | B5: 177.2 | C5: 162.6 | D5: 150.9 | E5: 141.7
A6: 5 | B6: 195.3 | C6: 162.6 | D6: 141.6 | E6: 128.3
A7: 7 | B7: 212.5 | C7: 162.6 | D7: 135.4 | E7: 121.1
A8: 10.3 | B8: 247.3 | C8: 162.6 | D8: 127.4 | E8: 113.8
A10: CAGR 2025–30
A11: 2.5 | B11: 0.050643796 | C11: 0.032654612 | D11: 0.017440036 | E11: 0.0047106
A12: 5 | B12: 0.071205171 | C12: 0.032654612 | D12: 0.0044847227 | E12: -0.015145082
A13: 7 | B13: 0.08949519 | C13: 0.032654612 | D13: -0.0043826079 | E13: -0.026385288
A14: 10.3 | B14: 0.12306922 | C14: 0.032654612 | D14: -0.016431544 | E14: -0.038433296

Sheet Countries
A1: Europe 2025 calibration — measured Eurostat data (vs U.S. revenue proxy)
A2: Computed by analysis/src/choice_nights_driver_countries.py. Platform guest-nights (Airbnb+Booking+Expedia, Eurostat tour_ce_omr) x Airbnb listing share (FR 69% / ES 50% / IT 53% / DE 51%, myDataValue/AirDNA) vs hotel guest-nights (Eurostat I551; ES & DE are 2024 vintage). Guest-nights are converted to party-nights by people per party, not rooms per party. Party mixes transplanted (Airbnb global fit; U.S. hotel travel-party est.); CONTESTABLE 38% is the U.S. F&F figure. Static output, not formulas.
A4: Country | B4: Segment | C4: Airbnb party-nights (mm) | D4: of which contestable (mm) | E4: Hotel party-nights (mm) | F4: P(Airbnb | contestable pool) | G4: Airbnb share of all lodging
A5: France | B5: solo | C5: 13 | D5: 4.9 | E5: 53.2 | F5: 0.084745229 | G5: 0.19592368
A6: France | B6: pair | C6: 18.4 | D6: 7 | E6: 45.5 | F6: 0.13288417 | G6: 0.2873866
A7: France | B7: 3-4 | C7: 15.7 | D7: 6 | E7: 15.2 | F7: 0.28210776 | G7: 0.50838763
A8: France | B8: 5+ | C8: 6.9 | D8: 2.6 | E8: 4.4 | F8: 0.37480282 | G8: 0.61204513
A9: France | B9: TOTAL | C9: 53.9 | D9: 20.5 | E9: 118.2 | F9: 0.14760638 | G9: 0.31304641
A10: Spain | B10: solo | C10: 8.3 | D10: 3.2 | E10: 87.7 | F10: 0.034846861 | G10: 0.08676898
A11: Spain | B11: pair | C11: 11.8 | D11: 4.5 | E11: 75.1 | F11: 0.05638764 | G11: 0.13588682
A12: Spain | B12: 3-4 | C12: 10.1 | D12: 3.8 | E12: 25 | F12: 0.13287192 | G12: 0.28736483
A13: Spain | B13: 5+ | C13: 4.4 | D13: 1.7 | E13: 7.2 | F13: 0.18947306 | G13: 0.38087082
A14: Spain | B14: TOTAL | C14: 34.6 | D14: 13.2 | E14: 194.9 | F14: 0.06325304 | G14: 0.15088381
A15: Italy | B15: solo | C15: 6.5 | D15: 2.5 | E15: 69.6 | F15: 0.03424716 | G15: 0.085354743
A16: Italy | B16: pair | C16: 9.2 | D16: 3.5 | E16: 59.6 | F16: 0.055438524 | G16: 0.1337893
... A24: Germany | B24: TOTAL | C24: 12.7 | D24: 4.8 | E24: 161 | F24: 0.029128487 | G24: 0.073176184
A26: U.S. comparison: 10.9% of lodging party-nights (Calibration_2025). France is the outlier (31%); Spain/Italy ~15% sit at U.S. levels; Germany 7%. Rest-of-world plug candidates: weight these by Airbnb regional nights.

Sheet Global
A1: Global nights build — replaces the 10% rest-of-world plug
A2: Computed by analysis/src/choice_nights_driver_global.py. US = full segment choice model (beta 5.0, team ADR line ex-FX from model/assumptions.md WS13 base). EMEA = measured 4-country Eurostat calibration scaled to EMEA's 215mm nights, same M/P/N machinery in aggregate (category growth 7%→5% vs ~10% implied). NA-ex-US tracks the US. LatAm/APAC = explicit fades from disclosed +18%/+15%. Static output, not formulas.
A4: Year | B4: US | C4: NA ex-US | D4: EMEA | E4: LatAm | F4: APAC | G4: Global nights (mm) | H4: Growth
A5: 2025 | B5: 138.4 | C5: 19.6 | D5: 215 | E5: 90 | F5: 70 | G5: 533
A6: 2026 | B6: 142.4 | C6: 20.1 | D6: 221.8 | E6: 104.4 | F6: 79.1 | G6: 567.9 | H6: 0.0655
A7: 2027 | B7: 145.1 | C7: 20.5 | D7: 232.8 | E7: 119 | F7: 88.6 | G7: 606 | H7: 0.0671
A8: 2028 | B8: 149.8 | C8: 21.2 | D8: 243.6 | E8: 133.3 | F8: 98.3 | G8: 646.2 | H8: 0.0663
A9: 2029 | B9: 154.7 | C9: 21.9 | D9: 253.6 | E9: 148 | F9: 108.2 | G9: 686.2 | H9: 0.0619
A10: 2030 | B10: 159.3 | C10: 22.5 | D10: 263.8 | E10: 162.8 | F10: 117.9 | G10: 726.2 | H10: 0.0583
A13: BY AIRBNB REPORTING SEGMENT (mm nights)
A14: Year | B14: North America | C14: EMEA | D14: LatAm | E14: APAC | F14: Total
A15: 2025 | B15: 158 | C15: 215 | D15: 90 | E15: 70 | F15: 533
A16: 2026 | B16: 162.5 | C16: 221.8 | D16: 104.4 | E16: 79.1 | F16: 567.8
A17: 2027 | B17: 165.6 | C17: 232.8 | D17: 119 | E17: 88.6 | F17: 606
A18: 2028 | B18: 171 | C18: 243.6 | D18: 133.3 | E18: 98.3 | F18: 646.2
A19: 2029 | B19: 176.6 | C19: 253.6 | D19: 148 | E19: 108.2 | F19: 686.4
A20: 2030 | B20: 181.8 | C20: 263.8 | D20: 162.8 | E20: 117.9 | F20: 726.3
A21: CAGR 2025-30 | B21: 0.0285 | C21: 0.0418 | D21: 0.1259 | E21: 0.1099 | F21: 0.0638
A23: Confidence differs sharply by region. North America is the full segment choice model; EMEA is calibrated on measured Eurostat platform and hotel nights for FR/ES/IT/DE and scaled. LatAm and APAC are growth fades off disclosed 2025 rates with NO hotel-side data and no choice model - yet they are 30% of 2025 nights and 62% of the 2025-30 growth. That is the least evidenced part of the forecast and the first place to spend more research.
A25: Reconciliation: team model WS13 base has total nights FY26 +9.9%, FY27 +8.9%, FY28 +7.4%; this build runs +7.1% / +7.2% / +7.1%. The gap is almost entirely North America (team 2H26 NA +7-8% vs this model's US +3.3% for 2026) — the choice model says NA growth at that pace needs share gains or category adoption above the 2025 exit rate.
