Workbook
Name Scenario: 'Cover'!$B$4
Name NIGHTS_1Q23: 'Drivers'!$E$2
Name NIGHTS_2Q23: 'Drivers'!$F$2
Name NIGHTS_3Q23: 'Drivers'!$G$2
Name NIGHTS_4Q23: 'Drivers'!$H$2
Name NIGHTS_1Q24: 'Drivers'!$I$2
Name NIGHTS_2Q24: 'Drivers'!$J$2
Name NIGHTS_3Q24: 'Drivers'!$K$2
Name NIGHTS_4Q24: 'Drivers'!$L$2
Name NIGHTS_1Q25: 'Drivers'!$M$2
Name NIGHTS_2Q25: 'Drivers'!$N$2
Name NIGHTS_3Q25: 'Drivers'!$O$2
Name NIGHTS_4Q25: 'Drivers'!$P$2
Name NIGHTS_1Q26: 'Drivers'!$Q$2
Name NIGHTS_2Q26: 'Drivers'!$R$2
Name NIGHTS_3Q26: 'Drivers'!$S$2
Name ADR_1Q23: 'Drivers'!$E$3
Name ADR_2Q23: 'Drivers'!$F$3
Name ADR_3Q23: 'Drivers'!$G$3
Name ADR_4Q23: 'Drivers'!$H$3
Name ADR_1Q24: 'Drivers'!$I$3
Name ADR_2Q24: 'Drivers'!$J$3
Name ADR_3Q24: 'Drivers'!$K$3
Name ADR_4Q24: 'Drivers'!$L$3
Name ADR_1Q25: 'Drivers'!$M$3
Name ADR_2Q25: 'Drivers'!$N$3
Name ADR_3Q25: 'Drivers'!$O$3
Name ADR_4Q25: 'Drivers'!$P$3
Name ADR_1Q26: 'Drivers'!$Q$3
Name ADR_2Q26: 'Drivers'!$R$3
Name ADR_3Q26: 'Drivers'!$S$3
Name ADR_4Q26: 'Drivers'!$T$3
Name GBV_1Q23: 'Drivers'!$E$4
Name GBV_2Q23: 'Drivers'!$F$4
Name GBV_3Q23: 'Drivers'!$G$4
Name GBV_4Q23: 'Drivers'!$H$4
Name GBV_1Q24: 'Drivers'!$I$4
Name GBV_2Q24: 'Drivers'!$J$4
Name GBV_3Q24: 'Drivers'!$K$4
Name GBV_4Q24: 'Drivers'!$L$4
Name GBV_1Q25: 'Drivers'!$M$4
Name GBV_2Q25: 'Drivers'!$N$4
Name GBV_3Q25: 'Drivers'!$O$4
Name GBV_4Q25: 'Drivers'!$P$4
Name GBV_1Q26: 'Drivers'!$Q$4
Name GBV_2Q26: 'Drivers'!$R$4
Name GBV_3Q26: 'Drivers'!$S$4
Name FX_REV_3Q26: 'Drivers'!$S$5
Name FX_REV_4Q26: 'Drivers'!$T$5
Name FX_REV_1Q27: 'Drivers'!$U$5
Name FX_REV_2Q27: 'Drivers'!$V$5
Name FX_ADR_3Q26: 'Drivers'!$S$6
Name FX_ADR_4Q26: 'Drivers'!$T$6
Name FX_ADR_1Q27: 'Drivers'!$U$6
Name FX_ADR_2Q27: 'Drivers'!$V$6
Name STREET_NIGHTS_3Q26: 'Drivers'!$S$7
Name STREET_NIGHTS_4Q26: 'Drivers'!$T$7
Name STREET_ADR_3Q26: 'Drivers'!$S$8
Name REV_1Q23: 'Revenue and Guide'!$E$2
Name REV_2Q23: 'Revenue and Guide'!$F$2

Sheet Cover
A1: Airbnb (ABNB) — pitch model v2
A2: Price date 2026-09-16 · spot $167.51
A4: Scenario | B4: base
A6: Yellow cells are inputs; each carries a defined name (id_period), a grade, and a decision id. Every other number is a formula in those names: use Formulas > Trace Precedents.

Sheet Drivers
A1: id | B1: line | C1: unit | D1: grade · decision | E1: 1Q23 | F1: 2Q23 | G1: 3Q23 | H1: 4Q23 | I1: 1Q24 | J1: 2Q24 | K1: 3Q24 | L1: 4Q24 | M1: 1Q25 | N1: 2Q25 | O1: 3Q25 | P1: 4Q25 | Q1: 1Q26 | R1: 2Q26 | S1: 3Q26 | T1: 4Q26 | U1: 1Q27 | V1: 2Q27 | W1: 3Q27 | X1: 4Q27 | Y1: FY26 | Z1: FY27 | AA1: ALL
A2: NIGHTS | B2: Nights booked (m) | C2: m | D2: B · DEC-0003 / B · DEC-0004 | E2: =INDEX('Scenario Data'!$E$2:$G$2,MATCH(Scenario,'Scenario Data'!$E$1:$G$1,0)) | F2: =INDEX('Scenario Data'!$E$3:$G$3,MATCH(Scenario,'Scenario Data'!$E$1:$G$1,0)) | G2: =INDEX('Scenario Data'!$E$4:$G$4,MATCH(Scenario,'Scenario Data'!$E$1:$G$1,0)) | H2: =INDEX('Scenario Data'!$E$5:$G$5,MATCH(Scenario,'Scenario Data'!$E$1:$G$1,0)) | I2: =INDEX('Scenario Data'!$E$6:$G$6,MATCH(Scenario,'Scenario Data'!$E$1:$G$1,0)) | J2: =INDEX('Scenario Data'!$E$7:$G$7,MATCH(Scenario,'Scenario Data'!$E$1:$G$1,0)) | K2: =INDEX('Scenario Data'!$E$8:$G$8,MATCH(Scenario,'Scenario Data'!$E$1:$G$1,0)) | L2: =INDEX('Scenario Data'!$E$9:$G$9,MATCH(Scenario,'Scenario Data'!$E$1:$G$1,0)) | M2: =INDEX('Scenario Data'!$E$10:$G$10,MATCH(Scenario,'Scenario Data'!$E$1:$G$1,0)) | N2: =INDEX('Scenario Data'!$E$11:$G$11,MATCH(Scenario,'Scenario Data'!$E$1:$G$1,0)) | O2: =INDEX('Scenario Data'!$E$12:$G$12,MATCH(Scenario,'Scenario Data'!$E$1:$G$1,0)) | P2: =INDEX('Scenario Data'!$E$13:$G$13,MATCH(Scenario,'Scenario Data'!$E$1:$G$1,0)) | Q2: =INDEX('Scenario Data'!$E$14:$G$14,MATCH(Scenario,'Scenario Data'!$E$1:$G$1,0)) | R2: =INDEX('Scenario Data'!$E$15:$G$15,MATCH(Scenario,'Scenario Data'!$E$1:$G$1,0)) | S2: =INDEX('Scenario Data'!$E$16:$G$16,MATCH(Scenario,'Scenario Data'!$E$1:$G$1,0))
A3: ADR | B3: ADR ($) | C3: usd | D3: B · DEC-0003 / B · DEC-0008 | E3: =INDEX('Scenario Data'!$E$17:$G$17,MATCH(Scenario,'Scenario Data'!$E$1:$G$1,0)) | F3: =INDEX('Scenario Data'!$E$18:$G$18,MATCH(Scenario,'Scenario Data'!$E$1:$G$1,0)) | G3: =INDEX('Scenario Data'!$E$19:$G$19,MATCH(Scenario,'Scenario Data'!$E$1:$G$1,0)) | H3: =INDEX('Scenario Data'!$E$20:$G$20,MATCH(Scenario,'Scenario Data'!$E$1:$G$1,0)) | I3: =INDEX('Scenario Data'!$E$21:$G$21,MATCH(Scenario,'Scenario Data'!$E$1:$G$1,0)) | J3: =INDEX('Scenario Data'!$E$22:$G$22,MATCH(Scenario,'Scenario Data'!$E$1:$G$1,0)) | K3: =INDEX('Scenario Data'!$E$23:$G$23,MATCH(Scenario,'Scenario Data'!$E$1:$G$1,0)) | L3: =INDEX('Scenario Data'!$E$24:$G$24,MATCH(Scenario,'Scenario Data'!$E$1:$G$1,0)) | M3: =INDEX('Scenario Data'!$E$25:$G$25,MATCH(Scenario,'Scenario Data'!$E$1:$G$1,0)) | N3: =INDEX('Scenario Data'!$E$26:$G$26,MATCH(Scenario,'Scenario Data'!$E$1:$G$1,0)) | O3: =INDEX('Scenario Data'!$E$27:$G$27,MATCH(Scenario,'Scenario Data'!$E$1:$G$1,0)) | P3: =INDEX('Scenario Data'!$E$28:$G$28,MATCH(Scenario,'Scenario Data'!$E$1:$G$1,0)) | Q3: =INDEX('Scenario Data'!$E$29:$G$29,MATCH(Scenario,'Scenario Data'!$E$1:$G$1,0)) | R3: =INDEX('Scenario Data'!$E$30:$G$30,MATCH(Scenario,'Scenario Data'!$E$1:$G$1,0)) | S3: =INDEX('Scenario Data'!$E$31:$G$31,MATCH(Scenario,'Scenario Data'!$E$1:$G$1,0)) | T3: =INDEX('Scenario Data'!$E$32:$G$32,MATCH(Scenario,'Scenario Data'!$E$1:$G$1,0))
A4: GBV | B4: GBV ($M) | C4: musd | D4: formula: NIGHTS * ADR | E4: =NIGHTS_1Q23*ADR_1Q23 | F4: =NIGHTS_2Q23*ADR_2Q23 | G4: =NIGHTS_3Q23*ADR_3Q23 | H4: =NIGHTS_4Q23*ADR_4Q23 | I4: =NIGHTS_1Q24*ADR_1Q24 | J4: =NIGHTS_2Q24*ADR_2Q24 | K4: =NIGHTS_3Q24*ADR_3Q24 | L4: =NIGHTS_4Q24*ADR_4Q24 | M4: =NIGHTS_1Q25*ADR_1Q25 | N4: =NIGHTS_2Q25*ADR_2Q25 | O4: =NIGHTS_3Q25*ADR_3Q25 | P4: =NIGHTS_4Q25*ADR_4Q25 | Q4: =NIGHTS_1Q26*ADR_1Q26 | R4: =NIGHTS_2Q26*ADR_2Q26 | S4: =NIGHTS_3Q26*ADR_3Q26
A5: FX_REV | B5: Revenue FX contribution (pp y/y) | C5: pp | D5: B · DEC-0010 | S5: =INDEX('Scenario Data'!$E$33:$G$33,MATCH(Scenario,'Scenario Data'!$E$1:$G$1,0)) | T5: =INDEX('Scenario Data'!$E$34:$G$34,MATCH(Scenario,'Scenario Data'!$E$1:$G$1,0)) | U5: =INDEX('Scenario Data'!$E$35:$G$35,MATCH(Scenario,'Scenario Data'!$E$1:$G$1,0)) | V5: =INDEX('Scenario Data'!$E$36:$G$36,MATCH(Scenario,'Scenario Data'!$E$1:$G$1,0))
A6: FX_ADR | B6: ADR FX contribution (pp y/y) | C6: pp | D6: B · DEC-0010 | S6: =INDEX('Scenario Data'!$E$37:$G$37,MATCH(Scenario,'Scenario Data'!$E$1:$G$1,0)) | T6: =INDEX('Scenario Data'!$E$38:$G$38,MATCH(Scenario,'Scenario Data'!$E$1:$G$1,0)) | U6: =INDEX('Scenario Data'!$E$39:$G$39,MATCH(Scenario,'Scenario Data'!$E$1:$G$1,0)) | V6: =INDEX('Scenario Data'!$E$40:$G$40,MATCH(Scenario,'Scenario Data'!$E$1:$G$1,0))
A7: STREET_NIGHTS | B7: Street nights (m) | C7: m | D7: B · DEC-0013 | S7: =INDEX('Scenario Data'!$E$41:$G$41,MATCH(Scenario,'Scenario Data'!$E$1:$G$1,0)) | T7: =INDEX('Scenario Data'!$E$42:$G$42,MATCH(Scenario,'Scenario Data'!$E$1:$G$1,0))
A8: STREET_ADR | B8: Street ADR ($) | C8: usd | D8: B · DEC-0013 | S8: =INDEX('Scenario Data'!$E$43:$G$43,MATCH(Scenario,'Scenario Data'!$E$1:$G$1,0))

Sheet Revenue and Guide
A1: id | B1: line | C1: unit | D1: grade · decision | E1: 1Q23 | F1: 2Q23 | G1: 3Q23 | H1: 4Q23 | I1: 1Q24 | J1: 2Q24 | K1: 3Q24 | L1: 4Q24 | M1: 1Q25 | N1: 2Q25 | O1: 3Q25 | P1: 4Q25 | Q1: 1Q26 | R1: 2Q26 | S1: 3Q26 | T1: 4Q26 | U1: 1Q27 | V1: 2Q27 | W1: 3Q27 | X1: 4Q27 | Y1: FY26 | Z1: FY27 | AA1: ALL
A2: REV | B2: Revenue ($M) | C2: musd | D2: B · DEC-0003 | E2: =INDEX('Scenario Data'!$E$44:$G$44,MATCH(Scenario,'Scenario Data'!$E$1:$G$1,0)) | F2: =INDEX('Scenario Data'!$E$45:$G$45,MATCH(Scenario,'Scenario Data'!$E$1:$G$1,0)) | G2: =INDEX('Scenario Data'!$E$46:$G$46,MATCH(Scenario,'Scenario Data'!$E$1:$G$1,0)) | H2: =INDEX('Scenario Data'!$E$47:$G$47,MATCH(Scenario,'Scenario Data'!$E$1:$G$1,0)) | I2: =INDEX('Scenario Data'!$E$48:$G$48,MATCH(Scenario,'Scenario Data'!$E$1:$G$1,0)) | J2: =INDEX('Scenario Data'!$E$49:$G$49,MATCH(Scenario,'Scenario Data'!$E$1:$G$1,0)) | K2: =INDEX('Scenario Data'!$E$50:$G$50,MATCH(Scenario,'Scenario Data'!$E$1:$G$1,0)) | L2: =INDEX('Scenario Data'!$E$51:$G$51,MATCH(Scenario,'Scenario Data'!$E$1:$G$1,0)) | M2: =INDEX('Scenario Data'!$E$52:$G$52,MATCH(Scenario,'Scenario Data'!$E$1:$G$1,0)) | N2: =INDEX('Scenario Data'!$E$53:$G$53,MATCH(Scenario,'Scenario Data'!$E$1:$G$1,0)) | O2: =INDEX('Scenario Data'!$E$54:$G$54,MATCH(Scenario,'Scenario Data'!$E$1:$G$1,0)) | P2: =INDEX('Scenario Data'!$E$55:$G$55,MATCH(Scenario,'Scenario Data'!$E$1:$G$1,0)) | Q2: =INDEX('Scenario Data'!$E$56:$G$56,MATCH(Scenario,'Scenario Data'!$E$1:$G$1,0)) | R2: =INDEX('Scenario Data'!$E$57:$G$57,MATCH(Scenario,'Scenario Data'!$E$1:$G$1,0))
A3: TAKE | B3: Take rate (%) | C3: pct | D3: formula: REV / GBV * 100 | E3: =REV_1Q23/GBV_1Q23*100 | F3: =REV_2Q23/GBV_2Q23*100 | G3: =REV_3Q23/GBV_3Q23*100 | H3: =REV_4Q23/GBV_4Q23*100 | I3: =REV_1Q24/GBV_1Q24*100 | J3: =REV_2Q24/GBV_2Q24*100 | K3: =REV_3Q24/GBV_3Q24*100 | L3: =REV_4Q24/GBV_4Q24*100 | M3: =REV_1Q25/GBV_1Q25*100 | N3: =REV_2Q25/GBV_2Q25*100 | O3: =REV_3Q25/GBV_3Q25*100 | P3: =REV_4Q25/GBV_4Q25*100 | Q3: =REV_1Q26/GBV_1Q26*100 | R3: =REV_2Q26/GBV_2Q26*100
A4: LAM_Q1 | B4: Kernel lambda, Q1 season (%) | C4: pct | D4: B · DEC-0006 | AA4: =INDEX('Scenario Data'!$E$58:$G$58,MATCH(Scenario,'Scenario Data'!$E$1:$G$1,0))
A5: LAM_Q2 | B5: Kernel lambda, Q2 season (%) | C5: pct | D5: B · DEC-0006 | AA5: =INDEX('Scenario Data'!$E$59:$G$59,MATCH(Scenario,'Scenario Data'!$E$1:$G$1,0))
A6: LAM_Q3 | B6: Kernel lambda, Q3 season (%) | C6: pct | D6: B · DEC-0006 | AA6: =INDEX('Scenario Data'!$E$60:$G$60,MATCH(Scenario,'Scenario Data'!$E$1:$G$1,0))
A7: LAM_Q4 | B7: Kernel lambda, Q4 season (%) | C7: pct | D7: B · DEC-0006 | AA7: =INDEX('Scenario Data'!$E$61:$G$61,MATCH(Scenario,'Scenario Data'!$E$1:$G$1,0))
A8: W1 | B8: Kernel weight, GBV[q-1] | C8: weight | D8: B · DEC-0006 | AA8: =INDEX('Scenario Data'!$E$62:$G$62,MATCH(Scenario,'Scenario Data'!$E$1:$G$1,0))
A9: W2 | B9: Kernel weight, GBV[q-2] | C9: weight | D9: B · DEC-0006 | AA9: =INDEX('Scenario Data'!$E$63:$G$63,MATCH(Scenario,'Scenario Data'!$E$1:$G$1,0))
A10: JW0 | B10: Joint-rule weight, GBV[t] (sensitivity only) | C10: weight | D10: B · DEC-0006 | AA10: =INDEX('Scenario Data'!$E$64:$G$64,MATCH(Scenario,'Scenario Data'!$E$1:$G$1,0))
A11: JW1 | B11: Joint-rule weight, GBV[t-1] (sensitivity only) | C11: weight | D11: B · DEC-0006 | AA11: =INDEX('Scenario Data'!$E$65:$G$65,MATCH(Scenario,'Scenario Data'!$E$1:$G$1,0))
A12: JW2 | B12: Joint-rule weight, GBV[t-2] (sensitivity only) | C12: weight | D12: B · DEC-0006 | AA12: =INDEX('Scenario Data'!$E$66:$G$66,MATCH(Scenario,'Scenario Data'!$E$1:$G$1,0))
A13: JW3 | B13: Joint-rule weight, mean(GBV[t-3],GBV[t-4]) (sensitivity only) | C13: weight | D13: B · DEC-0006 | AA13: =INDEX('Scenario Data'!$E$67:$G$67,MATCH(Scenario,'Scenario Data'!$E$1:$G$1,0))
A14: REV_KERNEL | B14: Revenue, kernel ($M) | C14: musd | D14: formula: LAM_Q3@ALL / 100 * (W1@ALL * GBV[-1] + W2@ALL * GBV[-2]) | S14: =LAM_Q3_ALL/100*(W1_ALL*GBV_2Q26+W2_ALL*GBV_1Q26)
A15: CUSH | B15: Guide cushion, trailing-8 mean (pp) | C15: pctpt | D15: A · DEC-0001 | AA15: =INDEX('Scenario Data'!$E$68:$G$68,MATCH(Scenario,'Scenario Data'!$E$1:$G$1,0))
A16: STREET_REV | B16: Street revenue ($M) | C16: musd | D16: B · DEC-0013 | S16: =INDEX('Scenario Data'!$E$69:$G$69,MATCH(Scenario,'Scenario Data'!$E$1:$G$1,0)) | T16: =INDEX('Scenario Data'!$E$70:$G$70,MATCH(Scenario,'Scenario Data'!$E$1:$G$1,0)) | Y16: =INDEX('Scenario Data'!$E$71:$G$71,MATCH(Scenario,'Scenario Data'!$E$1:$G$1,0)) | Z16: =INDEX('Scenario Data'!$E$72:$G$72,MATCH(Scenario,'Scenario Data'!$E$1:$G$1,0))

Sheet Costs and Earnings
A1: id | B1: line | C1: unit | D1: grade · decision | E1: 1Q23 | F1: 2Q23 | G1: 3Q23 | H1: 4Q23 | I1: 1Q24 | J1: 2Q24 | K1: 3Q24 | L1: 4Q24 | M1: 1Q25 | N1: 2Q25 | O1: 3Q25 | P1: 4Q25 | Q1: 1Q26 | R1: 2Q26 | S1: 3Q26 | T1: 4Q26 | U1: 1Q27 | V1: 2Q27 | W1: 3Q27 | X1: 4Q27 | Y1: FY26 | Z1: FY27 | AA1: ALL
A2: COR | B2: Cost of revenue, cash ($M) | C2: musd | D2: B · DEC-0003 | E2: =INDEX('Scenario Data'!$E$73:$G$73,MATCH(Scenario,'Scenario Data'!$E$1:$G$1,0)) | F2: =INDEX('Scenario Data'!$E$74:$G$74,MATCH(Scenario,'Scenario Data'!$E$1:$G$1,0)) | G2: =INDEX('Scenario Data'!$E$75:$G$75,MATCH(Scenario,'Scenario Data'!$E$1:$G$1,0)) | H2: =INDEX('Scenario Data'!$E$76:$G$76,MATCH(Scenario,'Scenario Data'!$E$1:$G$1,0)) | I2: =INDEX('Scenario Data'!$E$77:$G$77,MATCH(Scenario,'Scenario Data'!$E$1:$G$1,0)) | J2: =INDEX('Scenario Data'!$E$78:$G$78,MATCH(Scenario,'Scenario Data'!$E$1:$G$1,0)) | K2: =INDEX('Scenario Data'!$E$79:$G$79,MATCH(Scenario,'Scenario Data'!$E$1:$G$1,0)) | L2: =INDEX('Scenario Data'!$E$80:$G$80,MATCH(Scenario,'Scenario Data'!$E$1:$G$1,0)) | M2: =INDEX('Scenario Data'!$E$81:$G$81,MATCH(Scenario,'Scenario Data'!$E$1:$G$1,0)) | N2: =INDEX('Scenario Data'!$E$82:$G$82,MATCH(Scenario,'Scenario Data'!$E$1:$G$1,0)) | O2: =INDEX('Scenario Data'!$E$83:$G$83,MATCH(Scenario,'Scenario Data'!$E$1:$G$1,0)) | P2: =INDEX('Scenario Data'!$E$84:$G$84,MATCH(Scenario,'Scenario Data'!$E$1:$G$1,0)) | Q2: =INDEX('Scenario Data'!$E$85:$G$85,MATCH(Scenario,'Scenario Data'!$E$1:$G$1,0)) | R2: =INDEX('Scenario Data'!$E$86:$G$86,MATCH(Scenario,'Scenario Data'!$E$1:$G$1,0))
A3: OPS | B3: Operations & support, cash ($M) | C3: musd | D3: B · DEC-0003 | E3: =INDEX('Scenario Data'!$E$87:$G$87,MATCH(Scenario,'Scenario Data'!$E$1:$G$1,0)) | F3: =INDEX('Scenario Data'!$E$88:$G$88,MATCH(Scenario,'Scenario Data'!$E$1:$G$1,0)) | G3: =INDEX('Scenario Data'!$E$89:$G$89,MATCH(Scenario,'Scenario Data'!$E$1:$G$1,0)) | H3: =INDEX('Scenario Data'!$E$90:$G$90,MATCH(Scenario,'Scenario Data'!$E$1:$G$1,0)) | I3: =INDEX('Scenario Data'!$E$91:$G$91,MATCH(Scenario,'Scenario Data'!$E$1:$G$1,0)) | J3: =INDEX('Scenario Data'!$E$92:$G$92,MATCH(Scenario,'Scenario Data'!$E$1:$G$1,0)) | K3: =INDEX('Scenario Data'!$E$93:$G$93,MATCH(Scenario,'Scenario Data'!$E$1:$G$1,0)) | L3: =INDEX('Scenario Data'!$E$94:$G$94,MATCH(Scenario,'Scenario Data'!$E$1:$G$1,0)) | M3: =INDEX('Scenario Data'!$E$95:$G$95,MATCH(Scenario,'Scenario Data'!$E$1:$G$1,0)) | N3: =INDEX('Scenario Data'!$E$96:$G$96,MATCH(Scenario,'Scenario Data'!$E$1:$G$1,0)) | O3: =INDEX('Scenario Data'!$E$97:$G$97,MATCH(Scenario,'Scenario Data'!$E$1:$G$1,0)) | P3: =INDEX('Scenario Data'!$E$98:$G$98,MATCH(Scenario,'Scenario Data'!$E$1:$G$1,0)) | Q3: =INDEX('Scenario Data'!$E$99:$G$99,MATCH(Scenario,'Scenario Data'!$E$1:$G$1,0)) | R3: =INDEX('Scenario Data'!$E$100:$G$100,MATCH(Scenario,'Scenario Data'!$E$1:$G$1,0))
A4: PD | B4: Product development, cash ($M) | C4: musd | D4: B · DEC-0003 | E4: =INDEX('Scenario Data'!$E$101:$G$101,MATCH(Scenario,'Scenario Data'!$E$1:$G$1,0)) | F4: =INDEX('Scenario Data'!$E$102:$G$102,MATCH(Scenario,'Scenario Data'!$E$1:$G$1,0)) | G4: =INDEX('Scenario Data'!$E$103:$G$103,MATCH(Scenario,'Scenario Data'!$E$1:$G$1,0)) | H4: =INDEX('Scenario Data'!$E$104:$G$104,MATCH(Scenario,'Scenario Data'!$E$1:$G$1,0)) | I4: =INDEX('Scenario Data'!$E$105:$G$105,MATCH(Scenario,'Scenario Data'!$E$1:$G$1,0)) | J4: =INDEX('Scenario Data'!$E$106:$G$106,MATCH(Scenario,'Scenario Data'!$E$1:$G$1,0)) | K4: =INDEX('Scenario Data'!$E$107:$G$107,MATCH(Scenario,'Scenario Data'!$E$1:$G$1,0)) | L4: =INDEX('Scenario Data'!$E$108:$G$108,MATCH(Scenario,'Scenario Data'!$E$1:$G$1,0)) | M4: =INDEX('Scenario Data'!$E$109:$G$109,MATCH(Scenario,'Scenario Data'!$E$1:$G$1,0)) | N4: =INDEX('Scenario Data'!$E$110:$G$110,MATCH(Scenario,'Scenario Data'!$E$1:$G$1,0)) | O4: =INDEX('Scenario Data'!$E$111:$G$111,MATCH(Scenario,'Scenario Data'!$E$1:$G$1,0)) | P4: =INDEX('Scenario Data'!$E$112:$G$112,MATCH(Scenario,'Scenario Data'!$E$1:$G$1,0)) | Q4: =INDEX('Scenario Data'!$E$113:$G$113,MATCH(Scenario,'Scenario Data'!$E$1:$G$1,0)) | R4: =INDEX('Scenario Data'!$E$114:$G$114,MATCH(Scenario,'Scenario Data'!$E$1:$G$1,0))
A5: GA | B5: G&A ex lodging reserve, cash ($M) | C5: musd | D5: B · DEC-0003 | E5: =INDEX('Scenario Data'!$E$115:$G$115,MATCH(Scenario,'Scenario Data'!$E$1:$G$1,0)) | F5: =INDEX('Scenario Data'!$E$116:$G$116,MATCH(Scenario,'Scenario Data'!$E$1:$G$1,0)) | G5: =INDEX('Scenario Data'!$E$117:$G$117,MATCH(Scenario,'Scenario Data'!$E$1:$G$1,0)) | H5: =INDEX('Scenario Data'!$E$118:$G$118,MATCH(Scenario,'Scenario Data'!$E$1:$G$1,0)) | I5: =INDEX('Scenario Data'!$E$119:$G$119,MATCH(Scenario,'Scenario Data'!$E$1:$G$1,0)) | J5: =INDEX('Scenario Data'!$E$120:$G$120,MATCH(Scenario,'Scenario Data'!$E$1:$G$1,0)) | K5: =INDEX('Scenario Data'!$E$121:$G$121,MATCH(Scenario,'Scenario Data'!$E$1:$G$1,0)) | L5: =INDEX('Scenario Data'!$E$122:$G$122,MATCH(Scenario,'Scenario Data'!$E$1:$G$1,0)) | M5: =INDEX('Scenario Data'!$E$123:$G$123,MATCH(Scenario,'Scenario Data'!$E$1:$G$1,0)) | N5: =INDEX('Scenario Data'!$E$124:$G$124,MATCH(Scenario,'Scenario Data'!$E$1:$G$1,0)) | O5: =INDEX('Scenario Data'!$E$125:$G$125,MATCH(Scenario,'Scenario Data'!$E$1:$G$1,0)) | P5: =INDEX('Scenario Data'!$E$126:$G$126,MATCH(Scenario,'Scenario Data'!$E$1:$G$1,0)) | Q5: =INDEX('Scenario Data'!$E$127:$G$127,MATCH(Scenario,'Scenario Data'!$E$1:$G$1,0)) | R5: =INDEX('Scenario Data'!$E$128:$G$128,MATCH(Scenario,'Scenario Data'!$E$1:$G$1,0))
A6: SBC | B6: Stock-based compensation, total ($M) | C6: musd | D6: B · DEC-0003 | E6: =INDEX('Scenario Data'!$E$129:$G$129,MATCH(Scenario,'Scenario Data'!$E$1:$G$1,0)) | F6: =INDEX('Scenario Data'!$E$130:$G$130,MATCH(Scenario,'Scenario Data'!$E$1:$G$1,0)) | G6: =INDEX('Scenario Data'!$E$131:$G$131,MATCH(Scenario,'Scenario Data'!$E$1:$G$1,0)) | H6: =INDEX('Scenario Data'!$E$132:$G$132,MATCH(Scenario,'Scenario Data'!$E$1:$G$1,0)) | I6: =INDEX('Scenario Data'!$E$133:$G$133,MATCH(Scenario,'Scenario Data'!$E$1:$G$1,0)) | J6: =INDEX('Scenario Data'!$E$134:$G$134,MATCH(Scenario,'Scenario Data'!$E$1:$G$1,0)) | K6: =INDEX('Scenario Data'!$E$135:$G$135,MATCH(Scenario,'Scenario Data'!$E$1:$G$1,0)) | L6: =INDEX('Scenario Data'!$E$136:$G$136,MATCH(Scenario,'Scenario Data'!$E$1:$G$1,0)) | M6: =INDEX('Scenario Data'!$E$137:$G$137,MATCH(Scenario,'Scenario Data'!$E$1:$G$1,0)) | N6: =INDEX('Scenario Data'!$E$138:$G$138,MATCH(Scenario,'Scenario Data'!$E$1:$G$1,0)) | O6: =INDEX('Scenario Data'!$E$139:$G$139,MATCH(Scenario,'Scenario Data'!$E$1:$G$1,0)) | P6: =INDEX('Scenario Data'!$E$140:$G$140,MATCH(Scenario,'Scenario Data'!$E$1:$G$1,0)) | Q6: =INDEX('Scenario Data'!$E$141:$G$141,MATCH(Scenario,'Scenario Data'!$E$1:$G$1,0)) | R6: =INDEX('Scenario Data'!$E$142:$G$142,MATCH(Scenario,'Scenario Data'!$E$1:$G$1,0))
A7: DA | B7: Depreciation & amortization ($M) | C7: musd | D7: B · DEC-0003 | E7: =INDEX('Scenario Data'!$E$143:$G$143,MATCH(Scenario,'Scenario Data'!$E$1:$G$1,0)) | F7: =INDEX('Scenario Data'!$E$144:$G$144,MATCH(Scenario,'Scenario Data'!$E$1:$G$1,0)) | G7: =INDEX('Scenario Data'!$E$145:$G$145,MATCH(Scenario,'Scenario Data'!$E$1:$G$1,0)) | H7: =INDEX('Scenario Data'!$E$146:$G$146,MATCH(Scenario,'Scenario Data'!$E$1:$G$1,0)) | I7: =INDEX('Scenario Data'!$E$147:$G$147,MATCH(Scenario,'Scenario Data'!$E$1:$G$1,0)) | J7: =INDEX('Scenario Data'!$E$148:$G$148,MATCH(Scenario,'Scenario Data'!$E$1:$G$1,0)) | K7: =INDEX('Scenario Data'!$E$149:$G$149,MATCH(Scenario,'Scenario Data'!$E$1:$G$1,0)) | L7: =INDEX('Scenario Data'!$E$150:$G$150,MATCH(Scenario,'Scenario Data'!$E$1:$G$1,0)) | M7: =INDEX('Scenario Data'!$E$151:$G$151,MATCH(Scenario,'Scenario Data'!$E$1:$G$1,0)) | N7: =INDEX('Scenario Data'!$E$152:$G$152,MATCH(Scenario,'Scenario Data'!$E$1:$G$1,0)) | O7: =INDEX('Scenario Data'!$E$153:$G$153,MATCH(Scenario,'Scenario Data'!$E$1:$G$1,0)) | P7: =INDEX('Scenario Data'!$E$154:$G$154,MATCH(Scenario,'Scenario Data'!$E$1:$G$1,0)) | Q7: =INDEX('Scenario Data'!$E$155:$G$155,MATCH(Scenario,'Scenario Data'!$E$1:$G$1,0)) | R7: =INDEX('Scenario Data'!$E$156:$G$156,MATCH(Scenario,'Scenario Data'!$E$1:$G$1,0))
A8: EBITDA | B8: Adjusted EBITDA ($M) | C8: musd | D8: B · DEC-0003 | E8: =INDEX('Scenario Data'!$E$157:$G$157,MATCH(Scenario,'Scenario Data'!$E$1:$G$1,0)) | F8: =INDEX('Scenario Data'!$E$158:$G$158,MATCH(Scenario,'Scenario Data'!$E$1:$G$1,0)) | G8: =INDEX('Scenario Data'!$E$159:$G$159,MATCH(Scenario,'Scenario Data'!$E$1:$G$1,0)) | H8: =INDEX('Scenario Data'!$E$160:$G$160,MATCH(Scenario,'Scenario Data'!$E$1:$G$1,0)) | I8: =INDEX('Scenario Data'!$E$161:$G$161,MATCH(Scenario,'Scenario Data'!$E$1:$G$1,0)) | J8: =INDEX('Scenario Data'!$E$162:$G$162,MATCH(Scenario,'Scenario Data'!$E$1:$G$1,0)) | K8: =INDEX('Scenario Data'!$E$163:$G$163,MATCH(Scenario,'Scenario Data'!$E$1:$G$1,0)) | L8: =INDEX('Scenario Data'!$E$164:$G$164,MATCH(Scenario,'Scenario Data'!$E$1:$G$1,0)) | M8: =INDEX('Scenario Data'!$E$165:$G$165,MATCH(Scenario,'Scenario Data'!$E$1:$G$1,0)) | N8: =INDEX('Scenario Data'!$E$166:$G$166,MATCH(Scenario,'Scenario Data'!$E$1:$G$1,0)) | O8: =INDEX('Scenario Data'!$E$167:$G$167,MATCH(Scenario,'Scenario Data'!$E$1:$G$1,0)) | P8: =INDEX('Scenario Data'!$E$168:$G$168,MATCH(Scenario,'Scenario Data'!$E$1:$G$1,0)) | Q8: =INDEX('Scenario Data'!$E$169:$G$169,MATCH(Scenario,'Scenario Data'!$E$1:$G$1,0)) | R8: =INDEX('Scenario Data'!$E$170:$G$170,MATCH(Scenario,'Scenario Data'!$E$1:$G$1,0))
A9: SHARES | B9: Diluted shares, historical (m) | C9: m | D9: B · DEC-0003 | E9: =INDEX('Scenario Data'!$E$171:$G$171,MATCH(Scenario,'Scenario Data'!$E$1:$G$1,0)) | F9: =INDEX('Scenario Data'!$E$172:$G$172,MATCH(Scenario,'Scenario Data'!$E$1:$G$1,0)) | G9: =INDEX('Scenario Data'!$E$173:$G$173,MATCH(Scenario,'Scenario Data'!$E$1:$G$1,0)) | H9: =INDEX('Scenario Data'!$E$174:$G$174,MATCH(Scenario,'Scenario Data'!$E$1:$G$1,0)) | I9: =INDEX('Scenario Data'!$E$175:$G$175,MATCH(Scenario,'Scenario Data'!$E$1:$G$1,0)) | J9: =INDEX('Scenario Data'!$E$176:$G$176,MATCH(Scenario,'Scenario Data'!$E$1:$G$1,0)) | K9: =INDEX('Scenario Data'!$E$177:$G$177,MATCH(Scenario,'Scenario Data'!$E$1:$G$1,0)) | L9: =INDEX('Scenario Data'!$E$178:$G$178,MATCH(Scenario,'Scenario Data'!$E$1:$G$1,0)) | M9: =INDEX('Scenario Data'!$E$179:$G$179,MATCH(Scenario,'Scenario Data'!$E$1:$G$1,0)) | N9: =INDEX('Scenario Data'!$E$180:$G$180,MATCH(Scenario,'Scenario Data'!$E$1:$G$1,0)) | O9: =INDEX('Scenario Data'!$E$181:$G$181,MATCH(Scenario,'Scenario Data'!$E$1:$G$1,0)) | P9: =INDEX('Scenario Data'!$E$182:$G$182,MATCH(Scenario,'Scenario Data'!$E$1:$G$1,0)) | Q9: =INDEX('Scenario Data'!$E$183:$G$183,MATCH(Scenario,'Scenario Data'!$E$1:$G$1,0)) | R9: =INDEX('Scenario Data'!$E$184:$G$184,MATCH(Scenario,'Scenario Data'!$E$1:$G$1,0))
A10: SM | B10: Sales & marketing, cash ($M) | C10: musd | D10: B · DEC-0003 / B · DEC-0011 | E10: =INDEX('Scenario Data'!$E$185:$G$185,MATCH(Scenario,'Scenario Data'!$E$1:$G$1,0)) | F10: =INDEX('Scenario Data'!$E$186:$G$186,MATCH(Scenario,'Scenario Data'!$E$1:$G$1,0)) | G10: =INDEX('Scenario Data'!$E$187:$G$187,MATCH(Scenario,'Scenario Data'!$E$1:$G$1,0)) | H10: =INDEX('Scenario Data'!$E$188:$G$188,MATCH(Scenario,'Scenario Data'!$E$1:$G$1,0)) | I10: =INDEX('Scenario Data'!$E$189:$G$189,MATCH(Scenario,'Scenario Data'!$E$1:$G$1,0)) | J10: =INDEX('Scenario Data'!$E$190:$G$190,MATCH(Scenario,'Scenario Data'!$E$1:$G$1,0)) | K10: =INDEX('Scenario Data'!$E$191:$G$191,MATCH(Scenario,'Scenario Data'!$E$1:$G$1,0)) | L10: =INDEX('Scenario Data'!$E$192:$G$192,MATCH(Scenario,'Scenario Data'!$E$1:$G$1,0)) | M10: =INDEX('Scenario Data'!$E$193:$G$193,MATCH(Scenario,'Scenario Data'!$E$1:$G$1,0)) | N10: =INDEX('Scenario Data'!$E$194:$G$194,MATCH(Scenario,'Scenario Data'!$E$1:$G$1,0)) | O10: =INDEX('Scenario Data'!$E$195:$G$195,MATCH(Scenario,'Scenario Data'!$E$1:$G$1,0)) | P10: =INDEX('Scenario Data'!$E$196:$G$196,MATCH(Scenario,'Scenario Data'!$E$1:$G$1,0)) | Q10: =INDEX('Scenario Data'!$E$197:$G$197,MATCH(Scenario,'Scenario Data'!$E$1:$G$1,0)) | R10: =INDEX('Scenario Data'!$E$198:$G$198,MATCH(Scenario,'Scenario Data'!$E$1:$G$1,0)) | S10: =INDEX('Scenario Data'!$E$199:$G$199,MATCH(Scenario,'Scenario Data'!$E$1:$G$1,0)) | T10: =INDEX('Scenario Data'!$E$200:$G$200,MATCH(Scenario,'Scenario Data'!$E$1:$G$1,0)) | Y10: =INDEX('Scenario Data'!$E$201:$G$201,MATCH(Scenario,'Scenario Data'!$E$1:$G$1,0)) | Z10: =INDEX('Scenario Data'!$E$202:$G$202,MATCH(Scenario,'Scenario Data'!$E$1:$G$1,0))
A11: STREET_EBITDA | B11: Street adjusted EBITDA ($M) | C11: musd | D11: B · DEC-0013 | S11: =INDEX('Scenario Data'!$E$203:$G$203,MATCH(Scenario,'Scenario Data'!$E$1:$G$1,0)) | Z11: =INDEX('Scenario Data'!$E$204:$G$204,MATCH(Scenario,'Scenario Data'!$E$1:$G$1,0))
A12: STREET_EPS | B12: Street diluted EPS ($) | C12: usd | D12: B · DEC-0013 | S12: =INDEX('Scenario Data'!$E$205:$G$205,MATCH(Scenario,'Scenario Data'!$E$1:$G$1,0)) | Z12: =INDEX('Scenario Data'!$E$206:$G$206,MATCH(Scenario,'Scenario Data'!$E$1:$G$1,0))
A13: STREET_MARGIN | B13: Street adjusted EBITDA margin (%) | C13: pct | D13: B · DEC-0013 | Z13: =INDEX('Scenario Data'!$E$207:$G$207,MATCH(Scenario,'Scenario Data'!$E$1:$G$1,0))

Sheet Valuation and Call
A1: id | B1: line | C1: unit | D1: grade · decision | E1: 1Q23 | F1: 2Q23 | G1: 3Q23 | H1: 4Q23 | I1: 1Q24 | J1: 2Q24 | K1: 3Q24 | L1: 4Q24 | M1: 1Q25 | N1: 2Q25 | O1: 3Q25 | P1: 4Q25 | Q1: 1Q26 | R1: 2Q26 | S1: 3Q26 | T1: 4Q26 | U1: 1Q27 | V1: 2Q27 | W1: 3Q27 | X1: 4Q27 | Y1: FY26 | Z1: FY27 | AA1: ALL
A2: MULT | B2: Exit EV / adj. EBITDA multiple (x) | C2: x | D2: B · DEC-0014 | Z2: =INDEX('Scenario Data'!$E$208:$G$208,MATCH(Scenario,'Scenario Data'!$E$1:$G$1,0))
A3: SLOPE | B3: Exit multiple slope (turns per pp of growth) | C3: x | D3: B · DEC-0015 | AA3: =INDEX('Scenario Data'!$E$209:$G$209,MATCH(Scenario,'Scenario Data'!$E$1:$G$1,0))
A4: SPOT | B4: Spot price ($) | C4: usd | D4: B · DEC-0015 | AA4: =INDEX('Scenario Data'!$E$210:$G$210,MATCH(Scenario,'Scenario Data'!$E$1:$G$1,0))
A5: NETCASH | B5: Net cash ex client-held float ($M) | C5: musd | D5: B · DEC-0015 | AA5: =INDEX('Scenario Data'!$E$211:$G$211,MATCH(Scenario,'Scenario Data'!$E$1:$G$1,0))
A6: SHARES_DIL | B6: Diluted shares, valuation basis (m) | C6: m | D6: B · DEC-0015 | AA6: =INDEX('Scenario Data'!$E$212:$G$212,MATCH(Scenario,'Scenario Data'!$E$1:$G$1,0))

Sheet 5 Nov Event Card
A1: id | B1: line | C1: unit | D1: grade · decision | E1: 1Q23 | F1: 2Q23 | G1: 3Q23 | H1: 4Q23 | I1: 1Q24 | J1: 2Q24 | K1: 3Q24 | L1: 4Q24 | M1: 1Q25 | N1: 2Q25 | O1: 3Q25 | P1: 4Q25 | Q1: 1Q26 | R1: 2Q26 | S1: 3Q26 | T1: 4Q26 | U1: 1Q27 | V1: 2Q27 | W1: 3Q27 | X1: 4Q27 | Y1: FY26 | Z1: FY27 | AA1: ALL

Sheet Street
A1: id | B1: line | C1: unit | D1: grade · decision | E1: 1Q23 | F1: 2Q23 | G1: 3Q23 | H1: 4Q23 | I1: 1Q24 | J1: 2Q24 | K1: 3Q24 | L1: 4Q24 | M1: 1Q25 | N1: 2Q25 | O1: 3Q25 | P1: 4Q25 | Q1: 1Q26 | R1: 2Q26 | S1: 3Q26 | T1: 4Q26 | U1: 1Q27 | V1: 2Q27 | W1: 3Q27 | X1: 4Q27 | Y1: FY26 | Z1: FY27 | AA1: ALL

Sheet Evidence
A1: id | B1: line | C1: kind | D1: periods | E1: grade | F1: decision | G1: tolerance | H1: dossier | I1: receipt | J1: expr
A2: NIGHTS | B2: Nights booked (m) | C2: input | D2: 1Q23–2Q26 | E2: B | F2: DEC-0003 | G2: 0.1 | H2: docs/pitch-model-v2/dossiers/H0_h0_history.md | I2: data/processed/pitch_model_v2/receipts/H0/receipt.json
A3: NIGHTS | B3: Nights booked (m) | C3: input | D3: 3Q26–3Q26 | E3: B | F3: DEC-0004 | G3: 0.1 | H3: docs/pitch-model-v2/dossiers/D1_d1_nights_3q26.md | I3: data/processed/pitch_model_v2/receipts/D1/receipt.json
A4: ADR | B4: ADR ($) | C4: input | D4: 1Q23–2Q26 | E4: B | F4: DEC-0003 | G4: 0.01 | H4: docs/pitch-model-v2/dossiers/H0_h0_history.md | I4: data/processed/pitch_model_v2/receipts/H0/receipt.json
A5: ADR | B5: ADR ($) | C5: input | D5: 3Q26–4Q26 | E5: B | F5: DEC-0008 | G5: 0.01 | H5: docs/pitch-model-v2/dossiers/D4_d4_adr.md | I5: data/processed/pitch_model_v2/receipts/D4/receipt.json
A6: GBV | B6: GBV ($M) | C6: formula | D6: 1Q23–3Q26 | J6: NIGHTS * ADR
A7: FX_REV | B7: Revenue FX contribution (pp y/y) | C7: input | D7: 3Q26–2Q27 | E7: B | F7: DEC-0010 | G7: 0.01 | H7: docs/pitch-model-v2/dossiers/D5_d5_fx.md | I7: data/processed/pitch_model_v2/receipts/D5/receipt.json
A8: FX_ADR | B8: ADR FX contribution (pp y/y) | C8: input | D8: 3Q26–2Q27 | E8: B | F8: DEC-0010 | G8: 0.01 | H8: docs/pitch-model-v2/dossiers/D5_d5_fx.md | I8: data/processed/pitch_model_v2/receipts/D5/receipt.json
A9: STREET_NIGHTS | B9: Street nights (m) | C9: input | D9: 3Q26–4Q26 | E9: B | F9: DEC-0013 | G9: 0.1 | H9: docs/pitch-model-v2/dossiers/V1_v1_street.md | I9: data/processed/pitch_model_v2/receipts/V1/receipt_l0_pytest.json
A10: STREET_ADR | B10: Street ADR ($) | C10: input | D10: 3Q26–3Q26 | E10: B | F10: DEC-0013 | G10: 0.01 | H10: docs/pitch-model-v2/dossiers/V1_v1_street.md | I10: data/processed/pitch_model_v2/receipts/V1/receipt_l0_pytest.json
A11: REV | B11: Revenue ($M) | C11: input | D11: 1Q23–2Q26 | E11: B | F11: DEC-0003 | G11: 0.5 | H11: docs/pitch-model-v2/dossiers/H0_h0_history.md | I11: data/processed/pitch_model_v2/receipts/H0/receipt.json
A12: TAKE | B12: Take rate (%) | C12: formula | D12: 1Q23–2Q26 | J12: REV / GBV * 100
A13: LAM_Q1 | B13: Kernel lambda, Q1 season (%) | C13: input | D13: ALL–ALL | E13: B | F13: DEC-0006 | G13: 0.01 | H13: docs/pitch-model-v2/dossiers/R1_r1_kernel.md | I13: data/processed/pitch_model_v2/receipts/R1/receipt.json
A14: LAM_Q2 | B14: Kernel lambda, Q2 season (%) | C14: input | D14: ALL–ALL | E14: B | F14: DEC-0006 | G14: 0.01 | H14: docs/pitch-model-v2/dossiers/R1_r1_kernel.md | I14: data/processed/pitch_model_v2/receipts/R1/receipt.json
A15: LAM_Q3 | B15: Kernel lambda, Q3 season (%) | C15: input | D15: ALL–ALL | E15: B | F15: DEC-0006 | G15: 0.01 | H15: docs/pitch-model-v2/dossiers/R1_r1_kernel.md | I15: data/processed/pitch_model_v2/receipts/R1/receipt.json
A16: LAM_Q4 | B16: Kernel lambda, Q4 season (%) | C16: input | D16: ALL–ALL | E16: B | F16: DEC-0006 | G16: 0.01 | H16: docs/pitch-model-v2/dossiers/R1_r1_kernel.md | I16: data/processed/pitch_model_v2/receipts/R1/receipt.json
A17: W1 | B17: Kernel weight, GBV[q-1] | C17: input | D17: ALL–ALL | E17: B | F17: DEC-0006 | G17: 0.001 | H17: docs/pitch-model-v2/dossiers/R1_r1_kernel.md | I17: data/processed/pitch_model_v2/receipts/R1/receipt.json
A18: W2 | B18: Kernel weight, GBV[q-2] | C18: input | D18: ALL–ALL | E18: B | F18: DEC-0006 | G18: 0.001 | H18: docs/pitch-model-v2/dossiers/R1_r1_kernel.md | I18: data/processed/pitch_model_v2/receipts/R1/receipt.json
A19: JW0 | B19: Joint-rule weight, GBV[t] (sensitivity only) | C19: input | D19: ALL–ALL | E19: B | F19: DEC-0006 | G19: 0.001 | H19: docs/pitch-model-v2/dossiers/R1_r1_kernel.md | I19: data/processed/pitch_model_v2/receipts/R1/receipt.json
A20: JW1 | B20: Joint-rule weight, GBV[t-1] (sensitivity only) | C20: input | D20: ALL–ALL | E20: B | F20: DEC-0006 | G20: 0.001 | H20: docs/pitch-model-v2/dossiers/R1_r1_kernel.md | I20: data/processed/pitch_model_v2/receipts/R1/receipt.json
A21: JW2 | B21: Joint-rule weight, GBV[t-2] (sensitivity only) | C21: input | D21: ALL–ALL | E21: B | F21: DEC-0006 | G21: 0.001 | H21: docs/pitch-model-v2/dossiers/R1_r1_kernel.md | I21: data/processed/pitch_model_v2/receipts/R1/receipt.json
A22: JW3 | B22: Joint-rule weight, mean(GBV[t-3],GBV[t-4]) (sensitivity only) | C22: input | D22: ALL–ALL | E22: B | F22: DEC-0006 | G22: 0.001 | H22: docs/pitch-model-v2/dossiers/R1_r1_kernel.md | I22: data/processed/pitch_model_v2/receipts/R1/receipt.json
A23: REV_KERNEL | B23: Revenue, kernel ($M) | C23: formula | D23: 3Q26–3Q26 | J23: LAM_Q3@ALL / 100 * (W1@ALL * GBV[-1] + W2@ALL * GBV[-2])
A24: CUSH | B24: Guide cushion, trailing-8 mean (pp) | C24: input | D24: ALL–ALL | E24: A | F24: DEC-0001 | G24: 0.01 | H24: docs/pitch-model-v2/dossiers/R3_r3_cushion.md | I24: data/processed/pitch_model_v2/receipts/R3/receipt.json
A25: STREET_REV | B25: Street revenue ($M) | C25: input | D25: 3Q26–FY27 | E25: B | F25: DEC-0013 | G25: 0.5 | H25: docs/pitch-model-v2/dossiers/V1_v1_street.md | I25: data/processed/pitch_model_v2/receipts/V1/receipt_l0_pytest.json
A26: COR | B26: Cost of revenue, cash ($M) | C26: input | D26: 1Q23–2Q26 | E26: B | F26: DEC-0003 | G26: 0.5 | H26: docs/pitch-model-v2/dossiers/H0_h0_history.md | I26: data/processed/pitch_model_v2/receipts/H0/receipt.json
A27: OPS | B27: Operations & support, cash ($M) | C27: input | D27: 1Q23–2Q26 | E27: B | F27: DEC-0003 | G27: 0.5 | H27: docs/pitch-model-v2/dossiers/H0_h0_history.md | I27: data/processed/pitch_model_v2/receipts/H0/receipt.json
A28: PD | B28: Product development, cash ($M) | C28: input | D28: 1Q23–2Q26 | E28: B | F28: DEC-0003 | G28: 0.5 | H28: docs/pitch-model-v2/dossiers/H0_h0_history.md | I28: data/processed/pitch_model_v2/receipts/H0/receipt.json
A29: GA | B29: G&A ex lodging reserve, cash ($M) | C29: input | D29: 1Q23–2Q26 | E29: B | F29: DEC-0003 | G29: 0.5 | H29: docs/pitch-model-v2/dossiers/H0_h0_history.md | I29: data/processed/pitch_model_v2/receipts/H0/receipt.json
A30: SBC | B30: Stock-based compensation, total ($M) | C30: input | D30: 1Q23–2Q26 | E30: B | F30: DEC-0003 | G30: 0.5 | H30: docs/pitch-model-v2/dossiers/H0_h0_history.md | I30: data/processed/pitch_model_v2/receipts/H0/receipt.json
A31: DA | B31: Depreciation & amortization ($M) | C31: input | D31: 1Q23–2Q26 | E31: B | F31: DEC-0003 | G31: 0.5 | H31: docs/pitch-model-v2/dossiers/H0_h0_history.md | I31: data/processed/pitch_model_v2/receipts/H0/receipt.json
A32: EBITDA | B32: Adjusted EBITDA ($M) | C32: input | D32: 1Q23–2Q26 | E32: B | F32: DEC-0003 | G32: 0.5 | H32: docs/pitch-model-v2/dossiers/H0_h0_history.md | I32: data/processed/pitch_model_v2/receipts/H0/receipt.json
A33: SHARES | B33: Diluted shares, historical (m) | C33: input | D33: 1Q23–2Q26 | E33: B | F33: DEC-0003 | G33: 0.1 | H33: docs/pitch-model-v2/dossiers/H0_h0_history.md | I33: data/processed/pitch_model_v2/receipts/H0/receipt.json
A34: SM | B34: Sales & marketing, cash ($M) | C34: input | D34: 1Q23–2Q26 | E34: B | F34: DEC-0003 | G34: 0.5 | H34: docs/pitch-model-v2/dossiers/H0_h0_history.md | I34: data/processed/pitch_model_v2/receipts/H0/receipt.json
A35: SM | B35: Sales & marketing, cash ($M) | C35: input | D35: 3Q26–FY27 | E35: B | F35: DEC-0011 | G35: 0.5 | H35: docs/pitch-model-v2/dossiers/C4_c4_sales_marketing.md | I35: data/processed/pitch_model_v2/receipts/C4/receipt.json
... A43: SHARES_DIL | B43: Diluted shares, valuation basis (m) | C43: input | D43: ALL–ALL | E43: B | F43: DEC-0015 | G43: 0.1 | H43: docs/pitch-model-v2/dossiers/V2_v2_multiple.md | I43: data/processed/pitch_model_v2/receipts/V2/receipt.json

Sheet Decision Log
A1: id | B1: line | C1: period | D1: scenario | E1: value | F1: reason | G1: rejected | H1: date
A2: DEC-0001 | B2: R3 | C2: 3Q26 | D2: base | E2: 1.857 | F2: trailing-8 mean cushion (pct points), the registered harness-scored statistic; implied guide = revenue / (1 + CUSH/100) | G2: 1.790 (median); both-as-scenarios | H2: 2026-09-18
A3: DEC-0002 | B3: R3 | C3: all | D3: all | E3: volunteer no-edge | F3: when asked about the cushion, state guide-to-print mechanics AND that Street-to-guide fails both windows (7/14, 4/10) | G3: answer narrowly | H3: 2026-09-18
A4: DEC-0003 | B4: H0 | C4: 1Q23-2Q26 | D4: actual | E4: panel basis | F4: G&A on ga_cash_ex_lodging; SBC and diluted shares at 4Q23/4Q25 from the margin-build panel's documented corrections (640.0m/614.0m shares; $290M/$411M SBC); grade B accepted | G4: driver-history values (653.0m/613.0m; $270M/$400M) | H4: 2026-09-18
A5: DEC-0004 | B5: D1 | C5: 3Q26 | D5: base | E5: 146.3 | F5: reviews stays index bias-corrected read, +9.5%; three routes agree at 9.49-9.52; band 8.5-11.0 for pre-registration and 6 Nov scoring, P10-P90 of N(9.5,1.70) for workbook scenarios; memo wording becomes the three-ratio sentence (0.68 W2 / 0.84 W1 / 0.76 re-vintaged; clears 0.75 on neither) | G5: team baseline 146.8m; index point with baseline band | H5: 2026-09-18
A6: DEC-0005 | B6: V1 | C6: 3Q26 | D6: street | E6: 149 | F6: 3Q26 Street nights bar corrected to the cited 12 Sep Bloomberg MODL capture (n 28); memo v3's 148.9m came from a 4 Sep capture; E_positioning_card.py already says 149.0 | G6: 148.9 (keep memo, fix script) | H6: 2026-09-18
A7: DEC-0006 | B7: R1 | C7: all | D7: all | E7: fixed kernel for revenue | F7: λ by season (Q1 12.66, Q2 13.71, Q3 17.24, Q4 12.03 pct; last3_ex_covid window, digger recommendation pending Theo's confirmation) with weights 2/3 on GBV[q-1] and 1/3 on GBV[q-2] drives forward revenue only (R2, R5); joint 7-parameter rule carried as a labelled sensitivity row; PIT backtest shown with the guide-morning information set named | G7: joint rule; guide-growth baseline as spine | H7: 2026-09-18
A8: DEC-0007 | B8: R4 | C8: 4Q26 | D8: all | E8: C1 log model | F8: implied guide = EXP(season_Q4 + beta × LN(0.4·GBV_4Q26 + 0.4·GBV_3Q26 + 0.2·GBV_2Q26)) from Theo's gbv_guidance_inference_v1 coefficients (19 guides, fitted 16 Sep 2026); no cushion step; the kernel-revenue ÷ (1+CUSH/100) guide shown beside it as a labelled cross-check row; GBV_4Q26 is a live formula (nights × ADR) so the guide moves with the scenario | G8: kernel ÷ cushion as primary; frozen 4Q26 GBV input | H8: 2026-09-18
A9: DEC-0008 | B9: D4 | C9: 3Q26 | D9: base | E9: 176.88 | F9: ADR card v3 without the fee-migration term K (what memo v3 prints); K (+0.17pp) carried as a labelled sensitivity; docs/adrv3 SYNTHESIS §5 to be amended to match; grade B accepted (decomposition descriptive) | G9: with_K 177.17 | H9: 2026-09-18
A10: DEC-0009 | B10: D4 | C10: 4Q26 | D10: all | E10: carry residual | F10: like-for-like price residual carried at last-quarter level (4.85pp) in base and breaker; lap-only 3.06pp is the short scenario (2.2pp of ADR, ~$65M revenue) | G10: lap-only in base | H10: 2026-09-18
A11: DEC-0010 | B11: D5 | C11: 4Q26 | D11: all | E11: 0.98 | F11: revenue FX +0.98pp base (spot held; Φ×0.851 adopted), +0.52 short (USD one sigma stronger), +1.45 breaker (one sigma weaker); confidence set +0.3 to +2.2; memo's "84% observed for 4Q26" relabelled as a 3Q26 figure; grade B accepted | G11: shape-only fit +0.75; other mapping | H11: 2026-09-18
A12: DEC-0011 | B12: C4 | C12: all | D12: all | E12: line build; budget | F12: cost stack from 40_line_build for composition (3Q26 S&M $778M reconciled to the management sentence treated as a budget); the calibrated combination's dollar object reserved for the 5 Nov card; evidence-only $710M / 52.4% shown as the upside risk case; FY27 S&M band 21.9-23.5% stated | G12: combination as stack; sentence as floor | H12: 2026-09-18
A13: DEC-0012 | B13: V1 | C13: all | D13: street | E13: grade B | F13: the frozen L0 register tests (exit 0) are this line's reproduction; consensus_stamp_v2 verify-mode exit 1 logged as a tooling defect (it can only pass once, right after its own append) | G13: keep C, scenario rows only | H13: 2026-09-18
A14: DEC-0013 | B14: V1 | C14: all | D14: street | E14: LSEG family | F14: LSEG-family panel is the headline Street row (n 35-37, consistent with memo v3 EBITDA/EPS rows); Zacks as scenario street_zacks footnote rows where it differs (4Q26 3200 vs 3158-3162); FY27 margin shown on both bases (36.45 implied, 35.06 LSEG field) | G14: equal rows | H14: 2026-09-18
A15: DEC-0014 | B15: V2 | C15: FY27 | D15: all | E15: 12.29 / 16.03 / 20.76 | F15: exit EV/adj. EBITDA multiples re-anchored by the line's own +0.486 turns/pt slope to the final model's growths (bear/base/bull); the WS12 blend to be re-run on those growths before finals; slope quoted as +0.49 turns/pt with 95% CI 0.32-0.65, n 35 overlapping monthly changes, descriptive | G15: keep 13.5/16.5/18.5 + footnote; re-run blend now | H15: 2026-09-18
A16: DEC-0015 | B16: V2 | C16: all | D16: all | E16: 167.51 provisional | F16: spot price and date left PROVISIONAL at memo v3's $167.51 (16 Sep 2026 close) per Theo: construct the model line by line first, decide the refresh when the model stands; every upside is recomputed at that refresh | G16: refresh now | H16: 2026-09-18
A17: DEC-0016 | B17: all | C17: all | D17: all | E17: no leaning | F17: standing rule from Theo: scenarios are mechanical consequences of stated assumptions and the model generates the price; no input is chosen to match a priced downside or the memo's target. Consequence for D4: short 3Q26 ADR stays at the lap-only 173.80 (DEC-0009); the mean-reversion floor 172.97 stays a dossier note, not an input | G17: pick the floor to match memo v3's 0.12 downside | H17: 2026-09-18
A18: DEC-0017 | B18: R4 | C18: 4Q26 | D18: all | E18: deferred | F18: guide mechanism decision parked per Theo ("focus on the guidance later; gather understanding; full focus on the income statement"); R4C coefficients graded B and stored (HAC3 interval quoted when used); no GUIDE line enters the spec until this is reopened; the C1-vs-baselines backtest (RMSE 65.9 vs 50.5 blend vs 63.5 guide-growth) is on record in the R4C dossier | G18: C1 primary now; blend primary; guide-growth primary | H18: 2026-09-18

Sheet Scenario Data
A1: id | B1: period | C1: label | D1: unit | E1: base | F1: short | G1: breaker
A2: NIGHTS | B2: 1Q23 | C2: Nights booked (m) | D2: m | E2: 121.1 | F2: 121.1 | G2: 121.1
A3: NIGHTS | B3: 2Q23 | C3: Nights booked (m) | D3: m | E3: 115.1 | F3: 115.1 | G3: 115.1
A4: NIGHTS | B4: 3Q23 | C4: Nights booked (m) | D4: m | E4: 113.2 | F4: 113.2 | G4: 113.2
A5: NIGHTS | B5: 4Q23 | C5: Nights booked (m) | D5: m | E5: 98.8 | F5: 98.8 | G5: 98.8
A6: NIGHTS | B6: 1Q24 | C6: Nights booked (m) | D6: m | E6: 132.6 | F6: 132.6 | G6: 132.6
A7: NIGHTS | B7: 2Q24 | C7: Nights booked (m) | D7: m | E7: 125.1 | F7: 125.1 | G7: 125.1
A8: NIGHTS | B8: 3Q24 | C8: Nights booked (m) | D8: m | E8: 122.8 | F8: 122.8 | G8: 122.8
A9: NIGHTS | B9: 4Q24 | C9: Nights booked (m) | D9: m | E9: 111 | F9: 111 | G9: 111
A10: NIGHTS | B10: 1Q25 | C10: Nights booked (m) | D10: m | E10: 143.1 | F10: 143.1 | G10: 143.1
A11: NIGHTS | B11: 2Q25 | C11: Nights booked (m) | D11: m | E11: 134.4 | F11: 134.4 | G11: 134.4
A12: NIGHTS | B12: 3Q25 | C12: Nights booked (m) | D12: m | E12: 133.6 | F12: 133.6 | G12: 133.6
A13: NIGHTS | B13: 4Q25 | C13: Nights booked (m) | D13: m | E13: 121.9 | F13: 121.9 | G13: 121.9
... A212: SHARES_DIL | B212: ALL | C212: Diluted shares, valuation basis (m) | D212: m | E212: 597 | F212: 597 | G212: 597
